Workbook

Sheet StartHere
A1: Workflow Steps
A2: 1. Complete 'Me' first
A3: 2. Interview Mum & Dad separately
A4: 3. Enforce Max-2-Essential rule
A5: 4. Review DiscussionSummary
A6: 5. Verify suburb data
A8: Boundaries Table
A9: Type | B9: Description
A10: Manual | B10: Editable input cells in yellow
A11: Automatic | B11: Calculated outputs

Sheet Settings
A1: Parameter | B1: Value | C1: Notes
A2: Say in the decision: Mum | B2: 1
A3: Say in the decision: Dad | B3: 1
A4: Say in the decision: Me | B4: 1
A5: Max D (Essential) answers per person | B5: 2
A6: Purchase costs allowance (% of price) | B6: 0.06 | C6: (provisional estimate, not SRO calculation)
A7: Forced-choice override margin | B7: 0.02
A9: Priority Rating Scale | B9: Level | C9: Score
A10: A | B10: Level 1, Not needed | C10: 0
A11: B | B11: Level 2, Nice to have | C11: 1
A12: C | B12: Level 3, Important | C12: 2
A13: D | B13: Level 4, Essential | C13: 4
A15: Draft Baseline Weights | B15: Weight
A16: Q15.1 Nature | B16: 0.18
A17: Q15.2 Near family in GW | B17: 0
A18: Q15.3 Indian community | B18: 0.18
A19: Q15.4 Beach | B19: 0.1
A20: Q15.5 Hospital | B20: 0.15
A21: Q15.6 Train/bus | B21: 0.15
A22: Q15.7 Shops/doctor | B22: 0.09
A23: Q15.8 Village character | B23: 0.07
A24: Q15.9 Price | B24: 0.08
A25: Q15.10 Easy city trip | B25: 0
A27: Property fit parameters (rounds 5–6) | B27: Value (approved) | C27: Survey reference | D27: B blank until approved (G5; B38/B39 at G3). Intake changes no fit result
A28: Separation floor (1–4) | C28: =CleanedAnswers!E64 | D28: R6.1, household MAX
A29: Separation ceiling (1–4) | C29: =CleanedAnswers!E65 | D29: R6.2, household MIN
A30: Separation importance (3 Essential / 2 Important / 1 Nice to have) | C30: =CleanedAnswers!E66 | D30: R6.3, household MAX
A31: Mobility must-have (0–3) | C31: =CleanedAnswers!E67 | D31: R6.4, household MAX
A32: Garden preferred band (1–4) | C32: =CleanedAnswers!E68 | D32: R6.5a, household MEDIAN
A33: Garden capacity band (1–4) | C33: =CleanedAnswers!E69 | D33: R6.5b, household MEDIAN
A34: Front-door access (1–4) | C34: =CleanedAnswers!E70 | D34: R6.6, household MIN
A35: Land-size band: courtyard (m², up to) | C35: 400 | D35: Estimate
A36: Land-size band: small garden (m², up to) | C36: 650 | D36: Estimate
A37: Land-size band: medium garden (m², up to) | C37: 1000 | D37: Estimate; above = large
A38: M scale (min) | C38: 90 | D38: Proposed; B set at G3 (M/O decoupling)
A39: O scale (min) | C39: 90 | D39: Proposed; B set at G3 (M/O decoupling)

Sheet RawResponses
A1: Timestamp | B1: [Q0] Whose answers are these? | C1: [Q1] | D1: [Q2] | E1: [Q3] Total budget | F1: [Q4] Max drive to GW | G1: [Q4b] Max drive to GW (if D) | H1: [Q5] Max drive to ED | I1: [Q6] Stairs | J1: [Q7] Garden | K1: [Q7a] Living arrangement | L1: [Q7b] Home size | M1: [Q8] | N1: [Q9] | O1: [Q10] | P1: [Q11] | Q1: [Q12] | R1: [Q13] | S1: [Q13b] | T1: [Q13c] | U1: [Q14] | V1: [Q15.1] Nature | W1: [Q15.2] Near family in GW | X1: [Q15.3] Indian community | Y1: [Q15.4] Beach | Z1: [Q15.5] Hospital | AA1: [Q15.6] Train/bus | AB1: [Q15.7] Shops/doctor | AC1: [Q15.8] Village character | AD1: [Q15.9] Price | AE1: [Q15.10] Easy city trip | AF1: [Q15 Notes] | AG1: [Q16] | AH1: [Q17] | AI1: [Q18] | AJ1: [Q19] | AK1: [Q20] | AL1: [Q21] | AM1: [Gap-form notes] | AN1: [Q13d] Green village vs multicultural neighbourhood (reference-only) | AO1: [R5.1] Time in Glen Waverley in person | AP1: [R5.2] GW drive: firm limit | AQ1: [R5.3] GW drive: preferred | AR1: [R5.4] ED drive: firm limit | AS1: [R5.5] Community place used most | AT1: [R5.6] Community place: longest regular drive | AU1: [R5.7] Church: particular denomination | AV1: [R5 Notes] | AW1: [R6.1] Separation: least that would work | AX1: [R6.2] Separation: most that still feels like one household | AY1: [R6.3] Separation: importance of having it already | AZ1: [R6.4] Mobility: must-have in 10-15 years | BA1: [R6.5a] Outdoor space wanted | BB1: [R6.5b] Garden upkeep capacity | BC1: [R6.6] Supermarket and GP from the front door | BD1: [R6.7] Privacy: one thing that matters most | BE1: [R6 Notes]
A2: 0.375 | B2: Dad | E2: 1000000 | F2: C - 35m | H2: C - 30m | I2: B - Some stairs | J2: B - Small garden | O2: Nature | P2: Village character | Q2: Shops & doctor | V2: C | W2: C | X2: C | Y2: C | Z2: C | AA2: C | AB2: C | AC2: C | AD2: D | AE2: D
A3: 0.38541667 | B3: Me | F3: B - 25m | H3: B - 20m | I3: A - None | J3: C - Courtyard | O3: Nature | P3: Village character | Q3: Shops & doctor | V3: D | W3: D | X3: C | Y3: C | Z3: C | AA3: C | AB3: C | AC3: C | AD3: C | AE3: C
A4: 0.39583333 | B4: Mum | E4: 1250000 | F4: B - 25m | H4: B - 20m | I4: A - None at all (Single-level only) | J4: C - Courtyard | K4: D - Self-contained space | O4: Near family in GW | P4: Village character | Q4: Shops & doctor | V4: D | W4: D | X4: D | Y4: C | Z4: C | AA4: C | AB4: C | AC4: C | AD4: C | AE4: C
A5: 0.40625 | B5: Dad | E5: 1500000 | F5: D - 45 min or more | G5: 75 | H5: D - no limit | I5: C - Doesn't matter | J5: E - Depends on Garden | O5: Near family in GW | P5: Village character | Q5: Shops & doctor | V5: D | W5: D | X5: C | Y5: C | Z5: C | AA5: C | AB5: C | AC5: C | AD5: C | AE5: C
A6: 46322.083 | B6: Dad | C6: A — Green views and quiet | D6: D — Looking after the house and land | E6: 1500000 | F6: D - 45 min or more | G6: 75 | H6: D - no limit | I6: C - Doesn't matter | J6: E - Depends on Garden | K6: A — Yes, living together | L6: E — Not decided / depends (see notes) | M6: C — Hills and forest all around | N6: B — Indian groceries and restaurants | O6: Near family in GW | P6: Village character | Q6: Shops & doctor | S6: A — Scenic country or coastal town, 60–90 min from family | T6: A — Inland forest, hills and gardens | U6: A — Stay put and rely on taxis or family | V6: D | W6: D | X6: C | Y6: C | Z6: C | AA6: C | AB6: C | AC6: C | AD6: C | AE6: C | AM6: Merged: row 5 + gap form (Claude artifact) 2026-10-27T02:00:03Z UTC. Notes: Q3–Q7b: ideally D, or min 3 bedrooms
A7: 46322.085 | B7: Mum | C7: A — Green views and quiet | D7: E — None of these / depends (see notes) | E7: 1250000 | F7: B - 25m | H7: B - 20m | I7: A - None at all (Single-level only) | J7: C - Courtyard | K7: A — Yes, living together | L7: E — Not decided / depends (see notes) | M7: A — A green outlook from the house | N7: A — A church or place of worship nearby | O7: Near family in GW | P7: Village character | Q7: Shops & doctor | S7: B — Leafy metropolitan suburb within 35 min of family | T7: B — Coastal or bay town with greenery and water walks | U7: A — Stay put and rely on taxis or family | V7: D | W7: D | X7: D | Y7: C | Z7: C | AA7: C | AB7: C | AC7: C | AD7: C | AE7: C | AM7: Merged: row 4 + gap form (Claude artifact) 2026-10-27T02:02:10Z UTC. Notes: Q1–Q2: B, D, i actually never wanted to live here, it was too remote and cut off. | Q3–Q7b: 3+ bedrooms, but ideally D
A8: 46322.087 | B8: Me | C8: B — Being near the beach | D8: B — Being far from family | F8: B - 25m | H8: B - 20m | I8: A - None | J8: C - Courtyard | K8: A — Yes, living together | L8: D — A self-contained space (granny flat or separate unit) | M8: E — None of these / depends (see notes) | N8: D — Friendly neighbours of any background | O8: Nature | P8: Village character | Q8: Shops & doctor | S8: A — Scenic country or coastal town, 60–90 min from family | T8: B — Coastal or bay town with greenery and water walks | U8: C — Take the train or bus to family and the hospital | V8: D | W8: D | X8: C | Y8: C | Z8: C | AA8: C | AB8: C | AC8: C | AD8: C | AE8: C | AM8: Merged: row 3 + gap form (Claude artifact) 2026-10-27T02:05:04Z UTC. Notes: Q8–Q9: When you picture nature near your new home | Q14: When I picture nature near new home, its a scenic viewpoint like from arthurs seat, of greenery and coast
A9: 46322.255 | B9: Mum | C9: A — Green views and quiet | D9: E — None of these / depends (see notes) | E9: 1250000 | F9: B - 25m | H9: B - 20m | I9: A - None at all (Single-level only) | J9: C - Courtyard | K9: A — Yes, living together | L9: E — Not decided / depends (see notes) | M9: A — A green outlook from the house | N9: A — A church or place of worship nearby | O9: Near family in GW | P9: Village character | Q9: Shops & doctor | R9: A — Indian shops and community in your own suburb, less green | S9: B — Leafy metropolitan suburb within 35 min of family | T9: B — Coastal or bay town with greenery and water walks | U9: A — Stay put and rely on taxis or family | V9: B | W9: C | X9: C | Y9: B | Z9: D | AA9: C | AB9: D | AC9: B | AD9: B | AE9: A | AM9: Round 2 (Q13, Q15) 2026-10-27T06:07:44Z merged onto row 7. | Merged: row 4 + gap form (Claude artifact) 2026-10-27T02:02:10Z UTC. Notes: Q1–Q2: B, D, i actually never wanted to live here, it was too remote and cut off. | Q3–Q7b: 3+ bedrooms, but ideally D
A10: 46322.256 | B10: Dad | C10: A — Green views and quiet | D10: D — Looking after the house and land | E10: 1500000 | F10: D - 45 min or more | G10: 75 | H10: D - no limit | I10: C - Doesn't matter | J10: E - Depends on Garden | K10: A — Yes, living together | L10: E — Not decided / depends (see notes) | M10: C — Hills and forest all around | N10: B — Indian groceries and restaurants | O10: Near family in GW | P10: Village character | Q10: Shops & doctor | R10: B — Very green, community a 30-min drive away | S10: A — Scenic country or coastal town, 60–90 min from family | T10: A — Inland forest, hills and gardens | U10: A — Stay put and rely on taxis or family | V10: D | W10: B | X10: B | Y10: B | Z10: B | AA10: C | AB10: C | AC10: C | AD10: C | AE10: A | AM10: Round 2 (Q13, Q15) 2026-10-27T06:08:36Z merged onto row 6. | Merged: row 5 + gap form (Claude artifact) 2026-10-27T02:00:03Z UTC. Notes: Q3–Q7b: ideally D, or min 3 bedrooms
A11: 46322.257 | B11: Me | C11: B — Being near the beach | D11: B — Being far from family | F11: B - 25m | H11: B - 20m | I11: A - None | J11: C - Courtyard | K11: A — Yes, living together | L11: D — A self-contained space (granny flat or separate unit) | M11: E — None of these / depends (see notes) | N11: D — Friendly neighbours of any background | O11: Nature | P11: Village character | Q11: Shops & doctor | R11: B — Very green, community a 30-min drive away | S11: A — Scenic country or coastal town, 60–90 min from family | T11: B — Coastal or bay town with greenery and water walks | U11: C — Take the train or bus to family and the hospital | V11: D | W11: A | X11: B | Y11: D | Z11: B | AA11: C | AB11: C | AC11: A | AD11: A | AE11: C | AM11: Round 2 (Q13, Q15) 2026-10-27T06:10:46Z merged onto row 8. | Merged: row 3 + gap form (Claude artifact) 2026-10-27T02:05:04Z UTC. Notes: Q8–Q9: When you picture nature near your new home | Q14: When I picture nature near new home, its a scenic viewpoint like from arthurs seat, of greenery and coast
A12: 46322.273 | B12: Mum | C12: A — Green views and quiet | D12: E — None of these / depends (see notes) | E12: 1250000 | F12: B - 25m | H12: B - 20m | I12: A - None at all (Single-level only) | J12: C - Courtyard | K12: A — Yes, living together | L12: E — Not decided / depends (see notes) | M12: A — A green outlook from the house | N12: A — A church or place of worship nearby | O12: A — A forest street, 35 min from Glen Waverley | P12: A — Flat suburban streets, beach 10 min away | Q12: A — A quiet street, driving 15 min to the shops and doctor | R12: A — Indian shops and community in your own suburb, less green | S12: B — Leafy metropolitan suburb within 35 min of family | T12: B — Coastal or bay town with greenery and water walks | U12: A — Stay put and rely on taxis or family | V12: B | W12: C | X12: C | Y12: B | Z12: D | AA12: C | AB12: D | AC12: B | AD12: B | AE12: A | AM12: Round 3 (Q10–Q12) 2026-10-27T06:33:30Z merged onto row 9. | Round 2 (Q13, Q15) 2026-10-27T06:07:44Z merged onto row 7. | Merged: row 4 + gap form (Claude artifact) 2026-10-27T02:02:10Z UTC. Notes: Q1–Q2: B, D, i actually never wanted to live here, it was too remote and cut off. | Q3–Q7b: 3+ bedrooms, but ideally D
A13: 46322.274 | B13: Dad | C13: A — Green views and quiet | D13: D — Looking after the house and land | E13: 1500000 | F13: D - 45 min or more | G13: 75 | H13: D - no limit | I13: C - Doesn't matter | J13: E - Depends on Garden | K13: A — Yes, living together | L13: E — Not decided / depends (see notes) | M13: C — Hills and forest all around | N13: B — Indian groceries and restaurants | O13: A — A forest street, 35 min from Glen Waverley | P13: B — Hills and bush, beach an hour away | Q13: A — A quiet street, driving 15 min to the shops and doctor | R13: B — Very green, community a 30-min drive away | S13: A — Scenic country or coastal town, 60–90 min from family | T13: A — Inland forest, hills and gardens | U13: A — Stay put and rely on taxis or family | V13: D | W13: B | X13: B | Y13: B | Z13: B | AA13: C | AB13: C | AC13: C | AD13: C | AE13: A | AM13: Round 3 (Q10–Q12) 2026-10-27T06:33:57Z merged onto row 10. | Round 2 (Q13, Q15) 2026-10-27T06:08:36Z merged onto row 6. | Merged: row 5 + gap form (Claude artifact) 2026-10-27T02:00:03Z UTC. Notes: Q3–Q7b: ideally D, or min 3 bedrooms
A14: 46322.274 | B14: Me | C14: B — Being near the beach | D14: B — Being far from family | F14: B - 25m | H14: B - 20m | I14: A - None | J14: C - Courtyard | K14: A — Yes, living together | L14: D — A self-contained space (granny flat or separate unit) | M14: E — None of these / depends (see notes) | N14: D — Friendly neighbours of any background | O14: A — A forest street, 35 min from Glen Waverley | P14: A — Flat suburban streets, beach 10 min away | Q14: B — A busier street, walking to the shops, doctor and station | R14: B — Very green, community a 30-min drive away | S14: A — Scenic country or coastal town, 60–90 min from family | T14: B — Coastal or bay town with greenery and water walks | U14: C — Take the train or bus to family and the hospital | V14: D | W14: A | X14: B | Y14: D | Z14: B | AA14: C | AB14: C | AC14: A | AD14: A | AE14: C | AM14: Round 3 (Q10–Q12) 2026-10-27T06:34:22Z merged onto row 11. | Round 2 (Q13, Q15) 2026-10-27T06:10:46Z merged onto row 8. | Merged: row 3 + gap form (Claude artifact) 2026-10-27T02:05:04Z UTC. Notes: Q8–Q9: When you picture nature near your new home | Q14: When I picture nature near new home, its a scenic viewpoint like from arthurs seat, of greenery and coast
A15: 46322.278 | B15: Mum | C15: A — Green views and quiet | D15: E — None of these / depends (see notes) | E15: 1250000 | F15: B - 25m | H15: B - 20m | I15: A - None at all (Single-level only) | J15: C - Courtyard | K15: A — Yes, living together | L15: E — Not decided / depends (see notes) | M15: A — A green outlook from the house | N15: A — A church or place of worship nearby | O15: B — A leafy suburban street, 15 min from Glen Waverley | P15: A — Flat suburban streets, beach 10 min away | Q15: A — A quiet street, driving 15 min to the shops and doctor | R15: A — Indian shops and community in your own suburb, less green | S15: B — Leafy metropolitan suburb within 35 min of family | T15: B — Coastal or bay town with greenery and water walks | U15: A — Stay put and rely on taxis or family | V15: B | W15: C | X15: C | Y15: B | Z15: D | AA15: C | AB15: D | AC15: B | AD15: B | AE15: A | AM15: Round 3 resubmission 2026-10-27T06:40:04Z merged onto row 12: Mum changed Q10 from A (forest street) to B (leafy street 15 min from GW); Q11, Q12 unchanged. | Round 3 (Q10–Q12) 2026-10-27T06:33:30Z merged onto row 9. | Round 2 (Q13, Q15) 2026-10-27T06:07:44Z merged onto row 7. | Merged: row 4 + gap form (Claude artifact) 2026-10-27T02:02:10Z UTC. Notes: Q1–Q2: B, D, i actually never wanted to live here, it was too remote and cut off. | Q3–Q7b: 3+ bedrooms, but ideally D

Sheet CleanedAnswers
A1: Person | B1: Latest Row | C1: Q15 Essential Count
A2: Mum | B2: =IFERROR(LOOKUP(2,1/(RawResponses!$B$2:$B$500="Mum"),ROW(RawResponses!$B$2:$B$500)),"") | C2: {=IF(COUNTIF(INDEX(RawResponses!$A:$AL, B2, 22):INDEX(RawResponses!$A:$AL, B2, 31), "D")>Settings!$B$5, "Too many D's ("&COUNTIF(INDEX(RawResponses!$A:$AL, B2, 22):INDEX(RawResponses!$A:$AL, B2, 31), "D")&")", "OK ("&COUNTIF(INDEX(RawResponses!$A:$AL, B2, 22):INDEX(RawResponses!$A:$AL, B2, 31), "D")&")")}
A3: Dad | B3: =IFERROR(LOOKUP(2,1/(RawResponses!$B$2:$B$500="Dad"),ROW(RawResponses!$B$2:$B$500)),"") | C3: {=IF(COUNTIF(INDEX(RawResponses!$A:$AL, B3, 22):INDEX(RawResponses!$A:$AL, B3, 31), "D")>Settings!$B$5, "Too many D's ("&COUNTIF(INDEX(RawResponses!$A:$AL, B3, 22):INDEX(RawResponses!$A:$AL, B3, 31), "D")&")", "OK ("&COUNTIF(INDEX(RawResponses!$A:$AL, B3, 22):INDEX(RawResponses!$A:$AL, B3, 31), "D")&")")}
A4: Me | B4: =IFERROR(LOOKUP(2,1/(RawResponses!$B$2:$B$500="Me"),ROW(RawResponses!$B$2:$B$500)),"") | C4: {=IF(COUNTIF(INDEX(RawResponses!$A:$AL, B4, 22):INDEX(RawResponses!$A:$AL, B4, 31), "D")>Settings!$B$5, "Too many D's ("&COUNTIF(INDEX(RawResponses!$A:$AL, B4, 22):INDEX(RawResponses!$A:$AL, B4, 31), "D")&")", "OK ("&COUNTIF(INDEX(RawResponses!$A:$AL, B4, 22):INDEX(RawResponses!$A:$AL, B4, 31), "D")&")")}
A6: Question ID | B6: Mum Answer | C6: Dad Answer | D6: Me Answer | E6: Mum Code | F6: Dad Code | G6: Me Code
A7: [Q3] Total budget | B7: {=INDEX(RawResponses!$A:$AL, $B$2, MATCH($A7&"*", RawResponses!$A$1:$AL$1, 0))} | C7: {=INDEX(RawResponses!$A:$AL, $B$3, MATCH($A7&"*", RawResponses!$A$1:$AL$1, 0))} | D7: =INDEX(RawResponses!$A:$AL, $B$4, MATCH($A7&"*", RawResponses!$A$1:$AL$1, 0)) | E7: =LEFT(B7, 1) | F7: =LEFT(C7, 1) | G7: =LEFT(D7, 1)
A8: [Q4] Max drive to GW | B8: {=INDEX(RawResponses!$A:$AL, $B$2, MATCH($A8&"*", RawResponses!$A$1:$AL$1, 0))} | C8: {=INDEX(RawResponses!$A:$AL, $B$3, MATCH($A8&"*", RawResponses!$A$1:$AL$1, 0))} | D8: {=INDEX(RawResponses!$A:$AL, $B$4, MATCH($A8&"*", RawResponses!$A$1:$AL$1, 0))} | E8: =LEFT(B8, 1) | F8: =LEFT(C8, 1) | G8: =LEFT(D8, 1)
A9: [Q4b] Max drive to GW (if D) | B9: =INDEX(RawResponses!$A:$AL, $B$2, MATCH($A9&"*", RawResponses!$A$1:$AL$1, 0)) | C9: {=INDEX(RawResponses!$A:$AL, $B$3, MATCH($A9&"*", RawResponses!$A$1:$AL$1, 0))} | D9: =INDEX(RawResponses!$A:$AL, $B$4, MATCH($A9&"*", RawResponses!$A$1:$AL$1, 0)) | E9: =IF(B9="","",B9) | F9: =IF(C9="","",C9) | G9: =IF(D9="","",D9)
A10: [Q5] Max drive to ED | B10: {=INDEX(RawResponses!$A:$AL, $B$2, MATCH($A10&"*", RawResponses!$A$1:$AL$1, 0))} | C10: {=INDEX(RawResponses!$A:$AL, $B$3, MATCH($A10&"*", RawResponses!$A$1:$AL$1, 0))} | D10: {=INDEX(RawResponses!$A:$AL, $B$4, MATCH($A10&"*", RawResponses!$A$1:$AL$1, 0))} | E10: =LEFT(B10, 1) | F10: =LEFT(C10, 1) | G10: =LEFT(D10, 1)
A11: [Q6] Stairs | B11: {=INDEX(RawResponses!$A:$AL, $B$2, MATCH($A11&"*", RawResponses!$A$1:$AL$1, 0))} | C11: {=INDEX(RawResponses!$A:$AL, $B$3, MATCH($A11&"*", RawResponses!$A$1:$AL$1, 0))} | D11: {=INDEX(RawResponses!$A:$AL, $B$4, MATCH($A11&"*", RawResponses!$A$1:$AL$1, 0))} | E11: =LEFT(B11, 1) | F11: =LEFT(C11, 1) | G11: =LEFT(D11, 1)
A12: [Q7] Garden | B12: {=INDEX(RawResponses!$A:$AL, $B$2, MATCH($A12&"*", RawResponses!$A$1:$AL$1, 0))} | C12: {=INDEX(RawResponses!$A:$AL, $B$3, MATCH($A12&"*", RawResponses!$A$1:$AL$1, 0))} | D12: {=INDEX(RawResponses!$A:$AL, $B$4, MATCH($A12&"*", RawResponses!$A$1:$AL$1, 0))} | E12: =LEFT(B12, 1) | F12: =LEFT(C12, 1) | G12: =LEFT(D12, 1)
A13: [Q7a] Living arrangement | B13: {=INDEX(RawResponses!$A:$AL, $B$2, MATCH($A13&"*", RawResponses!$A$1:$AL$1, 0))} | C13: =INDEX(RawResponses!$A:$AL, $B$3, MATCH($A13&"*", RawResponses!$A$1:$AL$1, 0)) | D13: =INDEX(RawResponses!$A:$AL, $B$4, MATCH($A13&"*", RawResponses!$A$1:$AL$1, 0)) | E13: =LEFT(B13, 1) | F13: =LEFT(C13, 1) | G13: =LEFT(D13, 1)
A14: [Q7b] Home size | B14: =INDEX(RawResponses!$A:$AL, $B$2, MATCH($A14&"*", RawResponses!$A$1:$AL$1, 0)) | C14: =INDEX(RawResponses!$A:$AL, $B$3, MATCH($A14&"*", RawResponses!$A$1:$AL$1, 0)) | D14: =INDEX(RawResponses!$A:$AL, $B$4, MATCH($A14&"*", RawResponses!$A$1:$AL$1, 0)) | E14: =LEFT(B14, 1) | F14: =LEFT(C14, 1) | G14: =LEFT(D14, 1)
A15: [Q10] | B15: {=INDEX(RawResponses!$A:$AL, $B$2, MATCH($A15&"*", RawResponses!$A$1:$AL$1, 0))} | C15: {=INDEX(RawResponses!$A:$AL, $B$3, MATCH($A15&"*", RawResponses!$A$1:$AL$1, 0))} | D15: {=INDEX(RawResponses!$A:$AL, $B$4, MATCH($A15&"*", RawResponses!$A$1:$AL$1, 0))} | E15: =LEFT(B15, 1) | F15: =LEFT(C15, 1) | G15: =LEFT(D15, 1)
A16: [Q11] | B16: {=INDEX(RawResponses!$A:$AL, $B$2, MATCH($A16&"*", RawResponses!$A$1:$AL$1, 0))} | C16: {=INDEX(RawResponses!$A:$AL, $B$3, MATCH($A16&"*", RawResponses!$A$1:$AL$1, 0))} | D16: {=INDEX(RawResponses!$A:$AL, $B$4, MATCH($A16&"*", RawResponses!$A$1:$AL$1, 0))} | E16: =LEFT(B16, 1) | F16: =LEFT(C16, 1) | G16: =LEFT(D16, 1)
A17: [Q12] | B17: {=INDEX(RawResponses!$A:$AL, $B$2, MATCH($A17&"*", RawResponses!$A$1:$AL$1, 0))} | C17: {=INDEX(RawResponses!$A:$AL, $B$3, MATCH($A17&"*", RawResponses!$A$1:$AL$1, 0))} | D17: {=INDEX(RawResponses!$A:$AL, $B$4, MATCH($A17&"*", RawResponses!$A$1:$AL$1, 0))} | E17: =LEFT(B17, 1) | F17: =LEFT(C17, 1) | G17: =LEFT(D17, 1)
A18: [Q13] | B18: =INDEX(RawResponses!$A:$AL, $B$2, MATCH($A18&"*", RawResponses!$A$1:$AL$1, 0)) | C18: =INDEX(RawResponses!$A:$AL, $B$3, MATCH($A18&"*", RawResponses!$A$1:$AL$1, 0)) | D18: =INDEX(RawResponses!$A:$AL, $B$4, MATCH($A18&"*", RawResponses!$A$1:$AL$1, 0)) | E18: =LEFT(B18, 1) | F18: =LEFT(C18, 1) | G18: =LEFT(D18, 1)
A19: [Q15.1] Nature | B19: {=INDEX(RawResponses!$A:$AL, $B$2, MATCH($A19&"*", RawResponses!$A$1:$AL$1, 0))} | C19: {=INDEX(RawResponses!$A:$AL, $B$3, MATCH($A19&"*", RawResponses!$A$1:$AL$1, 0))} | D19: {=INDEX(RawResponses!$A:$AL, $B$4, MATCH($A19&"*", RawResponses!$A$1:$AL$1, 0))} | E19: =LEFT(B19, 1) | F19: =LEFT(C19, 1) | G19: =LEFT(D19, 1)
A20: [Q15.2] Near family in GW | B20: {=INDEX(RawResponses!$A:$AL, $B$2, MATCH($A20&"*", RawResponses!$A$1:$AL$1, 0))} | C20: {=INDEX(RawResponses!$A:$AL, $B$3, MATCH($A20&"*", RawResponses!$A$1:$AL$1, 0))} | D20: {=INDEX(RawResponses!$A:$AL, $B$4, MATCH($A20&"*", RawResponses!$A$1:$AL$1, 0))} | E20: =LEFT(B20, 1) | F20: =LEFT(C20, 1) | G20: =LEFT(D20, 1)
A21: [Q15.3] Indian community | B21: {=INDEX(RawResponses!$A:$AL, $B$2, MATCH($A21&"*", RawResponses!$A$1:$AL$1, 0))} | C21: {=INDEX(RawResponses!$A:$AL, $B$3, MATCH($A21&"*", RawResponses!$A$1:$AL$1, 0))} | D21: {=INDEX(RawResponses!$A:$AL, $B$4, MATCH($A21&"*", RawResponses!$A$1:$AL$1, 0))} | E21: =LEFT(B21, 1) | F21: =LEFT(C21, 1) | G21: =LEFT(D21, 1)
A22: [Q15.4] Beach | B22: {=INDEX(RawResponses!$A:$AL, $B$2, MATCH($A22&"*", RawResponses!$A$1:$AL$1, 0))} | C22: {=INDEX(RawResponses!$A:$AL, $B$3, MATCH($A22&"*", RawResponses!$A$1:$AL$1, 0))} | D22: {=INDEX(RawResponses!$A:$AL, $B$4, MATCH($A22&"*", RawResponses!$A$1:$AL$1, 0))} | E22: =LEFT(B22, 1) | F22: =LEFT(C22, 1) | G22: =LEFT(D22, 1)
A23: [Q15.5] Hospital | B23: {=INDEX(RawResponses!$A:$AL, $B$2, MATCH($A23&"*", RawResponses!$A$1:$AL$1, 0))} | C23: {=INDEX(RawResponses!$A:$AL, $B$3, MATCH($A23&"*", RawResponses!$A$1:$AL$1, 0))} | D23: {=INDEX(RawResponses!$A:$AL, $B$4, MATCH($A23&"*", RawResponses!$A$1:$AL$1, 0))} | E23: =LEFT(B23, 1) | F23: =LEFT(C23, 1) | G23: =LEFT(D23, 1)
A24: [Q15.6] Train/bus | B24: {=INDEX(RawResponses!$A:$AL, $B$2, MATCH($A24&"*", RawResponses!$A$1:$AL$1, 0))} | C24: {=INDEX(RawResponses!$A:$AL, $B$3, MATCH($A24&"*", RawResponses!$A$1:$AL$1, 0))} | D24: {=INDEX(RawResponses!$A:$AL, $B$4, MATCH($A24&"*", RawResponses!$A$1:$AL$1, 0))} | E24: =LEFT(B24, 1) | F24: =LEFT(C24, 1) | G24: =LEFT(D24, 1)
A25: [Q15.7] Shops/doctor | B25: {=INDEX(RawResponses!$A:$AL, $B$2, MATCH($A25&"*", RawResponses!$A$1:$AL$1, 0))} | C25: {=INDEX(RawResponses!$A:$AL, $B$3, MATCH($A25&"*", RawResponses!$A$1:$AL$1, 0))} | D25: {=INDEX(RawResponses!$A:$AL, $B$4, MATCH($A25&"*", RawResponses!$A$1:$AL$1, 0))} | E25: =LEFT(B25, 1) | F25: =LEFT(C25, 1) | G25: =LEFT(D25, 1)
A26: [Q15.8] Village character | B26: {=INDEX(RawResponses!$A:$AL, $B$2, MATCH($A26&"*", RawResponses!$A$1:$AL$1, 0))} | C26: {=INDEX(RawResponses!$A:$AL, $B$3, MATCH($A26&"*", RawResponses!$A$1:$AL$1, 0))} | D26: {=INDEX(RawResponses!$A:$AL, $B$4, MATCH($A26&"*", RawResponses!$A$1:$AL$1, 0))} | E26: =LEFT(B26, 1) | F26: =LEFT(C26, 1) | G26: =LEFT(D26, 1)
A27: [Q15.9] Price | B27: {=INDEX(RawResponses!$A:$AL, $B$2, MATCH($A27&"*", RawResponses!$A$1:$AL$1, 0))} | C27: {=INDEX(RawResponses!$A:$AL, $B$3, MATCH($A27&"*", RawResponses!$A$1:$AL$1, 0))} | D27: {=INDEX(RawResponses!$A:$AL, $B$4, MATCH($A27&"*", RawResponses!$A$1:$AL$1, 0))} | E27: =LEFT(B27, 1) | F27: =LEFT(C27, 1) | G27: =LEFT(D27, 1)
A28: [Q15.10] Easy city trip | B28: {=INDEX(RawResponses!$A:$AL, $B$2, MATCH($A28&"*", RawResponses!$A$1:$AL$1, 0))} | C28: {=INDEX(RawResponses!$A:$AL, $B$3, MATCH($A28&"*", RawResponses!$A$1:$AL$1, 0))} | D28: {=INDEX(RawResponses!$A:$AL, $B$4, MATCH($A28&"*", RawResponses!$A$1:$AL$1, 0))} | E28: =LEFT(B28, 1) | F28: =LEFT(C28, 1) | G28: =LEFT(D28, 1)
A30: Context answers (shown for discussion; not weighted)
A31: Question ID | B31: Mum Answer | C31: Dad Answer | D31: Me Answer | E31: Mum Code | F31: Dad Code | G31: Me Code
A32: [Q1] | B32: =IFERROR(IF(INDEX(RawResponses!$A:$AM,$B$2,MATCH($A32&"*",RawResponses!$A$1:$AM$1,0))="","",INDEX(RawResponses!$A:$AM,$B$2,MATCH($A32&"*",RawResponses!$A$1:$AM$1,0))),"") | C32: =IFERROR(IF(INDEX(RawResponses!$A:$AM,$B$3,MATCH($A32&"*",RawResponses!$A$1:$AM$1,0))="","",INDEX(RawResponses!$A:$AM,$B$3,MATCH($A32&"*",RawResponses!$A$1:$AM$1,0))),"") | D32: =IFERROR(IF(INDEX(RawResponses!$A:$AM,$B$4,MATCH($A32&"*",RawResponses!$A$1:$AM$1,0))="","",INDEX(RawResponses!$A:$AM,$B$4,MATCH($A32&"*",RawResponses!$A$1:$AM$1,0))),"") | E32: =LEFT(B32,1) | F32: =LEFT(C32,1) | G32: =LEFT(D32,1)
A33: [Q2] | B33: =IFERROR(IF(INDEX(RawResponses!$A:$AM,$B$2,MATCH($A33&"*",RawResponses!$A$1:$AM$1,0))="","",INDEX(RawResponses!$A:$AM,$B$2,MATCH($A33&"*",RawResponses!$A$1:$AM$1,0))),"") | C33: =IFERROR(IF(INDEX(RawResponses!$A:$AM,$B$3,MATCH($A33&"*",RawResponses!$A$1:$AM$1,0))="","",INDEX(RawResponses!$A:$AM,$B$3,MATCH($A33&"*",RawResponses!$A$1:$AM$1,0))),"") | D33: =IFERROR(IF(INDEX(RawResponses!$A:$AM,$B$4,MATCH($A33&"*",RawResponses!$A$1:$AM$1,0))="","",INDEX(RawResponses!$A:$AM,$B$4,MATCH($A33&"*",RawResponses!$A$1:$AM$1,0))),"") | E33: =LEFT(B33,1) | F33: =LEFT(C33,1) | G33: =LEFT(D33,1)
A34: [Q8] | B34: =IFERROR(IF(INDEX(RawResponses!$A:$AM,$B$2,MATCH($A34&"*",RawResponses!$A$1:$AM$1,0))="","",INDEX(RawResponses!$A:$AM,$B$2,MATCH($A34&"*",RawResponses!$A$1:$AM$1,0))),"") | C34: =IFERROR(IF(INDEX(RawResponses!$A:$AM,$B$3,MATCH($A34&"*",RawResponses!$A$1:$AM$1,0))="","",INDEX(RawResponses!$A:$AM,$B$3,MATCH($A34&"*",RawResponses!$A$1:$AM$1,0))),"") | D34: =IFERROR(IF(INDEX(RawResponses!$A:$AM,$B$4,MATCH($A34&"*",RawResponses!$A$1:$AM$1,0))="","",INDEX(RawResponses!$A:$AM,$B$4,MATCH($A34&"*",RawResponses!$A$1:$AM$1,0))),"") | E34: =LEFT(B34,1) | F34: =LEFT(C34,1) | G34: =LEFT(D34,1)
A35: [Q9] | B35: =IFERROR(IF(INDEX(RawResponses!$A:$AM,$B$2,MATCH($A35&"*",RawResponses!$A$1:$AM$1,0))="","",INDEX(RawResponses!$A:$AM,$B$2,MATCH($A35&"*",RawResponses!$A$1:$AM$1,0))),"") | C35: =IFERROR(IF(INDEX(RawResponses!$A:$AM,$B$3,MATCH($A35&"*",RawResponses!$A$1:$AM$1,0))="","",INDEX(RawResponses!$A:$AM,$B$3,MATCH($A35&"*",RawResponses!$A$1:$AM$1,0))),"") | D35: =IFERROR(IF(INDEX(RawResponses!$A:$AM,$B$4,MATCH($A35&"*",RawResponses!$A$1:$AM$1,0))="","",INDEX(RawResponses!$A:$AM,$B$4,MATCH($A35&"*",RawResponses!$A$1:$AM$1,0))),"") | E35: =LEFT(B35,1) | F35: =LEFT(C35,1) | G35: =LEFT(D35,1)
A36: [Q13b] | B36: =IFERROR(IF(INDEX(RawResponses!$A:$AM,$B$2,MATCH($A36&"*",RawResponses!$A$1:$AM$1,0))="","",INDEX(RawResponses!$A:$AM,$B$2,MATCH($A36&"*",RawResponses!$A$1:$AM$1,0))),"") | C36: =IFERROR(IF(INDEX(RawResponses!$A:$AM,$B$3,MATCH($A36&"*",RawResponses!$A$1:$AM$1,0))="","",INDEX(RawResponses!$A:$AM,$B$3,MATCH($A36&"*",RawResponses!$A$1:$AM$1,0))),"") | D36: =IFERROR(IF(INDEX(RawResponses!$A:$AM,$B$4,MATCH($A36&"*",RawResponses!$A$1:$AM$1,0))="","",INDEX(RawResponses!$A:$AM,$B$4,MATCH($A36&"*",RawResponses!$A$1:$AM$1,0))),"") | E36: =LEFT(B36,1) | F36: =LEFT(C36,1) | G36: =LEFT(D36,1)
A37: [Q13c] | B37: =IFERROR(IF(INDEX(RawResponses!$A:$AM,$B$2,MATCH($A37&"*",RawResponses!$A$1:$AM$1,0))="","",INDEX(RawResponses!$A:$AM,$B$2,MATCH($A37&"*",RawResponses!$A$1:$AM$1,0))),"") | C37: =IFERROR(IF(INDEX(RawResponses!$A:$AM,$B$3,MATCH($A37&"*",RawResponses!$A$1:$AM$1,0))="","",INDEX(RawResponses!$A:$AM,$B$3,MATCH($A37&"*",RawResponses!$A$1:$AM$1,0))),"") | D37: =IFERROR(IF(INDEX(RawResponses!$A:$AM,$B$4,MATCH($A37&"*",RawResponses!$A$1:$AM$1,0))="","",INDEX(RawResponses!$A:$AM,$B$4,MATCH($A37&"*",RawResponses!$A$1:$AM$1,0))),"") | E37: =LEFT(B37,1) | F37: =LEFT(C37,1) | G37: =LEFT(D37,1)
A38: [Q14] | B38: =IFERROR(IF(INDEX(RawResponses!$A:$AM,$B$2,MATCH($A38&"*",RawResponses!$A$1:$AM$1,0))="","",INDEX(RawResponses!$A:$AM,$B$2,MATCH($A38&"*",RawResponses!$A$1:$AM$1,0))),"") | C38: =IFERROR(IF(INDEX(RawResponses!$A:$AM,$B$3,MATCH($A38&"*",RawResponses!$A$1:$AM$1,0))="","",INDEX(RawResponses!$A:$AM,$B$3,MATCH($A38&"*",RawResponses!$A$1:$AM$1,0))),"") | D38: =IFERROR(IF(INDEX(RawResponses!$A:$AM,$B$4,MATCH($A38&"*",RawResponses!$A$1:$AM$1,0))="","",INDEX(RawResponses!$A:$AM,$B$4,MATCH($A38&"*",RawResponses!$A$1:$AM$1,0))),"") | E38: =LEFT(B38,1) | F38: =LEFT(C38,1) | G38: =LEFT(D38,1)
A39: [Gap-form notes] | B39: =IFERROR(IF(INDEX(RawResponses!$A:$AM,$B$2,MATCH($A39&"*",RawResponses!$A$1:$AM$1,0))="","",INDEX(RawResponses!$A:$AM,$B$2,MATCH($A39&"*",RawResponses!$A$1:$AM$1,0))),"") | C39: =IFERROR(IF(INDEX(RawResponses!$A:$AM,$B$3,MATCH($A39&"*",RawResponses!$A$1:$AM$1,0))="","",INDEX(RawResponses!$A:$AM,$B$3,MATCH($A39&"*",RawResponses!$A$1:$AM$1,0))),"") | D39: =IFERROR(IF(INDEX(RawResponses!$A:$AM,$B$4,MATCH($A39&"*",RawResponses!$A$1:$AM$1,0))="","",INDEX(RawResponses!$A:$AM,$B$4,MATCH($A39&"*",RawResponses!$A$1:$AM$1,0))),"")
A40: [Q13d] | B40: =IFERROR(IF(INDEX(RawResponses!$A:$AN,$B$2,MATCH($A40&"*",RawResponses!$A$1:$AN$1,0))="","",INDEX(RawResponses!$A:$AN,$B$2,MATCH($A40&"*",RawResponses!$A$1:$AN$1,0))),"") | C40: =IFERROR(IF(INDEX(RawResponses!$A:$AN,$B$3,MATCH($A40&"*",RawResponses!$A$1:$AN$1,0))="","",INDEX(RawResponses!$A:$AN,$B$3,MATCH($A40&"*",RawResponses!$A$1:$AN$1,0))),"") | D40: =IFERROR(IF(INDEX(RawResponses!$A:$AN,$B$4,MATCH($A40&"*",RawResponses!$A$1:$AN$1,0))="","",INDEX(RawResponses!$A:$AN,$B$4,MATCH($A40&"*",RawResponses!$A$1:$AN$1,0))),"") | E40: =LEFT(B40,1) | F40: =LEFT(C40,1) | G40: =LEFT(D40,1)
A41: [R5.1] Time in Glen Waverley in person | B41: =IFERROR(IF(INDEX(RawResponses!$A:$BE,$B$2,MATCH($A41&"*",RawResponses!$A$1:$BE$1,0))="","",INDEX(RawResponses!$A:$BE,$B$2,MATCH($A41&"*",RawResponses!$A$1:$BE$1,0))),"") | C41: =IFERROR(IF(INDEX(RawResponses!$A:$BE,$B$3,MATCH($A41&"*",RawResponses!$A$1:$BE$1,0))="","",INDEX(RawResponses!$A:$BE,$B$3,MATCH($A41&"*",RawResponses!$A$1:$BE$1,0))),"") | D41: =IFERROR(IF(INDEX(RawResponses!$A:$BE,$B$4,MATCH($A41&"*",RawResponses!$A$1:$BE$1,0))="","",INDEX(RawResponses!$A:$BE,$B$4,MATCH($A41&"*",RawResponses!$A$1:$BE$1,0))),"") | E41: =LEFT(B41,1) | F41: =LEFT(C41,1) | G41: =LEFT(D41,1)
A42: [R5.2] GW drive: firm limit | B42: =IFERROR(IF(INDEX(RawResponses!$A:$BE,$B$2,MATCH($A42&"*",RawResponses!$A$1:$BE$1,0))="","",INDEX(RawResponses!$A:$BE,$B$2,MATCH($A42&"*",RawResponses!$A$1:$BE$1,0))),"") | C42: =IFERROR(IF(INDEX(RawResponses!$A:$BE,$B$3,MATCH($A42&"*",RawResponses!$A$1:$BE$1,0))="","",INDEX(RawResponses!$A:$BE,$B$3,MATCH($A42&"*",RawResponses!$A$1:$BE$1,0))),"") | D42: =IFERROR(IF(INDEX(RawResponses!$A:$BE,$B$4,MATCH($A42&"*",RawResponses!$A$1:$BE$1,0))="","",INDEX(RawResponses!$A:$BE,$B$4,MATCH($A42&"*",RawResponses!$A$1:$BE$1,0))),"") | E42: =LEFT(B42,1) | F42: =LEFT(C42,1) | G42: =LEFT(D42,1)
A43: [R5.3] GW drive: preferred | B43: =IFERROR(IF(INDEX(RawResponses!$A:$BE,$B$2,MATCH($A43&"*",RawResponses!$A$1:$BE$1,0))="","",INDEX(RawResponses!$A:$BE,$B$2,MATCH($A43&"*",RawResponses!$A$1:$BE$1,0))),"") | C43: =IFERROR(IF(INDEX(RawResponses!$A:$BE,$B$3,MATCH($A43&"*",RawResponses!$A$1:$BE$1,0))="","",INDEX(RawResponses!$A:$BE,$B$3,MATCH($A43&"*",RawResponses!$A$1:$BE$1,0))),"") | D43: =IFERROR(IF(INDEX(RawResponses!$A:$BE,$B$4,MATCH($A43&"*",RawResponses!$A$1:$BE$1,0))="","",INDEX(RawResponses!$A:$BE,$B$4,MATCH($A43&"*",RawResponses!$A$1:$BE$1,0))),"") | E43: =LEFT(B43,1) | F43: =LEFT(C43,1) | G43: =LEFT(D43,1)
A44: [R5.4] ED drive: firm limit | B44: =IFERROR(IF(INDEX(RawResponses!$A:$BE,$B$2,MATCH($A44&"*",RawResponses!$A$1:$BE$1,0))="","",INDEX(RawResponses!$A:$BE,$B$2,MATCH($A44&"*",RawResponses!$A$1:$BE$1,0))),"") | C44: =IFERROR(IF(INDEX(RawResponses!$A:$BE,$B$3,MATCH($A44&"*",RawResponses!$A$1:$BE$1,0))="","",INDEX(RawResponses!$A:$BE,$B$3,MATCH($A44&"*",RawResponses!$A$1:$BE$1,0))),"") | D44: =IFERROR(IF(INDEX(RawResponses!$A:$BE,$B$4,MATCH($A44&"*",RawResponses!$A$1:$BE$1,0))="","",INDEX(RawResponses!$A:$BE,$B$4,MATCH($A44&"*",RawResponses!$A$1:$BE$1,0))),"") | E44: =LEFT(B44,1) | F44: =LEFT(C44,1) | G44: =LEFT(D44,1)
A45: [R5.5] Community place used most | B45: =IFERROR(IF(INDEX(RawResponses!$A:$BE,$B$2,MATCH($A45&"*",RawResponses!$A$1:$BE$1,0))="","",INDEX(RawResponses!$A:$BE,$B$2,MATCH($A45&"*",RawResponses!$A$1:$BE$1,0))),"") | C45: =IFERROR(IF(INDEX(RawResponses!$A:$BE,$B$3,MATCH($A45&"*",RawResponses!$A$1:$BE$1,0))="","",INDEX(RawResponses!$A:$BE,$B$3,MATCH($A45&"*",RawResponses!$A$1:$BE$1,0))),"") | D45: =IFERROR(IF(INDEX(RawResponses!$A:$BE,$B$4,MATCH($A45&"*",RawResponses!$A$1:$BE$1,0))="","",INDEX(RawResponses!$A:$BE,$B$4,MATCH($A45&"*",RawResponses!$A$1:$BE$1,0))),"") | E45: =LEFT(B45,1) | F45: =LEFT(C45,1) | G45: =LEFT(D45,1)
A46: [R5.6] Community place: longest regular drive | B46: =IFERROR(IF(INDEX(RawResponses!$A:$BE,$B$2,MATCH($A46&"*",RawResponses!$A$1:$BE$1,0))="","",INDEX(RawResponses!$A:$BE,$B$2,MATCH($A46&"*",RawResponses!$A$1:$BE$1,0))),"") | C46: =IFERROR(IF(INDEX(RawResponses!$A:$BE,$B$3,MATCH($A46&"*",RawResponses!$A$1:$BE$1,0))="","",INDEX(RawResponses!$A:$BE,$B$3,MATCH($A46&"*",RawResponses!$A$1:$BE$1,0))),"") | D46: =IFERROR(IF(INDEX(RawResponses!$A:$BE,$B$4,MATCH($A46&"*",RawResponses!$A$1:$BE$1,0))="","",INDEX(RawResponses!$A:$BE,$B$4,MATCH($A46&"*",RawResponses!$A$1:$BE$1,0))),"") | E46: =LEFT(B46,1) | F46: =LEFT(C46,1) | G46: =LEFT(D46,1)
A47: [R5.7] Church: particular denomination | B47: =IFERROR(IF(INDEX(RawResponses!$A:$BE,$B$2,MATCH($A47&"*",RawResponses!$A$1:$BE$1,0))="","",INDEX(RawResponses!$A:$BE,$B$2,MATCH($A47&"*",RawResponses!$A$1:$BE$1,0))),"") | C47: =IFERROR(IF(INDEX(RawResponses!$A:$BE,$B$3,MATCH($A47&"*",RawResponses!$A$1:$BE$1,0))="","",INDEX(RawResponses!$A:$BE,$B$3,MATCH($A47&"*",RawResponses!$A$1:$BE$1,0))),"") | D47: =IFERROR(IF(INDEX(RawResponses!$A:$BE,$B$4,MATCH($A47&"*",RawResponses!$A$1:$BE$1,0))="","",INDEX(RawResponses!$A:$BE,$B$4,MATCH($A47&"*",RawResponses!$A$1:$BE$1,0))),"") | E47: =LEFT(B47,1) | F47: =LEFT(C47,1) | G47: =LEFT(D47,1)
A48: [R5 Notes] | B48: =IFERROR(IF(INDEX(RawResponses!$A:$BE,$B$2,MATCH($A48&"*",RawResponses!$A$1:$BE$1,0))="","",INDEX(RawResponses!$A:$BE,$B$2,MATCH($A48&"*",RawResponses!$A$1:$BE$1,0))),"") | C48: =IFERROR(IF(INDEX(RawResponses!$A:$BE,$B$3,MATCH($A48&"*",RawResponses!$A$1:$BE$1,0))="","",INDEX(RawResponses!$A:$BE,$B$3,MATCH($A48&"*",RawResponses!$A$1:$BE$1,0))),"") | D48: =IFERROR(IF(INDEX(RawResponses!$A:$BE,$B$4,MATCH($A48&"*",RawResponses!$A$1:$BE$1,0))="","",INDEX(RawResponses!$A:$BE,$B$4,MATCH($A48&"*",RawResponses!$A$1:$BE$1,0))),"")
A49: [R6.1] Separation: least that would work | B49: =IFERROR(IF(INDEX(RawResponses!$A:$BE,$B$2,MATCH($A49&"*",RawResponses!$A$1:$BE$1,0))="","",INDEX(RawResponses!$A:$BE,$B$2,MATCH($A49&"*",RawResponses!$A$1:$BE$1,0))),"") | C49: =IFERROR(IF(INDEX(RawResponses!$A:$BE,$B$3,MATCH($A49&"*",RawResponses!$A$1:$BE$1,0))="","",INDEX(RawResponses!$A:$BE,$B$3,MATCH($A49&"*",RawResponses!$A$1:$BE$1,0))),"") | D49: =IFERROR(IF(INDEX(RawResponses!$A:$BE,$B$4,MATCH($A49&"*",RawResponses!$A$1:$BE$1,0))="","",INDEX(RawResponses!$A:$BE,$B$4,MATCH($A49&"*",RawResponses!$A$1:$BE$1,0))),"") | E49: =LEFT(B49,1) | F49: =LEFT(C49,1) | G49: =LEFT(D49,1)
A50: [R6.2] Separation: most that still feels like one household | B50: =IFERROR(IF(INDEX(RawResponses!$A:$BE,$B$2,MATCH($A50&"*",RawResponses!$A$1:$BE$1,0))="","",INDEX(RawResponses!$A:$BE,$B$2,MATCH($A50&"*",RawResponses!$A$1:$BE$1,0))),"") | C50: =IFERROR(IF(INDEX(RawResponses!$A:$BE,$B$3,MATCH($A50&"*",RawResponses!$A$1:$BE$1,0))="","",INDEX(RawResponses!$A:$BE,$B$3,MATCH($A50&"*",RawResponses!$A$1:$BE$1,0))),"") | D50: =IFERROR(IF(INDEX(RawResponses!$A:$BE,$B$4,MATCH($A50&"*",RawResponses!$A$1:$BE$1,0))="","",INDEX(RawResponses!$A:$BE,$B$4,MATCH($A50&"*",RawResponses!$A$1:$BE$1,0))),"") | E50: =LEFT(B50,1) | F50: =LEFT(C50,1) | G50: =LEFT(D50,1)
A51: [R6.3] Separation: importance of having it already | B51: =IFERROR(IF(INDEX(RawResponses!$A:$BE,$B$2,MATCH($A51&"*",RawResponses!$A$1:$BE$1,0))="","",INDEX(RawResponses!$A:$BE,$B$2,MATCH($A51&"*",RawResponses!$A$1:$BE$1,0))),"") | C51: =IFERROR(IF(INDEX(RawResponses!$A:$BE,$B$3,MATCH($A51&"*",RawResponses!$A$1:$BE$1,0))="","",INDEX(RawResponses!$A:$BE,$B$3,MATCH($A51&"*",RawResponses!$A$1:$BE$1,0))),"") | D51: =IFERROR(IF(INDEX(RawResponses!$A:$BE,$B$4,MATCH($A51&"*",RawResponses!$A$1:$BE$1,0))="","",INDEX(RawResponses!$A:$BE,$B$4,MATCH($A51&"*",RawResponses!$A$1:$BE$1,0))),"") | E51: =LEFT(B51,1) | F51: =LEFT(C51,1) | G51: =LEFT(D51,1)
A52: [R6.4] Mobility: must-have in 10-15 years | B52: =IFERROR(IF(INDEX(RawResponses!$A:$BE,$B$2,MATCH($A52&"*",RawResponses!$A$1:$BE$1,0))="","",INDEX(RawResponses!$A:$BE,$B$2,MATCH($A52&"*",RawResponses!$A$1:$BE$1,0))),"") | C52: =IFERROR(IF(INDEX(RawResponses!$A:$BE,$B$3,MATCH($A52&"*",RawResponses!$A$1:$BE$1,0))="","",INDEX(RawResponses!$A:$BE,$B$3,MATCH($A52&"*",RawResponses!$A$1:$BE$1,0))),"") | D52: =IFERROR(IF(INDEX(RawResponses!$A:$BE,$B$4,MATCH($A52&"*",RawResponses!$A$1:$BE$1,0))="","",INDEX(RawResponses!$A:$BE,$B$4,MATCH($A52&"*",RawResponses!$A$1:$BE$1,0))),"") | E52: =LEFT(B52,1) | F52: =LEFT(C52,1) | G52: =LEFT(D52,1)
A53: [R6.5a] Outdoor space wanted | B53: =IFERROR(IF(INDEX(RawResponses!$A:$BE,$B$2,MATCH($A53&"*",RawResponses!$A$1:$BE$1,0))="","",INDEX(RawResponses!$A:$BE,$B$2,MATCH($A53&"*",RawResponses!$A$1:$BE$1,0))),"") | C53: =IFERROR(IF(INDEX(RawResponses!$A:$BE,$B$3,MATCH($A53&"*",RawResponses!$A$1:$BE$1,0))="","",INDEX(RawResponses!$A:$BE,$B$3,MATCH($A53&"*",RawResponses!$A$1:$BE$1,0))),"") | D53: =IFERROR(IF(INDEX(RawResponses!$A:$BE,$B$4,MATCH($A53&"*",RawResponses!$A$1:$BE$1,0))="","",INDEX(RawResponses!$A:$BE,$B$4,MATCH($A53&"*",RawResponses!$A$1:$BE$1,0))),"") | E53: =LEFT(B53,1) | F53: =LEFT(C53,1) | G53: =LEFT(D53,1)
A54: [R6.5b] Garden upkeep capacity | B54: =IFERROR(IF(INDEX(RawResponses!$A:$BE,$B$2,MATCH($A54&"*",RawResponses!$A$1:$BE$1,0))="","",INDEX(RawResponses!$A:$BE,$B$2,MATCH($A54&"*",RawResponses!$A$1:$BE$1,0))),"") | C54: =IFERROR(IF(INDEX(RawResponses!$A:$BE,$B$3,MATCH($A54&"*",RawResponses!$A$1:$BE$1,0))="","",INDEX(RawResponses!$A:$BE,$B$3,MATCH($A54&"*",RawResponses!$A$1:$BE$1,0))),"") | D54: =IFERROR(IF(INDEX(RawResponses!$A:$BE,$B$4,MATCH($A54&"*",RawResponses!$A$1:$BE$1,0))="","",INDEX(RawResponses!$A:$BE,$B$4,MATCH($A54&"*",RawResponses!$A$1:$BE$1,0))),"") | E54: =LEFT(B54,1) | F54: =LEFT(C54,1) | G54: =LEFT(D54,1)
A55: [R6.6] Supermarket and GP from the front door | B55: =IFERROR(IF(INDEX(RawResponses!$A:$BE,$B$2,MATCH($A55&"*",RawResponses!$A$1:$BE$1,0))="","",INDEX(RawResponses!$A:$BE,$B$2,MATCH($A55&"*",RawResponses!$A$1:$BE$1,0))),"") | C55: =IFERROR(IF(INDEX(RawResponses!$A:$BE,$B$3,MATCH($A55&"*",RawResponses!$A$1:$BE$1,0))="","",INDEX(RawResponses!$A:$BE,$B$3,MATCH($A55&"*",RawResponses!$A$1:$BE$1,0))),"") | D55: =IFERROR(IF(INDEX(RawResponses!$A:$BE,$B$4,MATCH($A55&"*",RawResponses!$A$1:$BE$1,0))="","",INDEX(RawResponses!$A:$BE,$B$4,MATCH($A55&"*",RawResponses!$A$1:$BE$1,0))),"") | E55: =LEFT(B55,1) | F55: =LEFT(C55,1) | G55: =LEFT(D55,1)
A56: [R6.7] Privacy: one thing that matters most | B56: =IFERROR(IF(INDEX(RawResponses!$A:$BE,$B$2,MATCH($A56&"*",RawResponses!$A$1:$BE$1,0))="","",INDEX(RawResponses!$A:$BE,$B$2,MATCH($A56&"*",RawResponses!$A$1:$BE$1,0))),"") | C56: =IFERROR(IF(INDEX(RawResponses!$A:$BE,$B$3,MATCH($A56&"*",RawResponses!$A$1:$BE$1,0))="","",INDEX(RawResponses!$A:$BE,$B$3,MATCH($A56&"*",RawResponses!$A$1:$BE$1,0))),"") | D56: =IFERROR(IF(INDEX(RawResponses!$A:$BE,$B$4,MATCH($A56&"*",RawResponses!$A$1:$BE$1,0))="","",INDEX(RawResponses!$A:$BE,$B$4,MATCH($A56&"*",RawResponses!$A$1:$BE$1,0))),"") | E56: =LEFT(B56,1) | F56: =LEFT(C56,1) | G56: =LEFT(D56,1)
A57: [R6 Notes] | B57: =IFERROR(IF(INDEX(RawResponses!$A:$BE,$B$2,MATCH($A57&"*",RawResponses!$A$1:$BE$1,0))="","",INDEX(RawResponses!$A:$BE,$B$2,MATCH($A57&"*",RawResponses!$A$1:$BE$1,0))),"") | C57: =IFERROR(IF(INDEX(RawResponses!$A:$BE,$B$3,MATCH($A57&"*",RawResponses!$A$1:$BE$1,0))="","",INDEX(RawResponses!$A:$BE,$B$3,MATCH($A57&"*",RawResponses!$A$1:$BE$1,0))),"") | D57: =IFERROR(IF(INDEX(RawResponses!$A:$BE,$B$4,MATCH($A57&"*",RawResponses!$A$1:$BE$1,0))="","",INDEX(RawResponses!$A:$BE,$B$4,MATCH($A57&"*",RawResponses!$A$1:$BE$1,0))),"")
A58: Derived (B–D per person; E household)
A59: GW firm limit (min) | B59: =IFERROR(IF(E42="","",CHOOSE(FIND(E42,"ABCDE"),25,35,45,60,90)),"") | C59: =IFERROR(IF(F42="","",CHOOSE(FIND(F42,"ABCDE"),25,35,45,60,90)),"") | D59: =IFERROR(IF(G42="","",CHOOSE(FIND(G42,"ABCDE"),25,35,45,60,90)),"") | E59: =IF(COUNTIF(E42:G42,"?")<3,"",MIN(B59:D59))
A60: GW preferred (min) | B60: =IFERROR(IF(E43="","",CHOOSE(FIND(E43,"ABCDE"),25,35,45,60,90)),"") | C60: =IFERROR(IF(F43="","",CHOOSE(FIND(F43,"ABCDE"),25,35,45,60,90)),"") | D60: =IFERROR(IF(G43="","",CHOOSE(FIND(G43,"ABCDE"),25,35,45,60,90)),"") | E60: =IF(COUNTIF(E43:G43,"?")<3,"",MIN(B60:D60))
A61: ED firm limit (min; blank = no limit) | B61: =IFERROR(IF(E44="","",CHOOSE(FIND(E44,"ABCDE"),15,20,30,45,"")),"") | C61: =IFERROR(IF(F44="","",CHOOSE(FIND(F44,"ABCDE"),15,20,30,45,"")),"") | D61: =IFERROR(IF(G44="","",CHOOSE(FIND(G44,"ABCDE"),15,20,30,45,"")),"") | E61: =IF(COUNTIF(E44:G44,"?")<3,"",IF(COUNT(B61:D61)=0,"No cap",MIN(B61:D61)))
A62: Community place index (grocery 1, temple 2, church 3, none 0) | B62: =IFERROR(IF(E45="","",CHOOSE(FIND(E45,"ABCDE"),1,2,3,0)),"") | C62: =IFERROR(IF(F45="","",CHOOSE(FIND(F45,"ABCDE"),1,2,3,0)),"") | D62: =IFERROR(IF(G45="","",CHOOSE(FIND(G45,"ABCDE"),1,2,3,0)),"")
A63: Community drive limit (min) | B63: =IFERROR(IF(E46="","",CHOOSE(FIND(E46,"ABCDE"),10,20,30,45,"")),"") | C63: =IFERROR(IF(F46="","",CHOOSE(FIND(F46,"ABCDE"),10,20,30,45,"")),"") | D63: =IFERROR(IF(G46="","",CHOOSE(FIND(G46,"ABCDE"),10,20,30,45,"")),"")
A64: Separation floor (1–4) | B64: =IFERROR(IF(E49="","",CHOOSE(FIND(E49,"ABCDE"),1,2,3,4)),"") | C64: =IFERROR(IF(F49="","",CHOOSE(FIND(F49,"ABCDE"),1,2,3,4)),"") | D64: =IFERROR(IF(G49="","",CHOOSE(FIND(G49,"ABCDE"),1,2,3,4)),"") | E64: =IF(COUNTIF(E49:G49,"?")<3,"",MAX(B64:D64))
A65: Separation ceiling (1–4) | B65: =IFERROR(IF(E50="","",CHOOSE(FIND(E50,"ABCDE"),1,2,3,4)),"") | C65: =IFERROR(IF(F50="","",CHOOSE(FIND(F50,"ABCDE"),1,2,3,4)),"") | D65: =IFERROR(IF(G50="","",CHOOSE(FIND(G50,"ABCDE"),1,2,3,4)),"") | E65: =IF(COUNTIF(E50:G50,"?")<3,"",MIN(B65:D65)) | F65: =IF(OR(E64="",E65=""),"",IF(E64>E65,"CONFLICT: no layout suits everyone","OK"))
A66: Separation importance (3 Essential, 2 Important, 1 Nice to have) | B66: =IFERROR(IF(E51="","",CHOOSE(FIND(E51,"ABCDE"),3,2,1)),"") | C66: =IFERROR(IF(F51="","",CHOOSE(FIND(F51,"ABCDE"),3,2,1)),"") | D66: =IFERROR(IF(G51="","",CHOOSE(FIND(G51,"ABCDE"),3,2,1)),"") | E66: =IF(COUNTIF(E51:G51,"?")<3,"",MAX(B66:D66))
A67: Mobility must-have (0–3) | B67: =IFERROR(IF(E52="","",CHOOSE(FIND(E52,"ABCDE"),0,1,2,3)),"") | C67: =IFERROR(IF(F52="","",CHOOSE(FIND(F52,"ABCDE"),0,1,2,3)),"") | D67: =IFERROR(IF(G52="","",CHOOSE(FIND(G52,"ABCDE"),0,1,2,3)),"") | E67: =IF(COUNTIF(E52:G52,"?")<3,"",MAX(B67:D67))
A68: Garden preferred band (1–4) | B68: =IFERROR(IF(E53="","",CHOOSE(FIND(E53,"ABCDE"),1,2,3,4)),"") | C68: =IFERROR(IF(F53="","",CHOOSE(FIND(F53,"ABCDE"),1,2,3,4)),"") | D68: =IFERROR(IF(G53="","",CHOOSE(FIND(G53,"ABCDE"),1,2,3,4)),"") | E68: =IF(COUNTIF(E53:G53,"?")<3,"",MEDIAN(B68:D68))
A69: Garden capacity band (1–4) | B69: =IFERROR(IF(E54="","",CHOOSE(FIND(E54,"ABCDE"),1,2,3,4)),"") | C69: =IFERROR(IF(F54="","",CHOOSE(FIND(F54,"ABCDE"),1,2,3,4)),"") | D69: =IFERROR(IF(G54="","",CHOOSE(FIND(G54,"ABCDE"),1,2,3,4)),"") | E69: =IF(COUNTIF(E54:G54,"?")<3,"",MEDIAN(B69:D69))
A70: Front-door access (1 must walk … 4 drive up to 20 min) | B70: =IFERROR(IF(E55="","",CHOOSE(FIND(E55,"ABCDE"),1,2,3,4)),"") | C70: =IFERROR(IF(F55="","",CHOOSE(FIND(F55,"ABCDE"),1,2,3,4)),"") | D70: =IFERROR(IF(G55="","",CHOOSE(FIND(G55,"ABCDE"),1,2,3,4)),"") | E70: =IF(COUNTIF(E55:G55,"?")<3,"",MIN(B70:D70))
A71: Validation (R6.2 ≥ R6.1; R5.5/R5.6 and R5.5/R5.7 consistent) | B71: =IFERROR(IF(E45&E46&E47&E49&E50="","",IF(AND(LEN(E45&E46&E47&E49&E50)=5,E50>=E49,IF(E45="D",E46="E",E46<>"E"),IF(E45="C",E47<>"C",E47="C")),"OK","Check")),"Check") | C71: =IFERROR(IF(F45&F46&F47&F49&F50="","",IF(AND(LEN(F45&F46&F47&F49&F50)=5,F50>=F49,IF(F45="D",F46="E",F46<>"E"),IF(F45="C",F47<>"C",F47="C")),"OK","Check")),"Check") | D71: =IFERROR(IF(G45&G46&G47&G49&G50="","",IF(AND(LEN(G45&G46&G47&G49&G50)=5,G50>=G49,IF(G45="D",G46="E",G46<>"E"),IF(G45="C",G47<>"C",G47="C")),"OK","Check")),"Check")

Sheet Filters
A1: Filter | B1: Strictest Constraint | C1: Notes | D1: Survey-derived value (reference only)
A2: Q3 Total budget | B2: 1500000 | C2: Confirmed family decision 27 Oct 2026: budget cap set to $1,500,000 maximum purchase price (excluding transaction & moving costs). Replaces survey strictest of $1,250,000. | D2: 1250000
A3: Total acquisition ceiling (Price + 6% costs) | B3: =B2 * (1 + Settings!B6) | C3: Total outlay cap ($1,590,000) including 6% stamp duty/conveyancing/moving allowance on $1,500,000 purchase price.
A4: Q4/Q4b Max drive to GW | B4: 90 | C4: Family decision 26 Oct 2026: hard max 90 min (60 min preferred); a train option is now preferred, not required (see row 9, changed by NJD, family to confirm). Replaces survey strictest of 25 min (Mum/Me); Dad said up to 75. | D4: =MIN(IF(CleanedAnswers!E8="D",IF(ISNUMBER(CleanedAnswers!B9),CleanedAnswers!B9,999),IFERROR(CHOOSE(MATCH(CleanedAnswers!E8,{"A","B","C"},0),15,25,35),999)),IF(CleanedAnswers!F8="D",IF(ISNUMBER(CleanedAnswers!C9),CleanedAnswers!C9,999),IFERROR(CHOOSE(MATCH(CleanedAnswers!F8,{"A","B","C"},0),15,25,35),999)),IF(CleanedAnswers!G8="D",IF(ISNUMBER(CleanedAnswers!D9),CleanedAnswers!D9,999),IFERROR(CHOOSE(MATCH(CleanedAnswers!G8,{"A","B","C"},0),15,25,35),999)))
A5: Q5 Max drive to ED | B5: 90 | C5: Family decision 26 Oct 2026: hard cap 90 min, and ED time is also scored (SuburbScorecard column O). Replaces survey strictest of 20 min (Mum/Me); Dad said no limit.
A6: Q6 Stairs | B6: Stairs allowed (single-level not required) | C6: CORRECTED 27 Oct 2026 by NJD: stairs are allowed, so this is no longer a hard filter. Previous value was the survey strictest answer (formula kept in D6). | D6: =IF(COUNTIF(CleanedAnswers!E11:G11, "A")>0, "A — None at all (Single-level only)", "Check")
A7: Q7a/Q7b Living arrangement | B7: Needs discussion (Living arrangement undecided): D — Self-contained space
A8: Q7 Garden | B8: Needs discussion (Depends — see notes)
A9: Train option | B9: Preferred, not required (scored via SuburbScorecard column S) | C9: CHANGED 26 Oct 2026 by NJD from 'Required (a train station in or at the edge of the suburb)', which had been recorded as a family decision earlier that day. Family to confirm. Reason: a hard rule removes bush and coastal areas that have not been viewed. Column AB on SuburbScorecard: Yes / No.
A10: Drive-time basis | B10: Google Maps drive time, 'leave now' typical traffic, looked up 26 Oct 2026 | C10: Not tested at peak hour. J = to Glen Waverley (suburb centre). K = to the nearest 24-hr public ED listed in SuburbScorecard column AD. Train Yes/No is from recall and sheet notes, not checked against timetables.

Sheet PriorityWeights
A1: Question | B1: Mum Code | C1: Dad Code | D1: Me Code | E1: Mum Score | F1: Dad Score | G1: Me Score | H1: Mum Norm | I1: Dad Norm | J1: Me Norm | K1: Combined Weight
A2: Nature | B2: =CleanedAnswers!E19 | C2: =CleanedAnswers!F19 | D2: =CleanedAnswers!G19 | E2: =VLOOKUP(B2, Settings!$A$10:$C$13, 3, FALSE()) | F2: =VLOOKUP(C2, Settings!$A$10:$C$13, 3, FALSE()) | G2: =VLOOKUP(D2, Settings!$A$10:$C$13, 3, FALSE()) | H2: =E2/SUM(E$2:E$11) | I2: =F2/SUM(F$2:F$11) | J2: =G2/SUM(G$2:G$11) | K2: =(H2*Settings!$B$2 + I2*Settings!$B$3 + J2*Settings!$B$4)/(Settings!$B$2+Settings!$B$3+Settings!$B$4)
A3: Near family in GW | B3: =CleanedAnswers!E20 | C3: =CleanedAnswers!F20 | D3: =CleanedAnswers!G20 | E3: =VLOOKUP(B3, Settings!$A$10:$C$13, 3, FALSE()) | F3: =VLOOKUP(C3, Settings!$A$10:$C$13, 3, FALSE()) | G3: =VLOOKUP(D3, Settings!$A$10:$C$13, 3, FALSE()) | H3: =E3/SUM(E$2:E$11) | I3: =F3/SUM(F$2:F$11) | J3: =G3/SUM(G$2:G$11) | K3: =(H3*Settings!$B$2 + I3*Settings!$B$3 + J3*Settings!$B$4)/(Settings!$B$2+Settings!$B$3+Settings!$B$4)
A4: Indian community | B4: =CleanedAnswers!E21 | C4: =CleanedAnswers!F21 | D4: =CleanedAnswers!G21 | E4: =VLOOKUP(B4, Settings!$A$10:$C$13, 3, FALSE()) | F4: =VLOOKUP(C4, Settings!$A$10:$C$13, 3, FALSE()) | G4: =VLOOKUP(D4, Settings!$A$10:$C$13, 3, FALSE()) | H4: =E4/SUM(E$2:E$11) | I4: =F4/SUM(F$2:F$11) | J4: =G4/SUM(G$2:G$11) | K4: =(H4*Settings!$B$2 + I4*Settings!$B$3 + J4*Settings!$B$4)/(Settings!$B$2+Settings!$B$3+Settings!$B$4)
A5: Beach | B5: =CleanedAnswers!E22 | C5: =CleanedAnswers!F22 | D5: =CleanedAnswers!G22 | E5: =VLOOKUP(B5, Settings!$A$10:$C$13, 3, FALSE()) | F5: =VLOOKUP(C5, Settings!$A$10:$C$13, 3, FALSE()) | G5: =VLOOKUP(D5, Settings!$A$10:$C$13, 3, FALSE()) | H5: =E5/SUM(E$2:E$11) | I5: =F5/SUM(F$2:F$11) | J5: =G5/SUM(G$2:G$11) | K5: =(H5*Settings!$B$2 + I5*Settings!$B$3 + J5*Settings!$B$4)/(Settings!$B$2+Settings!$B$3+Settings!$B$4)
A6: Hospital | B6: =CleanedAnswers!E23 | C6: =CleanedAnswers!F23 | D6: =CleanedAnswers!G23 | E6: =VLOOKUP(B6, Settings!$A$10:$C$13, 3, FALSE()) | F6: =VLOOKUP(C6, Settings!$A$10:$C$13, 3, FALSE()) | G6: =VLOOKUP(D6, Settings!$A$10:$C$13, 3, FALSE()) | H6: =E6/SUM(E$2:E$11) | I6: =F6/SUM(F$2:F$11) | J6: =G6/SUM(G$2:G$11) | K6: =(H6*Settings!$B$2 + I6*Settings!$B$3 + J6*Settings!$B$4)/(Settings!$B$2+Settings!$B$3+Settings!$B$4)
A7: Train/bus | B7: =CleanedAnswers!E24 | C7: =CleanedAnswers!F24 | D7: =CleanedAnswers!G24 | E7: =VLOOKUP(B7, Settings!$A$10:$C$13, 3, FALSE()) | F7: =VLOOKUP(C7, Settings!$A$10:$C$13, 3, FALSE()) | G7: =VLOOKUP(D7, Settings!$A$10:$C$13, 3, FALSE()) | H7: =E7/SUM(E$2:E$11) | I7: =F7/SUM(F$2:F$11) | J7: =G7/SUM(G$2:G$11) | K7: =(H7*Settings!$B$2 + I7*Settings!$B$3 + J7*Settings!$B$4)/(Settings!$B$2+Settings!$B$3+Settings!$B$4)
A8: Shops/doctor | B8: =CleanedAnswers!E25 | C8: =CleanedAnswers!F25 | D8: =CleanedAnswers!G25 | E8: =VLOOKUP(B8, Settings!$A$10:$C$13, 3, FALSE()) | F8: =VLOOKUP(C8, Settings!$A$10:$C$13, 3, FALSE()) | G8: =VLOOKUP(D8, Settings!$A$10:$C$13, 3, FALSE()) | H8: =E8/SUM(E$2:E$11) | I8: =F8/SUM(F$2:F$11) | J8: =G8/SUM(G$2:G$11) | K8: =(H8*Settings!$B$2 + I8*Settings!$B$3 + J8*Settings!$B$4)/(Settings!$B$2+Settings!$B$3+Settings!$B$4)
A9: Village character | B9: =CleanedAnswers!E26 | C9: =CleanedAnswers!F26 | D9: =CleanedAnswers!G26 | E9: =VLOOKUP(B9, Settings!$A$10:$C$13, 3, FALSE()) | F9: =VLOOKUP(C9, Settings!$A$10:$C$13, 3, FALSE()) | G9: =VLOOKUP(D9, Settings!$A$10:$C$13, 3, FALSE()) | H9: =E9/SUM(E$2:E$11) | I9: =F9/SUM(F$2:F$11) | J9: =G9/SUM(G$2:G$11) | K9: =(H9*Settings!$B$2 + I9*Settings!$B$3 + J9*Settings!$B$4)/(Settings!$B$2+Settings!$B$3+Settings!$B$4)
A10: Price | B10: =CleanedAnswers!E27 | C10: =CleanedAnswers!F27 | D10: =CleanedAnswers!G27 | E10: =VLOOKUP(B10, Settings!$A$10:$C$13, 3, FALSE()) | F10: =VLOOKUP(C10, Settings!$A$10:$C$13, 3, FALSE()) | G10: =VLOOKUP(D10, Settings!$A$10:$C$13, 3, FALSE()) | H10: =E10/SUM(E$2:E$11) | I10: =F10/SUM(F$2:F$11) | J10: =G10/SUM(G$2:G$11) | K10: =(H10*Settings!$B$2 + I10*Settings!$B$3 + J10*Settings!$B$4)/(Settings!$B$2+Settings!$B$3+Settings!$B$4)
A11: Easy city trip | B11: =CleanedAnswers!E28 | C11: =CleanedAnswers!F28 | D11: =CleanedAnswers!G28 | E11: =VLOOKUP(B11, Settings!$A$10:$C$13, 3, FALSE()) | F11: =VLOOKUP(C11, Settings!$A$10:$C$13, 3, FALSE()) | G11: =VLOOKUP(D11, Settings!$A$10:$C$13, 3, FALSE()) | H11: =E11/SUM(E$2:E$11) | I11: =F11/SUM(F$2:F$11) | J11: =G11/SUM(G$2:G$11) | K11: =(H11*Settings!$B$2 + I11*Settings!$B$3 + J11*Settings!$B$4)/(Settings!$B$2+Settings!$B$3+Settings!$B$4)

Sheet ForcedChoiceCorrections
A1: Matchup | B1: Result | H1: Question | I1: A-side priority | J1: B-side priority | K1: Mum vote | L1: Dad vote | M1: Me vote | N1: A votes (weighted) | O1: B votes (weighted) | P1: Winning side | Q1: Winner | R1: Loser | S1: Winner weight | T1: Loser weight | U1: Transfer
A2: Trade-offs: see H1:U5 (live, blueprint rule). | H2: Q10 | I2: Nature | J2: Near family in GW | K2: =IF(OR(CleanedAnswers!B15=$I2,LEFT(CleanedAnswers!B15,3)="A —"),"A",IF(OR(CleanedAnswers!B15=$J2,LEFT(CleanedAnswers!B15,3)="B —"),"B","")) | L2: =IF(OR(CleanedAnswers!C15=$I2,LEFT(CleanedAnswers!C15,3)="A —"),"A",IF(OR(CleanedAnswers!C15=$J2,LEFT(CleanedAnswers!C15,3)="B —"),"B","")) | M2: =IF(OR(CleanedAnswers!D15=$I2,LEFT(CleanedAnswers!D15,3)="A —"),"A",IF(OR(CleanedAnswers!D15=$J2,LEFT(CleanedAnswers!D15,3)="B —"),"B","")) | N2: =(K2="A")*Settings!$B$2+(L2="A")*Settings!$B$3+(M2="A")*Settings!$B$4 | O2: =(K2="B")*Settings!$B$2+(L2="B")*Settings!$B$3+(M2="B")*Settings!$B$4 | P2: =IF(N2+O2=0,"",IF(N2>O2,"A",IF(O2>N2,"B","Split"))) | Q2: =IF(P2="A",I2,IF(P2="B",J2,"")) | R2: =IF(P2="A",J2,IF(P2="B",I2,"")) | S2: =IF(Q2="","",INDEX($D$6:$D$15,MATCH(Q2,$A$6:$A$15,0))) | T2: =IF(R2="","",INDEX($D$6:$D$15,MATCH(R2,$A$6:$A$15,0))) | U2: =IF(OR(Q2="",NOT(ISNUMBER(S2)),NOT(ISNUMBER(T2))),0,IF(S2<T2+Settings!$B$7,MIN(T2,(T2-S2+Settings!$B$7)/2),0))
H3: Q11 | I3: Beach | J3: Nature | K3: =IF(OR(CleanedAnswers!B16=$I3,LEFT(CleanedAnswers!B16,3)="A —"),"A",IF(OR(CleanedAnswers!B16=$J3,LEFT(CleanedAnswers!B16,3)="B —"),"B","")) | L3: =IF(OR(CleanedAnswers!C16=$I3,LEFT(CleanedAnswers!C16,3)="A —"),"A",IF(OR(CleanedAnswers!C16=$J3,LEFT(CleanedAnswers!C16,3)="B —"),"B","")) | M3: =IF(OR(CleanedAnswers!D16=$I3,LEFT(CleanedAnswers!D16,3)="A —"),"A",IF(OR(CleanedAnswers!D16=$J3,LEFT(CleanedAnswers!D16,3)="B —"),"B","")) | N3: =(K3="A")*Settings!$B$2+(L3="A")*Settings!$B$3+(M3="A")*Settings!$B$4 | O3: =(K3="B")*Settings!$B$2+(L3="B")*Settings!$B$3+(M3="B")*Settings!$B$4 | P3: =IF(N3+O3=0,"",IF(N3>O3,"A",IF(O3>N3,"B","Split"))) | Q3: =IF(P3="A",I3,IF(P3="B",J3,"")) | R3: =IF(P3="A",J3,IF(P3="B",I3,"")) | S3: =IF(Q3="","",INDEX($D$6:$D$15,MATCH(Q3,$A$6:$A$15,0))) | T3: =IF(R3="","",INDEX($D$6:$D$15,MATCH(R3,$A$6:$A$15,0))) | U3: =IF(OR(Q3="",NOT(ISNUMBER(S3)),NOT(ISNUMBER(T3))),0,IF(S3<T3+Settings!$B$7,MIN(T3,(T3-S3+Settings!$B$7)/2),0))
H4: Q12 | I4: Village character | J4: Shops & doctor | K4: =IF(OR(CleanedAnswers!B17=$I4,LEFT(CleanedAnswers!B17,3)="A —"),"A",IF(OR(CleanedAnswers!B17=$J4,LEFT(CleanedAnswers!B17,3)="B —"),"B","")) | L4: =IF(OR(CleanedAnswers!C17=$I4,LEFT(CleanedAnswers!C17,3)="A —"),"A",IF(OR(CleanedAnswers!C17=$J4,LEFT(CleanedAnswers!C17,3)="B —"),"B","")) | M4: =IF(OR(CleanedAnswers!D17=$I4,LEFT(CleanedAnswers!D17,3)="A —"),"A",IF(OR(CleanedAnswers!D17=$J4,LEFT(CleanedAnswers!D17,3)="B —"),"B","")) | N4: =(K4="A")*Settings!$B$2+(L4="A")*Settings!$B$3+(M4="A")*Settings!$B$4 | O4: =(K4="B")*Settings!$B$2+(L4="B")*Settings!$B$3+(M4="B")*Settings!$B$4 | P4: =IF(N4+O4=0,"",IF(N4>O4,"A",IF(O4>N4,"B","Split"))) | Q4: =IF(P4="A",I4,IF(P4="B",J4,"")) | R4: =IF(P4="A",J4,IF(P4="B",I4,"")) | S4: =IF(Q4="","",INDEX($D$6:$D$15,MATCH(Q4,$A$6:$A$15,0))) | T4: =IF(R4="","",INDEX($D$6:$D$15,MATCH(R4,$A$6:$A$15,0))) | U4: =IF(OR(Q4="",NOT(ISNUMBER(S4)),NOT(ISNUMBER(T4))),0,IF(S4<T4+Settings!$B$7,MIN(T4,(T4-S4+Settings!$B$7)/2),0))
A5: Final Normalized Weights | B5: Weight | C5: Net forced-choice correction (live) | D5: Survey weight (PriorityWeights K) | E5: Previous typed weight (pre 27 Oct link) | F5: Manual tweak (editable, e.g. 0.03 = +3 pts) | H5: Q13 | I5: Indian community | J5: Nature | K5: =IF(OR(CleanedAnswers!B18=$I5,LEFT(CleanedAnswers!B18,3)="A —"),"A",IF(OR(CleanedAnswers!B18=$J5,LEFT(CleanedAnswers!B18,3)="B —"),"B","")) | L5: =IF(OR(CleanedAnswers!C18=$I5,LEFT(CleanedAnswers!C18,3)="A —"),"A",IF(OR(CleanedAnswers!C18=$J5,LEFT(CleanedAnswers!C18,3)="B —"),"B","")) | M5: =IF(OR(CleanedAnswers!D18=$I5,LEFT(CleanedAnswers!D18,3)="A —"),"A",IF(OR(CleanedAnswers!D18=$J5,LEFT(CleanedAnswers!D18,3)="B —"),"B","")) | N5: =(K5="A")*Settings!$B$2+(L5="A")*Settings!$B$3+(M5="A")*Settings!$B$4 | O5: =(K5="B")*Settings!$B$2+(L5="B")*Settings!$B$3+(M5="B")*Settings!$B$4 | P5: =IF(N5+O5=0,"",IF(N5>O5,"A",IF(O5>N5,"B","Split"))) | Q5: =IF(P5="A",I5,IF(P5="B",J5,"")) | R5: =IF(P5="A",J5,IF(P5="B",I5,"")) | S5: =IF(Q5="","",INDEX($D$6:$D$15,MATCH(Q5,$A$6:$A$15,0))) | T5: =IF(R5="","",INDEX($D$6:$D$15,MATCH(R5,$A$6:$A$15,0))) | U5: =IF(OR(Q5="",NOT(ISNUMBER(S5)),NOT(ISNUMBER(T5))),0,IF(S5<T5+Settings!$B$7,MIN(T5,(T5-S5+Settings!$B$7)/2),0))
A6: Near family in GW | B6: =MAX(0,D6+C6+F6)/SUMPRODUCT((D$6:D$15+C$6:C$15+F$6:F$15>0)*(D$6:D$15+C$6:C$15+F$6:F$15)) | C6: =SUMIF($Q$2:$Q$5,A6,$U$2:$U$5)-SUMIF($R$2:$R$5,A6,$U$2:$U$5) | D6: =PriorityWeights!K3 | E6: 0.153 | F6: 0
A7: Nature | B7: =MAX(0,D7+C7+F7)/SUMPRODUCT((D$6:D$15+C$6:C$15+F$6:F$15>0)*(D$6:D$15+C$6:C$15+F$6:F$15)) | C7: =SUMIF($Q$2:$Q$5,A7,$U$2:$U$5)-SUMIF($R$2:$R$5,A7,$U$2:$U$5) | D7: =PriorityWeights!K2 | E7: 0.133 | F7: 0
A8: Hospital | B8: =MAX(0,D8+C8+F8)/SUMPRODUCT((D$6:D$15+C$6:C$15+F$6:F$15>0)*(D$6:D$15+C$6:C$15+F$6:F$15)) | C8: =SUMIF($Q$2:$Q$5,A8,$U$2:$U$5)-SUMIF($R$2:$R$5,A8,$U$2:$U$5) | D8: =PriorityWeights!K6 | E8: 0.133 | F8: 0
A9: Indian community | B9: =MAX(0,D9+C9+F9)/SUMPRODUCT((D$6:D$15+C$6:C$15+F$6:F$15>0)*(D$6:D$15+C$6:C$15+F$6:F$15)) | C9: =SUMIF($Q$2:$Q$5,A9,$U$2:$U$5)-SUMIF($R$2:$R$5,A9,$U$2:$U$5) | D9: =PriorityWeights!K4 | E9: 0.117 | F9: 0
A10: Shops & doctor | B10: =MAX(0,D10+C10+F10)/SUMPRODUCT((D$6:D$15+C$6:C$15+F$6:F$15>0)*(D$6:D$15+C$6:C$15+F$6:F$15)) | C10: =SUMIF($Q$2:$Q$5,A10,$U$2:$U$5)-SUMIF($R$2:$R$5,A10,$U$2:$U$5) | D10: =PriorityWeights!K8 | E10: 0.108 | F10: 0
A11: Village character | B11: =MAX(0,D11+C11+F11)/SUMPRODUCT((D$6:D$15+C$6:C$15+F$6:F$15>0)*(D$6:D$15+C$6:C$15+F$6:F$15)) | C11: =SUMIF($Q$2:$Q$5,A11,$U$2:$U$5)-SUMIF($R$2:$R$5,A11,$U$2:$U$5) | D11: =PriorityWeights!K9 | E11: 0.088 | F11: 0
A12: Train/bus | B12: =MAX(0,D12+C12+F12)/SUMPRODUCT((D$6:D$15+C$6:C$15+F$6:F$15>0)*(D$6:D$15+C$6:C$15+F$6:F$15)) | C12: =SUMIF($Q$2:$Q$5,A12,$U$2:$U$5)-SUMIF($R$2:$R$5,A12,$U$2:$U$5) | D12: =PriorityWeights!K7 | E12: 0.081 | F12: 0
A13: Price | B13: =MAX(0,D13+C13+F13)/SUMPRODUCT((D$6:D$15+C$6:C$15+F$6:F$15>0)*(D$6:D$15+C$6:C$15+F$6:F$15)) | C13: =SUMIF($Q$2:$Q$5,A13,$U$2:$U$5)-SUMIF($R$2:$R$5,A13,$U$2:$U$5) | D13: =PriorityWeights!K10 | E13: 0.081 | F13: 0
A14: Beach | B14: =MAX(0,D14+C14+F14)/SUMPRODUCT((D$6:D$15+C$6:C$15+F$6:F$15>0)*(D$6:D$15+C$6:C$15+F$6:F$15)) | C14: =SUMIF($Q$2:$Q$5,A14,$U$2:$U$5)-SUMIF($R$2:$R$5,A14,$U$2:$U$5) | D14: =PriorityWeights!K5 | E14: 0.061 | F14: 0
A15: City trip | B15: =MAX(0,D15+C15+F15)/SUMPRODUCT((D$6:D$15+C$6:C$15+F$6:F$15>0)*(D$6:D$15+C$6:C$15+F$6:F$15)) | C15: =SUMIF($Q$2:$Q$5,A15,$U$2:$U$5)-SUMIF($R$2:$R$5,A15,$U$2:$U$5) | D15: =PriorityWeights!K11 | E15: 0.045 | F15: 0
A16: Total | B16: =SUM(B6:B15)
A18: Note (27 Oct 2026): B = survey weight (D) + live trade-off correction (C, rule from survey blueprint: winner moved 2 pts ahead of loser) + manual tweak (F), floored at 0 and renormalised. E = old typed weights.

Sheet SuburbScorecard
A1: Location | B1: Region | C1: Shortlist Status | D1: Parents Inland/Bush Fit (P) | E1: My Coastal-Nature Fit (Y) | F1: Primary Investigation Lens | G1: Published House Price | H1: Price Basis | I1: Price + Est. 6% Costs | J1: Drive to GW (min) | K1: Drive to 24-Hr Public ED (min) | L1: Hard Filter Status | M1: Score: Near family in GW | N1: Score: Nature | O1: Score: Hospital | P1: Score: Indian community | Q1: Score: Shops & doctor | R1: Score: Village character | S1: Score: Train/bus | T1: Score: Price | U1: Score: Beach | V1: Score: City trip | W1: Scores Entered | X1: Weighted Score (0-10) | Y1: Rank (Passing Only) | Z1: Healthcare & ABS Verification Notes | AA1: Legacy import text (frozen 27 Oct 2026; not used by any formula — edit columns A–H and Z instead) | AB1: Train Option (Yes/No) | AC1: Train Station / Basis | AD1: ED Used for Drive Time (K) | AE1: Budget cap — purchase price | AF1: Budget basis | AG1: Price evidence type | AH1: Price evidence date | AI1: Budget result | AJ1: Budget note | AK1: ABS SAL code (2021) | AL1: Population (ABS 2021) | AM1: Median age | AN1: % aged 65+ | AO1: % born overseas (of all people) | AP1: % birthplace not stated | AQ1: % born in India | AR1: % Indian ancestry | AS1: % Hinduism | AT1: % Sikhism | AU1: % other language at home | AV1: Top 3 languages other than English (% of people) | AW1: Demography source and caveats | AX1: Community comparison band (display-only) | AY1: Drive to nearest Indian grocery (min; 10:00 weekday, top of range) | AZ1: Drive to nearest Hindu temple (min; 10:00 weekday, top of range) | BA1: Drive to nearest church (min; 10:00 weekday, top of range) | BB1: Community drive basis and evidence (Checked / Estimate / Needs verification) | BF1: Slope/stairs risk (display-only, Estimate; feeds nothing)
A2: Blackburn | B2: East Melbourne | C2: Active Shortlist | D2: Medium (Leafy streets) | E2: Low (Inland) | F2: Leafy daily living vs housing cost | G2: 1600000 | H2: Sale median, rolling 12m (OnTheHouse); unit $820k | I2: {=IF(ISNUMBER(G2:G90), IF(G2:G90>0, G2:G90 * (1 + Settings!$B$6), ""), "")} | J2: 11 | K2: 7 | L2: Active — needs data | O2: =IF(K2="","",ROUND(MAX(0,10*(1-K2/Filters!$B$5)),1)) | W2: =IF(M2="",0,COUNT(M2:V2)) | X2: =IF(W2<10,"",M2*ForcedChoiceCorrections!$B$6+N2*ForcedChoiceCorrections!$B$7+O2*ForcedChoiceCorrections!$B$8+P2*ForcedChoiceCorrections!$B$9+Q2*ForcedChoiceCorrections!$B$10+R2*ForcedChoiceCorrections!$B$11+S2*ForcedChoiceCorrections!$B$12+T2*ForcedChoiceCorrections!$B$13+U2*ForcedChoiceCorrections!$B$14+V2*ForcedChoiceCorrections!$B$15) | Y2: =IF(AND(ISNUMBER(SEARCH("pass",L2)),ISNUMBER(X2)),COUNTIFS(L$2:L$90,"*pass*",X$2:X$90,">"&X2)+1,"") | Z2: ABS 2021: 32.4% overseas-born, 31.6% non-Eng HH. Station/ED journeys unverified. | AA2: 1. Blackburn | East Melbourne | Active Shortlist | P: Medium (Leafy streets) | Y: Low (Inland) | Lens: Leafy daily living vs housing cost | Price: 1600000 | Basis: Sale median, rolling 12m (OnTheHouse); unit $820k | Note: ABS 2021: 32.4% overseas-born, 31.6% non-Eng HH. Station/ED journeys unverified. | AB2: Yes | AC2: Blackburn station, Lilydale line (recall; verify) | AD2: Box Hill Hospital ED | AE2: 1500000 | AF2: Maximum purchase price, excluding transaction and moving costs | AG2: Suburb median | AH2: 26 Oct 2026 | AI2: Needs data | AJ2: House median $1.60M (OnTheHouse) exceeds $1.5M cap, but unit/villa median is $820k. Awaiting documented search for suitable single-level homes/units under $1.5M. | AK2: SAL20252 | AL2: 14478 | AM2: 41 | AN2: 0.185 | AO2: 0.324 | AP2: 0.03 | AQ2: 0.043 | AR2: 0.048 | AS2: 0.035 | AT2: 0.011 | AU2: 0.279 | AV2: Mandarin 10.4%; Cantonese 3.2%; Hindi 1.3% | AW2: ABS 2021 Census General Community Profile DataPack, Suburbs and Localities (SAL), Victoria (tables G01, G02, G08, G09, G13, G14); downloaded 27 Oct 2026 from abs.gov.au. Place of usual residence. | AX2: =IF(AU2="","",IF(OR(AU2>=0.5,AQ2>=0.08),"High",IF(OR(AU2>=0.3,AQ2>=0.04),"Medium","Low")))
A3: Ringwood | B3: East Melbourne | C3: Active Shortlist | D3: Medium-High (Foothills gateway) | E3: Low (Inland) | F3: Rail, services & access to greener surroundings | G3: 1045000 | H3: Sale median, rolling 12m (OnTheHouse); unit $650k | I3: 1107700 | J3: 12 | K3: 5 | L3: Active — provisional pass | M3: =IF(J3="","",ROUND(MAX(0,10*(1-J3/Filters!$B$4)),1)) | N3: 4 | O3: =IF(K3="","",ROUND(MAX(0,10*(1-K3/Filters!$B$5)),1)) | P3: 6 | Q3: 10 | R3: 3 | S3: 9 | T3: =IF(G3="","",ROUND(MAX(0,MIN(10,10*(Filters!$B$2-G3)/(Filters!$B$2-500000))),1)) | U3: 0 | V3: 7 | W3: =IF(M3="",0,COUNT(M3:V3)) | X3: =IF(W3<10,"",M3*ForcedChoiceCorrections!$B$6+N3*ForcedChoiceCorrections!$B$7+O3*ForcedChoiceCorrections!$B$8+P3*ForcedChoiceCorrections!$B$9+Q3*ForcedChoiceCorrections!$B$10+R3*ForcedChoiceCorrections!$B$11+S3*ForcedChoiceCorrections!$B$12+T3*ForcedChoiceCorrections!$B$13+U3*ForcedChoiceCorrections!$B$14+V3*ForcedChoiceCorrections!$B$15) | Y3: =IF(AND(ISNUMBER(SEARCH("pass",L3)),ISNUMBER(X3)),COUNTIFS(L$2:L$90,"*pass*",X$2:X$90,">"&X3)+1,"") | Z3: ABS 2021: 35.7% overseas-born, 33.3% non-Eng HH. Belgrave/Lilydale rail; Maroondah Hospital ED nearby (verify drive). | SCORES 27 Oct 2026: M (near family) and T (price) are formulas from J and G; O from K. N, P, Q, R, S, U, V are ESTIMATES (Claude, general knowledge, not site-checked); S also rests on train Yes/No marked 'verify'. | CHECKED 27 Oct 2026, source run C1 (suburb level; Wikipedia, Victorian Places, ABS 2021 GCP DataPack). Pop 19,144; 20 km E of CBD [Wikipedia Ringwood] (23 km per Victorian Places). Train: major hub; Ringwood station is the junction of the Lilydale and Belgrave lines; Heatherdale station also in the suburb; many bus routes [Wikipedia]; S 9 consistent. Shops: Eastland Shopping Centre (opened 1967, redeveloped) and Ringwood Town Square [Wikipedia; Victorian Places]; Q 10 consistent. Nature: Ringwood Lake 8.5 ha park with a bushland walking circuit; Jubilee Park [Wikipedia; Victorian Places]; N 4 consistent. Village: commercial centre on a highway with bypass routes [Victorian Places]; R 3 consistent. Indian community: India-born 3.2% (618), Indian ancestry 3.7%, Hinduism 2.7%, Sikhism 0.7% [ABS 2021 GCP SAL22174]; P 6 generous next to Berwick 7 at 6.1% (4-5 arguable). City trip: 20 km by train; journey time not stated; V 7 estimate. NOT checked: GPs, journey time. Scores unchanged. | AA3: 2. Ringwood | East Melbourne | Active Shortlist | P: Medium-High (Foothills gateway) | Y: Low (Inland) | Lens: Rail, services & access to greener surroundings | Price: 1045000 | Basis: Sale median, rolling 12m (OnTheHouse); unit $650k | Note: ABS 2021: 35.7% overseas-born, 33.3% non-Eng HH. Belgrave/Lilydale rail; Maroondah Hospital ED nearby (verify drive). | AB3: Yes | AC3: Ringwood station, Lilydale/Belgrave lines (recall; verify) | AD3: Maroondah Hospital ED | AE3: 1500000 | AF3: Maximum purchase price, excluding transaction and moving costs | AG3: Suburb median | AH3: 26 Oct 2026 | AI3: Pass | AJ3: Published house price ($1,045,000) is under $1.5M cap. | AK3: SAL22174 | AL3: 19144 | AM3: 38 | AN3: 0.172 | AO3: 0.357 | AP3: 0.034 | AQ3: 0.032 | AR3: 0.037 | AS3: 0.027 | AT3: 0.007 | AU3: 0.316 | AV3: Mandarin 9.0%; Cantonese 3.2%; Persian 1.5% | AW3: ABS 2021 Census General Community Profile DataPack, Suburbs and Localities (SAL), Victoria (tables G01, G02, G08, G09, G13, G14); downloaded 27 Oct 2026 from abs.gov.au. Place of usual residence. | AX3: =IF(AU3="","",IF(OR(AU3>=0.5,AQ3>=0.08),"High",IF(OR(AU3>=0.3,AQ3>=0.04),"Medium","Low")))
A4: Heidelberg | B4: North-East Melbourne | C4: Active Shortlist | D4: Medium (Yarra parkland) | E4: Low (Inland) | F4: Healthcare-led established suburb option | G4: 1452000 | H4: Sale median, rolling 12m (35 sales); unit $700k | I4: 1539120 | J4: 25 | K4: 4 | L4: Active — provisional pass | M4: =IF(J4="","",ROUND(MAX(0,10*(1-J4/Filters!$B$4)),1)) | N4: 6 | O4: =IF(K4="","",ROUND(MAX(0,10*(1-K4/Filters!$B$5)),1)) | P4: 5 | Q4: 8 | R4: 4 | S4: 8 | T4: =IF(G4="","",ROUND(MAX(0,MIN(10,10*(Filters!$B$2-G4)/(Filters!$B$2-500000))),1)) | U4: 0 | V4: 8 | W4: =IF(M4="",0,COUNT(M4:V4)) | X4: =IF(W4<10,"",M4*ForcedChoiceCorrections!$B$6+N4*ForcedChoiceCorrections!$B$7+O4*ForcedChoiceCorrections!$B$8+P4*ForcedChoiceCorrections!$B$9+Q4*ForcedChoiceCorrections!$B$10+R4*ForcedChoiceCorrections!$B$11+S4*ForcedChoiceCorrections!$B$12+T4*ForcedChoiceCorrections!$B$13+U4*ForcedChoiceCorrections!$B$14+V4*ForcedChoiceCorrections!$B$15) | Y4: =IF(AND(ISNUMBER(SEARCH("pass",L4)),ISNUMBER(X4)),COUNTIFS(L$2:L$90,"*pass*",X$2:X$90,">"&X4)+1,"") | Z4: ABS 2021: 28.1% overseas-born, 28.4% non-Eng HH. Austin Hospital precinct; verify residential pocket & gradients. | SCORES 27 Oct 2026: M (near family) and T (price) are formulas from J and G; O from K. N, P, Q, R, S, U, V are ESTIMATES (Claude, general knowledge, not site-checked); S also rests on train Yes/No marked 'verify'. | CHECKED 27 Oct 2026, source run C1 (suburb level; Wikipedia, Victorian Places, ABS 2021 GCP DataPack). Pop 7,360; 11 km NE of CBD, City of Banyule [Wikipedia Heidelberg]. Hospital: Austin Hospital (with Mercy Hospital for Women) is in the suburb [Wikipedia]. Shops: Heidelberg Central (Burgundy St) 'over 230 retail and professional businesses'; Warringal Shopping Centre [Wikipedia]; Q 8 consistent (9 arguable). Train: station at the west end of Burgundy St [Victorian Places]; Hurstbridge line [AC]; S 8 consistent. Nature: eastern flank is the Yarra Flats and Warringal wetlands [Victorian Places]; N 6 consistent. Village: old Waringal village core (St John's 1849, Old England Hotel 1848) but now 'a mature suburb' dominated by the hospital [Victorian Places]; R 4 consistent. Indian community: India-born 3.0%, Indian ancestry 3.5%, Hinduism 2.9% [ABS 2021 GCP SAL21167]; P 5 consistent. City trip: 11 km by train; V 8 consistent. NOT checked: supermarket name, GPs, journey time. Victorian Places gives '2 km', an error; Wikipedia 11 km used. Scores unchanged. | AA4: 3. Heidelberg | North-East Melbourne | Active Shortlist | P: Medium (Yarra parkland) | Y: Low (Inland) | Lens: Healthcare-led established suburb option | Price: 1452000 | Basis: Sale median, rolling 12m (35 sales); unit $700k | Note: ABS 2021: 28.1% overseas-born, 28.4% non-Eng HH. Austin Hospital precinct; verify residential pocket & gradients. | AB4: Yes | AC4: Heidelberg station, Hurstbridge line (recall; verify) | AD4: Austin Hospital ED | AE4: 1500000 | AF4: Maximum purchase price, excluding transaction and moving costs | AG4: Suburb median | AH4: 26 Oct 2026 | AI4: Pass | AJ4: House median $1.452M (35 sales) is under $1.5M cap. Passes GW drive (25m) and ED drive (4m). | AK4: SAL21167 | AL4: 7360 | AM4: 39 | AN4: 0.179 | AO4: 0.281 | AP4: 0.042 | AQ4: 0.03 | AR4: 0.035 | AS4: 0.029 | AT4: 0.002 | AU4: 0.237 | AV4: Italian 2.7%; Mandarin 2.7%; Greek 1.8% | AW4: ABS 2021 Census General Community Profile DataPack, Suburbs and Localities (SAL), Victoria (tables G01, G02, G08, G09, G13, G14); downloaded 27 Oct 2026 from abs.gov.au. Place of usual residence. | AX4: =IF(AU4="","",IF(OR(AU4>=0.5,AQ4>=0.08),"High",IF(OR(AU4>=0.3,AQ4>=0.04),"Medium","Low")))
A5: Eltham | B5: North-East Melbourne | C5: Active Shortlist | D5: High (Bushland/trees) | E5: Low (Inland) | F5: Green/scenic lifestyle hypothesis | G5: 1273000 | H5: Sale median, rolling 12m (195 sales); unit $805k | I5: 1349380 | J5: 26 | K5: 16 | L5: Active — provisional pass | M5: =IF(J5="","",ROUND(MAX(0,10*(1-J5/Filters!$B$4)),1)) | N5: 8 | O5: =IF(K5="","",ROUND(MAX(0,10*(1-K5/Filters!$B$5)),1)) | P5: 3 | Q5: 8 | R5: 7 | S5: 8 | T5: =IF(G5="","",ROUND(MAX(0,MIN(10,10*(Filters!$B$2-G5)/(Filters!$B$2-500000))),1)) | U5: 0 | V5: 7 | W5: =IF(M5="",0,COUNT(M5:V5)) | X5: =IF(W5<10,"",M5*ForcedChoiceCorrections!$B$6+N5*ForcedChoiceCorrections!$B$7+O5*ForcedChoiceCorrections!$B$8+P5*ForcedChoiceCorrections!$B$9+Q5*ForcedChoiceCorrections!$B$10+R5*ForcedChoiceCorrections!$B$11+S5*ForcedChoiceCorrections!$B$12+T5*ForcedChoiceCorrections!$B$13+U5*ForcedChoiceCorrections!$B$14+V5*ForcedChoiceCorrections!$B$15) | Y5: =IF(AND(ISNUMBER(SEARCH("pass",L5)),ISNUMBER(X5)),COUNTIFS(L$2:L$90,"*pass*",X$2:X$90,">"&X5)+1,"") | Z5: ABS 2021: 18.5% overseas-born, 14.0% non-Eng HH. Hurstbridge line; verify ED & GW drive times. | SCORES 27 Oct 2026: M (near family) and T (price) are formulas from J and G; O from K. N, P, Q, R, S, U, V are ESTIMATES (Claude, general knowledge, not site-checked); S also rests on train Yes/No marked 'verify'. | CHECKED 27 Oct 2026, source run C1 (suburb level; Wikipedia, Victorian Places, ABS 2021 GCP DataPack). Pop 18,847; 20 km NE of CBD, Shire of Nillumbik [Wikipedia Eltham]. Nature: green wedge leaves 'extensive areas undeveloped within and to three sides of the suburb'; Barak Bushlands, Laughing Waters bushland (riparian and open forest), Diamond Creek Trail, Maroondah Aqueduct Trail [Wikipedia]; N 8 consistent. Village: central shopping strip on Main Road, Sunday farmers' market, Montsalvat artists' colony, mud-brick heritage (Alistair Knox) [Wikipedia]; R 7 consistent. Train: Eltham station, Hurstbridge line; major bus interchange (SmartBus 902 etc.) [Wikipedia]; S 8 consistent. Shops: supermarket not named; Q 8 estimate. Indian community: India-born 0.7%, Hinduism 0.6% [ABS 2021 GCP SAL20865]; P 3 generous (2 arguable). City trip: 20 km by train; V 7 estimate. NOT checked: GPs, supermarket, journey time. Scores unchanged. | AA5: 4. Eltham | North-East Melbourne | Active Shortlist | P: High (Bushland/trees) | Y: Low (Inland) | Lens: Green/scenic lifestyle hypothesis | Price: 1273000 | Basis: Sale median, rolling 12m (195 sales); unit $805k | Note: ABS 2021: 18.5% overseas-born, 14.0% non-Eng HH. Hurstbridge line; verify ED & GW drive times. | AB5: Yes | AC5: Eltham station, Hurstbridge line (recall; verify) | AD5: Austin Hospital ED | AE5: 1500000 | AF5: Maximum purchase price, excluding transaction and moving costs | AG5: Suburb median | AH5: 26 Oct 2026 | AI5: Pass | AJ5: House median $1.273M (195 sales) is under $1.5M cap. Passes GW drive (26m) and ED drive (16m). | AK5: SAL20865 | AL5: 18847 | AM5: 43 | AN5: 0.185 | AO5: 0.185 | AP5: 0.024 | AQ5: 0.007 | AR5: 0.013 | AS5: 0.006 | AT5: 0.001 | AU5: 0.105 | AV5: Mandarin 1.6%; Italian 1.0%; Greek 0.9% | AW5: ABS 2021 Census General Community Profile DataPack, Suburbs and Localities (SAL), Victoria (tables G01, G02, G08, G09, G13, G14); downloaded 27 Oct 2026 from abs.gov.au. Place of usual residence. | AX5: =IF(AU5="","",IF(OR(AU5>=0.5,AQ5>=0.08),"High",IF(OR(AU5>=0.3,AQ5>=0.04),"Medium","Low")))
A6: Upper Ferntree Gully | B6: East / Foothills | C6: Active Shortlist | D6: High (Foothills/forest) | E6: Low (Inland) | F6: Forest/foothills lifestyle with hospital & rail access | G6: 872133 | H6: AVM estimate (30 Sep 2026), NOT a verified sale median | I6: 924460.98 | J6: 16 | K6: 2 | L6: Active — provisional pass | M6: =IF(J6="","",ROUND(MAX(0,10*(1-J6/Filters!$B$4)),1)) | N6: 8 | O6: =IF(K6="","",ROUND(MAX(0,10*(1-K6/Filters!$B$5)),1)) | P6: 5 | Q6: 6 | R6: 5 | S6: 7 | T6: =IF(G6="","",ROUND(MAX(0,MIN(10,10*(Filters!$B$2-G6)/(Filters!$B$2-500000))),1)) | U6: 0 | V6: 6 | W6: =IF(M6="",0,COUNT(M6:V6)) | X6: =IF(W6<10,"",M6*ForcedChoiceCorrections!$B$6+N6*ForcedChoiceCorrections!$B$7+O6*ForcedChoiceCorrections!$B$8+P6*ForcedChoiceCorrections!$B$9+Q6*ForcedChoiceCorrections!$B$10+R6*ForcedChoiceCorrections!$B$11+S6*ForcedChoiceCorrections!$B$12+T6*ForcedChoiceCorrections!$B$13+U6*ForcedChoiceCorrections!$B$14+V6*ForcedChoiceCorrections!$B$15) | Y6: =IF(AND(ISNUMBER(SEARCH("pass",L6)),ISNUMBER(X6)),COUNTIFS(L$2:L$90,"*pass*",X$2:X$90,">"&X6)+1,"") | Z6: ABS 2021: 19.2% overseas-born, 12.2% non-Eng HH. Belgrave line; 10-min walk/bus 732 to Angliss Hospital (verify 24-hr ED status & drive). 27 Oct 2026: OnTheHouse gives the same house AVM ($872,133) for Upper Ferntree Gully and Ferntree Gully — likely postcode-level, weak. | SCORES 27 Oct 2026: M (near family) and T (price) are formulas from J and G; O from K. N, P, Q, R, S, U, V are ESTIMATES (Claude, general knowledge, not site-checked); S also rests on train Yes/No marked 'verify'. Price = postcode-level AVM shared with FTG. | CHECKED 27 Oct 2026, source run C1 (suburb level; Wikipedia, Victorian Places, ABS 2021 GCP DataPack). Pop 3,417; 32 km E of CBD [Wikipedia Upper Ferntree Gully]. Nature: Ferntree Gully Park (Dandenong Ranges National Park) incl. the '1,000 steps' Kokoda walk; Ferny Creek reserves [Wikipedia]; N 8 consistent. Hospital: Angliss Hospital is in the suburb, with medical consulting rooms nearby [Wikipedia]. Shops: 'limited retail outlets (mainly food, hairdressing, banking, chemist, post office)' along Burwood Hwy; Ferntree Plaza the largest centre [Wikipedia]; Q 6 consistent. Village: highway strip with used-car yards [Wikipedia]; R 5 consistent. Train: station on the Belgrave line [AC]; S 7 not re-checked. Indian community: India-born 1.0%, Hinduism 0.3% [ABS 2021 GCP SAL22614]; P 5 not supported (2 arguable). City trip: 32 km by train; V 6 estimate. NOT checked: GPs by name, supermarket, journey time. Scores unchanged. | AA6: 5. Upper Ferntree Gully | East / Foothills | Active Shortlist | P: High (Foothills/forest) | Y: Low (Inland) | Lens: Forest/foothills lifestyle with hospital & rail access | Price: 872133 | Basis: AVM estimate (30 Sep 2026), NOT a verified sale median | Note: ABS 2021: 19.2% overseas-born, 12.2% non-Eng HH. Belgrave line; 10-min walk/bus 732 to Angliss Hospital (verify 24-hr ED status & drive). | AB6: Yes | AC6: Upper Ferntree Gully station, Belgrave line (per sheet note) | AD6: Angliss Hospital ED (24-hr status still to verify) | AE6: 1500000 | AF6: Maximum purchase price, excluding transaction and moving costs | AG6: Suburb median | AH6: 26 Oct 2026 | AI6: Pass | AJ6: Published house price ($872,133) is under $1.5M cap. | AK6: SAL22614 | AL6: 3417 | AM6: 41 | AN6: 0.184 | AO6: 0.192 | AP6: 0.036 | AQ6: 0.01 | AR6: 0.014 | AS6: 0.003 | AT6: 0 | AU6: 0.083 | AV6: German 1.2%; Greek 0.8%; Mandarin 0.7% | AW6: ABS 2021 Census General Community Profile DataPack, Suburbs and Localities (SAL), Victoria (tables G01, G02, G08, G09, G13, G14); downloaded 27 Oct 2026 from abs.gov.au. Place of usual residence. | AX6: =IF(AU6="","",IF(OR(AU6>=0.5,AQ6>=0.08),"High",IF(OR(AU6>=0.3,AQ6>=0.04),"Medium","Low")))
A7: Glen Waverley | B7: East Melbourne | C7: Active Shortlist | D7: Low-Medium (Suburban) | E7: Low (Inland) | F7: Current stay baseline — multicultural convenience | G7: 1675000 | H7: Sale median, all bedrooms, 12 months (442 sales); unit $930k | I7: 1775500 | J7: 0 | K7: 13 | L7: Active — needs data | O7: =IF(K7="","",ROUND(MAX(0,10*(1-K7/Filters!$B$5)),1)) | W7: =IF(M7="",0,COUNT(M7:V7)) | X7: =IF(W7<10,"",M7*ForcedChoiceCorrections!$B$6+N7*ForcedChoiceCorrections!$B$7+O7*ForcedChoiceCorrections!$B$8+P7*ForcedChoiceCorrections!$B$9+Q7*ForcedChoiceCorrections!$B$10+R7*ForcedChoiceCorrections!$B$11+S7*ForcedChoiceCorrections!$B$12+T7*ForcedChoiceCorrections!$B$13+U7*ForcedChoiceCorrections!$B$14+V7*ForcedChoiceCorrections!$B$15) | Y7: =IF(AND(ISNUMBER(SEARCH("pass",L7)),ISNUMBER(X7)),COUNTIFS(L$2:L$90,"*pass*",X$2:X$90,">"&X7)+1,"") | Z7: ABS 2021: 58.7% overseas-born, 63.0% non-Eng HH. Baseline benchmark for family proximity. C 29 Oct 2026: G7 $1,675,000 and H7 442 sales from the realestate.com.au Glen Waverley suburb profile (house median, all bedrooms, past 12 months; figure read by the user 29 Oct 2026), CHECKED. Replaces $1,763,500 (454 sales; no source named). Cross-checks: REIV $1,750,000 (1 Jul 2025-30 Jun 2026, via the 5 Northam St Statement of Information); Jellis Craig $1.68m (rolling 12 months, read 28 Oct 2026); realestate.com.au 4-bed median $1,603,000 (Oct 2025-Sep 2026, 175 sales). | AA7: 6. Glen Waverley | East Melbourne | Active Shortlist | P: Low-Medium (Suburban) | Y: Low (Inland) | Lens: Current stay baseline — multicultural convenience | Price: 1763500 | Basis: Sale median, rolling 12m (454 sales); unit $930k | Note: ABS 2021: 58.7% overseas-born, 63.0% non-Eng HH. Baseline benchmark for family proximity. | AB7: Yes | AC7: Glen Waverley station, Glen Waverley line (recall; verify) | AD7: Monash Medical Centre Clayton ED | AE7: 1500000 | AF7: Maximum purchase price, excluding transaction and moving costs | AG7: Suburb median | AH7: 29 Oct 2026 | AI7: Needs data | AJ7: House median $1.68M (442 sales, realestate.com.au) exceeds $1.5M cap; unit median $930k. Awaiting documented search for suitable single-level homes/units under $1.5M. | AK7: SAL21013 | AL7: 42642 | AM7: 40 | AN7: 0.198 | AO7: 0.587 | AP7: 0.033 | AQ7: 0.08 | AR7: 0.096 | AS7: 0.098 | AT7: 0.009 | AU7: 0.608 | AV7: Mandarin 23.3%; Cantonese 8.0%; Sinhalese 4.0% | AW7: ABS 2021 Census General Community Profile DataPack, Suburbs and Localities (SAL), Victoria (tables G01, G02, G08, G09, G13, G14); downloaded 27 Oct 2026 from abs.gov.au. Place of usual residence. | AX7: =IF(AU7="","",IF(OR(AU7>=0.5,AQ7>=0.08),"High",IF(OR(AU7>=0.3,AQ7>=0.04),"Medium","Low")))
A8: Warrandyte | B8: North-East / Yarra | C8: Active Shortlist | D8: High (River & state park) | E8: Low (River, non-coastal) | F8: River-and-bush living within metro boundary | G8: 1348901 | H8: AVM estimate (30 Sep 2026), NOT a verified sale median; unit $824,796; 84 sales in last 12m (OnTheHouse/Cotality, read 27 Oct 2026) | I8: =G8*(1+Settings!$B$6) | J8: 20 | K8: 14 | L8: Active — provisional pass | M8: =IF(J8="","",ROUND(MAX(0,10*(1-J8/Filters!$B$4)),1)) | N8: 9 | O8: =IF(K8="","",ROUND(MAX(0,10*(1-K8/Filters!$B$5)),1)) | P8: 3 | Q8: 6 | R8: 8 | S8: 3 | T8: =IF(G8="","",ROUND(MAX(0,MIN(10,10*(Filters!$B$2-G8)/(Filters!$B$2-500000))),1)) | U8: 0 | V8: 4 | W8: =IF(M8="",0,COUNT(M8:V8)) | X8: =IF(W8<10,"",M8*ForcedChoiceCorrections!$B$6+N8*ForcedChoiceCorrections!$B$7+O8*ForcedChoiceCorrections!$B$8+P8*ForcedChoiceCorrections!$B$9+Q8*ForcedChoiceCorrections!$B$10+R8*ForcedChoiceCorrections!$B$11+S8*ForcedChoiceCorrections!$B$12+T8*ForcedChoiceCorrections!$B$13+U8*ForcedChoiceCorrections!$B$14+V8*ForcedChoiceCorrections!$B$15) | Y8: =IF(AND(ISNUMBER(SEARCH("pass",L8)),ISNUMBER(X8)),COUNTIFS(L$2:L$90,"*pass*",X$2:X$90,">"&X8)+1,"") | Z8: ABS 2021: 17.7% aged 65+, 17.0% non-Eng HH. Direct city bus 906; no local rail; check fire overlay & ED drive. 27 Oct 2026 research pass: drive times/ED and/or AVM price added; L re-evaluated. | SCORES 27 Oct 2026: M (near family) and T (price) are formulas from J and G; O from K. N, P, Q, R, S, U, V are ESTIMATES (Claude, general knowledge, not site-checked); S also rests on train Yes/No marked 'verify'. | CHECKED 27 Oct 2026, source run C1 (suburb level; Wikipedia, Victorian Places, ABS 2021 GCP DataPack). Pop 5,541; 24 km NE of CBD on the Yarra River; town 'nestled into a gorge on the river' [Wikipedia Warrandyte]. Nature: Warrandyte State Park (Pound Bend, Fourth Hill, Black Flat, Mount Lofty), river swimming, canoeing, bushwalking, many reserves incl. Currawong Bush Park [Wikipedia]; N 9 consistent. Village: surviving colonial-era buildings, shops on Yarra St near the bridge, Mechanics' Institute arts community [Wikipedia]; R 8 consistent. Shops: Goldfields Shopping Centre plus Yarra St shops [Wikipedia]; supermarket not named; Q 6 estimate. Train: no station in either source; S 3 consistent (bus 906 not checked). Two community-run micro-retirement villages [Wikipedia]. Indian community: India-born 0.7%, Hinduism 0.7% [ABS 2021 GCP SAL22702]; P 3 generous (2 arguable). City trip: 24 km but no rail; V 4 estimate. NOT checked: GPs, bus, journey time, bushfire overlay. Scores unchanged. | AA8: 7. Warrandyte | North-East / Yarra | Active Shortlist | P: High (River & state park) | Y: Low (River, non-coastal) | Lens: River-and-bush living within metro boundary | Price: [Blank] | Basis: Not verified in report | Note: ABS 2021: 17.7% aged 65+, 17.0% non-Eng HH. Direct city bus 906; no local rail; check fire overlay & ED drive. | AB8: No | AC8: No rail; bus 906 (per sheet note) | AD8: Maroondah Hospital ED | AE8: 1500000 | AF8: Maximum purchase price, excluding transaction and moving costs | AG8: AVM estimate | AH8: 27 Oct 2026 | AI8: Pass | AJ8: AVM house value ($1,348,901) is under $1.5M cap. Not a sale median. | AK8: SAL22702 | AL8: 5541 | AM8: 45 | AN8: 0.176 | AO8: 0.202 | AP8: 0.024 | AQ8: 0.007 | AR8: 0.015 | AS8: 0.007 | AT8: 0.004 | AU8: 0.13 | AV8: Mandarin 2.9%; Greek 1.7%; Italian 1.6% | AW8: ABS 2021 Census General Community Profile DataPack, Suburbs and Localities (SAL), Victoria (tables G01, G02, G08, G09, G13, G14); downloaded 27 Oct 2026 from abs.gov.au. Place of usual residence. | AX8: =IF(AU8="","",IF(OR(AU8>=0.5,AQ8>=0.08),"High",IF(OR(AU8>=0.3,AQ8>=0.04),"Medium","Low")))
A9: Diamond Creek | B9: North-East Fringe | C9: Active Shortlist | D9: High (Green wedge & trail) | E9: Low (Inland) | F9: Practical metro nature compromise with rail | G9: 885000 | H9: 3-bed house median $885k; 4-bed $1,240k (Domain) | I9: 938100 | J9: 33 | K9: 19 | L9: Active — provisional pass | M9: =IF(J9="","",ROUND(MAX(0,10*(1-J9/Filters!$B$4)),1)) | N9: 7 | O9: =IF(K9="","",ROUND(MAX(0,10*(1-K9/Filters!$B$5)),1)) | P9: 2 | Q9: 7 | R9: 6 | S9: 7 | T9: =IF(G9="","",ROUND(MAX(0,MIN(10,10*(Filters!$B$2-G9)/(Filters!$B$2-500000))),1)) | U9: 0 | V9: 6 | W9: =IF(M9="",0,COUNT(M9:V9)) | X9: =IF(W9<10,"",M9*ForcedChoiceCorrections!$B$6+N9*ForcedChoiceCorrections!$B$7+O9*ForcedChoiceCorrections!$B$8+P9*ForcedChoiceCorrections!$B$9+Q9*ForcedChoiceCorrections!$B$10+R9*ForcedChoiceCorrections!$B$11+S9*ForcedChoiceCorrections!$B$12+T9*ForcedChoiceCorrections!$B$13+U9*ForcedChoiceCorrections!$B$14+V9*ForcedChoiceCorrections!$B$15) | Y9: =IF(AND(ISNUMBER(SEARCH("pass",L9)),ISNUMBER(X9)),COUNTIFS(L$2:L$90,"*pass*",X$2:X$90,">"&X9)+1,"") | Z9: ABS 2021: 13.1% aged 65+, 12.2% non-Eng HH. Hurstbridge line station & trail; verify ED & GW drive. | SCORES 27 Oct 2026: M (near family) and T (price) are formulas from J and G; O from K. N, P, Q, R, S, U, V are ESTIMATES (Claude, general knowledge, not site-checked); S also rests on train Yes/No marked 'verify'. | CHECKED 27 Oct 2026, source run C1 (suburb level; Wikipedia, Victorian Places, ABS 2021 GCP DataPack). Pop 12,503; 23 km NE of CBD, Shire of Nillumbik [Wikipedia Diamond Creek]. Train: shopping centre and station sit on the banks of the Diamond Creek; Hurstbridge line [Wikipedia]; S 7 consistent. Shops: a shopping centre near the station and a second centre across the line [Victorian Places]; Q 7 consistent (supermarket not named). Nature: creek corridor and the large Diamond Creek reserve [Victorian Places]; N 7 consistent. Village: 'a pleasant backwater' that grew suburban from the 1970s; heritage St John's (c1867) [Victorian Places; Wikipedia]; R 6 consistent. Community centre was a 2009 bushfire evacuation point [Wikipedia]. Indian community: India-born 0.7%, Hinduism 0.7% [ABS 2021 GCP SAL20752]; P 2 consistent. City trip: 23 km by train; V 6 estimate. NOT checked: GPs, supermarket, journey time. Scores unchanged. | AA9: 8. Diamond Creek | North-East Fringe | Active Shortlist | P: High (Green wedge & trail) | Y: Low (Inland) | Lens: Practical metro nature compromise with rail | Price: 885000 | Basis: 3-bed house median $885k; 4-bed $1,240k (Domain) | Note: ABS 2021: 13.1% aged 65+, 12.2% non-Eng HH. Hurstbridge line station & trail; verify ED & GW drive. | AB9: Yes | AC9: Diamond Creek station, Hurstbridge line (per sheet note) | AD9: Austin Hospital ED | AE9: 1500000 | AF9: Maximum purchase price, excluding transaction and moving costs | AG9: Suburb median | AH9: 26 Oct 2026 | AI9: Pass | AJ9: Published house price ($885,000) is under $1.5M cap. | AK9: SAL20752 | AL9: 12503 | AM9: 39 | AN9: 0.131 | AO9: 0.146 | AP9: 0.022 | AQ9: 0.007 | AR9: 0.011 | AS9: 0.007 | AT9: 0.002 | AU9: 0.087 | AV9: Italian 1.2%; Greek 0.7%; Mandarin 0.7% | AW9: ABS 2021 Census General Community Profile DataPack, Suburbs and Localities (SAL), Victoria (tables G01, G02, G08, G09, G13, G14); downloaded 27 Oct 2026 from abs.gov.au. Place of usual residence. | AX9: =IF(AU9="","",IF(OR(AU9>=0.5,AQ9>=0.08),"High",IF(OR(AU9>=0.3,AQ9>=0.04),"Medium","Low")))
A10: Mentone | B10: Bayside Melbourne | C10: Active Shortlist | D10: Low-Medium (Suburban gardens) | E10: High (Bay beach) | F10: Coastal daily living on metro rail line | G10: 1497099 | H10: Sale median (Aussie/CoreLogic); Woodards shows $1.30m | I10: 1586924.9 | J10: 25 | K10: 16 | L10: Active — provisional pass | M10: =IF(J10="","",ROUND(MAX(0,10*(1-J10/Filters!$B$4)),1)) | N10: 4 | O10: =IF(K10="","",ROUND(MAX(0,10*(1-K10/Filters!$B$5)),1)) | P10: 5 | Q10: 9 | R10: 6 | S10: 8 | T10: =IF(G10="","",ROUND(MAX(0,MIN(10,10*(Filters!$B$2-G10)/(Filters!$B$2-500000))),1)) | U10: 9 | V10: 8 | W10: =IF(M10="",0,COUNT(M10:V10)) | X10: =IF(W10<10,"",M10*ForcedChoiceCorrections!$B$6+N10*ForcedChoiceCorrections!$B$7+O10*ForcedChoiceCorrections!$B$8+P10*ForcedChoiceCorrections!$B$9+Q10*ForcedChoiceCorrections!$B$10+R10*ForcedChoiceCorrections!$B$11+S10*ForcedChoiceCorrections!$B$12+T10*ForcedChoiceCorrections!$B$13+U10*ForcedChoiceCorrections!$B$14+V10*ForcedChoiceCorrections!$B$15) | Y10: =IF(AND(ISNUMBER(SEARCH("pass",L10)),ISNUMBER(X10)),COUNTIFS(L$2:L$90,"*pass*",X$2:X$90,">"&X10)+1,"") | Z10: ABS 2021: 28.8% overseas-born, 22.4% non-Eng HH. Reconcile price sources & verify ED drive. | SCORES 27 Oct 2026: M (near family) and T (price) are formulas from J and G; O from K. N, P, Q, R, S, U, V are ESTIMATES (Claude, general knowledge, not site-checked); S also rests on train Yes/No marked 'verify'. | CHECKED 27 Oct 2026 (S train/bus, U beach, Q shops & doctor; web sources, suburb level, not address level): Mentone Beach + lifesaving club; Woolworths at Thrift Park; Southland next door (Wikipedia Mentone). GPs: Mentone Medical Clinic, St Kerellos Medical Centre (healthdirect). N, P, R, V remain estimates. | CHECKED 27 Oct 2026, second pass (N, P, R, V; suburb level). Nature: Mentone Beach along Beaumaris Bay [Wikipedia Mentone]; no bushland or large reserve named; N 4 consistent. Village: 'lively shopping area' on Como Pde West, Balcombe Rd, Mentone Pde with cafés, bakeries, bookshops; Mediterranean-named 1880s township streets [Wikipedia; Victorian Places]; R 6 consistent. Indian community: India-born 1.9%, Indian ancestry 2.5%, Hinduism 1.7% [ABS 2021 GCP SAL21648]; P 5 generous (3 arguable). City trip: 21-22 km SE on the Frankston line [Wikipedia; Victorian Places]; journey time not stated; V 8 plausible. Scores unchanged. | AA10: 9. Mentone | Bayside Melbourne | Active Shortlist | P: Low-Medium (Suburban gardens) | Y: High (Bay beach) | Lens: Coastal daily living on metro rail line | Price: 1497099 | Basis: Sale median (Aussie/CoreLogic); Woodards shows $1.30m | Note: ABS 2021: 28.8% overseas-born, 22.4% non-Eng HH. Reconcile price sources & verify ED drive. | AB10: Yes | AC10: Mentone station, Frankston line, rebuilt 2020 (checked: Wikipedia Mentone) | AD10: Monash Medical Centre Clayton ED | AE10: 1500000 | AF10: Maximum purchase price, excluding transaction and moving costs | AG10: Suburb median | AH10: 26 Oct 2026 | AI10: Pass | AJ10: House median $1.497M (CoreLogic) / $1.30M (Woodards) is under $1.5M cap. Passes GW drive (25m) and ED drive (16m). | AK10: SAL21648 | AL10: 13197 | AM10: 42 | AN10: 0.196 | AO10: 0.288 | AP10: 0.025 | AQ10: 0.019 | AR10: 0.025 | AS10: 0.017 | AT10: 0.002 | AU10: 0.198 | AV10: Greek 3.5%; Mandarin 3.0%; Russian 1.5% | AW10: ABS 2021 Census General Community Profile DataPack, Suburbs and Localities (SAL), Victoria (tables G01, G02, G08, G09, G13, G14); downloaded 27 Oct 2026 from abs.gov.au. Place of usual residence. | AX10: =IF(AU10="","",IF(OR(AU10>=0.5,AQ10>=0.08),"High",IF(OR(AU10>=0.3,AQ10>=0.04),"Medium","Low")))
A11: Frankston | B11: South / Coastal | C11: Active Shortlist | D11: Medium (Sweetwater/gullies) | E11: High (Bay beach) | F11: Coastal practicality & accessible property price | G11: 834296 | H11: Sale median, rolling 12m (Aussie/Cotality); unit $573k | I11: 884353.76 | J11: 25 | K11: 4 | L11: Active — provisional pass | M11: =IF(J11="","",ROUND(MAX(0,10*(1-J11/Filters!$B$4)),1)) | N11: 6 | O11: =IF(K11="","",ROUND(MAX(0,10*(1-K11/Filters!$B$5)),1)) | P11: 4 | Q11: 9 | R11: 3 | S11: 9 | T11: =IF(G11="","",ROUND(MAX(0,MIN(10,10*(Filters!$B$2-G11)/(Filters!$B$2-500000))),1)) | U11: 8 | V11: 6 | W11: =IF(M11="",0,COUNT(M11:V11)) | X11: =IF(W11<10,"",M11*ForcedChoiceCorrections!$B$6+N11*ForcedChoiceCorrections!$B$7+O11*ForcedChoiceCorrections!$B$8+P11*ForcedChoiceCorrections!$B$9+Q11*ForcedChoiceCorrections!$B$10+R11*ForcedChoiceCorrections!$B$11+S11*ForcedChoiceCorrections!$B$12+T11*ForcedChoiceCorrections!$B$13+U11*ForcedChoiceCorrections!$B$14+V11*ForcedChoiceCorrections!$B$15) | Y11: =IF(AND(ISNUMBER(SEARCH("pass",L11)),ISNUMBER(X11)),COUNTIFS(L$2:L$90,"*pass*",X$2:X$90,">"&X11)+1,"") | Z11: ABS 2021: 22.5% overseas-born, 15.2% non-Eng HH. Peninsula Univ Hospital ED; ~66m train to CBD. | SCORES 27 Oct 2026: M (near family) and T (price) are formulas from J and G; O from K. N, P, Q, R, S, U, V are ESTIMATES (Claude, general knowledge, not site-checked); S also rests on train Yes/No marked 'verify'. | CHECKED 27 Oct 2026 (S train/bus, U beach, Q shops & doctor; web sources, suburb level, not address level): Rail terminus + bus hub to Mornington, Rosebud etc. (Wikipedia). GP: myhealth Bayside (healthdirect). Beach U and supermarket not individually checked. N, P, R, V remain estimates. | CHECKED 27 Oct 2026, second pass (N, P, R, V; suburb level). Nature: 'generally a leafy suburb'; natural reserves Bunarong Park, Frankston Foreshore Reserve, Lower Sweetwater Creek Reserve, Paratea Reserve; over 20 indigenous orchid species; McClelland Sculpture Park in 16 ha of park and reserve [Wikipedia Frankston]; N 5 consistent (6 arguable). Village: regional centre with Bayside (250+ stores) and Karingal Hub; several vacant highway buildings noted [Wikipedia; Victorian Places]; R 3 consistent. Health hub: four hospitals in the suburb [Wikipedia]. Indian community: India-born 1.1%, Hinduism 0.8%; Malayalam 0.5% at home [ABS 2021 GCP SAL20947; Wikipedia]; P 4 generous (2 arguable). City trip: 39-40 km SE, line terminus [Wikipedia; Victorian Places]; V 6 plausible. Scores unchanged. | C3 28 Oct 2026: N 5->6 (source: 'generally a leafy suburb'; Bunarong Park, Lower Sweetwater Creek and Paratea reserves [Wikipedia Frankston]). | AA11: 10. Frankston | South / Coastal | Active Shortlist | P: Medium (Sweetwater/gullies) | Y: High (Bay beach) | Lens: Coastal practicality & accessible property price | Price: 834296 | Basis: Sale median, rolling 12m (Aussie/Cotality); unit $573k | Note: ABS 2021: 22.5% overseas-born, 15.2% non-Eng HH. Peninsula Univ Hospital ED; ~66m train to CBD. | AB11: Yes | AC11: Frankston station, terminus of Frankston and Stony Point lines; bus hub (checked: Wikipedia Frankston station) | AD11: Peninsula University Hospital ED | AE11: 1500000 | AF11: Maximum purchase price, excluding transaction and moving costs | AG11: Suburb median | AH11: 26 Oct 2026 | AI11: Pass | AJ11: Published house price ($834,296) is under $1.5M cap. | AK11: SAL20947 | AL11: 37331 | AM11: 39 | AN11: 0.179 | AO11: 0.225 | AP11: 0.069 | AQ11: 0.011 | AR11: 0.014 | AS11: 0.008 | AT11: 0.001 | AU11: 0.121 | AV11: Mandarin 1.4%; Greek 1.0%; Russian 0.6% | AW11: ABS 2021 Census General Community Profile DataPack, Suburbs and Localities (SAL), Victoria (tables G01, G02, G08, G09, G13, G14); downloaded 27 Oct 2026 from abs.gov.au. Place of usual residence. | AX11: =IF(AU11="","",IF(OR(AU11>=0.5,AQ11>=0.08),"High",IF(OR(AU11>=0.3,AQ11>=0.04),"Medium","Low")))
A12: Altona | B12: West Coastal | C12: Active Shortlist | D12: Low-Medium (Flat coastal) | E12: High (Bay beach/wetlands) | F12: Coastal village alternative at lower price point | G12: 1155073 | H12: AVM estimate (31 Aug 2026), NOT a verified sale median | I12: 1224377.4 | J12: 35 | K12: 15 | L12: Active — provisional pass | M12: =IF(J12="","",ROUND(MAX(0,10*(1-J12/Filters!$B$4)),1)) | N12: 4 | O12: =IF(K12="","",ROUND(MAX(0,10*(1-K12/Filters!$B$5)),1)) | P12: 6 | Q12: 8 | R12: 6 | S12: 8 | T12: =IF(G12="","",ROUND(MAX(0,MIN(10,10*(Filters!$B$2-G12)/(Filters!$B$2-500000))),1)) | U12: 8 | V12: 8 | W12: =IF(M12="",0,COUNT(M12:V12)) | X12: =IF(W12<10,"",M12*ForcedChoiceCorrections!$B$6+N12*ForcedChoiceCorrections!$B$7+O12*ForcedChoiceCorrections!$B$8+P12*ForcedChoiceCorrections!$B$9+Q12*ForcedChoiceCorrections!$B$10+R12*ForcedChoiceCorrections!$B$11+S12*ForcedChoiceCorrections!$B$12+T12*ForcedChoiceCorrections!$B$13+U12*ForcedChoiceCorrections!$B$14+V12*ForcedChoiceCorrections!$B$15) | Y12: =IF(AND(ISNUMBER(SEARCH("pass",L12)),ISNUMBER(X12)),COUNTIFS(L$2:L$90,"*pass*",X$2:X$90,">"&X12)+1,"") | Z12: ABS 2021: 28.3% overseas-born, 23.8% non-Eng HH. Cross-city drive to Glen Waverley needs testing. | SCORES 27 Oct 2026: M (near family) and T (price) are formulas from J and G; O from K. N, P, Q, R, S, U, V are ESTIMATES (Claude, general knowledge, not site-checked); S also rests on train Yes/No marked 'verify'. | CHECKED 27 Oct 2026 (S train/bus, U beach, Q shops & doctor; web sources, suburb level, not address level): Altona Bay beach, pier, coastal park (Victorian Places). GP: Pier Street Medical Centre (healthdirect). Coles Altona (grocerize). N, P, R, V remain estimates. | CHECKED 27 Oct 2026, second pass (N, P, R, V; suburb level). Nature: Altona Beach, one of only two swimming beaches in the western suburbs; conservation areas and wetlands along the bay shore; long bayside promenade [Wikipedia Altona]; north-western half is mixed industry [Wikipedia]; N 4 consistent. Village: Pier St and Esplanade precinct; annual beach festival; civic theatre [Wikipedia]; R 6 consistent. Indian community: India-born 1.4%, Indian ancestry 1.9%, Hinduism 1.1% [ABS 2021 GCP SAL20035]; P 6 not supported (3 arguable). City trip: 13 km SW by train (Altona loop) [Wikipedia]; V 8 consistent. Scores unchanged. Victorian Places page not found. | AA12: 11. Altona | West Coastal | Active Shortlist | P: Low-Medium (Flat coastal) | Y: High (Bay beach/wetlands) | Lens: Coastal village alternative at lower price point | Price: 1155073 | Basis: AVM estimate (31 Aug 2026), NOT a verified sale median | Note: ABS 2021: 28.3% overseas-born, 23.8% non-Eng HH. Cross-city drive to Glen Waverley needs testing. | AB12: Yes | AC12: Altona station, Altona loop of Werribee line (checked: Wikipedia Altona station) | AD12: Footscray Hospital ED | AE12: 1500000 | AF12: Maximum purchase price, excluding transaction and moving costs | AG12: Suburb median | AH12: 26 Oct 2026 | AI12: Pass | AJ12: Published house price ($1,155,073) is under $1.5M cap. | AK12: SAL20035 | AL12: 11490 | AM12: 42 | AN12: 0.194 | AO12: 0.283 | AP12: 0.044 | AQ12: 0.014 | AR12: 0.019 | AS12: 0.011 | AT12: 0.003 | AU12: 0.196 | AV12: Italian 1.6%; Greek 1.4%; Mandarin 1.4% | AW12: ABS 2021 Census General Community Profile DataPack, Suburbs and Localities (SAL), Victoria (tables G01, G02, G08, G09, G13, G14); downloaded 27 Oct 2026 from abs.gov.au. Place of usual residence. | AX12: =IF(AU12="","",IF(OR(AU12>=0.5,AQ12>=0.08),"High",IF(OR(AU12>=0.3,AQ12>=0.04),"Medium","Low")))
A13: Williamstown | B13: West Coastal | C13: Active Shortlist | D13: Medium (Botanic gardens) | E13: High (Historic harbor/beach) | F13: Picturesque coastal character vs cost | G13: 1642163 | H13: AVM estimate (30 Sep 2026), NOT a verified sale median | I13: 1740692.8 | J13: 31 | K13: 13 | L13: Active — needs data | O13: =IF(K13="","",ROUND(MAX(0,10*(1-K13/Filters!$B$5)),1)) | W13: =IF(M13="",0,COUNT(M13:V13)) | X13: =IF(W13<10,"",M13*ForcedChoiceCorrections!$B$6+N13*ForcedChoiceCorrections!$B$7+O13*ForcedChoiceCorrections!$B$8+P13*ForcedChoiceCorrections!$B$9+Q13*ForcedChoiceCorrections!$B$10+R13*ForcedChoiceCorrections!$B$11+S13*ForcedChoiceCorrections!$B$12+T13*ForcedChoiceCorrections!$B$13+U13*ForcedChoiceCorrections!$B$14+V13*ForcedChoiceCorrections!$B$15) | Y13: =IF(AND(ISNUMBER(SEARCH("pass",L13)),ISNUMBER(X13)),COUNTIFS(L$2:L$90,"*pass*",X$2:X$90,">"&X13)+1,"") | Z13: ABS 2021: 22.6% overseas-born, 20.0% non-Eng HH. Cross-city travel to Glen Waverley & ED capacity need checking. | AA13: 12. Williamstown | West Coastal | Active Shortlist | P: Medium (Botanic gardens) | Y: High (Historic harbor/beach) | Lens: Picturesque coastal character vs cost | Price: 1642163 | Basis: AVM estimate (30 Sep 2026), NOT a verified sale median | Note: ABS 2021: 22.6% overseas-born, 20.0% non-Eng HH. Cross-city travel to Glen Waverley & ED capacity need checking. | AB13: Yes | AC13: Williamstown station, Williamstown line (recall; verify) | AD13: Footscray Hospital ED | AE13: 1500000 | AF13: Maximum purchase price, excluding transaction and moving costs | AG13: AVM estimate | AH13: 26 Oct 2026 | AI13: Needs data | AJ13: Figure is an automated valuation model ($1.64M), not a verified sale median or specific property. Awaiting documented listing search under $1.5M. | AK13: SAL22792 | AL13: 14407 | AM13: 45 | AN13: 0.182 | AO13: 0.226 | AP13: 0.033 | AQ13: 0.005 | AR13: 0.009 | AS13: 0.005 | AT13: 0.001 | AU13: 0.149 | AV13: Greek 2.4%; Italian 1.6%; Vietnamese 1.0% | AW13: ABS 2021 Census General Community Profile DataPack, Suburbs and Localities (SAL), Victoria (tables G01, G02, G08, G09, G13, G14); downloaded 27 Oct 2026 from abs.gov.au. Place of usual residence. | AX13: =IF(AU13="","",IF(OR(AU13>=0.5,AQ13>=0.08),"High",IF(OR(AU13>=0.3,AQ13>=0.04),"Medium","Low")))
A14: Healesville | B14: Yarra Valley | C14: Active Shortlist | D14: High (Valley & mountains) | E14: Low (Inland) | F14: Larger Yarra Valley town comparator | G14: 837893 | H14: AVM estimate (30 Sep 2026), NOT a verified sale median; unit $618,926; 160 sales in last 12m (OnTheHouse/Cotality, read 27 Oct 2026) | I14: =G14*(1+Settings!$B$6) | J14: 43 | K14: 33 | L14: Active — provisional pass | M14: =IF(J14="","",ROUND(MAX(0,10*(1-J14/Filters!$B$4)),1)) | N14: 9 | O14: =IF(K14="","",ROUND(MAX(0,10*(1-K14/Filters!$B$5)),1)) | P14: 1 | Q14: 6 | R14: 8 | S14: 2 | T14: =IF(G14="","",ROUND(MAX(0,MIN(10,10*(Filters!$B$2-G14)/(Filters!$B$2-500000))),1)) | U14: 0 | V14: 2 | W14: =IF(M14="",0,COUNT(M14:V14)) | X14: =IF(W14<10,"",M14*ForcedChoiceCorrections!$B$6+N14*ForcedChoiceCorrections!$B$7+O14*ForcedChoiceCorrections!$B$8+P14*ForcedChoiceCorrections!$B$9+Q14*ForcedChoiceCorrections!$B$10+R14*ForcedChoiceCorrections!$B$11+S14*ForcedChoiceCorrections!$B$12+T14*ForcedChoiceCorrections!$B$13+U14*ForcedChoiceCorrections!$B$14+V14*ForcedChoiceCorrections!$B$15) | Y14: =IF(AND(ISNUMBER(SEARCH("pass",L14)),ISNUMBER(X14)),COUNTIFS(L$2:L$90,"*pass*",X$2:X$90,">"&X14)+1,"") | Z14: 2021 pop 7,589. CAUTION: Eastern Health directs urgent ED patients to Maroondah Hospital ED (not local). 27 Oct 2026 research pass: drive times/ED and/or AVM price added; L re-evaluated. | SCORES 27 Oct 2026: M (near family) and T (price) are formulas from J and G; O from K. N, P, Q, R, S, U, V are ESTIMATES (Claude, general knowledge, not site-checked); S also rests on train Yes/No marked 'verify'. | CHECKED 27 Oct 2026, source run C1 (suburb level; Wikipedia, Victorian Places, ABS 2021 GCP DataPack). Pop 7,589; 64 km NE of CBD on the Watts River [Wikipedia Healesville]. Nature: Healesville Sanctuary, Badger Weir picnic area, Maroondah Dam nearby; southern end of the Bicentennial Heritage Trail [Wikipedia]; N 9 consistent. Village: tourist town since the 1880s; Yarra Valley wine and food centre, organic market, cafés, festivals [Wikipedia]; R 8 consistent. Train: only the Yarra Valley tourist railway (Sundays, some holidays) [Wikipedia]; no metro or V/Line station; S 2 consistent. Indian community: India-born 0.2%, Hinduism 0.2% [ABS 2021 GCP SAL21158]; P 1 consistent. Older: median age 46, 23.7% aged 65+ [ABS]. City trip: 64 km, no rail; V 2 consistent. NOT checked: GPs, supermarket, bus. Scores unchanged. | AA14: 13. Healesville | Yarra Valley | Active Shortlist | P: High (Valley & mountains) | Y: Low (Inland) | Lens: Larger Yarra Valley town comparator | Price: [Blank] | Basis: Not verified in report | Note: 2021 pop 7,589. CAUTION: Eastern Health directs urgent ED patients to Maroondah Hospital ED (not local). | AB14: No | AC14: No rail (recall; verify) | AD14: Maroondah Hospital ED (sheet note: urgent ED cases go here) | AE14: 1500000 | AF14: Maximum purchase price, excluding transaction and moving costs | AG14: AVM estimate | AH14: 27 Oct 2026 | AI14: Pass | AJ14: AVM house value ($837,893) is under $1.5M cap. Not a sale median. | AK14: SAL21158 | AL14: 7589 | AM14: 46 | AN14: 0.237 | AO14: 0.15 | AP14: 0.056 | AQ14: 0.002 | AR14: 0.004 | AS14: 0.002 | AT14: 0 | AU14: 0.047 | AV14: German 0.7%; Italian 0.6%; Mandarin 0.3% | AW14: ABS 2021 Census General Community Profile DataPack, Suburbs and Localities (SAL), Victoria (tables G01, G02, G08, G09, G13, G14); downloaded 27 Oct 2026 from abs.gov.au. Place of usual residence. | AX14: =IF(AU14="","",IF(OR(AU14>=0.5,AQ14>=0.08),"High",IF(OR(AU14>=0.3,AQ14>=0.04),"Medium","Low")))
A15: Kyneton | B15: Macedon Ranges | C15: Active Shortlist | D15: High (Country town & gardens) | E15: Low (Inland river) | F15: Country-town practicality with V/Line rail | G15: 810000 | H15: 3-bed house median $810k; 4-bed $980k (Domain) | I15: 858600 | J15: 77 | K15: 47 | L15: Active — provisional pass | M15: =IF(J15="","",ROUND(MAX(0,10*(1-J15/Filters!$B$4)),1)) | N15: 7 | O15: =IF(K15="","",ROUND(MAX(0,10*(1-K15/Filters!$B$5)),1)) | P15: 1 | Q15: 7 | R15: 9 | S15: 5 | T15: =IF(G15="","",ROUND(MAX(0,MIN(10,10*(Filters!$B$2-G15)/(Filters!$B$2-500000))),1)) | U15: 0 | V15: 5 | W15: =IF(M15="",0,COUNT(M15:V15)) | X15: =IF(W15<10,"",M15*ForcedChoiceCorrections!$B$6+N15*ForcedChoiceCorrections!$B$7+O15*ForcedChoiceCorrections!$B$8+P15*ForcedChoiceCorrections!$B$9+Q15*ForcedChoiceCorrections!$B$10+R15*ForcedChoiceCorrections!$B$11+S15*ForcedChoiceCorrections!$B$12+T15*ForcedChoiceCorrections!$B$13+U15*ForcedChoiceCorrections!$B$14+V15*ForcedChoiceCorrections!$B$15) | Y15: =IF(AND(ISNUMBER(SEARCH("pass",L15)),ISNUMBER(X15)),COUNTIFS(L$2:L$90,"*pass*",X$2:X$90,">"&X15)+1,"") | Z15: ABS 2021: 25.0% aged 65+, 6.9% non-Eng HH. CAUTION: Local facility is 24-hr Urgent Care Centre, NOT a major public ED. | SCORES 27 Oct 2026: M (near family) and T (price) are formulas from J and G; O from K. N, P, Q, R, S, U, V are ESTIMATES (Claude, general knowledge, not site-checked); S also rests on train Yes/No marked 'verify'. | CHECKED 27 Oct 2026, source run C1 (suburb level; Wikipedia, Victorian Places, ABS 2021 GCP DataPack). Pop 7,513; Macedon Ranges, ~75 km NW of Melbourne [Wikipedia Kyneton; Victorian Places]. Train: heritage-listed station south of town, ~86 km from Melbourne on the Bendigo line; 'a terminus for two weekday peak-hour trains' [Wikipedia; Victorian Places]; S 5 consistent (frequency not checked). Village: three main streets; Piper St 'has the oldest streetscape', galleries, bookstores, cafés; historic museum [Wikipedia; Victorian Places]; R 9 consistent. Nature: botanic gardens, Campaspe River walks, Black Hill and Bald Hill reserves nearby [Wikipedia]; N 7 consistent. Indian community: India-born 0.5%, Hinduism 0.3% [ABS 2021 GCP SAL21414]; P 1 consistent. Older: median age 47, 25.0% aged 65+ [ABS]. City trip: 86 km by V/Line; V 5 estimate. NOT checked: GPs, supermarket, train journey time. Scores unchanged. | AA15: 14. Kyneton | Macedon Ranges | Active Shortlist | P: High (Country town & gardens) | Y: Low (Inland river) | Lens: Country-town practicality with V/Line rail | Price: 810000 | Basis: 3-bed house median $810k; 4-bed $980k (Domain) | Note: ABS 2021: 25.0% aged 65+, 6.9% non-Eng HH. CAUTION: Local facility is 24-hr Urgent Care Centre, NOT a major public ED. | AB15: Yes | AC15: Kyneton station, V/Line Bendigo (per sheet note) | AD15: Bendigo Hospital ED (local 24-hr urgent care is not an ED) | AE15: 1500000 | AF15: Maximum purchase price, excluding transaction and moving costs | AG15: Suburb median | AH15: 26 Oct 2026 | AI15: Pass | AJ15: Published house price ($810,000) is under $1.5M cap. | AK15: SAL21414 | AL15: 7513 | AM15: 47 | AN15: 0.25 | AO15: 0.145 | AP15: 0.059 | AQ15: 0.005 | AR15: 0.007 | AS15: 0.003 | AT15: 0.001 | AU15: 0.055 | AV15: Mandarin 1.3%; Italian 0.4%; French 0.3% | AW15: ABS 2021 Census General Community Profile DataPack, Suburbs and Localities (SAL), Victoria (tables G01, G02, G08, G09, G13, G14); downloaded 27 Oct 2026 from abs.gov.au. Place of usual residence. | AX15: =IF(AU15="","",IF(OR(AU15>=0.5,AQ15>=0.08),"High",IF(OR(AU15>=0.3,AQ15>=0.04),"Medium","Low")))
A16: Woodend | B16: Macedon Ranges | C16: Active Shortlist | D16: High (Macedon Ranges forest) | E16: Low (Inland) | F16: Walkable station country town in Macedon Ranges | G16: 890000 | H16: 3-bed house median $890k; 4-bed $1,150k (Domain) | I16: 943400 | J16: 68 | K16: 55 | L16: Active — provisional pass | M16: =IF(J16="","",ROUND(MAX(0,10*(1-J16/Filters!$B$4)),1)) | N16: 8 | O16: =IF(K16="","",ROUND(MAX(0,10*(1-K16/Filters!$B$5)),1)) | P16: 1 | Q16: 6 | R16: 9 | S16: 5 | T16: =IF(G16="","",ROUND(MAX(0,MIN(10,10*(Filters!$B$2-G16)/(Filters!$B$2-500000))),1)) | U16: 0 | V16: 5 | W16: =IF(M16="",0,COUNT(M16:V16)) | X16: =IF(W16<10,"",M16*ForcedChoiceCorrections!$B$6+N16*ForcedChoiceCorrections!$B$7+O16*ForcedChoiceCorrections!$B$8+P16*ForcedChoiceCorrections!$B$9+Q16*ForcedChoiceCorrections!$B$10+R16*ForcedChoiceCorrections!$B$11+S16*ForcedChoiceCorrections!$B$12+T16*ForcedChoiceCorrections!$B$13+U16*ForcedChoiceCorrections!$B$14+V16*ForcedChoiceCorrections!$B$15) | Y16: =IF(AND(ISNUMBER(SEARCH("pass",L16)),ISNUMBER(X16)),COUNTIFS(L$2:L$90,"*pass*",X$2:X$90,">"&X16)+1,"") | Z16: V/Line Bendigo line. Check winter comfort, major public ED drive time & family trip frequency. | SCORES 27 Oct 2026: M (near family) and T (price) are formulas from J and G; O from K. N, P, Q, R, S, U, V are ESTIMATES (Claude, general knowledge, not site-checked); S also rests on train Yes/No marked 'verify'. | CHECKED 27 Oct 2026, full pass (suburb level). Pop 6,732, elevation 580 m, ~71 km NW of Melbourne, Great Dividing Range foothills [Wikipedia Woodend]. 'Valley surrounded by forest and bushland'; walk Five Mile Creek through Children's Park; Hanging Rock and Mt Macedon ~10 min drive [Macedon Ranges Shire]; N 8 consistent. Village: 'distinctive rural village character', historic buildings, clock tower, verandahed shopping [Macedon Ranges Shire]; R 9 consistent. Train: station staffed, V/Line Bendigo/Echuca/Swan Hill, 78.09 km from Southern Cross, myki zone 4/5 overlap, parking [Wikipedia Woodend station]; Bendigo line weekend average 60 min frequency 7am-7pm [V/Line fact sheet]; weekday Woodend frequency and journey time NOT confirmed. Shops & doctor: IGA opened Aug 2022 at former Coles site, 19th Hole Shopping Centre, 7am-10pm [Midland Express 16 Aug 2022]; 4 GP clinics (Neal Street Medical, Brooke Street Medical Centre, Lifeline Healthcare Woodend, SkinGP) [healthdirect]; Q 6 supported, 7 arguable. Indian community: India, Indian ancestry, Hinduism/Sikhism, Hindi/Punjabi absent from ABS 2021 top responses (79.5% Australia-born, 53.3% no religion) [ABS SAL22833]; P 1 consistent. Beach 0 correct (inland). NOT checked: ED (AD still unconfirmed), winter comfort, trip frequency to Glen Waverley, city-trip time (V 5 is an estimate). Scores unchanged. | AA16: 15. Woodend | Macedon Ranges | Active Shortlist | P: High (Macedon Ranges forest) | Y: Low (Inland) | Lens: Walkable station country town in Macedon Ranges | Price: 890000 | Basis: 3-bed house median $890k; 4-bed $1,150k (Domain) | Note: V/Line Bendigo line. Check winter comfort, major public ED drive time & family trip frequency. | AB16: Yes | AC16: Woodend station, V/Line Bendigo (checked: Wikipedia Woodend station; weekday frequency not confirmed) | AD16: Bendigo Hospital ED (nearest ED not confirmed; Northern Hospital Epping not tested) | AE16: 1500000 | AF16: Maximum purchase price, excluding transaction and moving costs | AG16: Suburb median | AH16: 26 Oct 2026 | AI16: Pass | AJ16: Published house price ($890,000) is under $1.5M cap. | AK16: SAL22833 | AL16: 6732 | AM16: 45 | AN16: 0.22 | AO16: 0.161 | AP16: 0.044 | AQ16: 0.002 | AR16: 0.004 | AS16: 0.004 | AT16: 0 | AU16: 0.048 | AV16: German 0.7%; Italian 0.4%; French 0.3% | AW16: ABS 2021 Census General Community Profile DataPack, Suburbs and Localities (SAL), Victoria (tables G01, G02, G08, G09, G13, G14); downloaded 27 Oct 2026 from abs.gov.au. Place of usual residence. | AX16: =IF(AU16="","",IF(OR(AU16>=0.5,AQ16>=0.08),"High",IF(OR(AU16>=0.3,AQ16>=0.04),"Medium","Low")))
A17: Macedon | B17: Macedon Ranges | C17: Active Shortlist | D17: High (Forest & Honour Ave) | E17: Low (Inland) | F17: Landscape-led Macedon Ranges option | G17: 1147643 | H17: AVM estimate (30 Sep 2026), NOT a verified sale median; unit $836,750; 31 sales in last 12m (OnTheHouse/Cotality, read 27 Oct 2026) — few sales, weak | I17: =G17*(1+Settings!$B$6) | J17: 62 | K17: 60 | L17: Active — provisional pass | M17: =IF(J17="","",ROUND(MAX(0,10*(1-J17/Filters!$B$4)),1)) | N17: 9 | O17: =IF(K17="","",ROUND(MAX(0,10*(1-K17/Filters!$B$5)),1)) | P17: 1 | Q17: 3 | R17: 8 | S17: 5 | T17: =IF(G17="","",ROUND(MAX(0,MIN(10,10*(Filters!$B$2-G17)/(Filters!$B$2-500000))),1)) | U17: 0 | V17: 5 | W17: =IF(M17="",0,COUNT(M17:V17)) | X17: =IF(W17<10,"",M17*ForcedChoiceCorrections!$B$6+N17*ForcedChoiceCorrections!$B$7+O17*ForcedChoiceCorrections!$B$8+P17*ForcedChoiceCorrections!$B$9+Q17*ForcedChoiceCorrections!$B$10+R17*ForcedChoiceCorrections!$B$11+S17*ForcedChoiceCorrections!$B$12+T17*ForcedChoiceCorrections!$B$13+U17*ForcedChoiceCorrections!$B$14+V17*ForcedChoiceCorrections!$B$15) | Y17: =IF(AND(ISNUMBER(SEARCH("pass",L17)),ISNUMBER(X17)),COUNTIFS(L$2:L$90,"*pass*",X$2:X$90,">"&X17)+1,"") | Z17: Distinguish Macedon from Mount Macedon; check bushfire overlay, gradients & major ED journey. 27 Oct 2026 research pass: drive times/ED and/or AVM price added; L re-evaluated. | SCORES 27 Oct 2026: M (near family) and T (price) are formulas from J and G; O from K. N, P, Q, R, S, U, V are ESTIMATES (Claude, general knowledge, not site-checked); S also rests on train Yes/No marked 'verify'. Low sales count. | CHECKED 27 Oct 2026, source run C1 (suburb level; Wikipedia, Victorian Places, ABS 2021 GCP DataPack). Pop 2,073; foot of Mount Macedon, 58 km NW of Melbourne, on the Melbourne-Bendigo railway [Wikipedia Macedon; Victorian Places]. Nature: bushland foothills of the Mount Macedon range; vineyards nearby [Wikipedia]; N 10 plausible (9 arguable: town is at the foot, not on the mount). Village: rebuilt shops, churches and hall after the 1983 Ash Wednesday fire (499 houses, 8 lives lost in Macedon and Mount Macedon) [Victorian Places]; cafés and B&Bs, new planning controls 'to protect the character' [Wikipedia]; R 8 consistent. Bushfire risk is real and documented. Shops: small; supermarket not named; Q 3 consistent. Train: station on the Bendigo line [Victorian Places]; S 5 consistent (frequency not checked). Indian community: India-born 0.2%, Hinduism 0.2% [ABS 2021 GCP SAL21562]; P 1 consistent. City trip: 58 km by V/Line; V 5 estimate. NOT checked: GPs, nearest ED, journey time. Scores unchanged. | C3 28 Oct 2026: N 10->9 (source: town sits at the foot of Mount Macedon; surrounding bushland long harvested for timber [Wikipedia Macedon]; 10 kept for national-park settings). | AA17: 16. Macedon | Macedon Ranges | Active Shortlist | P: High (Forest & Honour Ave) | Y: Low (Inland) | Lens: Landscape-led Macedon Ranges option | Price: [Blank] | Basis: Not verified in report | Note: Distinguish Macedon from Mount Macedon; check bushfire overlay, gradients & major ED journey. | AB17: Yes | AC17: Macedon station, V/Line Bendigo (recall; verify) | AD17: Bendigo Hospital ED (nearest ED not confirmed; Northern Hospital Epping not tested) | AE17: 1500000 | AF17: Maximum purchase price, excluding transaction and moving costs | AG17: AVM estimate | AH17: 27 Oct 2026 | AI17: Pass | AJ17: AVM house value ($1,147,643) is under $1.5M cap. Not a sale median. | AK17: SAL21562 | AL17: 2073 | AM17: 44 | AN17: 0.192 | AO17: 0.132 | AP17: 0.053 | AQ17: 0.002 | AR17: 0.004 | AS17: 0.002 | AT17: 0 | AU17: 0.039 | AV17: French 0.5%; Polish 0.4%; Italian 0.3% | AW17: ABS 2021 Census General Community Profile DataPack, Suburbs and Localities (SAL), Victoria (tables G01, G02, G08, G09, G13, G14); downloaded 27 Oct 2026 from abs.gov.au. Place of usual residence. Small population: ABS randomly adjusts small counts, so treat shares under 1% as noise. | AX17: =IF(AU17="","",IF(OR(AU17>=0.5,AQ17>=0.08),"High",IF(OR(AU17>=0.3,AQ17>=0.04),"Medium","Low")))
A18: Torquay | B18: Surf Coast | C18: Active Shortlist | D18: Medium (Coastal heath) | E18: High (Surf Coast walk/beach) | F18: Everyday surf-coast walking lifestyle | G18: 1180000 | H18: House sale median $1,180,000; unit $891,250 (REA) | I18: 1250800 | J18: 88 | K18: 23 | L18: Active — provisional pass | M18: =IF(J18="","",ROUND(MAX(0,10*(1-J18/Filters!$B$4)),1)) | N18: 7 | O18: =IF(K18="","",ROUND(MAX(0,10*(1-K18/Filters!$B$5)),1)) | P18: 2 | Q18: 8 | R18: 5 | S18: 4 | T18: =IF(G18="","",ROUND(MAX(0,MIN(10,10*(Filters!$B$2-G18)/(Filters!$B$2-500000))),1)) | U18: 10 | V18: 3 | W18: =IF(M18="",0,COUNT(M18:V18)) | X18: =IF(W18<10,"",M18*ForcedChoiceCorrections!$B$6+N18*ForcedChoiceCorrections!$B$7+O18*ForcedChoiceCorrections!$B$8+P18*ForcedChoiceCorrections!$B$9+Q18*ForcedChoiceCorrections!$B$10+R18*ForcedChoiceCorrections!$B$11+S18*ForcedChoiceCorrections!$B$12+T18*ForcedChoiceCorrections!$B$13+U18*ForcedChoiceCorrections!$B$14+V18*ForcedChoiceCorrections!$B$15) | Y18: =IF(AND(ISNUMBER(SEARCH("pass",L18)),ISNUMBER(X18)),COUNTIFS(L$2:L$90,"*pass*",X$2:X$90,">"&X18)+1,"") | Z18: ABS 2021: 16.4% aged 65+, 7.4% non-Eng HH. Bus 54 to Marshall Station; relies on Univ Hospital Geelong for major public ED. | SCORES 27 Oct 2026: M (near family) and T (price) are formulas from J and G; O from K. N, P, Q, R, S, U, V are ESTIMATES (Claude, general knowledge, not site-checked); S also rests on train Yes/No marked 'verify'. GW drive 88 min, 2 min under cap. | CHECKED 27 Oct 2026 (S train/bus, U beach, Q shops & doctor; web sources, suburb level, not address level): Buses to Geelong/Marshall: S raised 3->4 (Bus News). GPs: Surfcoast Medical Centre, Orbit Medical, Banksia (healthdirect). Beach and supermarket not individually checked. N, P, R, V remain estimates. | CHECKED 27 Oct 2026, second pass (N, P, R, V; suburb level). Nature: surf beaches (Jan Juc, Bells Beach on the SW outskirts), Point Danger, Zeally Bay, Spring Creek on the western boundary [Wikipedia Torquay]; N 8 rests on coast, not bush (7 arguable). Village: population doubled 1991-2011 and 'some of its former holiday charm has been lost to redevelopment' [Victorian Places]; population triples in Jan-Feb; Surf Coast Plaza [Wikipedia]; R 6 generous (5 arguable). Indian community: India-born 0.2%, Hinduism 0.1% [ABS 2021 GCP SAL22551]; P 2 generous (1 arguable). City trip: 80 km W of Melbourne, 21 km S of Geelong [Victorian Places], no rail; V 3 plausible; journey time not checked. Scores unchanged. | C3 28 Oct 2026: N 8->7 (source: nature is coastal and already scored under U (10); no bushland named [Wikipedia Torquay]). | C3 28 Oct 2026: R 6->5 (source: 'some of its former holiday charm has been lost to redevelopment' [Victorian Places Torquay]). | AA18: 17. Torquay | Surf Coast | Active Shortlist | P: Medium (Coastal heath) | Y: High (Surf Coast walk/beach) | Lens: Everyday surf-coast walking lifestyle | Price: 1180000 | Basis: House sale median $1,180,000; unit $891,250 (REA) | Note: ABS 2021: 16.4% aged 65+, 7.4% non-Eng HH. Bus 54 to Marshall Station; relies on Univ Hospital Geelong for major public ED. | AB18: No | AC18: No rail; buses to Geelong and Marshall station, ~4 buses/hour on Surf Coast Hwy corridor (checked: Bus News) | AD18: University Hospital Geelong ED | AE18: 1500000 | AF18: Maximum purchase price, excluding transaction and moving costs | AG18: Suburb median | AH18: 26 Oct 2026 | AI18: Pass | AJ18: House median $1.180M is under $1.5M cap. Passes GW drive (88m <= 90m cap) and ED drive (23m). | AK18: SAL22551 | AL18: 18534 | AM18: 39 | AN18: 0.164 | AO18: 0.134 | AP18: 0.038 | AQ18: 0.002 | AR18: 0.004 | AS18: 0.001 | AT18: 0.001 | AU18: 0.047 | AV18: German 0.5%; Italian 0.5%; French 0.4% | AW18: ABS 2021 Census General Community Profile DataPack, Suburbs and Localities (SAL), Victoria (tables G01, G02, G08, G09, G13, G14); downloaded 27 Oct 2026 from abs.gov.au. Place of usual residence. | AX18: =IF(AU18="","",IF(OR(AU18>=0.5,AQ18>=0.08),"High",IF(OR(AU18>=0.3,AQ18>=0.04),"Medium","Low")))
A19: Ocean Grove | B19: Bellarine Peninsula | C19: Active Shortlist | D19: Medium-High (Nature reserve) | E19: High (Beach + woodland) | F19: Coast-plus-bushland alternative to Torquay | G19: 980000 | H19: House sale median $980,000 (325 sales); unit $770k | I19: 1038800 | J19: 92 | K19: 21 | L19: Fails: GW drive | O19: =IF(K19="","",ROUND(MAX(0,10*(1-K19/Filters!$B$5)),1)) | W19: =IF(M19="",0,COUNT(M19:V19)) | X19: =IF(W19<10,"",M19*ForcedChoiceCorrections!$B$6+N19*ForcedChoiceCorrections!$B$7+O19*ForcedChoiceCorrections!$B$8+P19*ForcedChoiceCorrections!$B$9+Q19*ForcedChoiceCorrections!$B$10+R19*ForcedChoiceCorrections!$B$11+S19*ForcedChoiceCorrections!$B$12+T19*ForcedChoiceCorrections!$B$13+U19*ForcedChoiceCorrections!$B$14+V19*ForcedChoiceCorrections!$B$15) | Y19: =IF(AND(ISNUMBER(SEARCH("pass",L19)),ISNUMBER(X19)),COUNTIFS(L$2:L$90,"*pass*",X$2:X$90,">"&X19)+1,"") | Z19: ABS 2021: 22.2% aged 65+, 5.1% non-Eng HH. 143-ha Nature Reserve; bus 55/56 to Geelong; relies on Univ Hospital Geelong ED. | AA19: 18. Ocean Grove | Bellarine Peninsula | Active Shortlist | P: Medium-High (Nature reserve) | Y: High (Beach + woodland) | Lens: Coast-plus-bushland alternative to Torquay | Price: 980000 | Basis: House sale median $980,000 (325 sales); unit $770k | Note: ABS 2021: 22.2% aged 65+, 5.1% non-Eng HH. 143-ha Nature Reserve; bus 55/56 to Geelong; relies on Univ Hospital Geelong ED. | AB19: No | AC19: No rail; bus 55/56 to Geelong (per sheet note) | AD19: University Hospital Geelong ED | AE19: 1500000 | AF19: Maximum purchase price, excluding transaction and moving costs | AG19: Suburb median | AH19: 26 Oct 2026 | AI19: Pass | AJ19: Published house price ($980,000) is under $1.5M cap. | AK19: SAL22005 | AL19: 17714 | AM19: 43 | AN19: 0.222 | AO19: 0.113 | AP19: 0.046 | AQ19: 0.002 | AR19: 0.003 | AS19: 0.001 | AT19: 0.001 | AU19: 0.034 | AV19: Italian 0.4%; German 0.3%; Mandarin 0.3% | AW19: ABS 2021 Census General Community Profile DataPack, Suburbs and Localities (SAL), Victoria (tables G01, G02, G08, G09, G13, G14); downloaded 27 Oct 2026 from abs.gov.au. Place of usual residence. | AX19: =IF(AU19="","",IF(OR(AU19>=0.5,AQ19>=0.08),"High",IF(OR(AU19>=0.3,AQ19>=0.04),"Medium","Low")))
A20: Newtown (Geelong) | B20: Geelong | C20: Active Shortlist | D20: Medium-High (Barwon River) | E20: Medium (Near bay/coast) | F20: Regional-city services + river sanctuary | G20: 1182945 | H20: AVM estimate (30 Sep 2026), NOT a verified sale median; unit $615,303; 216 sales in last 12m (OnTheHouse/Cotality, read 27 Oct 2026) | I20: =G20*(1+Settings!$B$6) | J20: 72 | K20: 7 | L20: Active — provisional pass | M20: =IF(J20="","",ROUND(MAX(0,10*(1-J20/Filters!$B$4)),1)) | N20: 5 | O20: =IF(K20="","",ROUND(MAX(0,10*(1-K20/Filters!$B$5)),1)) | P20: 4 | Q20: 8 | R20: 6 | S20: 4 | T20: =IF(G20="","",ROUND(MAX(0,MIN(10,10*(Filters!$B$2-G20)/(Filters!$B$2-500000))),1)) | U20: 3 | V20: 5 | W20: =IF(M20="",0,COUNT(M20:V20)) | X20: =IF(W20<10,"",M20*ForcedChoiceCorrections!$B$6+N20*ForcedChoiceCorrections!$B$7+O20*ForcedChoiceCorrections!$B$8+P20*ForcedChoiceCorrections!$B$9+Q20*ForcedChoiceCorrections!$B$10+R20*ForcedChoiceCorrections!$B$11+S20*ForcedChoiceCorrections!$B$12+T20*ForcedChoiceCorrections!$B$13+U20*ForcedChoiceCorrections!$B$14+V20*ForcedChoiceCorrections!$B$15) | Y20: =IF(AND(ISNUMBER(SEARCH("pass",L20)),ISNUMBER(X20)),COUNTIFS(L$2:L$90,"*pass*",X$2:X$90,">"&X20)+1,"") | Z20: ABS 2021: 17.6% aged 65+, 10.9% non-Eng HH. Balyang Sanctuary on Barwon River; major public ED at Univ Hospital Geelong. 27 Oct 2026 research pass: drive times/ED and/or AVM price added; L re-evaluated. | SCORES 27 Oct 2026: M (near family) and T (price) are formulas from J and G; O from K. N, P, Q, R, S, U, V are ESTIMATES (Claude, general knowledge, not site-checked); S also rests on train Yes/No marked 'verify'. | CHECKED 27 Oct 2026, source run C1 (suburb level; Wikipedia, Victorian Places, ABS 2021 GCP DataPack). Pop 10,445; inner western Geelong, 'one of the highest points of urban Geelong', many of Geelong's oldest houses [Wikipedia Newtown, Victoria]. Nature: Queens Park beside the Barwon River, Balyang Sanctuary, Chilwell Gardens, Windmill Reserve [Wikipedia]; N 5 consistent. Village: established residential suburb incl. Chilwell; R 6 plausible. Train: no station named in the suburb [Wikipedia]; S 4 consistent. Indian community: India-born 1.3%, Indian ancestry 1.6%, Hinduism 1.1% [ABS 2021 GCP SAL21938]; P 4 generous (3 arguable). NOT checked: shops, GPs, beach distance (U 3), city trip (V 5), Victorian Places page not found. Scores unchanged. | AA20: 19. Newtown (Geelong) | Geelong | Active Shortlist | P: Medium-High (Barwon River) | Y: Medium (Near bay/coast) | Lens: Regional-city services + river sanctuary | Price: [Blank] | Basis: Not verified in report | Note: ABS 2021: 17.6% aged 65+, 10.9% non-Eng HH. Balyang Sanctuary on Barwon River; major public ED at Univ Hospital Geelong. | AB20: No | AC20: No station in suburb; Geelong stations nearby (recall; verify) | AD20: University Hospital Geelong ED. Origin approximated (Balyang area); GW time from Geelong centre | AE20: 1500000 | AF20: Maximum purchase price, excluding transaction and moving costs | AG20: AVM estimate | AH20: 27 Oct 2026 | AI20: Pass | AJ20: AVM house value ($1,182,945) is under $1.5M cap. Not a sale median. | AK20: SAL21938 | AL20: 10445 | AM20: 40 | AN20: 0.176 | AO20: 0.145 | AP20: 0.033 | AQ20: 0.013 | AR20: 0.016 | AS20: 0.011 | AT20: 0.003 | AU20: 0.088 | AV20: Mandarin 1.3%; Italian 0.6%; Croatian 0.5% | AW20: ABS 2021 Census General Community Profile DataPack, Suburbs and Localities (SAL), Victoria (tables G01, G02, G08, G09, G13, G14); downloaded 27 Oct 2026 from abs.gov.au. Place of usual residence. Newtown (Greater Geelong), SAL21938. | AX20: =IF(AU20="","",IF(OR(AU20>=0.5,AQ20>=0.08),"High",IF(OR(AU20>=0.3,AQ20>=0.04),"Medium","Low")))
A21: Highton (Geelong) | B21: Geelong | C21: Active Shortlist | D21: Medium-High (Hills/river) | E21: Medium (Near coast) | F21: Village-centre regional-city comparator | G21: 957797 | H21: AVM estimate (30 Sep 2026), NOT a verified sale median; unit $538,492; 504 sales in last 12m (OnTheHouse/Cotality, read 27 Oct 2026) | I21: =G21*(1+Settings!$B$6) | J21: 74 | K21: 9 | L21: Active — provisional pass | M21: =IF(J21="","",ROUND(MAX(0,10*(1-J21/Filters!$B$4)),1)) | N21: 6 | O21: =IF(K21="","",ROUND(MAX(0,10*(1-K21/Filters!$B$5)),1)) | P21: 4 | Q21: 8 | R21: 5 | S21: 3 | T21: =IF(G21="","",ROUND(MAX(0,MIN(10,10*(Filters!$B$2-G21)/(Filters!$B$2-500000))),1)) | U21: 3 | V21: 4 | W21: =IF(M21="",0,COUNT(M21:V21)) | X21: =IF(W21<10,"",M21*ForcedChoiceCorrections!$B$6+N21*ForcedChoiceCorrections!$B$7+O21*ForcedChoiceCorrections!$B$8+P21*ForcedChoiceCorrections!$B$9+Q21*ForcedChoiceCorrections!$B$10+R21*ForcedChoiceCorrections!$B$11+S21*ForcedChoiceCorrections!$B$12+T21*ForcedChoiceCorrections!$B$13+U21*ForcedChoiceCorrections!$B$14+V21*ForcedChoiceCorrections!$B$15) | Y21: =IF(AND(ISNUMBER(SEARCH("pass",L21)),ISNUMBER(X21)),COUNTIFS(L$2:L$90,"*pass*",X$2:X$90,">"&X21)+1,"") | Z21: Highton Village UDF; compare pocket gradients, station access & Univ Hospital Geelong ED journey. 27 Oct 2026 research pass: drive times/ED and/or AVM price added; L re-evaluated. | SCORES 27 Oct 2026: M (near family) and T (price) are formulas from J and G; O from K. N, P, Q, R, S, U, V are ESTIMATES (Claude, general knowledge, not site-checked); S also rests on train Yes/No marked 'verify'. | CHECKED 27 Oct 2026, full pass (suburb level). Pop 20,736 [ABS 2021 SAL21187]. Barwon River banks and Barrabool Hills; Queens Park in a river bend; 20 parks/reserves listed; tree-lined streets [Wikipedia Highton; City of Greater Geelong]; N 6 consistent. Village: Highton Village strip on Belle Vue Ave with a supermarket, small strip on Porter Ave, Barrabool Hills Plaza (2016) with Woolworths [Wikipedia Highton]; R 5 left. Shops & doctor: GPs include Highton Village Medical Clinic, The Highton Clinic, 291 Roslyn Road Medical Practice, Barrabool Hills Family Medical [healthdirect]; Q 8 consistent. Train/bus: no station; bus 42 (south) and 43 (north) from Geelong station via CBD to Deakin Waurn Ponds [Wikipedia Highton]; S 3 consistent. Indian community: India-born 505 (2.4%), Hindi 126 (0.6%), Punjabi 119 (0.6%); Indian ancestry and Hinduism/Sikhism not in top 5 [ABS SAL21187]; P 4 consistent. NOT checked: beach access (U 3 is an estimate), city-trip time (V 4 estimate), Indian grocer/temple, Univ Hospital Geelong drive. Scores unchanged. | AA21: 20. Highton (Geelong) | Geelong | Active Shortlist | P: Medium-High (Hills/river) | Y: Medium (Near coast) | Lens: Village-centre regional-city comparator | Price: [Blank] | Basis: Not verified in report | Note: Highton Village UDF; compare pocket gradients, station access & Univ Hospital Geelong ED journey. | AB21: No | AC21: No station; bus 42/43 from Geelong station (checked: Wikipedia Highton) | AD21: University Hospital Geelong ED | AE21: 1500000 | AF21: Maximum purchase price, excluding transaction and moving costs | AG21: AVM estimate | AH21: 27 Oct 2026 | AI21: Pass | AJ21: AVM house value ($957,797) is under $1.5M cap. Not a sale median. | AK21: SAL21187 | AL21: 20736 | AM21: 39 | AN21: 0.183 | AO21: 0.194 | AP21: 0.033 | AQ21: 0.024 | AR21: 0.027 | AS21: 0.018 | AT21: 0.005 | AU21: 0.13 | AV21: Mandarin 1.9%; Italian 0.8%; Arabic 0.7% | AW21: ABS 2021 Census General Community Profile DataPack, Suburbs and Localities (SAL), Victoria (tables G01, G02, G08, G09, G13, G14); downloaded 27 Oct 2026 from abs.gov.au. Place of usual residence. | AX21: =IF(AU21="","",IF(OR(AU21>=0.5,AQ21>=0.08),"High",IF(OR(AU21>=0.3,AQ21>=0.04),"Medium","Low")))
A22: Belgrave | B22: Dandenong Ranges | C22: Active Shortlist | D22: High (Forest & hills) | E22: Low (Inland) | F22: Stronger hills lifestyle on metro rail line | G22: 856437 | H22: AVM estimate (30 Sep 2026), NOT a verified sale median; unit $647,854; 72 sales in last 12m (OnTheHouse/Cotality, read 27 Oct 2026) | I22: =G22*(1+Settings!$B$6) | J22: 21 | K22: 7 | L22: Active — provisional pass | M22: =IF(J22="","",ROUND(MAX(0,10*(1-J22/Filters!$B$4)),1)) | N22: 9 | O22: =IF(K22="","",ROUND(MAX(0,10*(1-K22/Filters!$B$5)),1)) | P22: 3 | Q22: 6 | R22: 8 | S22: 7 | T22: =IF(G22="","",ROUND(MAX(0,MIN(10,10*(Filters!$B$2-G22)/(Filters!$B$2-500000))),1)) | U22: 0 | V22: 5 | W22: =IF(M22="",0,COUNT(M22:V22)) | X22: =IF(W22<10,"",M22*ForcedChoiceCorrections!$B$6+N22*ForcedChoiceCorrections!$B$7+O22*ForcedChoiceCorrections!$B$8+P22*ForcedChoiceCorrections!$B$9+Q22*ForcedChoiceCorrections!$B$10+R22*ForcedChoiceCorrections!$B$11+S22*ForcedChoiceCorrections!$B$12+T22*ForcedChoiceCorrections!$B$13+U22*ForcedChoiceCorrections!$B$14+V22*ForcedChoiceCorrections!$B$15) | Y22: =IF(AND(ISNUMBER(SEARCH("pass",L22)),ISNUMBER(X22)),COUNTIFS(L$2:L$90,"*pass*",X$2:X$90,">"&X22)+1,"") | Z22: Belgrave metro rail terminus; check steep gradients, bushfire/storm closures & Angliss/Maroondah ED drive. 27 Oct 2026 research pass: drive times/ED and/or AVM price added; L re-evaluated. | SCORES 27 Oct 2026: M (near family) and T (price) are formulas from J and G; O from K. N, P, Q, R, S, U, V are ESTIMATES (Claude, general knowledge, not site-checked); S also rests on train Yes/No marked 'verify'. | CHECKED 27 Oct 2026 (S train/bus, U beach, Q shops & doctor; web sources, suburb level, not address level): Terminus (weekend off-peak shuttle) so S 7. Puffing Billy 100 m away. GP: Belgrave Medical Clinic (healthdirect). Supermarket not confirmed; Q partly estimate. N, P, R, V remain estimates. | CHECKED 27 Oct 2026, second pass (N, P, R, V; suburb level). Nature: Belgrave Lake Park, a biolink between Dandenong Ranges National Park, Birdsland and Lysterfield Lake Park, with platypus in Monbulk Creek and mountain grey gum slopes; Puffing Billy runs through 24 km of cool temperate rainforest and farmland [Wikipedia Belgrave]; N 9 consistent. Village: Main Street commercial district with galleries and bookshops; shops on Bayview Rd [Wikipedia]; R 8 consistent. Indian community: India-born 0.4%, Hinduism 0.2% [ABS 2021 GCP SAL20188]; P 3 generous (1 arguable). City trip: 36 km E, line terminus [Wikipedia]; V 5 estimate. Scores unchanged. | AA22: 21. Belgrave | Dandenong Ranges | Active Shortlist | P: High (Forest & hills) | Y: Low (Inland) | Lens: Stronger hills lifestyle on metro rail line | Price: [Blank] | Basis: Not verified in report | Note: Belgrave metro rail terminus; check steep gradients, bushfire/storm closures & Angliss/Maroondah ED drive. | AB22: Yes | AC22: Belgrave station, Belgrave line terminus; weekend shuttle to Ringwood off-peak; 6 bus routes (checked: Wikipedia Belgrave station) | AD22: Angliss Hospital ED (24-hr status still to verify) | AE22: 1500000 | AF22: Maximum purchase price, excluding transaction and moving costs | AG22: AVM estimate | AH22: 27 Oct 2026 | AI22: Pass | AJ22: AVM house value ($856,437) is under $1.5M cap. Not a sale median. | AK22: SAL20188 | AL22: 3894 | AM22: 38 | AN22: 0.13 | AO22: 0.186 | AP22: 0.026 | AQ22: 0.004 | AR22: 0.009 | AS22: 0.002 | AT22: 0 | AU22: 0.07 | AV22: German 0.8%; Mandarin 0.6%; French 0.5% | AW22: ABS 2021 Census General Community Profile DataPack, Suburbs and Localities (SAL), Victoria (tables G01, G02, G08, G09, G13, G14); downloaded 27 Oct 2026 from abs.gov.au. Place of usual residence. | AX22: =IF(AU22="","",IF(OR(AU22>=0.5,AQ22>=0.08),"High",IF(OR(AU22>=0.3,AQ22>=0.04),"Medium","Low")))
A23: Upwey | B23: Dandenong Ranges | C23: Active Shortlist | D23: High (Foothills village) | E23: Low (Inland) | F23: Village character vs healthcare/transport practicality | G23: 929500 | H23: House sale median $929,500 (104 sales, Property.com.au) | I23: 985270 | J23: 17 | K23: 4 | L23: Active — provisional pass | M23: =IF(J23="","",ROUND(MAX(0,10*(1-J23/Filters!$B$4)),1)) | N23: 9 | O23: =IF(K23="","",ROUND(MAX(0,10*(1-K23/Filters!$B$5)),1)) | P23: 3 | Q23: 5 | R23: 8 | S23: 8 | T23: =IF(G23="","",ROUND(MAX(0,MIN(10,10*(Filters!$B$2-G23)/(Filters!$B$2-500000))),1)) | U23: 0 | V23: 5 | W23: =IF(M23="",0,COUNT(M23:V23)) | X23: =IF(W23<10,"",M23*ForcedChoiceCorrections!$B$6+N23*ForcedChoiceCorrections!$B$7+O23*ForcedChoiceCorrections!$B$8+P23*ForcedChoiceCorrections!$B$9+Q23*ForcedChoiceCorrections!$B$10+R23*ForcedChoiceCorrections!$B$11+S23*ForcedChoiceCorrections!$B$12+T23*ForcedChoiceCorrections!$B$13+U23*ForcedChoiceCorrections!$B$14+V23*ForcedChoiceCorrections!$B$15) | Y23: =IF(AND(ISNUMBER(SEARCH("pass",L23)),ISNUMBER(X23)),COUNTIFS(L$2:L$90,"*pass*",X$2:X$90,">"&X23)+1,"") | Z23: Belgrave rail line township; closer to foothills edge than Belgrave. | SCORES 27 Oct 2026: M (near family) and T (price) are formulas from J and G; O from K. N, P, Q, R, S, U, V are ESTIMATES (Claude, general knowledge, not site-checked); S also rests on train Yes/No marked 'verify'. | CHECKED 27 Oct 2026 (S train/bus, U beach, Q shops & doctor; web sources, suburb level, not address level): Station beside Main St; medical centre on Main St; no supermarket mentioned: Q lowered 6->5. Adjoins Dandenong Ranges NP; Ferny, Monbulk creeks (Wikipedia Upwey). N, P, R, V remain estimates. | CHECKED 27 Oct 2026, second pass (N, P, R, V; suburb level). Nature: Glenfern Valley Bushlands, 40 ha of remnant and rehabilitated forest down to Ferny Creek; ridge-top Glenfern Rd with views [Wikipedia Upwey]; N 9 consistent. Village: Main Street 'instilling a traditional community village nature', cafés with kerbside dining, medical and dental centre [Wikipedia]; R 7 consistent (8 arguable); medical centre on Main St supports Q. Indian community: India-born 0.6%, Hinduism 0.3%; 80.7% Australia-born [ABS 2021 GCP SAL22620; Wikipedia]; P 3 generous (1 arguable). City trip: 33 km E on the Belgrave line [Wikipedia]; V 5 estimate. Scores unchanged. | C3 28 Oct 2026: R 7->8 (source: Main Street 'instilling a traditional community village nature', kerbside cafés [Wikipedia Upwey]). | AA23: 22. Upwey | Dandenong Ranges | Active Shortlist | P: High (Foothills village) | Y: Low (Inland) | Lens: Village character vs healthcare/transport practicality | Price: 929500 | Basis: House sale median $929,500 (104 sales, Property.com.au) | Note: Belgrave rail line township; closer to foothills edge than Belgrave. | AB23: Yes | AC23: Upwey station, Belgrave line, beside Main Street (checked: Wikipedia Upwey) | AD23: Angliss Hospital ED (24-hr status still to verify) | AE23: 1500000 | AF23: Maximum purchase price, excluding transaction and moving costs | AG23: Suburb median | AH23: 26 Oct 2026 | AI23: Pass | AJ23: Published house price ($929,500) is under $1.5M cap. | AK23: SAL22620 | AL23: 6818 | AM23: 41 | AN23: 0.147 | AO23: 0.169 | AP23: 0.024 | AQ23: 0.006 | AR23: 0.01 | AS23: 0.003 | AT23: 0 | AU23: 0.063 | AV23: Mandarin 0.5%; Italian 0.4%; Russian 0.4% | AW23: ABS 2021 Census General Community Profile DataPack, Suburbs and Localities (SAL), Victoria (tables G01, G02, G08, G09, G13, G14); downloaded 27 Oct 2026 from abs.gov.au. Place of usual residence. | AX23: =IF(AU23="","",IF(OR(AU23>=0.5,AQ23>=0.08),"High",IF(OR(AU23>=0.3,AQ23>=0.04),"Medium","Low")))
A24: Tecoma | B24: Dandenong Ranges | C24: Active Shortlist | D24: High (Foothills/forest) | E24: Low (Inland) | F24: Established rail township between Upwey & Belgrave | G24: 894304 | H24: AVM estimate (30 Sep 2026), NOT a verified sale median; unit $655,831; 38 sales in last 12m (OnTheHouse/Cotality, read 27 Oct 2026) — few sales, weak | I24: =G24*(1+Settings!$B$6) | J24: 19 | K24: 5 | L24: Active — provisional pass | M24: =IF(J24="","",ROUND(MAX(0,10*(1-J24/Filters!$B$4)),1)) | N24: 9 | O24: =IF(K24="","",ROUND(MAX(0,10*(1-K24/Filters!$B$5)),1)) | P24: 3 | Q24: 4 | R24: 6 | S24: 7 | T24: =IF(G24="","",ROUND(MAX(0,MIN(10,10*(Filters!$B$2-G24)/(Filters!$B$2-500000))),1)) | U24: 0 | V24: 5 | W24: =IF(M24="",0,COUNT(M24:V24)) | X24: =IF(W24<10,"",M24*ForcedChoiceCorrections!$B$6+N24*ForcedChoiceCorrections!$B$7+O24*ForcedChoiceCorrections!$B$8+P24*ForcedChoiceCorrections!$B$9+Q24*ForcedChoiceCorrections!$B$10+R24*ForcedChoiceCorrections!$B$11+S24*ForcedChoiceCorrections!$B$12+T24*ForcedChoiceCorrections!$B$13+U24*ForcedChoiceCorrections!$B$14+V24*ForcedChoiceCorrections!$B$15) | Y24: =IF(AND(ISNUMBER(SEARCH("pass",L24)),ISNUMBER(X24)),COUNTIFS(L$2:L$90,"*pass*",X$2:X$90,">"&X24)+1,"") | Z24: Belgrave rail line; council groups Belgrave-Tecoma-Upwey as established townships. 27 Oct 2026 research pass: drive times/ED and/or AVM price added; L re-evaluated. | SCORES 27 Oct 2026: M (near family) and T (price) are formulas from J and G; O from K. N, P, Q, R, S, U, V are ESTIMATES (Claude, general knowledge, not site-checked); S also rests on train Yes/No marked 'verify'. Low sales count. | CHECKED 27 Oct 2026, source run C1 (suburb level; Wikipedia, Victorian Places, ABS 2021 GCP DataPack). Pop 2,064; 35 km E of CBD, 1 km W of Belgrave, adjoining Sherbrooke Forest to the north [Wikipedia Tecoma]. Nature: 'residences are built in hilly country, well planted with trees'; bushfire exposure from the National Park to the north [Victorian Places]; N 9 consistent. Village: 'a small strip shopping centre, somewhat held in check by its proximity to Belgrave'; residents campaigned against a fast-food chain as out of character [Victorian Places]; R 6 consistent. Shops: Q 4 consistent (Belgrave next door). Train: Tecoma station on the Belgrave line [Victorian Places]; S 7 consistent. Indian community: India-born 0.3%, Hinduism 0.3%, Sikhism 0.4% [ABS 2021 GCP SAL22476]; P 3 generous (1-2 arguable). City trip: 35 km by train; V 5 estimate. NOT checked: GPs, journey time. Scores unchanged. | AA24: 23. Tecoma | Dandenong Ranges | Active Shortlist | P: High (Foothills/forest) | Y: Low (Inland) | Lens: Established rail township between Upwey & Belgrave | Price: [Blank] | Basis: Not verified in report | Note: Belgrave rail line; council groups Belgrave-Tecoma-Upwey as established townships. | AB24: Yes | AC24: Tecoma station, Belgrave line (per sheet note) | AD24: Angliss Hospital ED (24-hr status still to verify) | AE24: 1500000 | AF24: Maximum purchase price, excluding transaction and moving costs | AG24: AVM estimate | AH24: 27 Oct 2026 | AI24: Pass | AJ24: AVM house value ($894,304) is under $1.5M cap. Not a sale median. | AK24: SAL22476 | AL24: 2064 | AM24: 42 | AN24: 0.153 | AO24: 0.17 | AP24: 0.029 | AQ24: 0.003 | AR24: 0.009 | AS24: 0.003 | AT24: 0.004 | AU24: 0.045 | AV24: German 0.7%; Italian 0.5%; Hindi 0.4% | AW24: ABS 2021 Census General Community Profile DataPack, Suburbs and Localities (SAL), Victoria (tables G01, G02, G08, G09, G13, G14); downloaded 27 Oct 2026 from abs.gov.au. Place of usual residence. Small population: ABS randomly adjusts small counts, so treat shares under 1% as noise. | AX24: =IF(AU24="","",IF(OR(AU24>=0.5,AQ24>=0.08),"High",IF(OR(AU24>=0.3,AQ24>=0.04),"Medium","Low")))
A25: The Basin | B25: Dandenong Foothills | C25: Active Shortlist | D25: High (National park edge) | E25: Low (Inland) | F25: Forest-edge living without a ridge village | G25: 845187 | H25: AVM estimate (30 Sep 2026), NOT a verified sale median; unit $728,871; 66 sales in last 12m (OnTheHouse/Cotality, read 27 Oct 2026) | I25: =G25*(1+Settings!$B$6) | J25: 17 | K25: 10 | L25: Active — provisional pass | M25: =IF(J25="","",ROUND(MAX(0,10*(1-J25/Filters!$B$4)),1)) | N25: 8 | O25: =IF(K25="","",ROUND(MAX(0,10*(1-K25/Filters!$B$5)),1)) | P25: 4 | Q25: 4 | R25: 7 | S25: 3 | T25: =IF(G25="","",ROUND(MAX(0,MIN(10,10*(Filters!$B$2-G25)/(Filters!$B$2-500000))),1)) | U25: 0 | V25: 4 | W25: =IF(M25="",0,COUNT(M25:V25)) | X25: =IF(W25<10,"",M25*ForcedChoiceCorrections!$B$6+N25*ForcedChoiceCorrections!$B$7+O25*ForcedChoiceCorrections!$B$8+P25*ForcedChoiceCorrections!$B$9+Q25*ForcedChoiceCorrections!$B$10+R25*ForcedChoiceCorrections!$B$11+S25*ForcedChoiceCorrections!$B$12+T25*ForcedChoiceCorrections!$B$13+U25*ForcedChoiceCorrections!$B$14+V25*ForcedChoiceCorrections!$B$15) | Y25: =IF(AND(ISNUMBER(SEARCH("pass",L25)),ISNUMBER(X25)),COUNTIFS(L$2:L$90,"*pass*",X$2:X$90,">"&X25)+1,"") | Z25: Adjoins Dandenong Ranges National Park; verify bus/station link & Angliss Hospital ED drive. 27 Oct 2026 research pass: drive times/ED and/or AVM price added; L re-evaluated. | SCORES 27 Oct 2026: M (near family) and T (price) are formulas from J and G; O from K. N, P, Q, R, S, U, V are ESTIMATES (Claude, general knowledge, not site-checked); S also rests on train Yes/No marked 'verify'. | CHECKED 27 Oct 2026, source run C1 (suburb level; Wikipedia, Victorian Places, ABS 2021 GCP DataPack). Pop 4,497; 31 km E of CBD; part of a Melbourne green wedge, 'nestled into the forest covered foothills of Mount Dandenong' and Dandenong Ranges National Park incl. Doongalla Forest; bushy parks (Wicks Reserve) and farmland [Wikipedia The Basin]. N 8 consistent. Village: shops round 'The Basin Triangle' 'amidst a village atmosphere': licensed post office, two pubs, cafés, greengrocer, butcher, bookstore [Wikipedia]; R 7 consistent. Shops: no supermarket listed; Q 4 consistent. Transport: no station; bus 755 to Bayswater, Boronia and Ferntree Gully stations [Wikipedia]; S 3 consistent. Indian community: Vinayagar Hindu Temple is in the suburb [Wikipedia; Victorian Places 'a Hindu temple']; residents India-born 0.2%, Indian ancestry 0.9%, Hinduism 0.5% [ABS 2021 GCP SAL22496]; P 4 rests on the temple, not on residents. Hazards: 'topography causes strong wind which can fan severe fires'; 'much of the area is also flood prone' [Victorian Places]. City trip: 31 km [Wikipedia]; journey time not stated; V 4 estimate. NOT checked: GPs, bus frequency, journey time. Scores unchanged. | AA25: 24. The Basin | Dandenong Foothills | Active Shortlist | P: High (National park edge) | Y: Low (Inland) | Lens: Forest-edge living without a ridge village | Price: [Blank] | Basis: Not verified in report | Note: Adjoins Dandenong Ranges National Park; verify bus/station link & Angliss Hospital ED drive. | AB25: No | AC25: No station; bus link unverified (per sheet note) | AD25: Angliss Hospital ED (24-hr status still to verify) | AE25: 1500000 | AF25: Maximum purchase price, excluding transaction and moving costs | AG25: AVM estimate | AH25: 27 Oct 2026 | AI25: Pass | AJ25: AVM house value ($845,187) is under $1.5M cap. Not a sale median. | AK25: SAL22496 | AL25: 4497 | AM25: 40 | AN25: 0.172 | AO25: 0.17 | AP25: 0.034 | AQ25: 0.002 | AR25: 0.009 | AS25: 0.005 | AT25: 0 | AU25: 0.082 | AV25: German 1.8%; Mandarin 1.1%; Italian 0.5% | AW25: ABS 2021 Census General Community Profile DataPack, Suburbs and Localities (SAL), Victoria (tables G01, G02, G08, G09, G13, G14); downloaded 27 Oct 2026 from abs.gov.au. Place of usual residence. | AX25: =IF(AU25="","",IF(OR(AU25>=0.5,AQ25>=0.08),"High",IF(OR(AU25>=0.3,AQ25>=0.04),"Medium","Low")))
A26: Montrose | B26: Dandenong Foothills | C26: Active Shortlist | D26: High (Mountain backdrop) | E26: Low (Inland) | F26: Foothills township between suburbs & ridge | G26: 968458 | H26: AVM estimate (30 Sep 2026), NOT a verified sale median; unit $712,988; 85 sales in last 12m (OnTheHouse/Cotality, read 27 Oct 2026) | I26: =G26*(1+Settings!$B$6) | J26: 22 | K26: 12 | L26: Active — provisional pass | M26: =IF(J26="","",ROUND(MAX(0,10*(1-J26/Filters!$B$4)),1)) | N26: 8 | O26: =IF(K26="","",ROUND(MAX(0,10*(1-K26/Filters!$B$5)),1)) | P26: 3 | Q26: 5 | R26: 6 | S26: 3 | T26: =IF(G26="","",ROUND(MAX(0,MIN(10,10*(Filters!$B$2-G26)/(Filters!$B$2-500000))),1)) | U26: 0 | V26: 4 | W26: =IF(M26="",0,COUNT(M26:V26)) | X26: =IF(W26<10,"",M26*ForcedChoiceCorrections!$B$6+N26*ForcedChoiceCorrections!$B$7+O26*ForcedChoiceCorrections!$B$8+P26*ForcedChoiceCorrections!$B$9+Q26*ForcedChoiceCorrections!$B$10+R26*ForcedChoiceCorrections!$B$11+S26*ForcedChoiceCorrections!$B$12+T26*ForcedChoiceCorrections!$B$13+U26*ForcedChoiceCorrections!$B$14+V26*ForcedChoiceCorrections!$B$15) | Y26: =IF(AND(ISNUMBER(SEARCH("pass",L26)),ISNUMBER(X26)),COUNTIFS(L$2:L$90,"*pass*",X$2:X$90,">"&X26)+1,"") | Z26: Township shopping & community hub; verify non-rail transport, fire exposure & ED journey. 27 Oct 2026 research pass: drive times/ED and/or AVM price added; L re-evaluated. | SCORES 27 Oct 2026: M (near family) and T (price) are formulas from J and G; O from K. N, P, Q, R, S, U, V are ESTIMATES (Claude, general knowledge, not site-checked); S also rests on train Yes/No marked 'verify'. | CHECKED 27 Oct 2026, source run C1 (suburb level; Wikipedia, Victorian Places, ABS 2021 GCP DataPack). Pop 6,900; 33 km E of CBD at the foothills of Mount Dandenong, altitude 91-324 m [Wikipedia Montrose]. Nature: 'five bush reserves and two linear reserves'; government buy-back of steep land to protect bush; houses lost to fire in 1961 [Victorian Places]; N 8 consistent. Village: shopping area at Mount Dandenong and Swansea Rds with community centre and pioneer cottage; strong local preservation groups [Victorian Places]; R 6 consistent. Train: no station; 'not far from the Mooroolbark railway station' [Victorian Places]; S 3 consistent (bus not checked). Indian community: India-born 0.4%, Hinduism 0.2% [ABS 2021 GCP SAL21736]; P 3 generous (1-2 arguable). City trip: 33 km, no station; V 4 estimate. NOT checked: GPs, supermarket, bus. Scores unchanged. | AA26: 25. Montrose | Dandenong Foothills | Active Shortlist | P: High (Mountain backdrop) | Y: Low (Inland) | Lens: Foothills township between suburbs & ridge | Price: [Blank] | Basis: Not verified in report | Note: Township shopping & community hub; verify non-rail transport, fire exposure & ED journey. | AB26: No | AC26: No station; Mooroolbark/Lilydale stations nearby (recall; verify) | AD26: Maroondah Hospital ED | AE26: 1500000 | AF26: Maximum purchase price, excluding transaction and moving costs | AG26: AVM estimate | AH26: 27 Oct 2026 | AI26: Pass | AJ26: AVM house value ($968,458) is under $1.5M cap. Not a sale median. | AK26: SAL21736 | AL26: 6900 | AM26: 41 | AN26: 0.195 | AO26: 0.145 | AP26: 0.026 | AQ26: 0.004 | AR26: 0.007 | AS26: 0.002 | AT26: 0.001 | AU26: 0.048 | AV26: German 0.5%; Greek 0.3%; Italian 0.3% | AW26: ABS 2021 Census General Community Profile DataPack, Suburbs and Localities (SAL), Victoria (tables G01, G02, G08, G09, G13, G14); downloaded 27 Oct 2026 from abs.gov.au. Place of usual residence. | AX26: =IF(AU26="","",IF(OR(AU26>=0.5,AQ26>=0.08),"High",IF(OR(AU26>=0.3,AQ26>=0.04),"Medium","Low")))
A27: Mount Evelyn | B27: Yarra Ranges | C27: Active Shortlist | D27: High (Aqueduct & rail trails) | E27: Low (Inland) | F27: Forest village closer than Warburton | G27: 915472 | H27: AVM estimate (30 Sep 2026), NOT a verified sale median; unit $693,463; 130 sales in last 12m (OnTheHouse/Cotality, read 27 Oct 2026) | I27: =G27*(1+Settings!$B$6) | J27: 27 | K27: 17 | L27: Active — provisional pass | M27: =IF(J27="","",ROUND(MAX(0,10*(1-J27/Filters!$B$4)),1)) | N27: 8 | O27: =IF(K27="","",ROUND(MAX(0,10*(1-K27/Filters!$B$5)),1)) | P27: 2 | Q27: 5 | R27: 6 | S27: 3 | T27: =IF(G27="","",ROUND(MAX(0,MIN(10,10*(Filters!$B$2-G27)/(Filters!$B$2-500000))),1)) | U27: 0 | V27: 4 | W27: =IF(M27="",0,COUNT(M27:V27)) | X27: =IF(W27<10,"",M27*ForcedChoiceCorrections!$B$6+N27*ForcedChoiceCorrections!$B$7+O27*ForcedChoiceCorrections!$B$8+P27*ForcedChoiceCorrections!$B$9+Q27*ForcedChoiceCorrections!$B$10+R27*ForcedChoiceCorrections!$B$11+S27*ForcedChoiceCorrections!$B$12+T27*ForcedChoiceCorrections!$B$13+U27*ForcedChoiceCorrections!$B$14+V27*ForcedChoiceCorrections!$B$15) | Y27: =IF(AND(ISNUMBER(SEARCH("pass",L27)),ISNUMBER(X27)),COUNTIFS(L$2:L$90,"*pass*",X$2:X$90,">"&X27)+1,"") | Z27: Warburton Rail Trail & Aqueduct Trail (no passenger rail); verify Maroondah ED journey. 27 Oct 2026 research pass: drive times/ED and/or AVM price added; L re-evaluated. | SCORES 27 Oct 2026: M (near family) and T (price) are formulas from J and G; O from K. N, P, Q, R, S, U, V are ESTIMATES (Claude, general knowledge, not site-checked); S also rests on train Yes/No marked 'verify'. | CHECKED 27 Oct 2026, source run C1 (suburb level; Wikipedia, Victorian Places, ABS 2021 GCP DataPack). Pop 9,799; 37 km E of CBD, in a bend of Olinda Creek [Wikipedia Mount Evelyn]. Nature: Mount Evelyn Forest (part of Dandenong Ranges National Park) in the south; Warburton Rail Trail and Aqueduct Walk pass through [Wikipedia; Victorian Places]; N 8 consistent. Village: shopping centre west of the former station 'accompanied by several community meeting places and churches' [Victorian Places]; R 6 consistent. Train: railway closed 1965, now the rail trail [Wikipedia]; no station; S 3 consistent (bus not checked). Shops: supermarket not named; Q 5 estimate. Indian community: India-born 0.2%, Hinduism 0.2% [ABS 2021 GCP SAL21795]; P 2 consistent (1 arguable). City trip: 37 km, no rail; V 4 estimate. NOT checked: GPs, supermarket, bus, journey time. Scores unchanged. | AA27: 26. Mount Evelyn | Yarra Ranges | Active Shortlist | P: High (Aqueduct & rail trails) | Y: Low (Inland) | Lens: Forest village closer than Warburton | Price: [Blank] | Basis: Not verified in report | Note: Warburton Rail Trail & Aqueduct Trail (no passenger rail); verify Maroondah ED journey. | AB27: No | AC27: No passenger rail (per sheet note) | AD27: Maroondah Hospital ED | AE27: 1500000 | AF27: Maximum purchase price, excluding transaction and moving costs | AG27: AVM estimate | AH27: 27 Oct 2026 | AI27: Pass | AJ27: AVM house value ($915,472) is under $1.5M cap. Not a sale median. | AK27: SAL21795 | AL27: 9799 | AM27: 38 | AN27: 0.149 | AO27: 0.127 | AP27: 0.018 | AQ27: 0.002 | AR27: 0.005 | AS27: 0.002 | AT27: 0 | AU27: 0.042 | AV27: Italian 0.4%; German 0.2%; French 0.2% | AW27: ABS 2021 Census General Community Profile DataPack, Suburbs and Localities (SAL), Victoria (tables G01, G02, G08, G09, G13, G14); downloaded 27 Oct 2026 from abs.gov.au. Place of usual residence. | AX27: =IF(AU27="","",IF(OR(AU27>=0.5,AQ27>=0.08),"High",IF(OR(AU27>=0.3,AQ27>=0.04),"Medium","Low")))
A28: Croydon | B28: Outer East Melbourne | C28: Active Shortlist | D28: Medium (Leafy parks) | E28: Low (Inland) | F28: Practical outer-east control with rail & services | G28: 898896 | H28: AVM estimate (30 Sep 2026), NOT a verified sale median; unit $670,300; 704 sales in last 12m (OnTheHouse/Cotality, read 27 Oct 2026) | I28: =G28*(1+Settings!$B$6) | J28: 18 | K28: 6 | L28: Active — provisional pass | M28: =IF(J28="","",ROUND(MAX(0,10*(1-J28/Filters!$B$4)),1)) | N28: 5 | O28: =IF(K28="","",ROUND(MAX(0,10*(1-K28/Filters!$B$5)),1)) | P28: 5 | Q28: 9 | R28: 4 | S28: 8 | T28: =IF(G28="","",ROUND(MAX(0,MIN(10,10*(Filters!$B$2-G28)/(Filters!$B$2-500000))),1)) | U28: 0 | V28: 6 | W28: =IF(M28="",0,COUNT(M28:V28)) | X28: =IF(W28<10,"",M28*ForcedChoiceCorrections!$B$6+N28*ForcedChoiceCorrections!$B$7+O28*ForcedChoiceCorrections!$B$8+P28*ForcedChoiceCorrections!$B$9+Q28*ForcedChoiceCorrections!$B$10+R28*ForcedChoiceCorrections!$B$11+S28*ForcedChoiceCorrections!$B$12+T28*ForcedChoiceCorrections!$B$13+U28*ForcedChoiceCorrections!$B$14+V28*ForcedChoiceCorrections!$B$15) | Y28: =IF(AND(ISNUMBER(SEARCH("pass",L28)),ISNUMBER(X28)),COUNTIFS(L$2:L$90,"*pass*",X$2:X$90,">"&X28)+1,"") | Z28: Main St activity centre, train/bus interchange & Croydon Park; benchmark near Maroondah ED. 27 Oct 2026 research pass: drive times/ED and/or AVM price added; L re-evaluated. | SCORES 27 Oct 2026: M (near family) and T (price) are formulas from J and G; O from K. N, P, Q, R, S, U, V are ESTIMATES (Claude, general knowledge, not site-checked); S also rests on train Yes/No marked 'verify'. | CHECKED 27 Oct 2026, full pass (suburb level). Pop 28,608, 30 km E of CBD, elevation 124 m [Wikipedia Croydon; ABS SAL20682]. Nature: named green spaces are Croydon Park, Dorset Recreational Reserve, Silcock Reserve; Wikipedia does not describe bushland or hills, so N 5 rests on estimate only. Village: Croydon Main Street 187+ traders, Arndale Centre, Croydon Central, long-running Monday market; page also notes denser housing since late 1990s [Wikipedia]; R 4 consistent. Train: Croydon station (Lilydale line, myki zone 2) was closed 30 Jan 2024 for the Coolstore Rd level-crossing removal and REOPENED 12 Aug 2024; platforms to Flinders St via City Loop; 14-bay bus interchange (Nov 2024); 578 car spaces [Wikipedia Croydon station]; S 8 consistent. Shops & doctor: 8 GP clinics incl. Croydon Medical Centre, Main Medical Centre, Wicklow Ave Medical Centre, HealthMint Croydon [healthdirect]; Q 9 consistent. Indian community: India-born 665 (2.3%), Hindi 223 (0.8%); Indian ancestry and Hinduism/Sikhism not in top 5 [ABS SAL20682]; P 5 looks generous vs Highton 4 at similar share, left unchanged. NOT checked: city-trip time (V 6 estimate), Indian grocer/temple, Maroondah ED drive. Scores unchanged. | AA28: 27. Croydon | Outer East Melbourne | Active Shortlist | P: Medium (Leafy parks) | Y: Low (Inland) | Lens: Practical outer-east control with rail & services | Price: [Blank] | Basis: Not verified in report | Note: Main St activity centre, train/bus interchange & Croydon Park; benchmark near Maroondah ED. | AB28: Yes | AC28: Croydon station, Lilydale line, reopened 12 Aug 2024 (checked: Wikipedia Croydon station) | AD28: Maroondah Hospital ED | AE28: 1500000 | AF28: Maximum purchase price, excluding transaction and moving costs | AG28: AVM estimate | AH28: 27 Oct 2026 | AI28: Pass | AJ28: AVM house value ($898,896) is under $1.5M cap. Not a sale median. | AK28: SAL20682 | AL28: 28608 | AM28: 39 | AN28: 0.204 | AO28: 0.254 | AP28: 0.035 | AQ28: 0.023 | AR28: 0.029 | AS28: 0.022 | AT28: 0.005 | AU28: 0.189 | AV28: Mandarin 3.5%; Cantonese 1.2%; Hindi 0.8% | AW28: ABS 2021 Census General Community Profile DataPack, Suburbs and Localities (SAL), Victoria (tables G01, G02, G08, G09, G13, G14); downloaded 27 Oct 2026 from abs.gov.au. Place of usual residence. | AX28: =IF(AU28="","",IF(OR(AU28>=0.5,AQ28>=0.08),"High",IF(OR(AU28>=0.3,AQ28>=0.04),"Medium","Low")))
A29: Warragul | B29: West Gippsland | C29: Active Shortlist | D29: High (Rolling hills/gardens) | E29: Low (Inland) | F29: Regional town with V/Line rail & local hospital ED | G29: 620000 | H29: 3-bed house median $620k; 4-bed $732.5k (Domain) | I29: 657200 | J29: 58 | K29: 2 | L29: Active — provisional pass | M29: =IF(J29="","",ROUND(MAX(0,10*(1-J29/Filters!$B$4)),1)) | N29: 5 | O29: =IF(K29="","",ROUND(MAX(0,10*(1-K29/Filters!$B$5)),1)) | P29: 3 | Q29: 8 | R29: 6 | S29: 6 | T29: =IF(G29="","",ROUND(MAX(0,MIN(10,10*(Filters!$B$2-G29)/(Filters!$B$2-500000))),1)) | U29: 0 | V29: 4 | W29: =IF(M29="",0,COUNT(M29:V29)) | X29: =IF(W29<10,"",M29*ForcedChoiceCorrections!$B$6+N29*ForcedChoiceCorrections!$B$7+O29*ForcedChoiceCorrections!$B$8+P29*ForcedChoiceCorrections!$B$9+Q29*ForcedChoiceCorrections!$B$10+R29*ForcedChoiceCorrections!$B$11+S29*ForcedChoiceCorrections!$B$12+T29*ForcedChoiceCorrections!$B$13+U29*ForcedChoiceCorrections!$B$14+V29*ForcedChoiceCorrections!$B$15) | Y29: =IF(AND(ISNUMBER(SEARCH("pass",L29)),ISNUMBER(X29)),COUNTIFS(L$2:L$90,"*pass*",X$2:X$90,">"&X29)+1,"") | Z29: Town-centre V/Line station & West Gippsland Hospital ED (verify wait times & GW drive). | SCORES 27 Oct 2026: M (near family) and T (price) are formulas from J and G; O from K. N, P, Q, R, S, U, V are ESTIMATES (Claude, general knowledge, not site-checked); S also rests on train Yes/No marked 'verify'. | CHECKED 27 Oct 2026, full pass (suburb level). Pop 19,856; ~102 km SE of Melbourne; between the Strzelecki Ranges and Mt Baw Baw plateau [Wikipedia Warragul; ABS SAL22698]. Nature: Linear Park Arts Discovery Trail through town parks [Wikipedia]; Mount Worth State Park (temperate rainforest, Strzelecki Ranges) is the only outdoor site listed [Monash Rural Health Warragul page]; N 5 looks low for the setting, 6 arguable, but no trail detail found. Train: staffed V/Line station, Gippsland line (Traralgon/Bairnsdale), 99.67 km from Southern Cross, myki zone 6/7, 200 parking spaces [Wikipedia Warragul station]; at-least-hourly services and ~1 h 40 min from Southern Cross [Monash page; secondary source]; S 6 consistent. Shops & doctor: 7 GP clinics (Warragul Family Medicine, West Gippsland Medical Clinic x2, Latrobe Community Health, Warragul Medical Centre, Central Clinic, Gladstone St Medical) [healthdirect]; public hospital = West Gippsland Healthcare Group [Wikipedia]; supermarket names NOT confirmed; Q 8 consistent. Indian community: India-born 194 (1.0%), Punjabi 86 (0.4%); Indian ancestry and Hinduism/Sikhism not in top 5 [ABS SAL22698]; P 3 consistent. Village: Wikipedia calls it the main service centre of West Gippsland, with a monthly farmers' market in Civic Park (3rd Saturday); no village-character description found; R 6 unverified. NOT checked: city-trip (V 4 estimate), beach (0, inland), weekday frequency from official timetable. Scores unchanged. | AA29: 28. Warragul | West Gippsland | Active Shortlist | P: High (Rolling hills/gardens) | Y: Low (Inland) | Lens: Regional town with V/Line rail & local hospital ED | Price: 620000 | Basis: 3-bed house median $620k; 4-bed $732.5k (Domain) | Note: Town-centre V/Line station & West Gippsland Hospital ED (verify wait times & GW drive). | AB29: Yes | AC29: Warragul station, V/Line Gippsland line, myki 6/7, at-least-hourly (checked: Wikipedia Warragul station; Monash Rural Health) | AD29: West Gippsland Hospital ED (local) | AE29: 1500000 | AF29: Maximum purchase price, excluding transaction and moving costs | AG29: Suburb median | AH29: 26 Oct 2026 | AI29: Pass | AJ29: Published house price ($620,000) is under $1.5M cap. | AK29: SAL22698 | AL29: 19856 | AM29: 40 | AN29: 0.216 | AO29: 0.14 | AP29: 0.05 | AQ29: 0.01 | AR29: 0.013 | AS29: 0.007 | AT29: 0.004 | AU29: 0.068 | AV29: Mandarin 0.8%; Punjabi 0.4%; Italian 0.3% | AW29: ABS 2021 Census General Community Profile DataPack, Suburbs and Localities (SAL), Victoria (tables G01, G02, G08, G09, G13, G14); downloaded 27 Oct 2026 from abs.gov.au. Place of usual residence. | AX29: =IF(AU29="","",IF(OR(AU29>=0.5,AQ29>=0.08),"High",IF(OR(AU29>=0.3,AQ29>=0.04),"Medium","Low")))
A30: Mount Eliza | B30: Mornington Peninsula | C30: Active Shortlist | D30: High (Woodland & gullies) | E30: High (Canadian Bay/coast) | F30: Rare overlap of bushland reserves, village & bay | G30: 1610862 | H30: AVM estimate (30 Sep 2026), NOT a verified sale median; unit $778,590; 313 sales in last 12m (OnTheHouse/Cotality, read 27 Oct 2026) | I30: =G30*(1+Settings!$B$6) | J30: 34 | K30: 10 | L30: Active — needs data | O30: =IF(K30="","",ROUND(MAX(0,10*(1-K30/Filters!$B$5)),1)) | W30: =IF(M30="",0,COUNT(M30:V30)) | X30: =IF(W30<10,"",M30*ForcedChoiceCorrections!$B$6+N30*ForcedChoiceCorrections!$B$7+O30*ForcedChoiceCorrections!$B$8+P30*ForcedChoiceCorrections!$B$9+Q30*ForcedChoiceCorrections!$B$10+R30*ForcedChoiceCorrections!$B$11+S30*ForcedChoiceCorrections!$B$12+T30*ForcedChoiceCorrections!$B$13+U30*ForcedChoiceCorrections!$B$14+V30*ForcedChoiceCorrections!$B$15) | Y30: =IF(AND(ISNUMBER(SEARCH("pass",L30)),ISNUMBER(X30)),COUNTIFS(L$2:L$90,"*pass*",X$2:X$90,">"&X30)+1,"") | Z30: Tests BOTH parents' bushland preference and your coastal-nature preference; verify bus 781 & Frankston ED drive. 27 Oct 2026 research pass: drive times/ED and/or AVM price added; L re-evaluated. | AA30: 29. Mount Eliza | Mornington Peninsula | Active Shortlist | P: High (Woodland & gullies) | Y: High (Canadian Bay/coast) | Lens: Rare overlap of bushland reserves, village & bay | Price: [Blank] | Basis: Not verified in report | Note: Tests BOTH parents' bushland preference and your coastal-nature preference; verify bus 781 & Frankston ED drive. | AB30: No | AC30: No rail; bus 781 to Frankston (per sheet note) | AD30: Peninsula University Hospital ED | AE30: 1500000 | AF30: Maximum purchase price, excluding transaction and moving costs | AG30: AVM estimate | AH30: 27 Oct 2026 | AI30: Needs data | AJ30: AVM house value ($1,610,862) is over the $1.5M cap; needs a documented search for 3+ bed homes under the cap. | AK30: SAL21793 | AL30: 18734 | AM30: 45 | AN30: 0.223 | AO30: 0.223 | AP30: 0.032 | AQ30: 0.004 | AR30: 0.01 | AS30: 0.005 | AT30: 0.001 | AU30: 0.063 | AV30: Mandarin 0.8%; Greek 0.7%; Italian 0.5% | AW30: ABS 2021 Census General Community Profile DataPack, Suburbs and Localities (SAL), Victoria (tables G01, G02, G08, G09, G13, G14); downloaded 27 Oct 2026 from abs.gov.au. Place of usual residence. | AX30: =IF(AU30="","",IF(OR(AU30>=0.5,AQ30>=0.08),"High",IF(OR(AU30>=0.3,AQ30>=0.04),"Medium","Low")))
A31: Mornington | B31: Mornington Peninsula | C31: Active Shortlist | D31: Medium (Parks & gardens) | E31: High (Bay beaches/harbor) | F31: Established coastal town centre & Main Street | G31: 1096505 | H31: AVM estimate (30 Sep 2026), NOT a verified sale median; unit $790,244; 629 sales in last 12m (OnTheHouse/Cotality, read 27 Oct 2026) | I31: =G31*(1+Settings!$B$6) | J31: 40 | K31: 15 | L31: Active — provisional pass | M31: =IF(J31="","",ROUND(MAX(0,10*(1-J31/Filters!$B$4)),1)) | N31: 6 | O31: =IF(K31="","",ROUND(MAX(0,10*(1-K31/Filters!$B$5)),1)) | P31: 3 | Q31: 9 | R31: 7 | S31: 3 | T31: =IF(G31="","",ROUND(MAX(0,MIN(10,10*(Filters!$B$2-G31)/(Filters!$B$2-500000))),1)) | U31: 9 | V31: 3 | W31: =IF(M31="",0,COUNT(M31:V31)) | X31: =IF(W31<10,"",M31*ForcedChoiceCorrections!$B$6+N31*ForcedChoiceCorrections!$B$7+O31*ForcedChoiceCorrections!$B$8+P31*ForcedChoiceCorrections!$B$9+Q31*ForcedChoiceCorrections!$B$10+R31*ForcedChoiceCorrections!$B$11+S31*ForcedChoiceCorrections!$B$12+T31*ForcedChoiceCorrections!$B$13+U31*ForcedChoiceCorrections!$B$14+V31*ForcedChoiceCorrections!$B$15) | Y31: =IF(AND(ISNUMBER(SEARCH("pass",L31)),ISNUMBER(X31)),COUNTIFS(L$2:L$90,"*pass*",X$2:X$90,">"&X31)+1,"") | Z31: Substantial town services on bay; no passenger train (bus to Frankston); verify Frankston/Rosebud ED drive. 27 Oct 2026 research pass: drive times/ED and/or AVM price added; L re-evaluated. | SCORES 27 Oct 2026: M (near family) and T (price) are formulas from J and G; O from K. N, P, Q, R, S, U, V are ESTIMATES (Claude, general knowledge, not site-checked); S also rests on train Yes/No marked 'verify'. | CHECKED 27 Oct 2026 (S train/bus, U beach, Q shops & doctor; web sources, suburb level, not address level): No rail; bus to Frankston. Mothers Beach, Mills Beach patrolled (Visit Mornington Peninsula). GPs: Mornington Village Medical Centre, Mornington Medical Group (healthdirect). Supermarket not confirmed; Q partly estimate. N, P, R, V remain estimates. | CHECKED 27 Oct 2026, second pass (N, P, R, V; suburb level). Indian community: India-born, Indian ancestry, Hinduism/Sikhism and Hindi/Punjabi are all absent from the ABS 2021 top responses (pop 25,759; 74.0% Australia-born) [ABS QuickStats SAL21763]; web search found no Indian grocer or temple (no result is not proof). Nature: sources name parks and gardens only (Botanical Rose Gardens, Alexandra Park, Dallas Brooks Park, Narambi Reserve), no bushland, creeks or trails [Wikipedia Mornington; Visit Mornington Peninsula], so N 7 is NOT supported by what was found; left at 7, consider 6. Village: 'cosmopolitan seaside village', 1 km+ of shopping, 370+ retail outlets, Wednesday main-street market [Visit Mornington Peninsula]; R 7 consistent. City trip: 46 km SE of CBD, 13 km to Frankston, no rail (heritage line only), buses 781/784/785/788 to Frankston [Wikipedia]; V 3 consistent. NOT checked: supermarket names, drive time to CBD. Scores unchanged. | C3 28 Oct 2026: N 7->6 (source: earlier source run found parks and gardens only, no bushland named (flagged 'consider 6')). | AA31: 30. Mornington | Mornington Peninsula | Active Shortlist | P: Medium (Parks & gardens) | Y: High (Bay beaches/harbor) | Lens: Established coastal town centre & Main Street | Price: [Blank] | Basis: Not verified in report | Note: Substantial town services on bay; no passenger train (bus to Frankston); verify Frankston/Rosebud ED drive. | AB31: No | AC31: No rail; buses to Frankston station (checked: Wikipedia Frankston station bus list) | AD31: Peninsula University Hospital ED | AE31: 1500000 | AF31: Maximum purchase price, excluding transaction and moving costs | AG31: AVM estimate | AH31: 27 Oct 2026 | AI31: Pass | AJ31: AVM house value ($1,096,505) is under $1.5M cap. Not a sale median. | AK31: SAL21763 | AL31: 25759 | AM31: 50 | AN31: 0.312 | AO31: 0.212 | AP31: 0.048 | AQ31: 0.004 | AR31: 0.005 | AS31: 0.003 | AT31: 0.001 | AU31: 0.056 | AV31: Italian 0.7%; Greek 0.6%; Spanish 0.4% | AW31: ABS 2021 Census General Community Profile DataPack, Suburbs and Localities (SAL), Victoria (tables G01, G02, G08, G09, G13, G14); downloaded 27 Oct 2026 from abs.gov.au. Place of usual residence. | AX31: =IF(AU31="","",IF(OR(AU31>=0.5,AQ31>=0.08),"High",IF(OR(AU31>=0.3,AQ31>=0.04),"Medium","Low")))
A32: Clifton Springs | B32: Bellarine Peninsula | C32: Active Shortlist | D32: Medium (Dell & coastal reserve) | E32: High (Bay views & foreshore) | F32: High-value Bellarine coastal alternative | G32: 715000 | H32: House sale median $715,000 (196 sales, Property.com.au) | I32: 757900 | J32: 95 | K32: 23 | L32: Fails: GW drive | O32: =IF(K32="","",ROUND(MAX(0,10*(1-K32/Filters!$B$5)),1)) | W32: =IF(M32="",0,COUNT(M32:V32)) | X32: =IF(W32<10,"",M32*ForcedChoiceCorrections!$B$6+N32*ForcedChoiceCorrections!$B$7+O32*ForcedChoiceCorrections!$B$8+P32*ForcedChoiceCorrections!$B$9+Q32*ForcedChoiceCorrections!$B$10+R32*ForcedChoiceCorrections!$B$11+S32*ForcedChoiceCorrections!$B$12+T32*ForcedChoiceCorrections!$B$13+U32*ForcedChoiceCorrections!$B$14+V32*ForcedChoiceCorrections!$B$15) | Y32: =IF(AND(ISNUMBER(SEARCH("pass",L32)),ISNUMBER(X32)),COUNTIFS(L$2:L$90,"*pass*",X$2:X$90,">"&X32)+1,"") | Z32: Port Phillip bay frontage & Dell picnic area; verify Univ Hospital Geelong ED drive & public transport. | AA32: 31. Clifton Springs | Bellarine Peninsula | Active Shortlist | P: Medium (Dell & coastal reserve) | Y: High (Bay views & foreshore) | Lens: High-value Bellarine coastal alternative | Price: 715000 | Basis: House sale median $715,000 (196 sales, Property.com.au) | Note: Port Phillip bay frontage & Dell picnic area; verify Univ Hospital Geelong ED drive & public transport. | AB32: No | AC32: No rail; Geelong via bus (recall; verify) | AD32: University Hospital Geelong ED | AE32: 1500000 | AF32: Maximum purchase price, excluding transaction and moving costs | AG32: Suburb median | AH32: 26 Oct 2026 | AI32: Pass | AJ32: Published house price ($715,000) is under $1.5M cap. | AK32: SAL20575 | AL32: 7646 | AM32: 48 | AN32: 0.267 | AO32: 0.16 | AP32: 0.032 | AQ32: 0.002 | AR32: 0.003 | AS32: 0.001 | AT32: 0 | AU32: 0.046 | AV32: Italian 0.6%; Greek 0.4%; German 0.4% | AW32: ABS 2021 Census General Community Profile DataPack, Suburbs and Localities (SAL), Victoria (tables G01, G02, G08, G09, G13, G14); downloaded 27 Oct 2026 from abs.gov.au. Place of usual residence. | AX32: =IF(AU32="","",IF(OR(AU32>=0.5,AQ32>=0.08),"High",IF(OR(AU32>=0.3,AQ32>=0.04),"Medium","Low")))
A33: Warburton | B33: Yarra Valley | C33: Watchlist | D33: Very High (Mountain & river) | E33: Low (River, non-coastal) | F33: Maximum forest/mountain scenery test | G33: 717500 | H33: 3-bed house median $717.5k (34 sales); 4-bed $702.5k | I33: 760550 | J33: 65 | K33: 53 | L33: Provisional pass | M33: =IF(J33="","",ROUND(MAX(0,10*(1-J33/Filters!$B$4)),1)) | N33: 10 | O33: =IF(K33="","",ROUND(MAX(0,10*(1-K33/Filters!$B$5)),1)) | P33: 1 | Q33: 4 | R33: 8 | S33: 1 | T33: =IF(G33="","",ROUND(MAX(0,MIN(10,10*(Filters!$B$2-G33)/(Filters!$B$2-500000))),1)) | U33: 0 | V33: 1 | W33: =IF(M33="",0,COUNT(M33:V33)) | X33: =IF(W33<10,"",M33*ForcedChoiceCorrections!$B$6+N33*ForcedChoiceCorrections!$B$7+O33*ForcedChoiceCorrections!$B$8+P33*ForcedChoiceCorrections!$B$9+Q33*ForcedChoiceCorrections!$B$10+R33*ForcedChoiceCorrections!$B$11+S33*ForcedChoiceCorrections!$B$12+T33*ForcedChoiceCorrections!$B$13+U33*ForcedChoiceCorrections!$B$14+V33*ForcedChoiceCorrections!$B$15) | Y33: =IF(AND(ISNUMBER(SEARCH("pass",L33)),ISNUMBER(X33)),COUNTIFS(L$2:L$90,"*pass*",X$2:X$90,">"&X33)+1,"") | Z33: ABS 2021: 24.3% aged 65+, 8.1% non-Eng HH. Tough practicality test on winter comfort, fire risk & distant ED. 27 Oct 2026 research pass: drive times/ED and/or AVM price added; L re-evaluated. | SCORES 27 Oct 2026: M (near family) and T (price) are formulas from J and G; O from K. N, P, Q, R, S, U, V are ESTIMATES (Claude, general knowledge, not site-checked); S also rests on train Yes/No marked 'verify'. | CHECKED 27 Oct 2026, source run C1 (suburb level; Wikipedia, Victorian Places, ABS 2021 GCP DataPack). Pop 2,020; on the Yarra River, 76 km E of CBD [Wikipedia Warburton] (60 km per Victorian Places), foothills of the Great Dividing Range, adjoining Yarra State Forest via East Warburton [Victorian Places]. Nature: extensive walking trails, Warburton Bridges and River Walk, rail trail to Lilydale [Victorian Places]; N 10 consistent. Village: main street mostly retail, constrained by floodplain to the north; B&Bs, health resorts, golf course, festivals [Victorian Places]; R 8 consistent. Train: line closed (now rail trail) [Victorian Places]; S 1 consistent. Indian community: India-born 0.3%, Hinduism 0.4% [ABS 2021 GCP SAL22689]; P 1 consistent. Older: median age 50; 13.7% birthplace not stated [ABS]. City trip: 60-76 km, no rail; V 1 consistent. NOT checked: GPs, supermarket, bus, flood overlay. Scores unchanged. | AA33: 32. Warburton | Yarra Valley | Watchlist | P: Very High (Mountain & river) | Y: Low (River, non-coastal) | Lens: Maximum forest/mountain scenery test | Price: 717500 | Basis: 3-bed house median $717.5k (34 sales); 4-bed $702.5k | Note: ABS 2021: 24.3% aged 65+, 8.1% non-Eng HH. Tough practicality test on winter comfort, fire risk & distant ED. | AB33: No | AC33: No passenger rail (recall; verify) | AD33: Maroondah Hospital ED (drive times added 27 Oct 2026, Google Maps leave-now, not peak; Angliss may be closer, 24-hr status unverified) | AE33: 1500000 | AF33: Maximum purchase price, excluding transaction and moving costs | AG33: Suburb median | AH33: 26 Oct 2026 | AI33: Pass | AJ33: Published house price ($717,500) is under $1.5M cap. | AK33: SAL22689 | AL33: 2020 | AM33: 50 | AN33: 0.243 | AO33: 0.186 | AP33: 0.137 | AQ33: 0.003 | AR33: 0.002 | AS33: 0.004 | AT33: 0 | AU33: 0.053 | AV33: German 0.8%; Japanese 0.5%; Polish 0.3% | AW33: ABS 2021 Census General Community Profile DataPack, Suburbs and Localities (SAL), Victoria (tables G01, G02, G08, G09, G13, G14); downloaded 27 Oct 2026 from abs.gov.au. Place of usual residence. Small population: ABS randomly adjusts small counts, so treat shares under 1% as noise. | AX33: =IF(AU33="","",IF(OR(AU33>=0.5,AQ33>=0.08),"High",IF(OR(AU33>=0.3,AQ33>=0.04),"Medium","Low")))
A34: Trentham | B34: Macedon Ranges | C34: Watchlist | D34: High (Wombat Forest village) | E34: Low (Inland) | F34: Intimate forest village with older age profile | G34: 978750 | H34: 3-bed house median $978,750 (30 sales, Domain) | I34: 1037475 | J34: 97 | K34: 59 | L34: Fails: GW drive | O34: =IF(K34="","",ROUND(MAX(0,10*(1-K34/Filters!$B$5)),1)) | W34: =IF(M34="",0,COUNT(M34:V34)) | X34: =IF(W34<10,"",M34*ForcedChoiceCorrections!$B$6+N34*ForcedChoiceCorrections!$B$7+O34*ForcedChoiceCorrections!$B$8+P34*ForcedChoiceCorrections!$B$9+Q34*ForcedChoiceCorrections!$B$10+R34*ForcedChoiceCorrections!$B$11+S34*ForcedChoiceCorrections!$B$12+T34*ForcedChoiceCorrections!$B$13+U34*ForcedChoiceCorrections!$B$14+V34*ForcedChoiceCorrections!$B$15) | Y34: =IF(AND(ISNUMBER(SEARCH("pass",L34)),ISNUMBER(X34)),COUNTIFS(L$2:L$90,"*pass*",X$2:X$90,">"&X34)+1,"") | Z34: ABS 2021: 33.6% aged 65+, 4.7% non-Eng HH. CAUTION: Local health campus is community/aged care ONLY, not an ED. 27 Oct 2026 research pass: drive times/ED and/or AVM price added; L re-evaluated. | AA34: 33. Trentham | Macedon Ranges | Watchlist | P: High (Wombat Forest village) | Y: Low (Inland) | Lens: Intimate forest village with older age profile | Price: 978750 | Basis: 3-bed house median $978,750 (30 sales, Domain) | Note: ABS 2021: 33.6% aged 65+, 4.7% non-Eng HH. CAUTION: Local health campus is community/aged care ONLY, not an ED. | AB34: No | AC34: No station (line closed); nearest Woodend or Kyneton V/Line (recall; verify) | AD34: Grampians Health Ballarat (Ballarat Base) ED (24-hr: recall (major regional ED); Bendigo 68 min) (drive times: Google Maps leave-now, 27 Oct 2026 ~13:15–13:45 AEDT (midday, not peak), suburb name) | AE34: 1500000 | AF34: Maximum purchase price, excluding transaction and moving costs | AG34: Suburb median | AH34: 26 Oct 2026 | AI34: Pass | AJ34: Published house price ($978,750) is under $1.5M cap. | AK34: SAL22577 | AL34: 1382 | AM34: 56 | AN34: 0.336 | AO34: 0.179 | AP34: 0.083 | AQ34: 0.002 | AR34: 0.006 | AS34: 0 | AT34: 0 | AU34: 0.03 | AV34: French 0.8%; Croatian 0.4%; Turkish 0.3% | AW34: ABS 2021 Census General Community Profile DataPack, Suburbs and Localities (SAL), Victoria (tables G01, G02, G08, G09, G13, G14); downloaded 27 Oct 2026 from abs.gov.au. Place of usual residence. Small population: ABS randomly adjusts small counts, so treat shares under 1% as noise. | AX34: =IF(AU34="","",IF(OR(AU34>=0.5,AQ34>=0.08),"High",IF(OR(AU34>=0.3,AQ34>=0.04),"Medium","Low")))
A35: Olinda | B35: Dandenong Ridge | C35: Watchlist | D35: Very High (Botanic gardens/ridge) | E35: Low (Inland) | F35: Dandenongs ridge village — high scenic appeal | G35: 1020069 | H35: AVM estimate (30 Sep 2026), NOT a verified sale median; unit $1,214,582; 37 sales in last 12m (OnTheHouse/Cotality, read 27 Oct 2026) — few sales, weak | I35: =G35*(1+Settings!$B$6) | J35: 33 | K35: 15 | L35: Provisional pass | M35: =IF(J35="","",ROUND(MAX(0,10*(1-J35/Filters!$B$4)),1)) | N35: 10 | O35: =IF(K35="","",ROUND(MAX(0,10*(1-K35/Filters!$B$5)),1)) | P35: 2 | Q35: 3 | R35: 9 | S35: 2 | T35: =IF(G35="","",ROUND(MAX(0,MIN(10,10*(Filters!$B$2-G35)/(Filters!$B$2-500000))),1)) | U35: 0 | V35: 3 | W35: =IF(M35="",0,COUNT(M35:V35)) | X35: =IF(W35<10,"",M35*ForcedChoiceCorrections!$B$6+N35*ForcedChoiceCorrections!$B$7+O35*ForcedChoiceCorrections!$B$8+P35*ForcedChoiceCorrections!$B$9+Q35*ForcedChoiceCorrections!$B$10+R35*ForcedChoiceCorrections!$B$11+S35*ForcedChoiceCorrections!$B$12+T35*ForcedChoiceCorrections!$B$13+U35*ForcedChoiceCorrections!$B$14+V35*ForcedChoiceCorrections!$B$15) | Y35: =IF(AND(ISNUMBER(SEARCH("pass",L35)),ISNUMBER(X35)),COUNTIFS(L$2:L$90,"*pass*",X$2:X$90,">"&X35)+1,"") | Z35: Parks Vic documents severe-weather/fire closures; bus 694 to Belgrave; verify winter damp, slopes & insurance. 27 Oct 2026 research pass: drive times/ED and/or AVM price added; L re-evaluated. | SCORES 27 Oct 2026: M (near family) and T (price) are formulas from J and G; O from K. N, P, Q, R, S, U, V are ESTIMATES (Claude, general knowledge, not site-checked); S also rests on train Yes/No marked 'verify'. Low sales count. | CHECKED 27 Oct 2026, source run C1 (suburb level; Wikipedia, Victorian Places, ABS 2021 GCP DataPack). Pop 1,773; Dandenong Ranges township at the southern foot of Mount Dandenong, 37 km E of Melbourne [Wikipedia Olinda; Victorian Places]. Nature: Dandenong Ranges Botanic Garden (National Rhododendron Garden), R.J. Hamer Arboretum, Olinda Falls and Cascade walk, many walking trails [Wikipedia; Victorian Places]; N 10 consistent. Village: 'the highest number of hospitality, gallery and garden attractions of any location in the Dandenongs'; cafés, galleries, craft shops; shopping centre with hotel and post office [Victorian Places]; R 9 consistent. Shops: small centre, no supermarket named; Q 3 consistent. Train: none named; S 2 consistent. Indian community: India-born 0.2%, Hinduism 0.6% [ABS 2021 GCP SAL22009]; P 2 consistent (1 arguable). City trip: 37 km, no rail; V 3 estimate. NOT checked: GPs, bus, bushfire overlay. Scores unchanged. | AA35: 34. Olinda | Dandenong Ridge | Watchlist | P: Very High (Botanic gardens/ridge) | Y: Low (Inland) | Lens: Dandenongs ridge village — high scenic appeal | Price: [Blank] | Basis: Not verified in report | Note: Parks Vic documents severe-weather/fire closures; bus 694 to Belgrave; verify winter damp, slopes & insurance. | AB35: No | AC35: No station; nearest Upwey/Belgrave (recall; verify) | AD35: Angliss Hospital ED (24-hr: verified, Eastern Health site) (drive times: Google Maps leave-now, 27 Oct 2026 ~13:15–13:45 AEDT (midday, not peak), suburb name) | AE35: 1500000 | AF35: Maximum purchase price, excluding transaction and moving costs | AG35: AVM estimate | AH35: 27 Oct 2026 | AI35: Pass | AJ35: AVM house value ($1,020,069) is under $1.5M cap. Not a sale median. | AK35: SAL22009 | AL35: 1773 | AM35: 45 | AN35: 0.191 | AO35: 0.186 | AP35: 0.047 | AQ35: 0.002 | AR35: 0.008 | AS35: 0.006 | AT35: 0 | AU35: 0.071 | AV35: French 1.5%; Mandarin 0.8%; Japanese 0.5% | AW35: ABS 2021 Census General Community Profile DataPack, Suburbs and Localities (SAL), Victoria (tables G01, G02, G08, G09, G13, G14); downloaded 27 Oct 2026 from abs.gov.au. Place of usual residence. Small population: ABS randomly adjusts small counts, so treat shares under 1% as noise. | AX35: =IF(AU35="","",IF(OR(AU35>=0.5,AQ35>=0.08),"High",IF(OR(AU35>=0.3,AQ35>=0.04),"Medium","Low")))
A36: Sassafras | B36: Dandenong Ridge | C36: Watchlist | D36: Very High (Forest ridge village) | E36: Low (Inland) | F36: Dandenongs ridge village comparator | G36: 1006318 | H36: AVM estimate (30 Sep 2026), NOT a verified sale median; unit $1,279,170; 17 sales in last 12m (OnTheHouse/Cotality, read 27 Oct 2026) — few sales, weak | I36: =G36*(1+Settings!$B$6) | J36: 29 | K36: 11 | L36: Provisional pass | M36: =IF(J36="","",ROUND(MAX(0,10*(1-J36/Filters!$B$4)),1)) | N36: 10 | O36: =IF(K36="","",ROUND(MAX(0,10*(1-K36/Filters!$B$5)),1)) | P36: 2 | Q36: 3 | R36: 9 | S36: 2 | T36: =IF(G36="","",ROUND(MAX(0,MIN(10,10*(Filters!$B$2-G36)/(Filters!$B$2-500000))),1)) | U36: 0 | V36: 3 | W36: =IF(M36="",0,COUNT(M36:V36)) | X36: =IF(W36<10,"",M36*ForcedChoiceCorrections!$B$6+N36*ForcedChoiceCorrections!$B$7+O36*ForcedChoiceCorrections!$B$8+P36*ForcedChoiceCorrections!$B$9+Q36*ForcedChoiceCorrections!$B$10+R36*ForcedChoiceCorrections!$B$11+S36*ForcedChoiceCorrections!$B$12+T36*ForcedChoiceCorrections!$B$13+U36*ForcedChoiceCorrections!$B$14+V36*ForcedChoiceCorrections!$B$15) | Y36: =IF(AND(ISNUMBER(SEARCH("pass",L36)),ISNUMBER(X36)),COUNTIFS(L$2:L$90,"*pass*",X$2:X$90,">"&X36)+1,"") | Z36: High tourism traffic on weekends; check everyday grocery/medical convenience & bushfire overlay. 27 Oct 2026 research pass: drive times/ED and/or AVM price added; L re-evaluated. | SCORES 27 Oct 2026: M (near family) and T (price) are formulas from J and G; O from K. N, P, Q, R, S, U, V are ESTIMATES (Claude, general knowledge, not site-checked); S also rests on train Yes/No marked 'verify'. Low sales count. | CHECKED 27 Oct 2026, source run C1 (suburb level; Wikipedia, Victorian Places, ABS 2021 GCP DataPack). Pop 970; village ~500 m up in a saddle on the Dandenong Ranges ridgeline; much of the locality's west is Dandenong Ranges National Park; Sassafras Creek's banks almost entirely protected public land; Dandenong Ranges Tourist Track runs 15 km beside the creek [Wikipedia Sassafras]. N 10 consistent. Village: tourist village of boutique shops, cafés, Devonshire tea, toy and antique shops, nurseries [Wikipedia]; 'has a shopping centre, a hall, a school' [Victorian Places]; R 9 consistent. Shops: small centre only, no supermarket named; Q 3 consistent (estimate). Train: no station named in either source; S 2 consistent. Indian community: India-born 0, Hinduism 0.0% [ABS 2021 GCP SAL22239]; P 2 generous (1 arguable). City trip: 43 km E of CBD [Wikipedia]; journey time not stated; V 3 estimate. Hazard: area has burnt repeatedly since the 1850s, most recently 1962 [Wikipedia]. Small population: ABS perturbs small counts. NOT checked: GPs, supermarket, bus, journey time. Scores unchanged. | AA36: 35. Sassafras | Dandenong Ridge | Watchlist | P: Very High (Forest ridge village) | Y: Low (Inland) | Lens: Dandenongs ridge village comparator | Price: [Blank] | Basis: Not verified in report | Note: High tourism traffic on weekends; check everyday grocery/medical convenience & bushfire overlay. | AB36: No | AC36: No station; nearest Upwey/Belgrave (recall; verify) | AD36: Angliss Hospital ED (24-hr: verified, Eastern Health site) (drive times: Google Maps leave-now, 27 Oct 2026 ~13:15–13:45 AEDT (midday, not peak), suburb name) | AE36: 1500000 | AF36: Maximum purchase price, excluding transaction and moving costs | AG36: AVM estimate | AH36: 27 Oct 2026 | AI36: Pass | AJ36: AVM house value ($1,006,318) is under $1.5M cap. Not a sale median. | AK36: SAL22239 | AL36: 970 | AM36: 47 | AN36: 0.193 | AO36: 0.196 | AP36: 0.036 | AQ36: 0 | AR36: 0.006 | AS36: 0 | AT36: 0 | AU36: 0.072 | AV36: German 1.0%; Japanese 0.9%; Russian 0.7% | AW36: ABS 2021 Census General Community Profile DataPack, Suburbs and Localities (SAL), Victoria (tables G01, G02, G08, G09, G13, G14); downloaded 27 Oct 2026 from abs.gov.au. Place of usual residence. Small population: ABS randomly adjusts small counts, so treat shares under 1% as noise. | AX36: =IF(AU36="","",IF(OR(AU36>=0.5,AQ36>=0.08),"High",IF(OR(AU36>=0.3,AQ36>=0.04),"Medium","Low")))
A37: Mount Dandenong | B37: Dandenong Ridge | C37: Watchlist | D37: Very High (Canopy & views) | E37: Low (Inland) | F37: Ridge canopy living test | G37: 982029 | H37: AVM estimate (30 Sep 2026), NOT a verified sale median; unit $1,079,082; 30 sales in last 12m (OnTheHouse/Cotality, read 27 Oct 2026) — few sales, weak | I37: =G37*(1+Settings!$B$6) | J37: 30 | K37: 19 | L37: Provisional pass | M37: =IF(J37="","",ROUND(MAX(0,10*(1-J37/Filters!$B$4)),1)) | N37: 10 | O37: =IF(K37="","",ROUND(MAX(0,10*(1-K37/Filters!$B$5)),1)) | P37: 2 | Q37: 2 | R37: 7 | S37: 1 | T37: =IF(G37="","",ROUND(MAX(0,MIN(10,10*(Filters!$B$2-G37)/(Filters!$B$2-500000))),1)) | U37: 0 | V37: 3 | W37: =IF(M37="",0,COUNT(M37:V37)) | X37: =IF(W37<10,"",M37*ForcedChoiceCorrections!$B$6+N37*ForcedChoiceCorrections!$B$7+O37*ForcedChoiceCorrections!$B$8+P37*ForcedChoiceCorrections!$B$9+Q37*ForcedChoiceCorrections!$B$10+R37*ForcedChoiceCorrections!$B$11+S37*ForcedChoiceCorrections!$B$12+T37*ForcedChoiceCorrections!$B$13+U37*ForcedChoiceCorrections!$B$14+V37*ForcedChoiceCorrections!$B$15) | Y37: =IF(AND(ISNUMBER(SEARCH("pass",L37)),ISNUMBER(X37)),COUNTIFS(L$2:L$90,"*pass*",X$2:X$90,">"&X37)+1,"") | Z37: Requires property-specific slope, tree-fall, insurance & emergency egress verification. 27 Oct 2026 research pass: drive times/ED and/or AVM price added; L re-evaluated. | SCORES 27 Oct 2026: M (near family) and T (price) are formulas from J and G; O from K. N, P, Q, R, S, U, V are ESTIMATES (Claude, general knowledge, not site-checked); S also rests on train Yes/No marked 'verify'. Low sales count. | CHECKED 27 Oct 2026, source run C1 (suburb level; Wikipedia, Victorian Places, ABS 2021 GCP DataPack). Pop 1,271; 44 km E of CBD [Wikipedia Mount Dandenong] (35 km per Victorian Places); the 633 m peak is the highest in the Ranges. Nature: Doongalla Forest (Dandenong Ranges National Park) is in the suburb; William Ricketts Sanctuary; Burke's Lookout; fine gardens; light snow a few times most years [Victorian Places; Wikipedia]; N 10 consistent. Village: 'a small shopping centre and several restaurants' [Victorian Places]; R 7 consistent. Shops: Q 2 consistent. Train: none named; S 1 consistent. Indian community: India-born 0.6%, Hinduism 0.2% [ABS 2021 GCP SAL21787]; P 2 consistent. City trip: 35-44 km, no rail; V 3 estimate. Winter cold and snow are a consideration for older residents. NOT checked: GPs, bus. Scores unchanged. | AA37: 36. Mount Dandenong | Dandenong Ridge | Watchlist | P: Very High (Canopy & views) | Y: Low (Inland) | Lens: Ridge canopy living test | Price: [Blank] | Basis: Not verified in report | Note: Requires property-specific slope, tree-fall, insurance & emergency egress verification. | AB37: No | AC37: No station (recall; verify) | AD37: Angliss Hospital ED (24-hr: verified, Eastern Health site; Maroondah 24 min) (drive times: Google Maps leave-now, 27 Oct 2026 ~13:15–13:45 AEDT (midday, not peak), suburb name) | AE37: 1500000 | AF37: Maximum purchase price, excluding transaction and moving costs | AG37: AVM estimate | AH37: 27 Oct 2026 | AI37: Pass | AJ37: AVM house value ($982,029) is under $1.5M cap. Not a sale median. | AK37: SAL21787 | AL37: 1271 | AM37: 45 | AN37: 0.218 | AO37: 0.19 | AP37: 0.03 | AQ37: 0.006 | AR37: 0.008 | AS37: 0.002 | AT37: 0 | AU37: 0.056 | AV37: German 0.9%; Afrikaans 0.9%; Spanish 0.6% | AW37: ABS 2021 Census General Community Profile DataPack, Suburbs and Localities (SAL), Victoria (tables G01, G02, G08, G09, G13, G14); downloaded 27 Oct 2026 from abs.gov.au. Place of usual residence. Small population: ABS randomly adjusts small counts, so treat shares under 1% as noise. | AX37: =IF(AU37="","",IF(OR(AU37>=0.5,AQ37>=0.08),"High",IF(OR(AU37>=0.3,AQ37>=0.04),"Medium","Low")))
A38: Emerald | B38: Dandenong Ranges | C38: Watchlist | D38: High (Emerald Lake & hills) | E38: Low (Inland) | F38: Larger hills town south-east of ridge | G38: 980699 | H38: AVM estimate (30 Sep 2026), NOT a verified sale median; unit $641,682; 84 sales in last 12m (OnTheHouse/Cotality, read 27 Oct 2026) | I38: =G38*(1+Settings!$B$6) | J38: 35 | K38: 22 | L38: Provisional pass | M38: =IF(J38="","",ROUND(MAX(0,10*(1-J38/Filters!$B$4)),1)) | N38: 9 | O38: =IF(K38="","",ROUND(MAX(0,10*(1-K38/Filters!$B$5)),1)) | P38: 2 | Q38: 6 | R38: 8 | S38: 2 | T38: =IF(G38="","",ROUND(MAX(0,MIN(10,10*(Filters!$B$2-G38)/(Filters!$B$2-500000))),1)) | U38: 0 | V38: 3 | W38: =IF(M38="",0,COUNT(M38:V38)) | X38: =IF(W38<10,"",M38*ForcedChoiceCorrections!$B$6+N38*ForcedChoiceCorrections!$B$7+O38*ForcedChoiceCorrections!$B$8+P38*ForcedChoiceCorrections!$B$9+Q38*ForcedChoiceCorrections!$B$10+R38*ForcedChoiceCorrections!$B$11+S38*ForcedChoiceCorrections!$B$12+T38*ForcedChoiceCorrections!$B$13+U38*ForcedChoiceCorrections!$B$14+V38*ForcedChoiceCorrections!$B$15) | Y38: =IF(AND(ISNUMBER(SEARCH("pass",L38)),ISNUMBER(X38)),COUNTIFS(L$2:L$90,"*pass*",X$2:X$90,">"&X38)+1,"") | Z38: Emerald Lake precinct; separate from ridge villages—verify routine services & ED drive. 27 Oct 2026 research pass: drive times/ED and/or AVM price added; L re-evaluated. | SCORES 27 Oct 2026: M (near family) and T (price) are formulas from J and G; O from K. N, P, Q, R, S, U, V are ESTIMATES (Claude, general knowledge, not site-checked); S also rests on train Yes/No marked 'verify'. | CHECKED 27 Oct 2026, source run C1 (suburb level; Wikipedia, Victorian Places, ABS 2021 GCP DataPack). Pop 5,890; 44 km SE of CBD, Shires of Cardinia and Yarra Ranges [Wikipedia Emerald]. Nature: Emerald Lake park with walking tracks; Cardinia Reservoir Park (kangaroos, wombats); smaller reserves [Wikipedia; Victorian Places]; N 9 consistent. Village: 'an active shopping area', cooperative-owned hardware store, museum, golf club [Victorian Places]; R 8 consistent. Shops: Woolworths supermarket since 2011 [Victorian Places]; Q 6 consistent. Train: Puffing Billy heritage steam railway only (3 stations in Emerald) [Wikipedia]; S 2 consistent. Indian community: India-born 0.1%, Hinduism 0.0% [ABS 2021 GCP SAL20868]; P 2 generous (1 arguable). City trip: 44 km, no commuter rail; V 3 estimate. NOT checked: GPs, bus. Scores unchanged. | AA38: 37. Emerald | Dandenong Ranges | Watchlist | P: High (Emerald Lake & hills) | Y: Low (Inland) | Lens: Larger hills town south-east of ridge | Price: [Blank] | Basis: Not verified in report | Note: Emerald Lake precinct; separate from ridge villages—verify routine services & ED drive. | AB38: No | AC38: Puffing Billy tourist railway only (recall; verify) | AD38: Angliss Hospital ED (24-hr: verified, Eastern Health site; Casey 23 min) (drive times: Google Maps leave-now, 27 Oct 2026 ~13:15–13:45 AEDT (midday, not peak), suburb name) | AE38: 1500000 | AF38: Maximum purchase price, excluding transaction and moving costs | AG38: AVM estimate | AH38: 27 Oct 2026 | AI38: Pass | AJ38: AVM house value ($980,699) is under $1.5M cap. Not a sale median. | AK38: SAL20868 | AL38: 5890 | AM38: 43 | AN38: 0.186 | AO38: 0.165 | AP38: 0.035 | AQ38: 0.001 | AR38: 0.003 | AS38: 0 | AT38: 0 | AU38: 0.052 | AV38: Spanish 0.7%; German 0.5%; Japanese 0.5% | AW38: ABS 2021 Census General Community Profile DataPack, Suburbs and Localities (SAL), Victoria (tables G01, G02, G08, G09, G13, G14); downloaded 27 Oct 2026 from abs.gov.au. Place of usual residence. | AX38: =IF(AU38="","",IF(OR(AU38>=0.5,AQ38>=0.08),"High",IF(OR(AU38>=0.3,AQ38>=0.04),"Medium","Low")))
A39: Ferntree Gully | B39: East / Foothills | C39: Watchlist | D39: Medium-High (Foothills) | E39: Low (Inland) | F39: Larger housing/service catchment next to Upper FTG | G39: 872133 | H39: AVM estimate (30 Sep 2026), NOT a verified sale median; unit $678,759; 438 sales in last 12m (OnTheHouse/Cotality, read 27 Oct 2026) | I39: =G39*(1+Settings!$B$6) | J39: 14 | K39: 8 | L39: Provisional pass | M39: =IF(J39="","",ROUND(MAX(0,10*(1-J39/Filters!$B$4)),1)) | N39: 6 | O39: =IF(K39="","",ROUND(MAX(0,10*(1-K39/Filters!$B$5)),1)) | P39: 5 | Q39: 8 | R39: 4 | S39: 8 | T39: =IF(G39="","",ROUND(MAX(0,MIN(10,10*(Filters!$B$2-G39)/(Filters!$B$2-500000))),1)) | U39: 0 | V39: 6 | W39: =IF(M39="",0,COUNT(M39:V39)) | X39: =IF(W39<10,"",M39*ForcedChoiceCorrections!$B$6+N39*ForcedChoiceCorrections!$B$7+O39*ForcedChoiceCorrections!$B$8+P39*ForcedChoiceCorrections!$B$9+Q39*ForcedChoiceCorrections!$B$10+R39*ForcedChoiceCorrections!$B$11+S39*ForcedChoiceCorrections!$B$12+T39*ForcedChoiceCorrections!$B$13+U39*ForcedChoiceCorrections!$B$14+V39*ForcedChoiceCorrections!$B$15) | Y39: =IF(AND(ISNUMBER(SEARCH("pass",L39)),ISNUMBER(X39)),COUNTIFS(L$2:L$90,"*pass*",X$2:X$90,">"&X39)+1,"") | Z39: Belgrave line; compare flatter pockets and housing stock against Upper Ferntree Gully. 27 Oct 2026 research pass: drive times/ED and/or AVM price added; L re-evaluated. OnTheHouse shows the same house AVM ($872,133) for Ferntree Gully and Upper Ferntree Gully (same postcode) — treat as postcode-level, weak. | SCORES 27 Oct 2026: M (near family) and T (price) are formulas from J and G; O from K. N, P, Q, R, S, U, V are ESTIMATES (Claude, general knowledge, not site-checked); S also rests on train Yes/No marked 'verify'. Price = postcode-level AVM shared with Upper FTG. | CHECKED 27 Oct 2026, source run C1 (suburb level; Wikipedia, Victorian Places, ABS 2021 GCP DataPack). Pop 27,398; foothills of the Dandenong Ranges, 30 km E of CBD [Wikipedia Ferntree Gully]. Nature: large part of Dandenong Ranges National Park forms the backdrop; eastern boundary is the National Park; One Tree Hill; 'high fire risk area' near the park [Wikipedia]; N 6 consistent (village end greener). Shops: Mountain Gate Shopping Centre; Ferntree Gully Village with supermarkets, greengrocers, butchers, cafés; two supermarkets on Burwood Hwy [Wikipedia; Victorian Places]; Q 8 consistent. Village: historic village at the station, rest is 'mostly a large suburban area' [Victorian Places]; R 4 consistent. Train: 'one of the busiest railway stations in the City of Knox' (Belgrave line) [Wikipedia]; S 8 consistent. Indian community: India-born 2.3%, Indian ancestry 3.1%, Hinduism 2.4% [ABS 2021 GCP SAL20917]; P 5 plausible (4 arguable). City trip: 30 km by train; V 6 estimate. NOT checked: GPs by name, journey time. Scores unchanged. | AA39: 38. Ferntree Gully | East / Foothills | Watchlist | P: Medium-High (Foothills) | Y: Low (Inland) | Lens: Larger housing/service catchment next to Upper FTG | Price: [Blank] | Basis: Not verified in report | Note: Belgrave line; compare flatter pockets and housing stock against Upper Ferntree Gully. | AB39: Yes | AC39: Ferntree Gully station, Belgrave line (recall; verify) | AD39: Angliss Hospital ED (24-hr: verified, Eastern Health site) (drive times: Google Maps leave-now, 27 Oct 2026 ~13:15–13:45 AEDT (midday, not peak), suburb name) | AE39: 1500000 | AF39: Maximum purchase price, excluding transaction and moving costs | AG39: AVM estimate | AH39: 27 Oct 2026 | AI39: Pass | AJ39: AVM house value ($872,133) is under $1.5M cap. Not a sale median. | AK39: SAL20917 | AL39: 27398 | AM39: 40 | AN39: 0.174 | AO39: 0.253 | AP39: 0.032 | AQ39: 0.023 | AR39: 0.031 | AS39: 0.024 | AT39: 0.004 | AU39: 0.187 | AV39: Mandarin 3.7%; Cantonese 1.5%; Sinhalese 1.2% | AW39: ABS 2021 Census General Community Profile DataPack, Suburbs and Localities (SAL), Victoria (tables G01, G02, G08, G09, G13, G14); downloaded 27 Oct 2026 from abs.gov.au. Place of usual residence. | AX39: =IF(AU39="","",IF(OR(AU39>=0.5,AQ39>=0.08),"High",IF(OR(AU39>=0.3,AQ39>=0.04),"Medium","Low")))
A40: Berwick | B40: South-East Melbourne | C40: Watchlist | D40: Medium (Wilson Botanic Park) | E40: Low (Inland) | F40: Healthcare-led south-east comparator | G40: 935845 | H40: AVM estimate (30 Sep 2026), NOT a verified sale median; unit $669,669; 987 sales in last 12m (OnTheHouse/Cotality, read 27 Oct 2026) | I40: =G40*(1+Settings!$B$6) | J40: 25 | K40: 6 | L40: Provisional pass | M40: =IF(J40="","",ROUND(MAX(0,10*(1-J40/Filters!$B$4)),1)) | N40: 5 | O40: =IF(K40="","",ROUND(MAX(0,10*(1-K40/Filters!$B$5)),1)) | P40: 7 | Q40: 9 | R40: 6 | S40: 8 | T40: =IF(G40="","",ROUND(MAX(0,MIN(10,10*(Filters!$B$2-G40)/(Filters!$B$2-500000))),1)) | U40: 1 | V40: 6 | W40: =IF(M40="",0,COUNT(M40:V40)) | X40: =IF(W40<10,"",M40*ForcedChoiceCorrections!$B$6+N40*ForcedChoiceCorrections!$B$7+O40*ForcedChoiceCorrections!$B$8+P40*ForcedChoiceCorrections!$B$9+Q40*ForcedChoiceCorrections!$B$10+R40*ForcedChoiceCorrections!$B$11+S40*ForcedChoiceCorrections!$B$12+T40*ForcedChoiceCorrections!$B$13+U40*ForcedChoiceCorrections!$B$14+V40*ForcedChoiceCorrections!$B$15) | Y40: =IF(AND(ISNUMBER(SEARCH("pass",L40)),ISNUMBER(X40)),COUNTIFS(L$2:L$90,"*pass*",X$2:X$90,">"&X40)+1,"") | Z40: Monash Health Casey Hospital 24-hr ED on site; verify whether residential pockets feel green enough. 27 Oct 2026 research pass: drive times/ED and/or AVM price added; L re-evaluated. | SCORES 27 Oct 2026: M (near family) and T (price) are formulas from J and G; O from K. N, P, Q, R, S, U, V are ESTIMATES (Claude, general knowledge, not site-checked); S also rests on train Yes/No marked 'verify'. | CHECKED 27 Oct 2026 (S train/bus, U beach, Q shops & doctor; web sources, suburb level, not address level): Station; High St village + Berwick Market Place; Casey Hospital (Victorian Places). GPs: Doctors at Casey, Parkhill, O'Shea, Langmore (healthdirect). Wilson Botanic Park. N, P, R, V remain estimates. | CHECKED 27 Oct 2026, second pass (N, P, R, V; suburb level). Indian community: India-born 3,052 (6.1%), Indian ancestry 3,738 (7.4%), Hinduism 2,744 (5.5%), Hindi 778 (1.5%), Punjabi 718 (1.4%), pop 50,298 [ABS SAL20224]; strongly supports P 7 (8 arguable); no temple or grocer identified. Nature: Wilson Botanic Park ~39 ha with two former quarry lakes, woodland plantings, lookout tower [Wikipedia Wilson Botanic Park]; Edwin Flack Reserve is sporting grounds [Wikipedia Berwick]; no bushland described; N 5 consistent. Village: High Street is the core of Berwick Village (small shops, WWI Avenue of Honour poplars); three shopping precincts (Berwick Village, Eden Rise, Parkhill Plaza) [Wikipedia Berwick]; R 6 consistent. City trip: ~40 km SE of CBD, Pakenham line [Wikipedia]; journey time NOT stated; V 6 estimate. Scores unchanged. | AA40: 39. Berwick | South-East Melbourne | Watchlist | P: Medium (Wilson Botanic Park) | Y: Low (Inland) | Lens: Healthcare-led south-east comparator | Price: [Blank] | Basis: Not verified in report | Note: Monash Health Casey Hospital 24-hr ED on site; verify whether residential pockets feel green enough. | AB40: Yes | AC40: Berwick station, Pakenham line (checked: Victorian Places; Wikipedia Berwick station) | AD40: Casey Hospital ED (24-hr: recall (major metro ED)) (drive times: Google Maps leave-now, 27 Oct 2026 ~13:15–13:45 AEDT (midday, not peak), suburb name) | AE40: 1500000 | AF40: Maximum purchase price, excluding transaction and moving costs | AG40: AVM estimate | AH40: 27 Oct 2026 | AI40: Pass | AJ40: AVM house value ($935,845) is under $1.5M cap. Not a sale median. | AK40: SAL20224 | AL40: 50298 | AM40: 38 | AN40: 0.142 | AO40: 0.342 | AP40: 0.035 | AQ40: 0.061 | AR40: 0.074 | AS40: 0.055 | AT40: 0.013 | AU40: 0.287 | AV40: Mandarin 4.0%; Sinhalese 3.8%; Hindi 1.5% | AW40: ABS 2021 Census General Community Profile DataPack, Suburbs and Localities (SAL), Victoria (tables G01, G02, G08, G09, G13, G14); downloaded 27 Oct 2026 from abs.gov.au. Place of usual residence. | AX40: =IF(AU40="","",IF(OR(AU40>=0.5,AQ40>=0.08),"High",IF(OR(AU40>=0.3,AQ40>=0.04),"Medium","Low")))
