Workbook

Sheet StartHere
A1: Workflow Steps
A2: 1. Complete 'Me' first
A3: 2. Interview Mum & Dad separately
A4: 3. Enforce Max-2-Essential rule
A5: 4. Review DiscussionSummary
A6: 5. Verify suburb data
A8: Boundaries Table
A9: Type | B9: Description
A10: Manual | B10: Editable input cells in yellow
A11: Automatic | B11: Calculated outputs

Sheet Settings
A1: Parameter | B1: Value | C1: Notes
A2: Say in the decision: Mum | B2: 1
A3: Say in the decision: Dad | B3: 1
A4: Say in the decision: Me | B4: 1
A5: Max D (Essential) answers per person | B5: 2
A6: Purchase costs allowance (% of price) | B6: 0.06 | C6: (provisional estimate, not SRO calculation)
A7: Forced-choice override margin | B7: 0.02
A9: Priority Rating Scale | B9: Level | C9: Score
A10: A | B10: Level 1, Not needed | C10: 0
A11: B | B11: Level 2, Nice to have | C11: 1
A12: C | B12: Level 3, Important | C12: 2
A13: D | B13: Level 4, Essential | C13: 4
A15: Draft Baseline Weights | B15: Weight
A16: Q15.1 Nature | B16: 0.18
A17: Q15.2 Near family in GW | B17: 0
A18: Q15.3 Indian community | B18: 0.18
A19: Q15.4 Beach | B19: 0.1
A20: Q15.5 Hospital | B20: 0.15
A21: Q15.6 Train/bus | B21: 0.15
A22: Q15.7 Shops/doctor | B22: 0.09
A23: Q15.8 Village character | B23: 0.07
A24: Q15.9 Price | B24: 0.08
A25: Q15.10 Easy city trip | B25: 0

Sheet RawResponses
A1: Timestamp | B1: [Q0] Whose answers are these? | C1: [Q1] | D1: [Q2] | E1: [Q3] Total budget | F1: [Q4] Max drive to GW | G1: [Q4b] Max drive to GW (if D) | H1: [Q5] Max drive to ED | I1: [Q6] Stairs | J1: [Q7] Garden | K1: [Q7a] Living arrangement | L1: [Q7b] Home size | M1: [Q8] | N1: [Q9] | O1: [Q10] | P1: [Q11] | Q1: [Q12] | R1: [Q13] | S1: [Q13b] | T1: [Q13c] | U1: [Q14] | V1: [Q15.1] Nature | W1: [Q15.2] Near family in GW | X1: [Q15.3] Indian community | Y1: [Q15.4] Beach | Z1: [Q15.5] Hospital | AA1: [Q15.6] Train/bus | AB1: [Q15.7] Shops/doctor | AC1: [Q15.8] Village character | AD1: [Q15.9] Price | AE1: [Q15.10] Easy city trip | AF1: [Q15 Notes] | AG1: [Q16] | AH1: [Q17] | AI1: [Q18] | AJ1: [Q19] | AK1: [Q20] | AL1: [Q21] | AM1: [Gap-form notes]
A2: 0.375 | B2: Dad | E2: 1000000 | F2: C - 35m | H2: C - 30m | I2: B - Some stairs | J2: B - Small garden | O2: Nature | P2: Village character | Q2: Shops & doctor | V2: C | W2: C | X2: C | Y2: C | Z2: C | AA2: C | AB2: C | AC2: C | AD2: D | AE2: D
A3: 0.38541667 | B3: Me | F3: B - 25m | H3: B - 20m | I3: A - None | J3: C - Courtyard | O3: Nature | P3: Village character | Q3: Shops & doctor | V3: D | W3: D | X3: C | Y3: C | Z3: C | AA3: C | AB3: C | AC3: C | AD3: C | AE3: C
A4: 0.39583333 | B4: Mum | E4: 1250000 | F4: B - 25m | H4: B - 20m | I4: A - None at all (Single-level only) | J4: C - Courtyard | K4: D - Self-contained space | O4: Near family in GW | P4: Village character | Q4: Shops & doctor | V4: D | W4: D | X4: D | Y4: C | Z4: C | AA4: C | AB4: C | AC4: C | AD4: C | AE4: C
A5: 0.40625 | B5: Dad | E5: 1500000 | F5: D - 45 min or more | G5: 75 | H5: D - no limit | I5: C - Doesn't matter | J5: E - Depends on Garden | O5: Near family in GW | P5: Village character | Q5: Shops & doctor | V5: D | W5: D | X5: C | Y5: C | Z5: C | AA5: C | AB5: C | AC5: C | AD5: C | AE5: C
A6: 46322.083 | B6: Dad | C6: A — Green views and quiet | D6: D — Looking after the house and land | E6: 1500000 | F6: D - 45 min or more | G6: 75 | H6: D - no limit | I6: C - Doesn't matter | J6: E - Depends on Garden | K6: A — Yes, living together | L6: E — Not decided / depends (see notes) | M6: C — Hills and forest all around | N6: B — Indian groceries and restaurants | O6: Near family in GW | P6: Village character | Q6: Shops & doctor | S6: A — Scenic country or coastal town, 60–90 min from family | T6: A — Inland forest, hills and gardens | U6: A — Stay put and rely on taxis or family | V6: D | W6: D | X6: C | Y6: C | Z6: C | AA6: C | AB6: C | AC6: C | AD6: C | AE6: C | AM6: Merged: row 5 + gap form (Claude artifact) 2026-10-27T02:00:03Z UTC. Notes: Q3–Q7b: ideally D, or min 3 bedrooms
A7: 46322.085 | B7: Mum | C7: A — Green views and quiet | D7: E — None of these / depends (see notes) | E7: 1250000 | F7: B - 25m | H7: B - 20m | I7: A - None at all (Single-level only) | J7: C - Courtyard | K7: A — Yes, living together | L7: E — Not decided / depends (see notes) | M7: A — A green outlook from the house | N7: A — A church or place of worship nearby | O7: Near family in GW | P7: Village character | Q7: Shops & doctor | S7: B — Leafy metropolitan suburb within 35 min of family | T7: B — Coastal or bay town with greenery and water walks | U7: A — Stay put and rely on taxis or family | V7: D | W7: D | X7: D | Y7: C | Z7: C | AA7: C | AB7: C | AC7: C | AD7: C | AE7: C | AM7: Merged: row 4 + gap form (Claude artifact) 2026-10-27T02:02:10Z UTC. Notes: Q1–Q2: B, D, i actually never wanted to live here, it was too remote and cut off. | Q3–Q7b: 3+ bedrooms, but ideally D
A8: 46322.087 | B8: Me | C8: B — Being near the beach | D8: B — Being far from family | F8: B - 25m | H8: B - 20m | I8: A - None | J8: C - Courtyard | K8: A — Yes, living together | L8: D — A self-contained space (granny flat or separate unit) | M8: E — None of these / depends (see notes) | N8: D — Friendly neighbours of any background | O8: Nature | P8: Village character | Q8: Shops & doctor | S8: A — Scenic country or coastal town, 60–90 min from family | T8: B — Coastal or bay town with greenery and water walks | U8: C — Take the train or bus to family and the hospital | V8: D | W8: D | X8: C | Y8: C | Z8: C | AA8: C | AB8: C | AC8: C | AD8: C | AE8: C | AM8: Merged: row 3 + gap form (Claude artifact) 2026-10-27T02:05:04Z UTC. Notes: Q8–Q9: When you picture nature near your new home | Q14: When I picture nature near new home, its a scenic viewpoint like from arthurs seat, of greenery and coast
A9: 46322.255 | B9: Mum | C9: A — Green views and quiet | D9: E — None of these / depends (see notes) | E9: 1250000 | F9: B - 25m | H9: B - 20m | I9: A - None at all (Single-level only) | J9: C - Courtyard | K9: A — Yes, living together | L9: E — Not decided / depends (see notes) | M9: A — A green outlook from the house | N9: A — A church or place of worship nearby | O9: Near family in GW | P9: Village character | Q9: Shops & doctor | R9: A — Indian shops and community in your own suburb, less green | S9: B — Leafy metropolitan suburb within 35 min of family | T9: B — Coastal or bay town with greenery and water walks | U9: A — Stay put and rely on taxis or family | V9: B | W9: C | X9: C | Y9: B | Z9: D | AA9: C | AB9: D | AC9: B | AD9: B | AE9: A | AM9: Round 2 (Q13, Q15) 2026-10-27T06:07:44Z merged onto row 7. | Merged: row 4 + gap form (Claude artifact) 2026-10-27T02:02:10Z UTC. Notes: Q1–Q2: B, D, i actually never wanted to live here, it was too remote and cut off. | Q3–Q7b: 3+ bedrooms, but ideally D
A10: 46322.256 | B10: Dad | C10: A — Green views and quiet | D10: D — Looking after the house and land | E10: 1500000 | F10: D - 45 min or more | G10: 75 | H10: D - no limit | I10: C - Doesn't matter | J10: E - Depends on Garden | K10: A — Yes, living together | L10: E — Not decided / depends (see notes) | M10: C — Hills and forest all around | N10: B — Indian groceries and restaurants | O10: Near family in GW | P10: Village character | Q10: Shops & doctor | R10: B — Very green, community a 30-min drive away | S10: A — Scenic country or coastal town, 60–90 min from family | T10: A — Inland forest, hills and gardens | U10: A — Stay put and rely on taxis or family | V10: D | W10: B | X10: B | Y10: B | Z10: B | AA10: C | AB10: C | AC10: C | AD10: C | AE10: A | AM10: Round 2 (Q13, Q15) 2026-10-27T06:08:36Z merged onto row 6. | Merged: row 5 + gap form (Claude artifact) 2026-10-27T02:00:03Z UTC. Notes: Q3–Q7b: ideally D, or min 3 bedrooms
A11: 46322.257 | B11: Me | C11: B — Being near the beach | D11: B — Being far from family | F11: B - 25m | H11: B - 20m | I11: A - None | J11: C - Courtyard | K11: A — Yes, living together | L11: D — A self-contained space (granny flat or separate unit) | M11: E — None of these / depends (see notes) | N11: D — Friendly neighbours of any background | O11: Nature | P11: Village character | Q11: Shops & doctor | R11: B — Very green, community a 30-min drive away | S11: A — Scenic country or coastal town, 60–90 min from family | T11: B — Coastal or bay town with greenery and water walks | U11: C — Take the train or bus to family and the hospital | V11: D | W11: A | X11: B | Y11: D | Z11: B | AA11: C | AB11: C | AC11: A | AD11: A | AE11: C | AM11: Round 2 (Q13, Q15) 2026-10-27T06:10:46Z merged onto row 8. | Merged: row 3 + gap form (Claude artifact) 2026-10-27T02:05:04Z UTC. Notes: Q8–Q9: When you picture nature near your new home | Q14: When I picture nature near new home, its a scenic viewpoint like from arthurs seat, of greenery and coast
A12: 46322.273 | B12: Mum | C12: A — Green views and quiet | D12: E — None of these / depends (see notes) | E12: 1250000 | F12: B - 25m | H12: B - 20m | I12: A - None at all (Single-level only) | J12: C - Courtyard | K12: A — Yes, living together | L12: E — Not decided / depends (see notes) | M12: A — A green outlook from the house | N12: A — A church or place of worship nearby | O12: A — A forest street, 35 min from Glen Waverley | P12: A — Flat suburban streets, beach 10 min away | Q12: A — A quiet street, driving 15 min to the shops and doctor | R12: A — Indian shops and community in your own suburb, less green | S12: B — Leafy metropolitan suburb within 35 min of family | T12: B — Coastal or bay town with greenery and water walks | U12: A — Stay put and rely on taxis or family | V12: B | W12: C | X12: C | Y12: B | Z12: D | AA12: C | AB12: D | AC12: B | AD12: B | AE12: A | AM12: Round 3 (Q10–Q12) 2026-10-27T06:33:30Z merged onto row 9. | Round 2 (Q13, Q15) 2026-10-27T06:07:44Z merged onto row 7. | Merged: row 4 + gap form (Claude artifact) 2026-10-27T02:02:10Z UTC. Notes: Q1–Q2: B, D, i actually never wanted to live here, it was too remote and cut off. | Q3–Q7b: 3+ bedrooms, but ideally D
A13: 46322.274 | B13: Dad | C13: A — Green views and quiet | D13: D — Looking after the house and land | E13: 1500000 | F13: D - 45 min or more | G13: 75 | H13: D - no limit | I13: C - Doesn't matter | J13: E - Depends on Garden | K13: A — Yes, living together | L13: E — Not decided / depends (see notes) | M13: C — Hills and forest all around | N13: B — Indian groceries and restaurants | O13: A — A forest street, 35 min from Glen Waverley | P13: B — Hills and bush, beach an hour away | Q13: A — A quiet street, driving 15 min to the shops and doctor | R13: B — Very green, community a 30-min drive away | S13: A — Scenic country or coastal town, 60–90 min from family | T13: A — Inland forest, hills and gardens | U13: A — Stay put and rely on taxis or family | V13: D | W13: B | X13: B | Y13: B | Z13: B | AA13: C | AB13: C | AC13: C | AD13: C | AE13: A | AM13: Round 3 (Q10–Q12) 2026-10-27T06:33:57Z merged onto row 10. | Round 2 (Q13, Q15) 2026-10-27T06:08:36Z merged onto row 6. | Merged: row 5 + gap form (Claude artifact) 2026-10-27T02:00:03Z UTC. Notes: Q3–Q7b: ideally D, or min 3 bedrooms
A14: 46322.274 | B14: Me | C14: B — Being near the beach | D14: B — Being far from family | F14: B - 25m | H14: B - 20m | I14: A - None | J14: C - Courtyard | K14: A — Yes, living together | L14: D — A self-contained space (granny flat or separate unit) | M14: E — None of these / depends (see notes) | N14: D — Friendly neighbours of any background | O14: A — A forest street, 35 min from Glen Waverley | P14: A — Flat suburban streets, beach 10 min away | Q14: B — A busier street, walking to the shops, doctor and station | R14: B — Very green, community a 30-min drive away | S14: A — Scenic country or coastal town, 60–90 min from family | T14: B — Coastal or bay town with greenery and water walks | U14: C — Take the train or bus to family and the hospital | V14: D | W14: A | X14: B | Y14: D | Z14: B | AA14: C | AB14: C | AC14: A | AD14: A | AE14: C | AM14: Round 3 (Q10–Q12) 2026-10-27T06:34:22Z merged onto row 11. | Round 2 (Q13, Q15) 2026-10-27T06:10:46Z merged onto row 8. | Merged: row 3 + gap form (Claude artifact) 2026-10-27T02:05:04Z UTC. Notes: Q8–Q9: When you picture nature near your new home | Q14: When I picture nature near new home, its a scenic viewpoint like from arthurs seat, of greenery and coast
A15: 46322.278 | B15: Mum | C15: A — Green views and quiet | D15: E — None of these / depends (see notes) | E15: 1250000 | F15: B - 25m | H15: B - 20m | I15: A - None at all (Single-level only) | J15: C - Courtyard | K15: A — Yes, living together | L15: E — Not decided / depends (see notes) | M15: A — A green outlook from the house | N15: A — A church or place of worship nearby | O15: B — A leafy suburban street, 15 min from Glen Waverley | P15: A — Flat suburban streets, beach 10 min away | Q15: A — A quiet street, driving 15 min to the shops and doctor | R15: A — Indian shops and community in your own suburb, less green | S15: B — Leafy metropolitan suburb within 35 min of family | T15: B — Coastal or bay town with greenery and water walks | U15: A — Stay put and rely on taxis or family | V15: B | W15: C | X15: C | Y15: B | Z15: D | AA15: C | AB15: D | AC15: B | AD15: B | AE15: A | AM15: Round 3 resubmission 2026-10-27T06:40:04Z merged onto row 12: Mum changed Q10 from A (forest street) to B (leafy street 15 min from GW); Q11, Q12 unchanged. | Round 3 (Q10–Q12) 2026-10-27T06:33:30Z merged onto row 9. | Round 2 (Q13, Q15) 2026-10-27T06:07:44Z merged onto row 7. | Merged: row 4 + gap form (Claude artifact) 2026-10-27T02:02:10Z UTC. Notes: Q1–Q2: B, D, i actually never wanted to live here, it was too remote and cut off. | Q3–Q7b: 3+ bedrooms, but ideally D

Sheet CleanedAnswers
A1: Person | B1: Latest Row | C1: Q15 Essential Count
A2: Mum | B2: =IFERROR(LOOKUP(2,1/(RawResponses!$B$2:$B$500="Mum"),ROW(RawResponses!$B$2:$B$500)),"") | C2: {=IF(COUNTIF(INDEX(RawResponses!$A:$AL, B2, 22):INDEX(RawResponses!$A:$AL, B2, 31), "D")>Settings!$B$5, "Too many D's ("&COUNTIF(INDEX(RawResponses!$A:$AL, B2, 22):INDEX(RawResponses!$A:$AL, B2, 31), "D")&")", "OK ("&COUNTIF(INDEX(RawResponses!$A:$AL, B2, 22):INDEX(RawResponses!$A:$AL, B2, 31), "D")&")")}
A3: Dad | B3: =IFERROR(LOOKUP(2,1/(RawResponses!$B$2:$B$500="Dad"),ROW(RawResponses!$B$2:$B$500)),"") | C3: {=IF(COUNTIF(INDEX(RawResponses!$A:$AL, B3, 22):INDEX(RawResponses!$A:$AL, B3, 31), "D")>Settings!$B$5, "Too many D's ("&COUNTIF(INDEX(RawResponses!$A:$AL, B3, 22):INDEX(RawResponses!$A:$AL, B3, 31), "D")&")", "OK ("&COUNTIF(INDEX(RawResponses!$A:$AL, B3, 22):INDEX(RawResponses!$A:$AL, B3, 31), "D")&")")}
A4: Me | B4: =IFERROR(LOOKUP(2,1/(RawResponses!$B$2:$B$500="Me"),ROW(RawResponses!$B$2:$B$500)),"") | C4: {=IF(COUNTIF(INDEX(RawResponses!$A:$AL, B4, 22):INDEX(RawResponses!$A:$AL, B4, 31), "D")>Settings!$B$5, "Too many D's ("&COUNTIF(INDEX(RawResponses!$A:$AL, B4, 22):INDEX(RawResponses!$A:$AL, B4, 31), "D")&")", "OK ("&COUNTIF(INDEX(RawResponses!$A:$AL, B4, 22):INDEX(RawResponses!$A:$AL, B4, 31), "D")&")")}
A6: Question ID | B6: Mum Answer | C6: Dad Answer | D6: Me Answer | E6: Mum Code | F6: Dad Code | G6: Me Code
A7: [Q3] Total budget | B7: {=INDEX(RawResponses!$A:$AL, $B$2, MATCH($A7&"*", RawResponses!$A$1:$AL$1, 0))} | C7: {=INDEX(RawResponses!$A:$AL, $B$3, MATCH($A7&"*", RawResponses!$A$1:$AL$1, 0))} | D7: =INDEX(RawResponses!$A:$AL, $B$4, MATCH($A7&"*", RawResponses!$A$1:$AL$1, 0)) | E7: =LEFT(B7, 1) | F7: =LEFT(C7, 1) | G7: =LEFT(D7, 1)
A8: [Q4] Max drive to GW | B8: {=INDEX(RawResponses!$A:$AL, $B$2, MATCH($A8&"*", RawResponses!$A$1:$AL$1, 0))} | C8: {=INDEX(RawResponses!$A:$AL, $B$3, MATCH($A8&"*", RawResponses!$A$1:$AL$1, 0))} | D8: {=INDEX(RawResponses!$A:$AL, $B$4, MATCH($A8&"*", RawResponses!$A$1:$AL$1, 0))} | E8: =LEFT(B8, 1) | F8: =LEFT(C8, 1) | G8: =LEFT(D8, 1)
A9: [Q4b] Max drive to GW (if D) | B9: =INDEX(RawResponses!$A:$AL, $B$2, MATCH($A9&"*", RawResponses!$A$1:$AL$1, 0)) | C9: {=INDEX(RawResponses!$A:$AL, $B$3, MATCH($A9&"*", RawResponses!$A$1:$AL$1, 0))} | D9: =INDEX(RawResponses!$A:$AL, $B$4, MATCH($A9&"*", RawResponses!$A$1:$AL$1, 0)) | E9: =IF(B9="","",B9) | F9: =IF(C9="","",C9) | G9: =IF(D9="","",D9)
A10: [Q5] Max drive to ED | B10: {=INDEX(RawResponses!$A:$AL, $B$2, MATCH($A10&"*", RawResponses!$A$1:$AL$1, 0))} | C10: {=INDEX(RawResponses!$A:$AL, $B$3, MATCH($A10&"*", RawResponses!$A$1:$AL$1, 0))} | D10: {=INDEX(RawResponses!$A:$AL, $B$4, MATCH($A10&"*", RawResponses!$A$1:$AL$1, 0))} | E10: =LEFT(B10, 1) | F10: =LEFT(C10, 1) | G10: =LEFT(D10, 1)
A11: [Q6] Stairs | B11: {=INDEX(RawResponses!$A:$AL, $B$2, MATCH($A11&"*", RawResponses!$A$1:$AL$1, 0))} | C11: {=INDEX(RawResponses!$A:$AL, $B$3, MATCH($A11&"*", RawResponses!$A$1:$AL$1, 0))} | D11: {=INDEX(RawResponses!$A:$AL, $B$4, MATCH($A11&"*", RawResponses!$A$1:$AL$1, 0))} | E11: =LEFT(B11, 1) | F11: =LEFT(C11, 1) | G11: =LEFT(D11, 1)
A12: [Q7] Garden | B12: {=INDEX(RawResponses!$A:$AL, $B$2, MATCH($A12&"*", RawResponses!$A$1:$AL$1, 0))} | C12: {=INDEX(RawResponses!$A:$AL, $B$3, MATCH($A12&"*", RawResponses!$A$1:$AL$1, 0))} | D12: {=INDEX(RawResponses!$A:$AL, $B$4, MATCH($A12&"*", RawResponses!$A$1:$AL$1, 0))} | E12: =LEFT(B12, 1) | F12: =LEFT(C12, 1) | G12: =LEFT(D12, 1)
A13: [Q7a] Living arrangement | B13: {=INDEX(RawResponses!$A:$AL, $B$2, MATCH($A13&"*", RawResponses!$A$1:$AL$1, 0))} | C13: =INDEX(RawResponses!$A:$AL, $B$3, MATCH($A13&"*", RawResponses!$A$1:$AL$1, 0)) | D13: =INDEX(RawResponses!$A:$AL, $B$4, MATCH($A13&"*", RawResponses!$A$1:$AL$1, 0)) | E13: =LEFT(B13, 1) | F13: =LEFT(C13, 1) | G13: =LEFT(D13, 1)
A14: [Q7b] Home size | B14: =INDEX(RawResponses!$A:$AL, $B$2, MATCH($A14&"*", RawResponses!$A$1:$AL$1, 0)) | C14: =INDEX(RawResponses!$A:$AL, $B$3, MATCH($A14&"*", RawResponses!$A$1:$AL$1, 0)) | D14: =INDEX(RawResponses!$A:$AL, $B$4, MATCH($A14&"*", RawResponses!$A$1:$AL$1, 0)) | E14: =LEFT(B14, 1) | F14: =LEFT(C14, 1) | G14: =LEFT(D14, 1)
A15: [Q10] | B15: {=INDEX(RawResponses!$A:$AL, $B$2, MATCH($A15&"*", RawResponses!$A$1:$AL$1, 0))} | C15: {=INDEX(RawResponses!$A:$AL, $B$3, MATCH($A15&"*", RawResponses!$A$1:$AL$1, 0))} | D15: {=INDEX(RawResponses!$A:$AL, $B$4, MATCH($A15&"*", RawResponses!$A$1:$AL$1, 0))} | E15: =LEFT(B15, 1) | F15: =LEFT(C15, 1) | G15: =LEFT(D15, 1)
A16: [Q11] | B16: {=INDEX(RawResponses!$A:$AL, $B$2, MATCH($A16&"*", RawResponses!$A$1:$AL$1, 0))} | C16: {=INDEX(RawResponses!$A:$AL, $B$3, MATCH($A16&"*", RawResponses!$A$1:$AL$1, 0))} | D16: {=INDEX(RawResponses!$A:$AL, $B$4, MATCH($A16&"*", RawResponses!$A$1:$AL$1, 0))} | E16: =LEFT(B16, 1) | F16: =LEFT(C16, 1) | G16: =LEFT(D16, 1)
A17: [Q12] | B17: {=INDEX(RawResponses!$A:$AL, $B$2, MATCH($A17&"*", RawResponses!$A$1:$AL$1, 0))} | C17: {=INDEX(RawResponses!$A:$AL, $B$3, MATCH($A17&"*", RawResponses!$A$1:$AL$1, 0))} | D17: {=INDEX(RawResponses!$A:$AL, $B$4, MATCH($A17&"*", RawResponses!$A$1:$AL$1, 0))} | E17: =LEFT(B17, 1) | F17: =LEFT(C17, 1) | G17: =LEFT(D17, 1)
A18: [Q13] | B18: =INDEX(RawResponses!$A:$AL, $B$2, MATCH($A18&"*", RawResponses!$A$1:$AL$1, 0)) | C18: =INDEX(RawResponses!$A:$AL, $B$3, MATCH($A18&"*", RawResponses!$A$1:$AL$1, 0)) | D18: =INDEX(RawResponses!$A:$AL, $B$4, MATCH($A18&"*", RawResponses!$A$1:$AL$1, 0)) | E18: =LEFT(B18, 1) | F18: =LEFT(C18, 1) | G18: =LEFT(D18, 1)
A19: [Q15.1] Nature | B19: {=INDEX(RawResponses!$A:$AL, $B$2, MATCH($A19&"*", RawResponses!$A$1:$AL$1, 0))} | C19: {=INDEX(RawResponses!$A:$AL, $B$3, MATCH($A19&"*", RawResponses!$A$1:$AL$1, 0))} | D19: {=INDEX(RawResponses!$A:$AL, $B$4, MATCH($A19&"*", RawResponses!$A$1:$AL$1, 0))} | E19: =LEFT(B19, 1) | F19: =LEFT(C19, 1) | G19: =LEFT(D19, 1)
A20: [Q15.2] Near family in GW | B20: {=INDEX(RawResponses!$A:$AL, $B$2, MATCH($A20&"*", RawResponses!$A$1:$AL$1, 0))} | C20: {=INDEX(RawResponses!$A:$AL, $B$3, MATCH($A20&"*", RawResponses!$A$1:$AL$1, 0))} | D20: {=INDEX(RawResponses!$A:$AL, $B$4, MATCH($A20&"*", RawResponses!$A$1:$AL$1, 0))} | E20: =LEFT(B20, 1) | F20: =LEFT(C20, 1) | G20: =LEFT(D20, 1)
A21: [Q15.3] Indian community | B21: {=INDEX(RawResponses!$A:$AL, $B$2, MATCH($A21&"*", RawResponses!$A$1:$AL$1, 0))} | C21: {=INDEX(RawResponses!$A:$AL, $B$3, MATCH($A21&"*", RawResponses!$A$1:$AL$1, 0))} | D21: {=INDEX(RawResponses!$A:$AL, $B$4, MATCH($A21&"*", RawResponses!$A$1:$AL$1, 0))} | E21: =LEFT(B21, 1) | F21: =LEFT(C21, 1) | G21: =LEFT(D21, 1)
A22: [Q15.4] Beach | B22: {=INDEX(RawResponses!$A:$AL, $B$2, MATCH($A22&"*", RawResponses!$A$1:$AL$1, 0))} | C22: {=INDEX(RawResponses!$A:$AL, $B$3, MATCH($A22&"*", RawResponses!$A$1:$AL$1, 0))} | D22: {=INDEX(RawResponses!$A:$AL, $B$4, MATCH($A22&"*", RawResponses!$A$1:$AL$1, 0))} | E22: =LEFT(B22, 1) | F22: =LEFT(C22, 1) | G22: =LEFT(D22, 1)
A23: [Q15.5] Hospital | B23: {=INDEX(RawResponses!$A:$AL, $B$2, MATCH($A23&"*", RawResponses!$A$1:$AL$1, 0))} | C23: {=INDEX(RawResponses!$A:$AL, $B$3, MATCH($A23&"*", RawResponses!$A$1:$AL$1, 0))} | D23: {=INDEX(RawResponses!$A:$AL, $B$4, MATCH($A23&"*", RawResponses!$A$1:$AL$1, 0))} | E23: =LEFT(B23, 1) | F23: =LEFT(C23, 1) | G23: =LEFT(D23, 1)
A24: [Q15.6] Train/bus | B24: {=INDEX(RawResponses!$A:$AL, $B$2, MATCH($A24&"*", RawResponses!$A$1:$AL$1, 0))} | C24: {=INDEX(RawResponses!$A:$AL, $B$3, MATCH($A24&"*", RawResponses!$A$1:$AL$1, 0))} | D24: {=INDEX(RawResponses!$A:$AL, $B$4, MATCH($A24&"*", RawResponses!$A$1:$AL$1, 0))} | E24: =LEFT(B24, 1) | F24: =LEFT(C24, 1) | G24: =LEFT(D24, 1)
A25: [Q15.7] Shops/doctor | B25: {=INDEX(RawResponses!$A:$AL, $B$2, MATCH($A25&"*", RawResponses!$A$1:$AL$1, 0))} | C25: {=INDEX(RawResponses!$A:$AL, $B$3, MATCH($A25&"*", RawResponses!$A$1:$AL$1, 0))} | D25: {=INDEX(RawResponses!$A:$AL, $B$4, MATCH($A25&"*", RawResponses!$A$1:$AL$1, 0))} | E25: =LEFT(B25, 1) | F25: =LEFT(C25, 1) | G25: =LEFT(D25, 1)
A26: [Q15.8] Village character | B26: {=INDEX(RawResponses!$A:$AL, $B$2, MATCH($A26&"*", RawResponses!$A$1:$AL$1, 0))} | C26: {=INDEX(RawResponses!$A:$AL, $B$3, MATCH($A26&"*", RawResponses!$A$1:$AL$1, 0))} | D26: {=INDEX(RawResponses!$A:$AL, $B$4, MATCH($A26&"*", RawResponses!$A$1:$AL$1, 0))} | E26: =LEFT(B26, 1) | F26: =LEFT(C26, 1) | G26: =LEFT(D26, 1)
A27: [Q15.9] Price | B27: {=INDEX(RawResponses!$A:$AL, $B$2, MATCH($A27&"*", RawResponses!$A$1:$AL$1, 0))} | C27: {=INDEX(RawResponses!$A:$AL, $B$3, MATCH($A27&"*", RawResponses!$A$1:$AL$1, 0))} | D27: {=INDEX(RawResponses!$A:$AL, $B$4, MATCH($A27&"*", RawResponses!$A$1:$AL$1, 0))} | E27: =LEFT(B27, 1) | F27: =LEFT(C27, 1) | G27: =LEFT(D27, 1)
A28: [Q15.10] Easy city trip | B28: {=INDEX(RawResponses!$A:$AL, $B$2, MATCH($A28&"*", RawResponses!$A$1:$AL$1, 0))} | C28: {=INDEX(RawResponses!$A:$AL, $B$3, MATCH($A28&"*", RawResponses!$A$1:$AL$1, 0))} | D28: {=INDEX(RawResponses!$A:$AL, $B$4, MATCH($A28&"*", RawResponses!$A$1:$AL$1, 0))} | E28: =LEFT(B28, 1) | F28: =LEFT(C28, 1) | G28: =LEFT(D28, 1)
A30: Context answers (shown for discussion; not weighted)
A31: Question ID | B31: Mum Answer | C31: Dad Answer | D31: Me Answer | E31: Mum Code | F31: Dad Code | G31: Me Code
A32: [Q1] | B32: =IFERROR(IF(INDEX(RawResponses!$A:$AM,$B$2,MATCH($A32&"*",RawResponses!$A$1:$AM$1,0))="","",INDEX(RawResponses!$A:$AM,$B$2,MATCH($A32&"*",RawResponses!$A$1:$AM$1,0))),"") | C32: =IFERROR(IF(INDEX(RawResponses!$A:$AM,$B$3,MATCH($A32&"*",RawResponses!$A$1:$AM$1,0))="","",INDEX(RawResponses!$A:$AM,$B$3,MATCH($A32&"*",RawResponses!$A$1:$AM$1,0))),"") | D32: =IFERROR(IF(INDEX(RawResponses!$A:$AM,$B$4,MATCH($A32&"*",RawResponses!$A$1:$AM$1,0))="","",INDEX(RawResponses!$A:$AM,$B$4,MATCH($A32&"*",RawResponses!$A$1:$AM$1,0))),"") | E32: =LEFT(B32,1) | F32: =LEFT(C32,1) | G32: =LEFT(D32,1)
A33: [Q2] | B33: =IFERROR(IF(INDEX(RawResponses!$A:$AM,$B$2,MATCH($A33&"*",RawResponses!$A$1:$AM$1,0))="","",INDEX(RawResponses!$A:$AM,$B$2,MATCH($A33&"*",RawResponses!$A$1:$AM$1,0))),"") | C33: =IFERROR(IF(INDEX(RawResponses!$A:$AM,$B$3,MATCH($A33&"*",RawResponses!$A$1:$AM$1,0))="","",INDEX(RawResponses!$A:$AM,$B$3,MATCH($A33&"*",RawResponses!$A$1:$AM$1,0))),"") | D33: =IFERROR(IF(INDEX(RawResponses!$A:$AM,$B$4,MATCH($A33&"*",RawResponses!$A$1:$AM$1,0))="","",INDEX(RawResponses!$A:$AM,$B$4,MATCH($A33&"*",RawResponses!$A$1:$AM$1,0))),"") | E33: =LEFT(B33,1) | F33: =LEFT(C33,1) | G33: =LEFT(D33,1)
A34: [Q8] | B34: =IFERROR(IF(INDEX(RawResponses!$A:$AM,$B$2,MATCH($A34&"*",RawResponses!$A$1:$AM$1,0))="","",INDEX(RawResponses!$A:$AM,$B$2,MATCH($A34&"*",RawResponses!$A$1:$AM$1,0))),"") | C34: =IFERROR(IF(INDEX(RawResponses!$A:$AM,$B$3,MATCH($A34&"*",RawResponses!$A$1:$AM$1,0))="","",INDEX(RawResponses!$A:$AM,$B$3,MATCH($A34&"*",RawResponses!$A$1:$AM$1,0))),"") | D34: =IFERROR(IF(INDEX(RawResponses!$A:$AM,$B$4,MATCH($A34&"*",RawResponses!$A$1:$AM$1,0))="","",INDEX(RawResponses!$A:$AM,$B$4,MATCH($A34&"*",RawResponses!$A$1:$AM$1,0))),"") | E34: =LEFT(B34,1) | F34: =LEFT(C34,1) | G34: =LEFT(D34,1)
A35: [Q9] | B35: =IFERROR(IF(INDEX(RawResponses!$A:$AM,$B$2,MATCH($A35&"*",RawResponses!$A$1:$AM$1,0))="","",INDEX(RawResponses!$A:$AM,$B$2,MATCH($A35&"*",RawResponses!$A$1:$AM$1,0))),"") | C35: =IFERROR(IF(INDEX(RawResponses!$A:$AM,$B$3,MATCH($A35&"*",RawResponses!$A$1:$AM$1,0))="","",INDEX(RawResponses!$A:$AM,$B$3,MATCH($A35&"*",RawResponses!$A$1:$AM$1,0))),"") | D35: =IFERROR(IF(INDEX(RawResponses!$A:$AM,$B$4,MATCH($A35&"*",RawResponses!$A$1:$AM$1,0))="","",INDEX(RawResponses!$A:$AM,$B$4,MATCH($A35&"*",RawResponses!$A$1:$AM$1,0))),"") | E35: =LEFT(B35,1) | F35: =LEFT(C35,1) | G35: =LEFT(D35,1)
A36: [Q13b] | B36: =IFERROR(IF(INDEX(RawResponses!$A:$AM,$B$2,MATCH($A36&"*",RawResponses!$A$1:$AM$1,0))="","",INDEX(RawResponses!$A:$AM,$B$2,MATCH($A36&"*",RawResponses!$A$1:$AM$1,0))),"") | C36: =IFERROR(IF(INDEX(RawResponses!$A:$AM,$B$3,MATCH($A36&"*",RawResponses!$A$1:$AM$1,0))="","",INDEX(RawResponses!$A:$AM,$B$3,MATCH($A36&"*",RawResponses!$A$1:$AM$1,0))),"") | D36: =IFERROR(IF(INDEX(RawResponses!$A:$AM,$B$4,MATCH($A36&"*",RawResponses!$A$1:$AM$1,0))="","",INDEX(RawResponses!$A:$AM,$B$4,MATCH($A36&"*",RawResponses!$A$1:$AM$1,0))),"") | E36: =LEFT(B36,1) | F36: =LEFT(C36,1) | G36: =LEFT(D36,1)
A37: [Q13c] | B37: =IFERROR(IF(INDEX(RawResponses!$A:$AM,$B$2,MATCH($A37&"*",RawResponses!$A$1:$AM$1,0))="","",INDEX(RawResponses!$A:$AM,$B$2,MATCH($A37&"*",RawResponses!$A$1:$AM$1,0))),"") | C37: =IFERROR(IF(INDEX(RawResponses!$A:$AM,$B$3,MATCH($A37&"*",RawResponses!$A$1:$AM$1,0))="","",INDEX(RawResponses!$A:$AM,$B$3,MATCH($A37&"*",RawResponses!$A$1:$AM$1,0))),"") | D37: =IFERROR(IF(INDEX(RawResponses!$A:$AM,$B$4,MATCH($A37&"*",RawResponses!$A$1:$AM$1,0))="","",INDEX(RawResponses!$A:$AM,$B$4,MATCH($A37&"*",RawResponses!$A$1:$AM$1,0))),"") | E37: =LEFT(B37,1) | F37: =LEFT(C37,1) | G37: =LEFT(D37,1)
A38: [Q14] | B38: =IFERROR(IF(INDEX(RawResponses!$A:$AM,$B$2,MATCH($A38&"*",RawResponses!$A$1:$AM$1,0))="","",INDEX(RawResponses!$A:$AM,$B$2,MATCH($A38&"*",RawResponses!$A$1:$AM$1,0))),"") | C38: =IFERROR(IF(INDEX(RawResponses!$A:$AM,$B$3,MATCH($A38&"*",RawResponses!$A$1:$AM$1,0))="","",INDEX(RawResponses!$A:$AM,$B$3,MATCH($A38&"*",RawResponses!$A$1:$AM$1,0))),"") | D38: =IFERROR(IF(INDEX(RawResponses!$A:$AM,$B$4,MATCH($A38&"*",RawResponses!$A$1:$AM$1,0))="","",INDEX(RawResponses!$A:$AM,$B$4,MATCH($A38&"*",RawResponses!$A$1:$AM$1,0))),"") | E38: =LEFT(B38,1) | F38: =LEFT(C38,1) | G38: =LEFT(D38,1)
A39: [Gap-form notes] | B39: =IFERROR(IF(INDEX(RawResponses!$A:$AM,$B$2,MATCH($A39&"*",RawResponses!$A$1:$AM$1,0))="","",INDEX(RawResponses!$A:$AM,$B$2,MATCH($A39&"*",RawResponses!$A$1:$AM$1,0))),"") | C39: =IFERROR(IF(INDEX(RawResponses!$A:$AM,$B$3,MATCH($A39&"*",RawResponses!$A$1:$AM$1,0))="","",INDEX(RawResponses!$A:$AM,$B$3,MATCH($A39&"*",RawResponses!$A$1:$AM$1,0))),"") | D39: =IFERROR(IF(INDEX(RawResponses!$A:$AM,$B$4,MATCH($A39&"*",RawResponses!$A$1:$AM$1,0))="","",INDEX(RawResponses!$A:$AM,$B$4,MATCH($A39&"*",RawResponses!$A$1:$AM$1,0))),"")

Sheet Filters
A1: Filter | B1: Strictest Constraint | C1: Notes | D1: Survey-derived value (reference only)
A2: Q3 Total budget | B2: 1500000 | C2: Confirmed family decision 27 Oct 2026: budget cap set to $1,500,000 maximum purchase price (excluding transaction & moving costs). Replaces survey strictest of $1,250,000. | D2: 1250000
A3: Total acquisition ceiling (Price + 6% costs) | B3: =B2 * (1 + Settings!B6) | C3: Total outlay cap ($1,590,000) including 6% stamp duty/conveyancing/moving allowance on $1,500,000 purchase price.
A4: Q4/Q4b Max drive to GW | B4: 90 | C4: Family decision 26 Oct 2026: hard max 90 min (60 min preferred); a train option is now preferred, not required (see row 9, changed by NJD, family to confirm). Replaces survey strictest of 25 min (Mum/Me); Dad said up to 75. | D4: =MIN(IF(CleanedAnswers!E8="D",IF(ISNUMBER(CleanedAnswers!B9),CleanedAnswers!B9,999),IFERROR(CHOOSE(MATCH(CleanedAnswers!E8,{"A","B","C"},0),15,25,35),999)),IF(CleanedAnswers!F8="D",IF(ISNUMBER(CleanedAnswers!C9),CleanedAnswers!C9,999),IFERROR(CHOOSE(MATCH(CleanedAnswers!F8,{"A","B","C"},0),15,25,35),999)),IF(CleanedAnswers!G8="D",IF(ISNUMBER(CleanedAnswers!D9),CleanedAnswers!D9,999),IFERROR(CHOOSE(MATCH(CleanedAnswers!G8,{"A","B","C"},0),15,25,35),999)))
A5: Q5 Max drive to ED | B5: 90 | C5: Family decision 26 Oct 2026: hard cap 90 min, and ED time is also scored (SuburbScorecard column O). Replaces survey strictest of 20 min (Mum/Me); Dad said no limit.
A6: Q6 Stairs | B6: Stairs allowed (single-level not required) | C6: CORRECTED 27 Oct 2026 by NJD: stairs are allowed, so this is no longer a hard filter. Previous value was the survey strictest answer (formula kept in D6). | D6: =IF(COUNTIF(CleanedAnswers!E11:G11, "A")>0, "A — None at all (Single-level only)", "Check")
A7: Q7a/Q7b Living arrangement | B7: Needs discussion (Living arrangement undecided): D — Self-contained space
A8: Q7 Garden | B8: Needs discussion (Depends — see notes)
A9: Train option | B9: Preferred, not required (scored via SuburbScorecard column S) | C9: CHANGED 26 Oct 2026 by NJD from 'Required (a train station in or at the edge of the suburb)', which had been recorded as a family decision earlier that day. Family to confirm. Reason: a hard rule removes bush and coastal areas that have not been viewed. Column AB on SuburbScorecard: Yes / No.
A10: Drive-time basis | B10: Google Maps drive time, 'leave now' typical traffic, looked up 26 Oct 2026 | C10: Not tested at peak hour. J = to Glen Waverley (suburb centre). K = to the nearest 24-hr public ED listed in SuburbScorecard column AD. Train Yes/No is from recall and sheet notes, not checked against timetables.

Sheet PriorityWeights
A1: Question | B1: Mum Code | C1: Dad Code | D1: Me Code | E1: Mum Score | F1: Dad Score | G1: Me Score | H1: Mum Norm | I1: Dad Norm | J1: Me Norm | K1: Combined Weight
A2: Nature | B2: =CleanedAnswers!E19 | C2: =CleanedAnswers!F19 | D2: =CleanedAnswers!G19 | E2: =VLOOKUP(B2, Settings!$A$10:$C$13, 3, FALSE()) | F2: =VLOOKUP(C2, Settings!$A$10:$C$13, 3, FALSE()) | G2: =VLOOKUP(D2, Settings!$A$10:$C$13, 3, FALSE()) | H2: =E2/SUM(E$2:E$11) | I2: =F2/SUM(F$2:F$11) | J2: =G2/SUM(G$2:G$11) | K2: =(H2*Settings!$B$2 + I2*Settings!$B$3 + J2*Settings!$B$4)/(Settings!$B$2+Settings!$B$3+Settings!$B$4)
A3: Near family in GW | B3: =CleanedAnswers!E20 | C3: =CleanedAnswers!F20 | D3: =CleanedAnswers!G20 | E3: =VLOOKUP(B3, Settings!$A$10:$C$13, 3, FALSE()) | F3: =VLOOKUP(C3, Settings!$A$10:$C$13, 3, FALSE()) | G3: =VLOOKUP(D3, Settings!$A$10:$C$13, 3, FALSE()) | H3: =E3/SUM(E$2:E$11) | I3: =F3/SUM(F$2:F$11) | J3: =G3/SUM(G$2:G$11) | K3: =(H3*Settings!$B$2 + I3*Settings!$B$3 + J3*Settings!$B$4)/(Settings!$B$2+Settings!$B$3+Settings!$B$4)
A4: Indian community | B4: =CleanedAnswers!E21 | C4: =CleanedAnswers!F21 | D4: =CleanedAnswers!G21 | E4: =VLOOKUP(B4, Settings!$A$10:$C$13, 3, FALSE()) | F4: =VLOOKUP(C4, Settings!$A$10:$C$13, 3, FALSE()) | G4: =VLOOKUP(D4, Settings!$A$10:$C$13, 3, FALSE()) | H4: =E4/SUM(E$2:E$11) | I4: =F4/SUM(F$2:F$11) | J4: =G4/SUM(G$2:G$11) | K4: =(H4*Settings!$B$2 + I4*Settings!$B$3 + J4*Settings!$B$4)/(Settings!$B$2+Settings!$B$3+Settings!$B$4)
A5: Beach | B5: =CleanedAnswers!E22 | C5: =CleanedAnswers!F22 | D5: =CleanedAnswers!G22 | E5: =VLOOKUP(B5, Settings!$A$10:$C$13, 3, FALSE()) | F5: =VLOOKUP(C5, Settings!$A$10:$C$13, 3, FALSE()) | G5: =VLOOKUP(D5, Settings!$A$10:$C$13, 3, FALSE()) | H5: =E5/SUM(E$2:E$11) | I5: =F5/SUM(F$2:F$11) | J5: =G5/SUM(G$2:G$11) | K5: =(H5*Settings!$B$2 + I5*Settings!$B$3 + J5*Settings!$B$4)/(Settings!$B$2+Settings!$B$3+Settings!$B$4)
A6: Hospital | B6: =CleanedAnswers!E23 | C6: =CleanedAnswers!F23 | D6: =CleanedAnswers!G23 | E6: =VLOOKUP(B6, Settings!$A$10:$C$13, 3, FALSE()) | F6: =VLOOKUP(C6, Settings!$A$10:$C$13, 3, FALSE()) | G6: =VLOOKUP(D6, Settings!$A$10:$C$13, 3, FALSE()) | H6: =E6/SUM(E$2:E$11) | I6: =F6/SUM(F$2:F$11) | J6: =G6/SUM(G$2:G$11) | K6: =(H6*Settings!$B$2 + I6*Settings!$B$3 + J6*Settings!$B$4)/(Settings!$B$2+Settings!$B$3+Settings!$B$4)
A7: Train/bus | B7: =CleanedAnswers!E24 | C7: =CleanedAnswers!F24 | D7: =CleanedAnswers!G24 | E7: =VLOOKUP(B7, Settings!$A$10:$C$13, 3, FALSE()) | F7: =VLOOKUP(C7, Settings!$A$10:$C$13, 3, FALSE()) | G7: =VLOOKUP(D7, Settings!$A$10:$C$13, 3, FALSE()) | H7: =E7/SUM(E$2:E$11) | I7: =F7/SUM(F$2:F$11) | J7: =G7/SUM(G$2:G$11) | K7: =(H7*Settings!$B$2 + I7*Settings!$B$3 + J7*Settings!$B$4)/(Settings!$B$2+Settings!$B$3+Settings!$B$4)
A8: Shops/doctor | B8: =CleanedAnswers!E25 | C8: =CleanedAnswers!F25 | D8: =CleanedAnswers!G25 | E8: =VLOOKUP(B8, Settings!$A$10:$C$13, 3, FALSE()) | F8: =VLOOKUP(C8, Settings!$A$10:$C$13, 3, FALSE()) | G8: =VLOOKUP(D8, Settings!$A$10:$C$13, 3, FALSE()) | H8: =E8/SUM(E$2:E$11) | I8: =F8/SUM(F$2:F$11) | J8: =G8/SUM(G$2:G$11) | K8: =(H8*Settings!$B$2 + I8*Settings!$B$3 + J8*Settings!$B$4)/(Settings!$B$2+Settings!$B$3+Settings!$B$4)
A9: Village character | B9: =CleanedAnswers!E26 | C9: =CleanedAnswers!F26 | D9: =CleanedAnswers!G26 | E9: =VLOOKUP(B9, Settings!$A$10:$C$13, 3, FALSE()) | F9: =VLOOKUP(C9, Settings!$A$10:$C$13, 3, FALSE()) | G9: =VLOOKUP(D9, Settings!$A$10:$C$13, 3, FALSE()) | H9: =E9/SUM(E$2:E$11) | I9: =F9/SUM(F$2:F$11) | J9: =G9/SUM(G$2:G$11) | K9: =(H9*Settings!$B$2 + I9*Settings!$B$3 + J9*Settings!$B$4)/(Settings!$B$2+Settings!$B$3+Settings!$B$4)
A10: Price | B10: =CleanedAnswers!E27 | C10: =CleanedAnswers!F27 | D10: =CleanedAnswers!G27 | E10: =VLOOKUP(B10, Settings!$A$10:$C$13, 3, FALSE()) | F10: =VLOOKUP(C10, Settings!$A$10:$C$13, 3, FALSE()) | G10: =VLOOKUP(D10, Settings!$A$10:$C$13, 3, FALSE()) | H10: =E10/SUM(E$2:E$11) | I10: =F10/SUM(F$2:F$11) | J10: =G10/SUM(G$2:G$11) | K10: =(H10*Settings!$B$2 + I10*Settings!$B$3 + J10*Settings!$B$4)/(Settings!$B$2+Settings!$B$3+Settings!$B$4)
A11: Easy city trip | B11: =CleanedAnswers!E28 | C11: =CleanedAnswers!F28 | D11: =CleanedAnswers!G28 | E11: =VLOOKUP(B11, Settings!$A$10:$C$13, 3, FALSE()) | F11: =VLOOKUP(C11, Settings!$A$10:$C$13, 3, FALSE()) | G11: =VLOOKUP(D11, Settings!$A$10:$C$13, 3, FALSE()) | H11: =E11/SUM(E$2:E$11) | I11: =F11/SUM(F$2:F$11) | J11: =G11/SUM(G$2:G$11) | K11: =(H11*Settings!$B$2 + I11*Settings!$B$3 + J11*Settings!$B$4)/(Settings!$B$2+Settings!$B$3+Settings!$B$4)

Sheet ForcedChoiceCorrections
A1: Matchup | B1: Result | H1: Question | I1: A-side priority | J1: B-side priority | K1: Mum vote | L1: Dad vote | M1: Me vote | N1: A votes (weighted) | O1: B votes (weighted) | P1: Winning side | Q1: Winner | R1: Loser | S1: Winner weight | T1: Loser weight | U1: Transfer
A2: Trade-offs: see H1:U5 (live, blueprint rule). | H2: Q10 | I2: Nature | J2: Near family in GW | K2: =IF(OR(CleanedAnswers!B15=$I2,LEFT(CleanedAnswers!B15,3)="A —"),"A",IF(OR(CleanedAnswers!B15=$J2,LEFT(CleanedAnswers!B15,3)="B —"),"B","")) | L2: =IF(OR(CleanedAnswers!C15=$I2,LEFT(CleanedAnswers!C15,3)="A —"),"A",IF(OR(CleanedAnswers!C15=$J2,LEFT(CleanedAnswers!C15,3)="B —"),"B","")) | M2: =IF(OR(CleanedAnswers!D15=$I2,LEFT(CleanedAnswers!D15,3)="A —"),"A",IF(OR(CleanedAnswers!D15=$J2,LEFT(CleanedAnswers!D15,3)="B —"),"B","")) | N2: =(K2="A")*Settings!$B$2+(L2="A")*Settings!$B$3+(M2="A")*Settings!$B$4 | O2: =(K2="B")*Settings!$B$2+(L2="B")*Settings!$B$3+(M2="B")*Settings!$B$4 | P2: =IF(N2+O2=0,"",IF(N2>O2,"A",IF(O2>N2,"B","Split"))) | Q2: =IF(P2="A",I2,IF(P2="B",J2,"")) | R2: =IF(P2="A",J2,IF(P2="B",I2,"")) | S2: =IF(Q2="","",INDEX($D$6:$D$15,MATCH(Q2,$A$6:$A$15,0))) | T2: =IF(R2="","",INDEX($D$6:$D$15,MATCH(R2,$A$6:$A$15,0))) | U2: =IF(OR(Q2="",NOT(ISNUMBER(S2)),NOT(ISNUMBER(T2))),0,IF(S2<T2+Settings!$B$7,MIN(T2,(T2-S2+Settings!$B$7)/2),0))
H3: Q11 | I3: Beach | J3: Nature | K3: =IF(OR(CleanedAnswers!B16=$I3,LEFT(CleanedAnswers!B16,3)="A —"),"A",IF(OR(CleanedAnswers!B16=$J3,LEFT(CleanedAnswers!B16,3)="B —"),"B","")) | L3: =IF(OR(CleanedAnswers!C16=$I3,LEFT(CleanedAnswers!C16,3)="A —"),"A",IF(OR(CleanedAnswers!C16=$J3,LEFT(CleanedAnswers!C16,3)="B —"),"B","")) | M3: =IF(OR(CleanedAnswers!D16=$I3,LEFT(CleanedAnswers!D16,3)="A —"),"A",IF(OR(CleanedAnswers!D16=$J3,LEFT(CleanedAnswers!D16,3)="B —"),"B","")) | N3: =(K3="A")*Settings!$B$2+(L3="A")*Settings!$B$3+(M3="A")*Settings!$B$4 | O3: =(K3="B")*Settings!$B$2+(L3="B")*Settings!$B$3+(M3="B")*Settings!$B$4 | P3: =IF(N3+O3=0,"",IF(N3>O3,"A",IF(O3>N3,"B","Split"))) | Q3: =IF(P3="A",I3,IF(P3="B",J3,"")) | R3: =IF(P3="A",J3,IF(P3="B",I3,"")) | S3: =IF(Q3="","",INDEX($D$6:$D$15,MATCH(Q3,$A$6:$A$15,0))) | T3: =IF(R3="","",INDEX($D$6:$D$15,MATCH(R3,$A$6:$A$15,0))) | U3: =IF(OR(Q3="",NOT(ISNUMBER(S3)),NOT(ISNUMBER(T3))),0,IF(S3<T3+Settings!$B$7,MIN(T3,(T3-S3+Settings!$B$7)/2),0))
H4: Q12 | I4: Village character | J4: Shops & doctor | K4: =IF(OR(CleanedAnswers!B17=$I4,LEFT(CleanedAnswers!B17,3)="A —"),"A",IF(OR(CleanedAnswers!B17=$J4,LEFT(CleanedAnswers!B17,3)="B —"),"B","")) | L4: =IF(OR(CleanedAnswers!C17=$I4,LEFT(CleanedAnswers!C17,3)="A —"),"A",IF(OR(CleanedAnswers!C17=$J4,LEFT(CleanedAnswers!C17,3)="B —"),"B","")) | M4: =IF(OR(CleanedAnswers!D17=$I4,LEFT(CleanedAnswers!D17,3)="A —"),"A",IF(OR(CleanedAnswers!D17=$J4,LEFT(CleanedAnswers!D17,3)="B —"),"B","")) | N4: =(K4="A")*Settings!$B$2+(L4="A")*Settings!$B$3+(M4="A")*Settings!$B$4 | O4: =(K4="B")*Settings!$B$2+(L4="B")*Settings!$B$3+(M4="B")*Settings!$B$4 | P4: =IF(N4+O4=0,"",IF(N4>O4,"A",IF(O4>N4,"B","Split"))) | Q4: =IF(P4="A",I4,IF(P4="B",J4,"")) | R4: =IF(P4="A",J4,IF(P4="B",I4,"")) | S4: =IF(Q4="","",INDEX($D$6:$D$15,MATCH(Q4,$A$6:$A$15,0))) | T4: =IF(R4="","",INDEX($D$6:$D$15,MATCH(R4,$A$6:$A$15,0))) | U4: =IF(OR(Q4="",NOT(ISNUMBER(S4)),NOT(ISNUMBER(T4))),0,IF(S4<T4+Settings!$B$7,MIN(T4,(T4-S4+Settings!$B$7)/2),0))
A5: Final Normalized Weights | B5: Weight | C5: Net forced-choice correction (live) | D5: Survey weight (PriorityWeights K) | E5: Previous typed weight (pre 27 Oct link) | F5: Manual tweak (editable, e.g. 0.03 = +3 pts) | H5: Q13 | I5: Indian community | J5: Nature | K5: =IF(OR(CleanedAnswers!B18=$I5,LEFT(CleanedAnswers!B18,3)="A —"),"A",IF(OR(CleanedAnswers!B18=$J5,LEFT(CleanedAnswers!B18,3)="B —"),"B","")) | L5: =IF(OR(CleanedAnswers!C18=$I5,LEFT(CleanedAnswers!C18,3)="A —"),"A",IF(OR(CleanedAnswers!C18=$J5,LEFT(CleanedAnswers!C18,3)="B —"),"B","")) | M5: =IF(OR(CleanedAnswers!D18=$I5,LEFT(CleanedAnswers!D18,3)="A —"),"A",IF(OR(CleanedAnswers!D18=$J5,LEFT(CleanedAnswers!D18,3)="B —"),"B","")) | N5: =(K5="A")*Settings!$B$2+(L5="A")*Settings!$B$3+(M5="A")*Settings!$B$4 | O5: =(K5="B")*Settings!$B$2+(L5="B")*Settings!$B$3+(M5="B")*Settings!$B$4 | P5: =IF(N5+O5=0,"",IF(N5>O5,"A",IF(O5>N5,"B","Split"))) | Q5: =IF(P5="A",I5,IF(P5="B",J5,"")) | R5: =IF(P5="A",J5,IF(P5="B",I5,"")) | S5: =IF(Q5="","",INDEX($D$6:$D$15,MATCH(Q5,$A$6:$A$15,0))) | T5: =IF(R5="","",INDEX($D$6:$D$15,MATCH(R5,$A$6:$A$15,0))) | U5: =IF(OR(Q5="",NOT(ISNUMBER(S5)),NOT(ISNUMBER(T5))),0,IF(S5<T5+Settings!$B$7,MIN(T5,(T5-S5+Settings!$B$7)/2),0))
A6: Near family in GW | B6: =MAX(0,D6+C6+F6)/SUMPRODUCT((D$6:D$15+C$6:C$15+F$6:F$15>0)*(D$6:D$15+C$6:C$15+F$6:F$15)) | C6: =SUMIF($Q$2:$Q$5,A6,$U$2:$U$5)-SUMIF($R$2:$R$5,A6,$U$2:$U$5) | D6: =PriorityWeights!K3 | E6: 0.153 | F6: 0
A7: Nature | B7: =MAX(0,D7+C7+F7)/SUMPRODUCT((D$6:D$15+C$6:C$15+F$6:F$15>0)*(D$6:D$15+C$6:C$15+F$6:F$15)) | C7: =SUMIF($Q$2:$Q$5,A7,$U$2:$U$5)-SUMIF($R$2:$R$5,A7,$U$2:$U$5) | D7: =PriorityWeights!K2 | E7: 0.133 | F7: 0
A8: Hospital | B8: =MAX(0,D8+C8+F8)/SUMPRODUCT((D$6:D$15+C$6:C$15+F$6:F$15>0)*(D$6:D$15+C$6:C$15+F$6:F$15)) | C8: =SUMIF($Q$2:$Q$5,A8,$U$2:$U$5)-SUMIF($R$2:$R$5,A8,$U$2:$U$5) | D8: =PriorityWeights!K6 | E8: 0.133 | F8: 0
A9: Indian community | B9: =MAX(0,D9+C9+F9)/SUMPRODUCT((D$6:D$15+C$6:C$15+F$6:F$15>0)*(D$6:D$15+C$6:C$15+F$6:F$15)) | C9: =SUMIF($Q$2:$Q$5,A9,$U$2:$U$5)-SUMIF($R$2:$R$5,A9,$U$2:$U$5) | D9: =PriorityWeights!K4 | E9: 0.117 | F9: 0
A10: Shops & doctor | B10: =MAX(0,D10+C10+F10)/SUMPRODUCT((D$6:D$15+C$6:C$15+F$6:F$15>0)*(D$6:D$15+C$6:C$15+F$6:F$15)) | C10: =SUMIF($Q$2:$Q$5,A10,$U$2:$U$5)-SUMIF($R$2:$R$5,A10,$U$2:$U$5) | D10: =PriorityWeights!K8 | E10: 0.108 | F10: 0
A11: Village character | B11: =MAX(0,D11+C11+F11)/SUMPRODUCT((D$6:D$15+C$6:C$15+F$6:F$15>0)*(D$6:D$15+C$6:C$15+F$6:F$15)) | C11: =SUMIF($Q$2:$Q$5,A11,$U$2:$U$5)-SUMIF($R$2:$R$5,A11,$U$2:$U$5) | D11: =PriorityWeights!K9 | E11: 0.088 | F11: 0
A12: Train/bus | B12: =MAX(0,D12+C12+F12)/SUMPRODUCT((D$6:D$15+C$6:C$15+F$6:F$15>0)*(D$6:D$15+C$6:C$15+F$6:F$15)) | C12: =SUMIF($Q$2:$Q$5,A12,$U$2:$U$5)-SUMIF($R$2:$R$5,A12,$U$2:$U$5) | D12: =PriorityWeights!K7 | E12: 0.081 | F12: 0
A13: Price | B13: =MAX(0,D13+C13+F13)/SUMPRODUCT((D$6:D$15+C$6:C$15+F$6:F$15>0)*(D$6:D$15+C$6:C$15+F$6:F$15)) | C13: =SUMIF($Q$2:$Q$5,A13,$U$2:$U$5)-SUMIF($R$2:$R$5,A13,$U$2:$U$5) | D13: =PriorityWeights!K10 | E13: 0.081 | F13: 0
A14: Beach | B14: =MAX(0,D14+C14+F14)/SUMPRODUCT((D$6:D$15+C$6:C$15+F$6:F$15>0)*(D$6:D$15+C$6:C$15+F$6:F$15)) | C14: =SUMIF($Q$2:$Q$5,A14,$U$2:$U$5)-SUMIF($R$2:$R$5,A14,$U$2:$U$5) | D14: =PriorityWeights!K5 | E14: 0.061 | F14: 0
A15: City trip | B15: =MAX(0,D15+C15+F15)/SUMPRODUCT((D$6:D$15+C$6:C$15+F$6:F$15>0)*(D$6:D$15+C$6:C$15+F$6:F$15)) | C15: =SUMIF($Q$2:$Q$5,A15,$U$2:$U$5)-SUMIF($R$2:$R$5,A15,$U$2:$U$5) | D15: =PriorityWeights!K11 | E15: 0.045 | F15: 0
A16: Total | B16: =SUM(B6:B15)
A18: Note (27 Oct 2026): B = survey weight (D) + live trade-off correction (C, rule from survey blueprint: winner moved 2 pts ahead of loser) + manual tweak (F), floored at 0 and renormalised. E = old typed weights.

Sheet SuburbScorecard
A1: Location | B1: Region | C1: Shortlist Status | D1: Parents Inland/Bush Fit (P) | E1: My Coastal-Nature Fit (Y) | F1: Primary Investigation Lens | G1: Published House Price | H1: Price Basis | I1: Price + Est. 6% Costs | J1: Drive to GW (min) | K1: Drive to 24-Hr Public ED (min) | L1: Hard Filter Status | M1: Score: Near family in GW | N1: Score: Nature | O1: Score: Hospital | P1: Score: Indian community | Q1: Score: Shops & doctor | R1: Score: Village character | S1: Score: Train/bus | T1: Score: Price | U1: Score: Beach | V1: Score: City trip | W1: Scores Entered | X1: Weighted Score (0-10) | Y1: Rank (Passing Only) | Z1: Healthcare & ABS Verification Notes | AA1: Legacy import text (frozen 27 Oct 2026; not used by any formula — edit columns A–H and Z instead) | AB1: Train Option (Yes/No) | AC1: Train Station / Basis | AD1: ED Used for Drive Time (K) | AE1: Budget cap — purchase price | AF1: Budget basis | AG1: Price evidence type | AH1: Price evidence date | AI1: Budget result | AJ1: Budget note
A2: Blackburn | B2: East Melbourne | C2: Active Shortlist | D2: Medium (Leafy streets) | E2: Low (Inland) | F2: Leafy daily living vs housing cost | G2: 1600000 | H2: Sale median, rolling 12m (OnTheHouse); unit $820k | I2: {=IF(ISNUMBER(G2:G90), IF(G2:G90>0, G2:G90 * (1 + Settings!$B$6), ""), "")} | J2: 11 | K2: 7 | L2: Active — needs data | O2: =IF(K2="","",ROUND(MAX(0,10*(1-K2/Filters!$B$5)),1)) | W2: =IF(M2="",0,COUNT(M2:V2)) | X2: =IF(W2<10,"",M2*ForcedChoiceCorrections!$B$6+N2*ForcedChoiceCorrections!$B$7+O2*ForcedChoiceCorrections!$B$8+P2*ForcedChoiceCorrections!$B$9+Q2*ForcedChoiceCorrections!$B$10+R2*ForcedChoiceCorrections!$B$11+S2*ForcedChoiceCorrections!$B$12+T2*ForcedChoiceCorrections!$B$13+U2*ForcedChoiceCorrections!$B$14+V2*ForcedChoiceCorrections!$B$15) | Y2: =IF(AND(ISNUMBER(SEARCH("pass",L2)),ISNUMBER(X2)),COUNTIFS(L$2:L$90,"*pass*",X$2:X$90,">"&X2)+1,"") | Z2: ABS 2021: 32.4% overseas-born, 31.6% non-Eng HH. Station/ED journeys unverified. | AA2: 1. Blackburn | East Melbourne | Active Shortlist | P: Medium (Leafy streets) | Y: Low (Inland) | Lens: Leafy daily living vs housing cost | Price: 1600000 | Basis: Sale median, rolling 12m (OnTheHouse); unit $820k | Note: ABS 2021: 32.4% overseas-born, 31.6% non-Eng HH. Station/ED journeys unverified. | AB2: Yes | AC2: Blackburn station, Lilydale line (recall; verify) | AD2: Box Hill Hospital ED | AE2: 1500000 | AF2: Maximum purchase price, excluding transaction and moving costs | AG2: Suburb median | AH2: 26 Oct 2026 | AI2: Needs data | AJ2: House median $1.60M (OnTheHouse) exceeds $1.5M cap, but unit/villa median is $820k. Awaiting documented search for suitable single-level homes/units under $1.5M.
A3: Ringwood | B3: East Melbourne | C3: Active Shortlist | D3: Medium-High (Foothills gateway) | E3: Low (Inland) | F3: Rail, services & access to greener surroundings | G3: 1045000 | H3: Sale median, rolling 12m (OnTheHouse); unit $650k | I3: 1107700 | J3: 12 | K3: 5 | L3: Active — provisional pass | M3: =IF(J3="","",ROUND(MAX(0,10*(1-J3/Filters!$B$4)),1)) | N3: 4 | O3: =IF(K3="","",ROUND(MAX(0,10*(1-K3/Filters!$B$5)),1)) | P3: 6 | Q3: 10 | R3: 3 | S3: 9 | T3: =IF(G3="","",ROUND(MAX(0,MIN(10,10*(Filters!$B$2-G3)/(Filters!$B$2-500000))),1)) | U3: 0 | V3: 7 | W3: =IF(M3="",0,COUNT(M3:V3)) | X3: =IF(W3<10,"",M3*ForcedChoiceCorrections!$B$6+N3*ForcedChoiceCorrections!$B$7+O3*ForcedChoiceCorrections!$B$8+P3*ForcedChoiceCorrections!$B$9+Q3*ForcedChoiceCorrections!$B$10+R3*ForcedChoiceCorrections!$B$11+S3*ForcedChoiceCorrections!$B$12+T3*ForcedChoiceCorrections!$B$13+U3*ForcedChoiceCorrections!$B$14+V3*ForcedChoiceCorrections!$B$15) | Y3: =IF(AND(ISNUMBER(SEARCH("pass",L3)),ISNUMBER(X3)),COUNTIFS(L$2:L$90,"*pass*",X$2:X$90,">"&X3)+1,"") | Z3: ABS 2021: 35.7% overseas-born, 33.3% non-Eng HH. Belgrave/Lilydale rail; Maroondah Hospital ED nearby (verify drive). | SCORES 27 Oct 2026: M (near family) and T (price) are formulas from J and G; O from K. N, P, Q, R, S, U, V are ESTIMATES (Claude, general knowledge, not site-checked); S also rests on train Yes/No marked 'verify'. | AA3: 2. Ringwood | East Melbourne | Active Shortlist | P: Medium-High (Foothills gateway) | Y: Low (Inland) | Lens: Rail, services & access to greener surroundings | Price: 1045000 | Basis: Sale median, rolling 12m (OnTheHouse); unit $650k | Note: ABS 2021: 35.7% overseas-born, 33.3% non-Eng HH. Belgrave/Lilydale rail; Maroondah Hospital ED nearby (verify drive). | AB3: Yes | AC3: Ringwood station, Lilydale/Belgrave lines (recall; verify) | AD3: Maroondah Hospital ED | AE3: 1500000 | AF3: Maximum purchase price, excluding transaction and moving costs | AG3: Suburb median | AH3: 26 Oct 2026 | AI3: Pass | AJ3: Published house price ($1,045,000) is under $1.5M cap.
A4: Heidelberg | B4: North-East Melbourne | C4: Active Shortlist | D4: Medium (Yarra parkland) | E4: Low (Inland) | F4: Healthcare-led established suburb option | G4: 1452000 | H4: Sale median, rolling 12m (35 sales); unit $700k | I4: 1539120 | J4: 25 | K4: 4 | L4: Active — provisional pass | M4: =IF(J4="","",ROUND(MAX(0,10*(1-J4/Filters!$B$4)),1)) | N4: 6 | O4: =IF(K4="","",ROUND(MAX(0,10*(1-K4/Filters!$B$5)),1)) | P4: 5 | Q4: 8 | R4: 4 | S4: 8 | T4: =IF(G4="","",ROUND(MAX(0,MIN(10,10*(Filters!$B$2-G4)/(Filters!$B$2-500000))),1)) | U4: 0 | V4: 8 | W4: =IF(M4="",0,COUNT(M4:V4)) | X4: =IF(W4<10,"",M4*ForcedChoiceCorrections!$B$6+N4*ForcedChoiceCorrections!$B$7+O4*ForcedChoiceCorrections!$B$8+P4*ForcedChoiceCorrections!$B$9+Q4*ForcedChoiceCorrections!$B$10+R4*ForcedChoiceCorrections!$B$11+S4*ForcedChoiceCorrections!$B$12+T4*ForcedChoiceCorrections!$B$13+U4*ForcedChoiceCorrections!$B$14+V4*ForcedChoiceCorrections!$B$15) | Y4: =IF(AND(ISNUMBER(SEARCH("pass",L4)),ISNUMBER(X4)),COUNTIFS(L$2:L$90,"*pass*",X$2:X$90,">"&X4)+1,"") | Z4: ABS 2021: 28.1% overseas-born, 28.4% non-Eng HH. Austin Hospital precinct; verify residential pocket & gradients. | SCORES 27 Oct 2026: M (near family) and T (price) are formulas from J and G; O from K. N, P, Q, R, S, U, V are ESTIMATES (Claude, general knowledge, not site-checked); S also rests on train Yes/No marked 'verify'. | AA4: 3. Heidelberg | North-East Melbourne | Active Shortlist | P: Medium (Yarra parkland) | Y: Low (Inland) | Lens: Healthcare-led established suburb option | Price: 1452000 | Basis: Sale median, rolling 12m (35 sales); unit $700k | Note: ABS 2021: 28.1% overseas-born, 28.4% non-Eng HH. Austin Hospital precinct; verify residential pocket & gradients. | AB4: Yes | AC4: Heidelberg station, Hurstbridge line (recall; verify) | AD4: Austin Hospital ED | AE4: 1500000 | AF4: Maximum purchase price, excluding transaction and moving costs | AG4: Suburb median | AH4: 26 Oct 2026 | AI4: Pass | AJ4: House median $1.452M (35 sales) is under $1.5M cap. Passes GW drive (25m) and ED drive (4m).
A5: Eltham | B5: North-East Melbourne | C5: Active Shortlist | D5: High (Bushland/trees) | E5: Low (Inland) | F5: Green/scenic lifestyle hypothesis | G5: 1273000 | H5: Sale median, rolling 12m (195 sales); unit $805k | I5: 1349380 | J5: 26 | K5: 16 | L5: Active — provisional pass | M5: =IF(J5="","",ROUND(MAX(0,10*(1-J5/Filters!$B$4)),1)) | N5: 8 | O5: =IF(K5="","",ROUND(MAX(0,10*(1-K5/Filters!$B$5)),1)) | P5: 3 | Q5: 8 | R5: 7 | S5: 8 | T5: =IF(G5="","",ROUND(MAX(0,MIN(10,10*(Filters!$B$2-G5)/(Filters!$B$2-500000))),1)) | U5: 0 | V5: 7 | W5: =IF(M5="",0,COUNT(M5:V5)) | X5: =IF(W5<10,"",M5*ForcedChoiceCorrections!$B$6+N5*ForcedChoiceCorrections!$B$7+O5*ForcedChoiceCorrections!$B$8+P5*ForcedChoiceCorrections!$B$9+Q5*ForcedChoiceCorrections!$B$10+R5*ForcedChoiceCorrections!$B$11+S5*ForcedChoiceCorrections!$B$12+T5*ForcedChoiceCorrections!$B$13+U5*ForcedChoiceCorrections!$B$14+V5*ForcedChoiceCorrections!$B$15) | Y5: =IF(AND(ISNUMBER(SEARCH("pass",L5)),ISNUMBER(X5)),COUNTIFS(L$2:L$90,"*pass*",X$2:X$90,">"&X5)+1,"") | Z5: ABS 2021: 18.5% overseas-born, 14.0% non-Eng HH. Hurstbridge line; verify ED & GW drive times. | SCORES 27 Oct 2026: M (near family) and T (price) are formulas from J and G; O from K. N, P, Q, R, S, U, V are ESTIMATES (Claude, general knowledge, not site-checked); S also rests on train Yes/No marked 'verify'. | AA5: 4. Eltham | North-East Melbourne | Active Shortlist | P: High (Bushland/trees) | Y: Low (Inland) | Lens: Green/scenic lifestyle hypothesis | Price: 1273000 | Basis: Sale median, rolling 12m (195 sales); unit $805k | Note: ABS 2021: 18.5% overseas-born, 14.0% non-Eng HH. Hurstbridge line; verify ED & GW drive times. | AB5: Yes | AC5: Eltham station, Hurstbridge line (recall; verify) | AD5: Austin Hospital ED | AE5: 1500000 | AF5: Maximum purchase price, excluding transaction and moving costs | AG5: Suburb median | AH5: 26 Oct 2026 | AI5: Pass | AJ5: House median $1.273M (195 sales) is under $1.5M cap. Passes GW drive (26m) and ED drive (16m).
A6: Upper Ferntree Gully | B6: East / Foothills | C6: Active Shortlist | D6: High (Foothills/forest) | E6: Low (Inland) | F6: Forest/foothills lifestyle with hospital & rail access | G6: 872133 | H6: AVM estimate (30 Sep 2026), NOT a verified sale median | I6: 924460.98 | J6: 16 | K6: 2 | L6: Active — provisional pass | M6: =IF(J6="","",ROUND(MAX(0,10*(1-J6/Filters!$B$4)),1)) | N6: 8 | O6: =IF(K6="","",ROUND(MAX(0,10*(1-K6/Filters!$B$5)),1)) | P6: 5 | Q6: 6 | R6: 5 | S6: 7 | T6: =IF(G6="","",ROUND(MAX(0,MIN(10,10*(Filters!$B$2-G6)/(Filters!$B$2-500000))),1)) | U6: 0 | V6: 6 | W6: =IF(M6="",0,COUNT(M6:V6)) | X6: =IF(W6<10,"",M6*ForcedChoiceCorrections!$B$6+N6*ForcedChoiceCorrections!$B$7+O6*ForcedChoiceCorrections!$B$8+P6*ForcedChoiceCorrections!$B$9+Q6*ForcedChoiceCorrections!$B$10+R6*ForcedChoiceCorrections!$B$11+S6*ForcedChoiceCorrections!$B$12+T6*ForcedChoiceCorrections!$B$13+U6*ForcedChoiceCorrections!$B$14+V6*ForcedChoiceCorrections!$B$15) | Y6: =IF(AND(ISNUMBER(SEARCH("pass",L6)),ISNUMBER(X6)),COUNTIFS(L$2:L$90,"*pass*",X$2:X$90,">"&X6)+1,"") | Z6: ABS 2021: 19.2% overseas-born, 12.2% non-Eng HH. Belgrave line; 10-min walk/bus 732 to Angliss Hospital (verify 24-hr ED status & drive). 27 Oct 2026: OnTheHouse gives the same house AVM ($872,133) for Upper Ferntree Gully and Ferntree Gully — likely postcode-level, weak. | SCORES 27 Oct 2026: M (near family) and T (price) are formulas from J and G; O from K. N, P, Q, R, S, U, V are ESTIMATES (Claude, general knowledge, not site-checked); S also rests on train Yes/No marked 'verify'. Price = postcode-level AVM shared with FTG. | AA6: 5. Upper Ferntree Gully | East / Foothills | Active Shortlist | P: High (Foothills/forest) | Y: Low (Inland) | Lens: Forest/foothills lifestyle with hospital & rail access | Price: 872133 | Basis: AVM estimate (30 Sep 2026), NOT a verified sale median | Note: ABS 2021: 19.2% overseas-born, 12.2% non-Eng HH. Belgrave line; 10-min walk/bus 732 to Angliss Hospital (verify 24-hr ED status & drive). | AB6: Yes | AC6: Upper Ferntree Gully station, Belgrave line (per sheet note) | AD6: Angliss Hospital ED (24-hr status still to verify) | AE6: 1500000 | AF6: Maximum purchase price, excluding transaction and moving costs | AG6: Suburb median | AH6: 26 Oct 2026 | AI6: Pass | AJ6: Published house price ($872,133) is under $1.5M cap.
A7: Glen Waverley | B7: East Melbourne | C7: Active Shortlist | D7: Low-Medium (Suburban) | E7: Low (Inland) | F7: Current stay baseline — multicultural convenience | G7: 1763500 | H7: Sale median, rolling 12m (454 sales); unit $930k | I7: 1869310 | J7: 0 | K7: 13 | L7: Active — needs data | O7: =IF(K7="","",ROUND(MAX(0,10*(1-K7/Filters!$B$5)),1)) | W7: =IF(M7="",0,COUNT(M7:V7)) | X7: =IF(W7<10,"",M7*ForcedChoiceCorrections!$B$6+N7*ForcedChoiceCorrections!$B$7+O7*ForcedChoiceCorrections!$B$8+P7*ForcedChoiceCorrections!$B$9+Q7*ForcedChoiceCorrections!$B$10+R7*ForcedChoiceCorrections!$B$11+S7*ForcedChoiceCorrections!$B$12+T7*ForcedChoiceCorrections!$B$13+U7*ForcedChoiceCorrections!$B$14+V7*ForcedChoiceCorrections!$B$15) | Y7: =IF(AND(ISNUMBER(SEARCH("pass",L7)),ISNUMBER(X7)),COUNTIFS(L$2:L$90,"*pass*",X$2:X$90,">"&X7)+1,"") | Z7: ABS 2021: 58.7% overseas-born, 63.0% non-Eng HH. Baseline benchmark for family proximity. | AA7: 6. Glen Waverley | East Melbourne | Active Shortlist | P: Low-Medium (Suburban) | Y: Low (Inland) | Lens: Current stay baseline — multicultural convenience | Price: 1763500 | Basis: Sale median, rolling 12m (454 sales); unit $930k | Note: ABS 2021: 58.7% overseas-born, 63.0% non-Eng HH. Baseline benchmark for family proximity. | AB7: Yes | AC7: Glen Waverley station, Glen Waverley line (recall; verify) | AD7: Monash Medical Centre Clayton ED | AE7: 1500000 | AF7: Maximum purchase price, excluding transaction and moving costs | AG7: Suburb median | AH7: 26 Oct 2026 | AI7: Needs data | AJ7: House median $1.76M (454 sales) exceeds $1.5M cap; unit median $930k. Awaiting documented search for suitable single-level homes/units under $1.5M.
A8: Warrandyte | B8: North-East / Yarra | C8: Active Shortlist | D8: High (River & state park) | E8: Low (River, non-coastal) | F8: River-and-bush living within metro boundary | G8: 1348901 | H8: AVM estimate (30 Sep 2026), NOT a verified sale median; unit $824,796; 84 sales in last 12m (OnTheHouse/Cotality, read 27 Oct 2026) | I8: =G8*(1+Settings!$B$6) | J8: 20 | K8: 14 | L8: Active — provisional pass | M8: =IF(J8="","",ROUND(MAX(0,10*(1-J8/Filters!$B$4)),1)) | N8: 9 | O8: =IF(K8="","",ROUND(MAX(0,10*(1-K8/Filters!$B$5)),1)) | P8: 3 | Q8: 6 | R8: 8 | S8: 3 | T8: =IF(G8="","",ROUND(MAX(0,MIN(10,10*(Filters!$B$2-G8)/(Filters!$B$2-500000))),1)) | U8: 0 | V8: 4 | W8: =IF(M8="",0,COUNT(M8:V8)) | X8: =IF(W8<10,"",M8*ForcedChoiceCorrections!$B$6+N8*ForcedChoiceCorrections!$B$7+O8*ForcedChoiceCorrections!$B$8+P8*ForcedChoiceCorrections!$B$9+Q8*ForcedChoiceCorrections!$B$10+R8*ForcedChoiceCorrections!$B$11+S8*ForcedChoiceCorrections!$B$12+T8*ForcedChoiceCorrections!$B$13+U8*ForcedChoiceCorrections!$B$14+V8*ForcedChoiceCorrections!$B$15) | Y8: =IF(AND(ISNUMBER(SEARCH("pass",L8)),ISNUMBER(X8)),COUNTIFS(L$2:L$90,"*pass*",X$2:X$90,">"&X8)+1,"") | Z8: ABS 2021: 17.7% aged 65+, 17.0% non-Eng HH. Direct city bus 906; no local rail; check fire overlay & ED drive. 27 Oct 2026 research pass: drive times/ED and/or AVM price added; L re-evaluated. | SCORES 27 Oct 2026: M (near family) and T (price) are formulas from J and G; O from K. N, P, Q, R, S, U, V are ESTIMATES (Claude, general knowledge, not site-checked); S also rests on train Yes/No marked 'verify'. | AA8: 7. Warrandyte | North-East / Yarra | Active Shortlist | P: High (River & state park) | Y: Low (River, non-coastal) | Lens: River-and-bush living within metro boundary | Price: [Blank] | Basis: Not verified in report | Note: ABS 2021: 17.7% aged 65+, 17.0% non-Eng HH. Direct city bus 906; no local rail; check fire overlay & ED drive. | AB8: No | AC8: No rail; bus 906 (per sheet note) | AD8: Maroondah Hospital ED | AE8: 1500000 | AF8: Maximum purchase price, excluding transaction and moving costs | AG8: AVM estimate | AH8: 27 Oct 2026 | AI8: Pass | AJ8: AVM house value ($1,348,901) is under $1.5M cap. Not a sale median.
A9: Diamond Creek | B9: North-East Fringe | C9: Active Shortlist | D9: High (Green wedge & trail) | E9: Low (Inland) | F9: Practical metro nature compromise with rail | G9: 885000 | H9: 3-bed house median $885k; 4-bed $1,240k (Domain) | I9: 938100 | J9: 33 | K9: 19 | L9: Active — provisional pass | M9: =IF(J9="","",ROUND(MAX(0,10*(1-J9/Filters!$B$4)),1)) | N9: 7 | O9: =IF(K9="","",ROUND(MAX(0,10*(1-K9/Filters!$B$5)),1)) | P9: 2 | Q9: 7 | R9: 6 | S9: 7 | T9: =IF(G9="","",ROUND(MAX(0,MIN(10,10*(Filters!$B$2-G9)/(Filters!$B$2-500000))),1)) | U9: 0 | V9: 6 | W9: =IF(M9="",0,COUNT(M9:V9)) | X9: =IF(W9<10,"",M9*ForcedChoiceCorrections!$B$6+N9*ForcedChoiceCorrections!$B$7+O9*ForcedChoiceCorrections!$B$8+P9*ForcedChoiceCorrections!$B$9+Q9*ForcedChoiceCorrections!$B$10+R9*ForcedChoiceCorrections!$B$11+S9*ForcedChoiceCorrections!$B$12+T9*ForcedChoiceCorrections!$B$13+U9*ForcedChoiceCorrections!$B$14+V9*ForcedChoiceCorrections!$B$15) | Y9: =IF(AND(ISNUMBER(SEARCH("pass",L9)),ISNUMBER(X9)),COUNTIFS(L$2:L$90,"*pass*",X$2:X$90,">"&X9)+1,"") | Z9: ABS 2021: 13.1% aged 65+, 12.2% non-Eng HH. Hurstbridge line station & trail; verify ED & GW drive. | SCORES 27 Oct 2026: M (near family) and T (price) are formulas from J and G; O from K. N, P, Q, R, S, U, V are ESTIMATES (Claude, general knowledge, not site-checked); S also rests on train Yes/No marked 'verify'. | AA9: 8. Diamond Creek | North-East Fringe | Active Shortlist | P: High (Green wedge & trail) | Y: Low (Inland) | Lens: Practical metro nature compromise with rail | Price: 885000 | Basis: 3-bed house median $885k; 4-bed $1,240k (Domain) | Note: ABS 2021: 13.1% aged 65+, 12.2% non-Eng HH. Hurstbridge line station & trail; verify ED & GW drive. | AB9: Yes | AC9: Diamond Creek station, Hurstbridge line (per sheet note) | AD9: Austin Hospital ED | AE9: 1500000 | AF9: Maximum purchase price, excluding transaction and moving costs | AG9: Suburb median | AH9: 26 Oct 2026 | AI9: Pass | AJ9: Published house price ($885,000) is under $1.5M cap.
A10: Mentone | B10: Bayside Melbourne | C10: Active Shortlist | D10: Low-Medium (Suburban gardens) | E10: High (Bay beach) | F10: Coastal daily living on metro rail line | G10: 1497099 | H10: Sale median (Aussie/CoreLogic); Woodards shows $1.30m | I10: 1586924.9 | J10: 25 | K10: 16 | L10: Active — provisional pass | M10: =IF(J10="","",ROUND(MAX(0,10*(1-J10/Filters!$B$4)),1)) | N10: 4 | O10: =IF(K10="","",ROUND(MAX(0,10*(1-K10/Filters!$B$5)),1)) | P10: 5 | Q10: 8 | R10: 6 | S10: 8 | T10: =IF(G10="","",ROUND(MAX(0,MIN(10,10*(Filters!$B$2-G10)/(Filters!$B$2-500000))),1)) | U10: 9 | V10: 8 | W10: =IF(M10="",0,COUNT(M10:V10)) | X10: =IF(W10<10,"",M10*ForcedChoiceCorrections!$B$6+N10*ForcedChoiceCorrections!$B$7+O10*ForcedChoiceCorrections!$B$8+P10*ForcedChoiceCorrections!$B$9+Q10*ForcedChoiceCorrections!$B$10+R10*ForcedChoiceCorrections!$B$11+S10*ForcedChoiceCorrections!$B$12+T10*ForcedChoiceCorrections!$B$13+U10*ForcedChoiceCorrections!$B$14+V10*ForcedChoiceCorrections!$B$15) | Y10: =IF(AND(ISNUMBER(SEARCH("pass",L10)),ISNUMBER(X10)),COUNTIFS(L$2:L$90,"*pass*",X$2:X$90,">"&X10)+1,"") | Z10: ABS 2021: 28.8% overseas-born, 22.4% non-Eng HH. Reconcile price sources & verify ED drive. | SCORES 27 Oct 2026: M (near family) and T (price) are formulas from J and G; O from K. N, P, Q, R, S, U, V are ESTIMATES (Claude, general knowledge, not site-checked); S also rests on train Yes/No marked 'verify'. | AA10: 9. Mentone | Bayside Melbourne | Active Shortlist | P: Low-Medium (Suburban gardens) | Y: High (Bay beach) | Lens: Coastal daily living on metro rail line | Price: 1497099 | Basis: Sale median (Aussie/CoreLogic); Woodards shows $1.30m | Note: ABS 2021: 28.8% overseas-born, 22.4% non-Eng HH. Reconcile price sources & verify ED drive. | AB10: Yes | AC10: Mentone station, Frankston line (recall; verify) | AD10: Monash Medical Centre Clayton ED | AE10: 1500000 | AF10: Maximum purchase price, excluding transaction and moving costs | AG10: Suburb median | AH10: 26 Oct 2026 | AI10: Pass | AJ10: House median $1.497M (CoreLogic) / $1.30M (Woodards) is under $1.5M cap. Passes GW drive (25m) and ED drive (16m).
A11: Frankston | B11: South / Coastal | C11: Active Shortlist | D11: Medium (Sweetwater/gullies) | E11: High (Bay beach) | F11: Coastal practicality & accessible property price | G11: 834296 | H11: Sale median, rolling 12m (Aussie/Cotality); unit $573k | I11: 884353.76 | J11: 25 | K11: 4 | L11: Active — provisional pass | M11: =IF(J11="","",ROUND(MAX(0,10*(1-J11/Filters!$B$4)),1)) | N11: 5 | O11: =IF(K11="","",ROUND(MAX(0,10*(1-K11/Filters!$B$5)),1)) | P11: 4 | Q11: 9 | R11: 3 | S11: 8 | T11: =IF(G11="","",ROUND(MAX(0,MIN(10,10*(Filters!$B$2-G11)/(Filters!$B$2-500000))),1)) | U11: 8 | V11: 6 | W11: =IF(M11="",0,COUNT(M11:V11)) | X11: =IF(W11<10,"",M11*ForcedChoiceCorrections!$B$6+N11*ForcedChoiceCorrections!$B$7+O11*ForcedChoiceCorrections!$B$8+P11*ForcedChoiceCorrections!$B$9+Q11*ForcedChoiceCorrections!$B$10+R11*ForcedChoiceCorrections!$B$11+S11*ForcedChoiceCorrections!$B$12+T11*ForcedChoiceCorrections!$B$13+U11*ForcedChoiceCorrections!$B$14+V11*ForcedChoiceCorrections!$B$15) | Y11: =IF(AND(ISNUMBER(SEARCH("pass",L11)),ISNUMBER(X11)),COUNTIFS(L$2:L$90,"*pass*",X$2:X$90,">"&X11)+1,"") | Z11: ABS 2021: 22.5% overseas-born, 15.2% non-Eng HH. Peninsula Univ Hospital ED; ~66m train to CBD. | SCORES 27 Oct 2026: M (near family) and T (price) are formulas from J and G; O from K. N, P, Q, R, S, U, V are ESTIMATES (Claude, general knowledge, not site-checked); S also rests on train Yes/No marked 'verify'. | AA11: 10. Frankston | South / Coastal | Active Shortlist | P: Medium (Sweetwater/gullies) | Y: High (Bay beach) | Lens: Coastal practicality & accessible property price | Price: 834296 | Basis: Sale median, rolling 12m (Aussie/Cotality); unit $573k | Note: ABS 2021: 22.5% overseas-born, 15.2% non-Eng HH. Peninsula Univ Hospital ED; ~66m train to CBD. | AB11: Yes | AC11: Frankston station, Frankston line (recall; verify) | AD11: Peninsula University Hospital ED | AE11: 1500000 | AF11: Maximum purchase price, excluding transaction and moving costs | AG11: Suburb median | AH11: 26 Oct 2026 | AI11: Pass | AJ11: Published house price ($834,296) is under $1.5M cap.
A12: Altona | B12: West Coastal | C12: Active Shortlist | D12: Low-Medium (Flat coastal) | E12: High (Bay beach/wetlands) | F12: Coastal village alternative at lower price point | G12: 1155073 | H12: AVM estimate (31 Aug 2026), NOT a verified sale median | I12: 1224377.4 | J12: 35 | K12: 15 | L12: Active — provisional pass | M12: =IF(J12="","",ROUND(MAX(0,10*(1-J12/Filters!$B$4)),1)) | N12: 4 | O12: =IF(K12="","",ROUND(MAX(0,10*(1-K12/Filters!$B$5)),1)) | P12: 6 | Q12: 8 | R12: 6 | S12: 7 | T12: =IF(G12="","",ROUND(MAX(0,MIN(10,10*(Filters!$B$2-G12)/(Filters!$B$2-500000))),1)) | U12: 8 | V12: 8 | W12: =IF(M12="",0,COUNT(M12:V12)) | X12: =IF(W12<10,"",M12*ForcedChoiceCorrections!$B$6+N12*ForcedChoiceCorrections!$B$7+O12*ForcedChoiceCorrections!$B$8+P12*ForcedChoiceCorrections!$B$9+Q12*ForcedChoiceCorrections!$B$10+R12*ForcedChoiceCorrections!$B$11+S12*ForcedChoiceCorrections!$B$12+T12*ForcedChoiceCorrections!$B$13+U12*ForcedChoiceCorrections!$B$14+V12*ForcedChoiceCorrections!$B$15) | Y12: =IF(AND(ISNUMBER(SEARCH("pass",L12)),ISNUMBER(X12)),COUNTIFS(L$2:L$90,"*pass*",X$2:X$90,">"&X12)+1,"") | Z12: ABS 2021: 28.3% overseas-born, 23.8% non-Eng HH. Cross-city drive to Glen Waverley needs testing. | SCORES 27 Oct 2026: M (near family) and T (price) are formulas from J and G; O from K. N, P, Q, R, S, U, V are ESTIMATES (Claude, general knowledge, not site-checked); S also rests on train Yes/No marked 'verify'. | AA12: 11. Altona | West Coastal | Active Shortlist | P: Low-Medium (Flat coastal) | Y: High (Bay beach/wetlands) | Lens: Coastal village alternative at lower price point | Price: 1155073 | Basis: AVM estimate (31 Aug 2026), NOT a verified sale median | Note: ABS 2021: 28.3% overseas-born, 23.8% non-Eng HH. Cross-city drive to Glen Waverley needs testing. | AB12: Yes | AC12: Altona station, Werribee line (recall; verify) | AD12: Footscray Hospital ED | AE12: 1500000 | AF12: Maximum purchase price, excluding transaction and moving costs | AG12: Suburb median | AH12: 26 Oct 2026 | AI12: Pass | AJ12: Published house price ($1,155,073) is under $1.5M cap.
A13: Williamstown | B13: West Coastal | C13: Active Shortlist | D13: Medium (Botanic gardens) | E13: High (Historic harbor/beach) | F13: Picturesque coastal character vs cost | G13: 1642163 | H13: AVM estimate (30 Sep 2026), NOT a verified sale median | I13: 1740692.8 | J13: 31 | K13: 13 | L13: Active — needs data | O13: =IF(K13="","",ROUND(MAX(0,10*(1-K13/Filters!$B$5)),1)) | W13: =IF(M13="",0,COUNT(M13:V13)) | X13: =IF(W13<10,"",M13*ForcedChoiceCorrections!$B$6+N13*ForcedChoiceCorrections!$B$7+O13*ForcedChoiceCorrections!$B$8+P13*ForcedChoiceCorrections!$B$9+Q13*ForcedChoiceCorrections!$B$10+R13*ForcedChoiceCorrections!$B$11+S13*ForcedChoiceCorrections!$B$12+T13*ForcedChoiceCorrections!$B$13+U13*ForcedChoiceCorrections!$B$14+V13*ForcedChoiceCorrections!$B$15) | Y13: =IF(AND(ISNUMBER(SEARCH("pass",L13)),ISNUMBER(X13)),COUNTIFS(L$2:L$90,"*pass*",X$2:X$90,">"&X13)+1,"") | Z13: ABS 2021: 22.6% overseas-born, 20.0% non-Eng HH. Cross-city travel to Glen Waverley & ED capacity need checking. | AA13: 12. Williamstown | West Coastal | Active Shortlist | P: Medium (Botanic gardens) | Y: High (Historic harbor/beach) | Lens: Picturesque coastal character vs cost | Price: 1642163 | Basis: AVM estimate (30 Sep 2026), NOT a verified sale median | Note: ABS 2021: 22.6% overseas-born, 20.0% non-Eng HH. Cross-city travel to Glen Waverley & ED capacity need checking. | AB13: Yes | AC13: Williamstown station, Williamstown line (recall; verify) | AD13: Footscray Hospital ED | AE13: 1500000 | AF13: Maximum purchase price, excluding transaction and moving costs | AG13: AVM estimate | AH13: 26 Oct 2026 | AI13: Needs data | AJ13: Figure is an automated valuation model ($1.64M), not a verified sale median or specific property. Awaiting documented listing search under $1.5M.
A14: Healesville | B14: Yarra Valley | C14: Active Shortlist | D14: High (Valley & mountains) | E14: Low (Inland) | F14: Larger Yarra Valley town comparator | G14: 837893 | H14: AVM estimate (30 Sep 2026), NOT a verified sale median; unit $618,926; 160 sales in last 12m (OnTheHouse/Cotality, read 27 Oct 2026) | I14: =G14*(1+Settings!$B$6) | J14: 43 | K14: 33 | L14: Active — provisional pass | M14: =IF(J14="","",ROUND(MAX(0,10*(1-J14/Filters!$B$4)),1)) | N14: 9 | O14: =IF(K14="","",ROUND(MAX(0,10*(1-K14/Filters!$B$5)),1)) | P14: 1 | Q14: 6 | R14: 8 | S14: 2 | T14: =IF(G14="","",ROUND(MAX(0,MIN(10,10*(Filters!$B$2-G14)/(Filters!$B$2-500000))),1)) | U14: 0 | V14: 2 | W14: =IF(M14="",0,COUNT(M14:V14)) | X14: =IF(W14<10,"",M14*ForcedChoiceCorrections!$B$6+N14*ForcedChoiceCorrections!$B$7+O14*ForcedChoiceCorrections!$B$8+P14*ForcedChoiceCorrections!$B$9+Q14*ForcedChoiceCorrections!$B$10+R14*ForcedChoiceCorrections!$B$11+S14*ForcedChoiceCorrections!$B$12+T14*ForcedChoiceCorrections!$B$13+U14*ForcedChoiceCorrections!$B$14+V14*ForcedChoiceCorrections!$B$15) | Y14: =IF(AND(ISNUMBER(SEARCH("pass",L14)),ISNUMBER(X14)),COUNTIFS(L$2:L$90,"*pass*",X$2:X$90,">"&X14)+1,"") | Z14: 2021 pop 7,589. CAUTION: Eastern Health directs urgent ED patients to Maroondah Hospital ED (not local). 27 Oct 2026 research pass: drive times/ED and/or AVM price added; L re-evaluated. | SCORES 27 Oct 2026: M (near family) and T (price) are formulas from J and G; O from K. N, P, Q, R, S, U, V are ESTIMATES (Claude, general knowledge, not site-checked); S also rests on train Yes/No marked 'verify'. | AA14: 13. Healesville | Yarra Valley | Active Shortlist | P: High (Valley & mountains) | Y: Low (Inland) | Lens: Larger Yarra Valley town comparator | Price: [Blank] | Basis: Not verified in report | Note: 2021 pop 7,589. CAUTION: Eastern Health directs urgent ED patients to Maroondah Hospital ED (not local). | AB14: No | AC14: No rail (recall; verify) | AD14: Maroondah Hospital ED (sheet note: urgent ED cases go here) | AE14: 1500000 | AF14: Maximum purchase price, excluding transaction and moving costs | AG14: AVM estimate | AH14: 27 Oct 2026 | AI14: Pass | AJ14: AVM house value ($837,893) is under $1.5M cap. Not a sale median.
A15: Kyneton | B15: Macedon Ranges | C15: Active Shortlist | D15: High (Country town & gardens) | E15: Low (Inland river) | F15: Country-town practicality with V/Line rail | G15: 810000 | H15: 3-bed house median $810k; 4-bed $980k (Domain) | I15: 858600 | J15: 77 | K15: 47 | L15: Active — provisional pass | M15: =IF(J15="","",ROUND(MAX(0,10*(1-J15/Filters!$B$4)),1)) | N15: 7 | O15: =IF(K15="","",ROUND(MAX(0,10*(1-K15/Filters!$B$5)),1)) | P15: 1 | Q15: 7 | R15: 9 | S15: 5 | T15: =IF(G15="","",ROUND(MAX(0,MIN(10,10*(Filters!$B$2-G15)/(Filters!$B$2-500000))),1)) | U15: 0 | V15: 5 | W15: =IF(M15="",0,COUNT(M15:V15)) | X15: =IF(W15<10,"",M15*ForcedChoiceCorrections!$B$6+N15*ForcedChoiceCorrections!$B$7+O15*ForcedChoiceCorrections!$B$8+P15*ForcedChoiceCorrections!$B$9+Q15*ForcedChoiceCorrections!$B$10+R15*ForcedChoiceCorrections!$B$11+S15*ForcedChoiceCorrections!$B$12+T15*ForcedChoiceCorrections!$B$13+U15*ForcedChoiceCorrections!$B$14+V15*ForcedChoiceCorrections!$B$15) | Y15: =IF(AND(ISNUMBER(SEARCH("pass",L15)),ISNUMBER(X15)),COUNTIFS(L$2:L$90,"*pass*",X$2:X$90,">"&X15)+1,"") | Z15: ABS 2021: 25.0% aged 65+, 6.9% non-Eng HH. CAUTION: Local facility is 24-hr Urgent Care Centre, NOT a major public ED. | SCORES 27 Oct 2026: M (near family) and T (price) are formulas from J and G; O from K. N, P, Q, R, S, U, V are ESTIMATES (Claude, general knowledge, not site-checked); S also rests on train Yes/No marked 'verify'. | AA15: 14. Kyneton | Macedon Ranges | Active Shortlist | P: High (Country town & gardens) | Y: Low (Inland river) | Lens: Country-town practicality with V/Line rail | Price: 810000 | Basis: 3-bed house median $810k; 4-bed $980k (Domain) | Note: ABS 2021: 25.0% aged 65+, 6.9% non-Eng HH. CAUTION: Local facility is 24-hr Urgent Care Centre, NOT a major public ED. | AB15: Yes | AC15: Kyneton station, V/Line Bendigo (per sheet note) | AD15: Bendigo Hospital ED (local 24-hr urgent care is not an ED) | AE15: 1500000 | AF15: Maximum purchase price, excluding transaction and moving costs | AG15: Suburb median | AH15: 26 Oct 2026 | AI15: Pass | AJ15: Published house price ($810,000) is under $1.5M cap.
A16: Woodend | B16: Macedon Ranges | C16: Active Shortlist | D16: High (Macedon Ranges forest) | E16: Low (Inland) | F16: Walkable station country town in Macedon Ranges | G16: 890000 | H16: 3-bed house median $890k; 4-bed $1,150k (Domain) | I16: 943400 | J16: 68 | K16: 55 | L16: Active — provisional pass | M16: =IF(J16="","",ROUND(MAX(0,10*(1-J16/Filters!$B$4)),1)) | N16: 8 | O16: =IF(K16="","",ROUND(MAX(0,10*(1-K16/Filters!$B$5)),1)) | P16: 1 | Q16: 6 | R16: 9 | S16: 5 | T16: =IF(G16="","",ROUND(MAX(0,MIN(10,10*(Filters!$B$2-G16)/(Filters!$B$2-500000))),1)) | U16: 0 | V16: 5 | W16: =IF(M16="",0,COUNT(M16:V16)) | X16: =IF(W16<10,"",M16*ForcedChoiceCorrections!$B$6+N16*ForcedChoiceCorrections!$B$7+O16*ForcedChoiceCorrections!$B$8+P16*ForcedChoiceCorrections!$B$9+Q16*ForcedChoiceCorrections!$B$10+R16*ForcedChoiceCorrections!$B$11+S16*ForcedChoiceCorrections!$B$12+T16*ForcedChoiceCorrections!$B$13+U16*ForcedChoiceCorrections!$B$14+V16*ForcedChoiceCorrections!$B$15) | Y16: =IF(AND(ISNUMBER(SEARCH("pass",L16)),ISNUMBER(X16)),COUNTIFS(L$2:L$90,"*pass*",X$2:X$90,">"&X16)+1,"") | Z16: V/Line Bendigo line. Check winter comfort, major public ED drive time & family trip frequency. | SCORES 27 Oct 2026: M (near family) and T (price) are formulas from J and G; O from K. N, P, Q, R, S, U, V are ESTIMATES (Claude, general knowledge, not site-checked); S also rests on train Yes/No marked 'verify'. | AA16: 15. Woodend | Macedon Ranges | Active Shortlist | P: High (Macedon Ranges forest) | Y: Low (Inland) | Lens: Walkable station country town in Macedon Ranges | Price: 890000 | Basis: 3-bed house median $890k; 4-bed $1,150k (Domain) | Note: V/Line Bendigo line. Check winter comfort, major public ED drive time & family trip frequency. | AB16: Yes | AC16: Woodend station, V/Line Bendigo (per sheet note) | AD16: Bendigo Hospital ED (nearest ED not confirmed; Northern Hospital Epping not tested) | AE16: 1500000 | AF16: Maximum purchase price, excluding transaction and moving costs | AG16: Suburb median | AH16: 26 Oct 2026 | AI16: Pass | AJ16: Published house price ($890,000) is under $1.5M cap.
A17: Macedon | B17: Macedon Ranges | C17: Active Shortlist | D17: High (Forest & Honour Ave) | E17: Low (Inland) | F17: Landscape-led Macedon Ranges option | G17: 1147643 | H17: AVM estimate (30 Sep 2026), NOT a verified sale median; unit $836,750; 31 sales in last 12m (OnTheHouse/Cotality, read 27 Oct 2026) — few sales, weak | I17: =G17*(1+Settings!$B$6) | J17: 62 | K17: 60 | L17: Active — provisional pass | M17: =IF(J17="","",ROUND(MAX(0,10*(1-J17/Filters!$B$4)),1)) | N17: 10 | O17: =IF(K17="","",ROUND(MAX(0,10*(1-K17/Filters!$B$5)),1)) | P17: 1 | Q17: 3 | R17: 8 | S17: 5 | T17: =IF(G17="","",ROUND(MAX(0,MIN(10,10*(Filters!$B$2-G17)/(Filters!$B$2-500000))),1)) | U17: 0 | V17: 5 | W17: =IF(M17="",0,COUNT(M17:V17)) | X17: =IF(W17<10,"",M17*ForcedChoiceCorrections!$B$6+N17*ForcedChoiceCorrections!$B$7+O17*ForcedChoiceCorrections!$B$8+P17*ForcedChoiceCorrections!$B$9+Q17*ForcedChoiceCorrections!$B$10+R17*ForcedChoiceCorrections!$B$11+S17*ForcedChoiceCorrections!$B$12+T17*ForcedChoiceCorrections!$B$13+U17*ForcedChoiceCorrections!$B$14+V17*ForcedChoiceCorrections!$B$15) | Y17: =IF(AND(ISNUMBER(SEARCH("pass",L17)),ISNUMBER(X17)),COUNTIFS(L$2:L$90,"*pass*",X$2:X$90,">"&X17)+1,"") | Z17: Distinguish Macedon from Mount Macedon; check bushfire overlay, gradients & major ED journey. 27 Oct 2026 research pass: drive times/ED and/or AVM price added; L re-evaluated. | SCORES 27 Oct 2026: M (near family) and T (price) are formulas from J and G; O from K. N, P, Q, R, S, U, V are ESTIMATES (Claude, general knowledge, not site-checked); S also rests on train Yes/No marked 'verify'. Low sales count. | AA17: 16. Macedon | Macedon Ranges | Active Shortlist | P: High (Forest & Honour Ave) | Y: Low (Inland) | Lens: Landscape-led Macedon Ranges option | Price: [Blank] | Basis: Not verified in report | Note: Distinguish Macedon from Mount Macedon; check bushfire overlay, gradients & major ED journey. | AB17: Yes | AC17: Macedon station, V/Line Bendigo (recall; verify) | AD17: Bendigo Hospital ED (nearest ED not confirmed; Northern Hospital Epping not tested) | AE17: 1500000 | AF17: Maximum purchase price, excluding transaction and moving costs | AG17: AVM estimate | AH17: 27 Oct 2026 | AI17: Pass | AJ17: AVM house value ($1,147,643) is under $1.5M cap. Not a sale median.
A18: Torquay | B18: Surf Coast | C18: Active Shortlist | D18: Medium (Coastal heath) | E18: High (Surf Coast walk/beach) | F18: Everyday surf-coast walking lifestyle | G18: 1180000 | H18: House sale median $1,180,000; unit $891,250 (REA) | I18: 1250800 | J18: 88 | K18: 23 | L18: Active — provisional pass | M18: =IF(J18="","",ROUND(MAX(0,10*(1-J18/Filters!$B$4)),1)) | N18: 8 | O18: =IF(K18="","",ROUND(MAX(0,10*(1-K18/Filters!$B$5)),1)) | P18: 2 | Q18: 8 | R18: 6 | S18: 3 | T18: =IF(G18="","",ROUND(MAX(0,MIN(10,10*(Filters!$B$2-G18)/(Filters!$B$2-500000))),1)) | U18: 10 | V18: 3 | W18: =IF(M18="",0,COUNT(M18:V18)) | X18: =IF(W18<10,"",M18*ForcedChoiceCorrections!$B$6+N18*ForcedChoiceCorrections!$B$7+O18*ForcedChoiceCorrections!$B$8+P18*ForcedChoiceCorrections!$B$9+Q18*ForcedChoiceCorrections!$B$10+R18*ForcedChoiceCorrections!$B$11+S18*ForcedChoiceCorrections!$B$12+T18*ForcedChoiceCorrections!$B$13+U18*ForcedChoiceCorrections!$B$14+V18*ForcedChoiceCorrections!$B$15) | Y18: =IF(AND(ISNUMBER(SEARCH("pass",L18)),ISNUMBER(X18)),COUNTIFS(L$2:L$90,"*pass*",X$2:X$90,">"&X18)+1,"") | Z18: ABS 2021: 16.4% aged 65+, 7.4% non-Eng HH. Bus 54 to Marshall Station; relies on Univ Hospital Geelong for major public ED. | SCORES 27 Oct 2026: M (near family) and T (price) are formulas from J and G; O from K. N, P, Q, R, S, U, V are ESTIMATES (Claude, general knowledge, not site-checked); S also rests on train Yes/No marked 'verify'. GW drive 88 min, 2 min under cap. | AA18: 17. Torquay | Surf Coast | Active Shortlist | P: Medium (Coastal heath) | Y: High (Surf Coast walk/beach) | Lens: Everyday surf-coast walking lifestyle | Price: 1180000 | Basis: House sale median $1,180,000; unit $891,250 (REA) | Note: ABS 2021: 16.4% aged 65+, 7.4% non-Eng HH. Bus 54 to Marshall Station; relies on Univ Hospital Geelong for major public ED. | AB18: No | AC18: No rail; bus 54 to Marshall Station (per sheet note) | AD18: University Hospital Geelong ED | AE18: 1500000 | AF18: Maximum purchase price, excluding transaction and moving costs | AG18: Suburb median | AH18: 26 Oct 2026 | AI18: Pass | AJ18: House median $1.180M is under $1.5M cap. Passes GW drive (88m <= 90m cap) and ED drive (23m).
A19: Ocean Grove | B19: Bellarine Peninsula | C19: Active Shortlist | D19: Medium-High (Nature reserve) | E19: High (Beach + woodland) | F19: Coast-plus-bushland alternative to Torquay | G19: 980000 | H19: House sale median $980,000 (325 sales); unit $770k | I19: 1038800 | J19: 92 | K19: 21 | L19: Fails: GW drive | O19: =IF(K19="","",ROUND(MAX(0,10*(1-K19/Filters!$B$5)),1)) | W19: =IF(M19="",0,COUNT(M19:V19)) | X19: =IF(W19<10,"",M19*ForcedChoiceCorrections!$B$6+N19*ForcedChoiceCorrections!$B$7+O19*ForcedChoiceCorrections!$B$8+P19*ForcedChoiceCorrections!$B$9+Q19*ForcedChoiceCorrections!$B$10+R19*ForcedChoiceCorrections!$B$11+S19*ForcedChoiceCorrections!$B$12+T19*ForcedChoiceCorrections!$B$13+U19*ForcedChoiceCorrections!$B$14+V19*ForcedChoiceCorrections!$B$15) | Y19: =IF(AND(ISNUMBER(SEARCH("pass",L19)),ISNUMBER(X19)),COUNTIFS(L$2:L$90,"*pass*",X$2:X$90,">"&X19)+1,"") | Z19: ABS 2021: 22.2% aged 65+, 5.1% non-Eng HH. 143-ha Nature Reserve; bus 55/56 to Geelong; relies on Univ Hospital Geelong ED. | AA19: 18. Ocean Grove | Bellarine Peninsula | Active Shortlist | P: Medium-High (Nature reserve) | Y: High (Beach + woodland) | Lens: Coast-plus-bushland alternative to Torquay | Price: 980000 | Basis: House sale median $980,000 (325 sales); unit $770k | Note: ABS 2021: 22.2% aged 65+, 5.1% non-Eng HH. 143-ha Nature Reserve; bus 55/56 to Geelong; relies on Univ Hospital Geelong ED. | AB19: No | AC19: No rail; bus 55/56 to Geelong (per sheet note) | AD19: University Hospital Geelong ED | AE19: 1500000 | AF19: Maximum purchase price, excluding transaction and moving costs | AG19: Suburb median | AH19: 26 Oct 2026 | AI19: Pass | AJ19: Published house price ($980,000) is under $1.5M cap.
A20: Newtown (Geelong) | B20: Geelong | C20: Active Shortlist | D20: Medium-High (Barwon River) | E20: Medium (Near bay/coast) | F20: Regional-city services + river sanctuary | G20: 1182945 | H20: AVM estimate (30 Sep 2026), NOT a verified sale median; unit $615,303; 216 sales in last 12m (OnTheHouse/Cotality, read 27 Oct 2026) | I20: =G20*(1+Settings!$B$6) | J20: 72 | K20: 7 | L20: Active — provisional pass | M20: =IF(J20="","",ROUND(MAX(0,10*(1-J20/Filters!$B$4)),1)) | N20: 5 | O20: =IF(K20="","",ROUND(MAX(0,10*(1-K20/Filters!$B$5)),1)) | P20: 4 | Q20: 8 | R20: 6 | S20: 4 | T20: =IF(G20="","",ROUND(MAX(0,MIN(10,10*(Filters!$B$2-G20)/(Filters!$B$2-500000))),1)) | U20: 3 | V20: 5 | W20: =IF(M20="",0,COUNT(M20:V20)) | X20: =IF(W20<10,"",M20*ForcedChoiceCorrections!$B$6+N20*ForcedChoiceCorrections!$B$7+O20*ForcedChoiceCorrections!$B$8+P20*ForcedChoiceCorrections!$B$9+Q20*ForcedChoiceCorrections!$B$10+R20*ForcedChoiceCorrections!$B$11+S20*ForcedChoiceCorrections!$B$12+T20*ForcedChoiceCorrections!$B$13+U20*ForcedChoiceCorrections!$B$14+V20*ForcedChoiceCorrections!$B$15) | Y20: =IF(AND(ISNUMBER(SEARCH("pass",L20)),ISNUMBER(X20)),COUNTIFS(L$2:L$90,"*pass*",X$2:X$90,">"&X20)+1,"") | Z20: ABS 2021: 17.6% aged 65+, 10.9% non-Eng HH. Balyang Sanctuary on Barwon River; major public ED at Univ Hospital Geelong. 27 Oct 2026 research pass: drive times/ED and/or AVM price added; L re-evaluated. | SCORES 27 Oct 2026: M (near family) and T (price) are formulas from J and G; O from K. N, P, Q, R, S, U, V are ESTIMATES (Claude, general knowledge, not site-checked); S also rests on train Yes/No marked 'verify'. | AA20: 19. Newtown (Geelong) | Geelong | Active Shortlist | P: Medium-High (Barwon River) | Y: Medium (Near bay/coast) | Lens: Regional-city services + river sanctuary | Price: [Blank] | Basis: Not verified in report | Note: ABS 2021: 17.6% aged 65+, 10.9% non-Eng HH. Balyang Sanctuary on Barwon River; major public ED at Univ Hospital Geelong. | AB20: No | AC20: No station in suburb; Geelong stations nearby (recall; verify) | AD20: University Hospital Geelong ED. Origin approximated (Balyang area); GW time from Geelong centre | AE20: 1500000 | AF20: Maximum purchase price, excluding transaction and moving costs | AG20: AVM estimate | AH20: 27 Oct 2026 | AI20: Pass | AJ20: AVM house value ($1,182,945) is under $1.5M cap. Not a sale median.
A21: Highton (Geelong) | B21: Geelong | C21: Active Shortlist | D21: Medium-High (Hills/river) | E21: Medium (Near coast) | F21: Village-centre regional-city comparator | G21: 957797 | H21: AVM estimate (30 Sep 2026), NOT a verified sale median; unit $538,492; 504 sales in last 12m (OnTheHouse/Cotality, read 27 Oct 2026) | I21: =G21*(1+Settings!$B$6) | J21: 74 | K21: 9 | L21: Active — provisional pass | M21: =IF(J21="","",ROUND(MAX(0,10*(1-J21/Filters!$B$4)),1)) | N21: 6 | O21: =IF(K21="","",ROUND(MAX(0,10*(1-K21/Filters!$B$5)),1)) | P21: 4 | Q21: 8 | R21: 5 | S21: 3 | T21: =IF(G21="","",ROUND(MAX(0,MIN(10,10*(Filters!$B$2-G21)/(Filters!$B$2-500000))),1)) | U21: 3 | V21: 4 | W21: =IF(M21="",0,COUNT(M21:V21)) | X21: =IF(W21<10,"",M21*ForcedChoiceCorrections!$B$6+N21*ForcedChoiceCorrections!$B$7+O21*ForcedChoiceCorrections!$B$8+P21*ForcedChoiceCorrections!$B$9+Q21*ForcedChoiceCorrections!$B$10+R21*ForcedChoiceCorrections!$B$11+S21*ForcedChoiceCorrections!$B$12+T21*ForcedChoiceCorrections!$B$13+U21*ForcedChoiceCorrections!$B$14+V21*ForcedChoiceCorrections!$B$15) | Y21: =IF(AND(ISNUMBER(SEARCH("pass",L21)),ISNUMBER(X21)),COUNTIFS(L$2:L$90,"*pass*",X$2:X$90,">"&X21)+1,"") | Z21: Highton Village UDF; compare pocket gradients, station access & Univ Hospital Geelong ED journey. 27 Oct 2026 research pass: drive times/ED and/or AVM price added; L re-evaluated. | SCORES 27 Oct 2026: M (near family) and T (price) are formulas from J and G; O from K. N, P, Q, R, S, U, V are ESTIMATES (Claude, general knowledge, not site-checked); S also rests on train Yes/No marked 'verify'. | AA21: 20. Highton (Geelong) | Geelong | Active Shortlist | P: Medium-High (Hills/river) | Y: Medium (Near coast) | Lens: Village-centre regional-city comparator | Price: [Blank] | Basis: Not verified in report | Note: Highton Village UDF; compare pocket gradients, station access & Univ Hospital Geelong ED journey. | AB21: No | AC21: No station; bus to Geelong (recall; verify) | AD21: University Hospital Geelong ED | AE21: 1500000 | AF21: Maximum purchase price, excluding transaction and moving costs | AG21: AVM estimate | AH21: 27 Oct 2026 | AI21: Pass | AJ21: AVM house value ($957,797) is under $1.5M cap. Not a sale median.
A22: Belgrave | B22: Dandenong Ranges | C22: Active Shortlist | D22: High (Forest & hills) | E22: Low (Inland) | F22: Stronger hills lifestyle on metro rail line | G22: 856437 | H22: AVM estimate (30 Sep 2026), NOT a verified sale median; unit $647,854; 72 sales in last 12m (OnTheHouse/Cotality, read 27 Oct 2026) | I22: =G22*(1+Settings!$B$6) | J22: 21 | K22: 7 | L22: Active — provisional pass | M22: =IF(J22="","",ROUND(MAX(0,10*(1-J22/Filters!$B$4)),1)) | N22: 9 | O22: =IF(K22="","",ROUND(MAX(0,10*(1-K22/Filters!$B$5)),1)) | P22: 3 | Q22: 6 | R22: 8 | S22: 7 | T22: =IF(G22="","",ROUND(MAX(0,MIN(10,10*(Filters!$B$2-G22)/(Filters!$B$2-500000))),1)) | U22: 0 | V22: 5 | W22: =IF(M22="",0,COUNT(M22:V22)) | X22: =IF(W22<10,"",M22*ForcedChoiceCorrections!$B$6+N22*ForcedChoiceCorrections!$B$7+O22*ForcedChoiceCorrections!$B$8+P22*ForcedChoiceCorrections!$B$9+Q22*ForcedChoiceCorrections!$B$10+R22*ForcedChoiceCorrections!$B$11+S22*ForcedChoiceCorrections!$B$12+T22*ForcedChoiceCorrections!$B$13+U22*ForcedChoiceCorrections!$B$14+V22*ForcedChoiceCorrections!$B$15) | Y22: =IF(AND(ISNUMBER(SEARCH("pass",L22)),ISNUMBER(X22)),COUNTIFS(L$2:L$90,"*pass*",X$2:X$90,">"&X22)+1,"") | Z22: Belgrave metro rail terminus; check steep gradients, bushfire/storm closures & Angliss/Maroondah ED drive. 27 Oct 2026 research pass: drive times/ED and/or AVM price added; L re-evaluated. | SCORES 27 Oct 2026: M (near family) and T (price) are formulas from J and G; O from K. N, P, Q, R, S, U, V are ESTIMATES (Claude, general knowledge, not site-checked); S also rests on train Yes/No marked 'verify'. | AA22: 21. Belgrave | Dandenong Ranges | Active Shortlist | P: High (Forest & hills) | Y: Low (Inland) | Lens: Stronger hills lifestyle on metro rail line | Price: [Blank] | Basis: Not verified in report | Note: Belgrave metro rail terminus; check steep gradients, bushfire/storm closures & Angliss/Maroondah ED drive. | AB22: Yes | AC22: Belgrave station, Belgrave line terminus (per sheet note) | AD22: Angliss Hospital ED (24-hr status still to verify) | AE22: 1500000 | AF22: Maximum purchase price, excluding transaction and moving costs | AG22: AVM estimate | AH22: 27 Oct 2026 | AI22: Pass | AJ22: AVM house value ($856,437) is under $1.5M cap. Not a sale median.
A23: Upwey | B23: Dandenong Ranges | C23: Active Shortlist | D23: High (Foothills village) | E23: Low (Inland) | F23: Village character vs healthcare/transport practicality | G23: 929500 | H23: House sale median $929,500 (104 sales, Property.com.au) | I23: 985270 | J23: 17 | K23: 4 | L23: Active — provisional pass | M23: =IF(J23="","",ROUND(MAX(0,10*(1-J23/Filters!$B$4)),1)) | N23: 9 | O23: =IF(K23="","",ROUND(MAX(0,10*(1-K23/Filters!$B$5)),1)) | P23: 3 | Q23: 6 | R23: 7 | S23: 7 | T23: =IF(G23="","",ROUND(MAX(0,MIN(10,10*(Filters!$B$2-G23)/(Filters!$B$2-500000))),1)) | U23: 0 | V23: 5 | W23: =IF(M23="",0,COUNT(M23:V23)) | X23: =IF(W23<10,"",M23*ForcedChoiceCorrections!$B$6+N23*ForcedChoiceCorrections!$B$7+O23*ForcedChoiceCorrections!$B$8+P23*ForcedChoiceCorrections!$B$9+Q23*ForcedChoiceCorrections!$B$10+R23*ForcedChoiceCorrections!$B$11+S23*ForcedChoiceCorrections!$B$12+T23*ForcedChoiceCorrections!$B$13+U23*ForcedChoiceCorrections!$B$14+V23*ForcedChoiceCorrections!$B$15) | Y23: =IF(AND(ISNUMBER(SEARCH("pass",L23)),ISNUMBER(X23)),COUNTIFS(L$2:L$90,"*pass*",X$2:X$90,">"&X23)+1,"") | Z23: Belgrave rail line township; closer to foothills edge than Belgrave. | SCORES 27 Oct 2026: M (near family) and T (price) are formulas from J and G; O from K. N, P, Q, R, S, U, V are ESTIMATES (Claude, general knowledge, not site-checked); S also rests on train Yes/No marked 'verify'. | AA23: 22. Upwey | Dandenong Ranges | Active Shortlist | P: High (Foothills village) | Y: Low (Inland) | Lens: Village character vs healthcare/transport practicality | Price: 929500 | Basis: House sale median $929,500 (104 sales, Property.com.au) | Note: Belgrave rail line township; closer to foothills edge than Belgrave. | AB23: Yes | AC23: Upwey station, Belgrave line (per sheet note) | AD23: Angliss Hospital ED (24-hr status still to verify) | AE23: 1500000 | AF23: Maximum purchase price, excluding transaction and moving costs | AG23: Suburb median | AH23: 26 Oct 2026 | AI23: Pass | AJ23: Published house price ($929,500) is under $1.5M cap.
A24: Tecoma | B24: Dandenong Ranges | C24: Active Shortlist | D24: High (Foothills/forest) | E24: Low (Inland) | F24: Established rail township between Upwey & Belgrave | G24: 894304 | H24: AVM estimate (30 Sep 2026), NOT a verified sale median; unit $655,831; 38 sales in last 12m (OnTheHouse/Cotality, read 27 Oct 2026) — few sales, weak | I24: =G24*(1+Settings!$B$6) | J24: 19 | K24: 5 | L24: Active — provisional pass | M24: =IF(J24="","",ROUND(MAX(0,10*(1-J24/Filters!$B$4)),1)) | N24: 9 | O24: =IF(K24="","",ROUND(MAX(0,10*(1-K24/Filters!$B$5)),1)) | P24: 3 | Q24: 4 | R24: 6 | S24: 7 | T24: =IF(G24="","",ROUND(MAX(0,MIN(10,10*(Filters!$B$2-G24)/(Filters!$B$2-500000))),1)) | U24: 0 | V24: 5 | W24: =IF(M24="",0,COUNT(M24:V24)) | X24: =IF(W24<10,"",M24*ForcedChoiceCorrections!$B$6+N24*ForcedChoiceCorrections!$B$7+O24*ForcedChoiceCorrections!$B$8+P24*ForcedChoiceCorrections!$B$9+Q24*ForcedChoiceCorrections!$B$10+R24*ForcedChoiceCorrections!$B$11+S24*ForcedChoiceCorrections!$B$12+T24*ForcedChoiceCorrections!$B$13+U24*ForcedChoiceCorrections!$B$14+V24*ForcedChoiceCorrections!$B$15) | Y24: =IF(AND(ISNUMBER(SEARCH("pass",L24)),ISNUMBER(X24)),COUNTIFS(L$2:L$90,"*pass*",X$2:X$90,">"&X24)+1,"") | Z24: Belgrave rail line; council groups Belgrave-Tecoma-Upwey as established townships. 27 Oct 2026 research pass: drive times/ED and/or AVM price added; L re-evaluated. | SCORES 27 Oct 2026: M (near family) and T (price) are formulas from J and G; O from K. N, P, Q, R, S, U, V are ESTIMATES (Claude, general knowledge, not site-checked); S also rests on train Yes/No marked 'verify'. Low sales count. | AA24: 23. Tecoma | Dandenong Ranges | Active Shortlist | P: High (Foothills/forest) | Y: Low (Inland) | Lens: Established rail township between Upwey & Belgrave | Price: [Blank] | Basis: Not verified in report | Note: Belgrave rail line; council groups Belgrave-Tecoma-Upwey as established townships. | AB24: Yes | AC24: Tecoma station, Belgrave line (per sheet note) | AD24: Angliss Hospital ED (24-hr status still to verify) | AE24: 1500000 | AF24: Maximum purchase price, excluding transaction and moving costs | AG24: AVM estimate | AH24: 27 Oct 2026 | AI24: Pass | AJ24: AVM house value ($894,304) is under $1.5M cap. Not a sale median.
A25: The Basin | B25: Dandenong Foothills | C25: Active Shortlist | D25: High (National park edge) | E25: Low (Inland) | F25: Forest-edge living without a ridge village | G25: 845187 | H25: AVM estimate (30 Sep 2026), NOT a verified sale median; unit $728,871; 66 sales in last 12m (OnTheHouse/Cotality, read 27 Oct 2026) | I25: =G25*(1+Settings!$B$6) | J25: 17 | K25: 10 | L25: Active — provisional pass | M25: =IF(J25="","",ROUND(MAX(0,10*(1-J25/Filters!$B$4)),1)) | N25: 8 | O25: =IF(K25="","",ROUND(MAX(0,10*(1-K25/Filters!$B$5)),1)) | P25: 4 | Q25: 4 | R25: 7 | S25: 3 | T25: =IF(G25="","",ROUND(MAX(0,MIN(10,10*(Filters!$B$2-G25)/(Filters!$B$2-500000))),1)) | U25: 0 | V25: 4 | W25: =IF(M25="",0,COUNT(M25:V25)) | X25: =IF(W25<10,"",M25*ForcedChoiceCorrections!$B$6+N25*ForcedChoiceCorrections!$B$7+O25*ForcedChoiceCorrections!$B$8+P25*ForcedChoiceCorrections!$B$9+Q25*ForcedChoiceCorrections!$B$10+R25*ForcedChoiceCorrections!$B$11+S25*ForcedChoiceCorrections!$B$12+T25*ForcedChoiceCorrections!$B$13+U25*ForcedChoiceCorrections!$B$14+V25*ForcedChoiceCorrections!$B$15) | Y25: =IF(AND(ISNUMBER(SEARCH("pass",L25)),ISNUMBER(X25)),COUNTIFS(L$2:L$90,"*pass*",X$2:X$90,">"&X25)+1,"") | Z25: Adjoins Dandenong Ranges National Park; verify bus/station link & Angliss Hospital ED drive. 27 Oct 2026 research pass: drive times/ED and/or AVM price added; L re-evaluated. | SCORES 27 Oct 2026: M (near family) and T (price) are formulas from J and G; O from K. N, P, Q, R, S, U, V are ESTIMATES (Claude, general knowledge, not site-checked); S also rests on train Yes/No marked 'verify'. | AA25: 24. The Basin | Dandenong Foothills | Active Shortlist | P: High (National park edge) | Y: Low (Inland) | Lens: Forest-edge living without a ridge village | Price: [Blank] | Basis: Not verified in report | Note: Adjoins Dandenong Ranges National Park; verify bus/station link & Angliss Hospital ED drive. | AB25: No | AC25: No station; bus link unverified (per sheet note) | AD25: Angliss Hospital ED (24-hr status still to verify) | AE25: 1500000 | AF25: Maximum purchase price, excluding transaction and moving costs | AG25: AVM estimate | AH25: 27 Oct 2026 | AI25: Pass | AJ25: AVM house value ($845,187) is under $1.5M cap. Not a sale median.
A26: Montrose | B26: Dandenong Foothills | C26: Active Shortlist | D26: High (Mountain backdrop) | E26: Low (Inland) | F26: Foothills township between suburbs & ridge | G26: 968458 | H26: AVM estimate (30 Sep 2026), NOT a verified sale median; unit $712,988; 85 sales in last 12m (OnTheHouse/Cotality, read 27 Oct 2026) | I26: =G26*(1+Settings!$B$6) | J26: 22 | K26: 12 | L26: Active — provisional pass | M26: =IF(J26="","",ROUND(MAX(0,10*(1-J26/Filters!$B$4)),1)) | N26: 8 | O26: =IF(K26="","",ROUND(MAX(0,10*(1-K26/Filters!$B$5)),1)) | P26: 3 | Q26: 5 | R26: 6 | S26: 3 | T26: =IF(G26="","",ROUND(MAX(0,MIN(10,10*(Filters!$B$2-G26)/(Filters!$B$2-500000))),1)) | U26: 0 | V26: 4 | W26: =IF(M26="",0,COUNT(M26:V26)) | X26: =IF(W26<10,"",M26*ForcedChoiceCorrections!$B$6+N26*ForcedChoiceCorrections!$B$7+O26*ForcedChoiceCorrections!$B$8+P26*ForcedChoiceCorrections!$B$9+Q26*ForcedChoiceCorrections!$B$10+R26*ForcedChoiceCorrections!$B$11+S26*ForcedChoiceCorrections!$B$12+T26*ForcedChoiceCorrections!$B$13+U26*ForcedChoiceCorrections!$B$14+V26*ForcedChoiceCorrections!$B$15) | Y26: =IF(AND(ISNUMBER(SEARCH("pass",L26)),ISNUMBER(X26)),COUNTIFS(L$2:L$90,"*pass*",X$2:X$90,">"&X26)+1,"") | Z26: Township shopping & community hub; verify non-rail transport, fire exposure & ED journey. 27 Oct 2026 research pass: drive times/ED and/or AVM price added; L re-evaluated. | SCORES 27 Oct 2026: M (near family) and T (price) are formulas from J and G; O from K. N, P, Q, R, S, U, V are ESTIMATES (Claude, general knowledge, not site-checked); S also rests on train Yes/No marked 'verify'. | AA26: 25. Montrose | Dandenong Foothills | Active Shortlist | P: High (Mountain backdrop) | Y: Low (Inland) | Lens: Foothills township between suburbs & ridge | Price: [Blank] | Basis: Not verified in report | Note: Township shopping & community hub; verify non-rail transport, fire exposure & ED journey. | AB26: No | AC26: No station; Mooroolbark/Lilydale stations nearby (recall; verify) | AD26: Maroondah Hospital ED | AE26: 1500000 | AF26: Maximum purchase price, excluding transaction and moving costs | AG26: AVM estimate | AH26: 27 Oct 2026 | AI26: Pass | AJ26: AVM house value ($968,458) is under $1.5M cap. Not a sale median.
A27: Mount Evelyn | B27: Yarra Ranges | C27: Active Shortlist | D27: High (Aqueduct & rail trails) | E27: Low (Inland) | F27: Forest village closer than Warburton | G27: 915472 | H27: AVM estimate (30 Sep 2026), NOT a verified sale median; unit $693,463; 130 sales in last 12m (OnTheHouse/Cotality, read 27 Oct 2026) | I27: =G27*(1+Settings!$B$6) | J27: 27 | K27: 17 | L27: Active — provisional pass | M27: =IF(J27="","",ROUND(MAX(0,10*(1-J27/Filters!$B$4)),1)) | N27: 8 | O27: =IF(K27="","",ROUND(MAX(0,10*(1-K27/Filters!$B$5)),1)) | P27: 2 | Q27: 5 | R27: 6 | S27: 3 | T27: =IF(G27="","",ROUND(MAX(0,MIN(10,10*(Filters!$B$2-G27)/(Filters!$B$2-500000))),1)) | U27: 0 | V27: 4 | W27: =IF(M27="",0,COUNT(M27:V27)) | X27: =IF(W27<10,"",M27*ForcedChoiceCorrections!$B$6+N27*ForcedChoiceCorrections!$B$7+O27*ForcedChoiceCorrections!$B$8+P27*ForcedChoiceCorrections!$B$9+Q27*ForcedChoiceCorrections!$B$10+R27*ForcedChoiceCorrections!$B$11+S27*ForcedChoiceCorrections!$B$12+T27*ForcedChoiceCorrections!$B$13+U27*ForcedChoiceCorrections!$B$14+V27*ForcedChoiceCorrections!$B$15) | Y27: =IF(AND(ISNUMBER(SEARCH("pass",L27)),ISNUMBER(X27)),COUNTIFS(L$2:L$90,"*pass*",X$2:X$90,">"&X27)+1,"") | Z27: Warburton Rail Trail & Aqueduct Trail (no passenger rail); verify Maroondah ED journey. 27 Oct 2026 research pass: drive times/ED and/or AVM price added; L re-evaluated. | SCORES 27 Oct 2026: M (near family) and T (price) are formulas from J and G; O from K. N, P, Q, R, S, U, V are ESTIMATES (Claude, general knowledge, not site-checked); S also rests on train Yes/No marked 'verify'. | AA27: 26. Mount Evelyn | Yarra Ranges | Active Shortlist | P: High (Aqueduct & rail trails) | Y: Low (Inland) | Lens: Forest village closer than Warburton | Price: [Blank] | Basis: Not verified in report | Note: Warburton Rail Trail & Aqueduct Trail (no passenger rail); verify Maroondah ED journey. | AB27: No | AC27: No passenger rail (per sheet note) | AD27: Maroondah Hospital ED | AE27: 1500000 | AF27: Maximum purchase price, excluding transaction and moving costs | AG27: AVM estimate | AH27: 27 Oct 2026 | AI27: Pass | AJ27: AVM house value ($915,472) is under $1.5M cap. Not a sale median.
A28: Croydon | B28: Outer East Melbourne | C28: Active Shortlist | D28: Medium (Leafy parks) | E28: Low (Inland) | F28: Practical outer-east control with rail & services | G28: 898896 | H28: AVM estimate (30 Sep 2026), NOT a verified sale median; unit $670,300; 704 sales in last 12m (OnTheHouse/Cotality, read 27 Oct 2026) | I28: =G28*(1+Settings!$B$6) | J28: 18 | K28: 6 | L28: Active — provisional pass | M28: =IF(J28="","",ROUND(MAX(0,10*(1-J28/Filters!$B$4)),1)) | N28: 5 | O28: =IF(K28="","",ROUND(MAX(0,10*(1-K28/Filters!$B$5)),1)) | P28: 5 | Q28: 9 | R28: 4 | S28: 8 | T28: =IF(G28="","",ROUND(MAX(0,MIN(10,10*(Filters!$B$2-G28)/(Filters!$B$2-500000))),1)) | U28: 0 | V28: 6 | W28: =IF(M28="",0,COUNT(M28:V28)) | X28: =IF(W28<10,"",M28*ForcedChoiceCorrections!$B$6+N28*ForcedChoiceCorrections!$B$7+O28*ForcedChoiceCorrections!$B$8+P28*ForcedChoiceCorrections!$B$9+Q28*ForcedChoiceCorrections!$B$10+R28*ForcedChoiceCorrections!$B$11+S28*ForcedChoiceCorrections!$B$12+T28*ForcedChoiceCorrections!$B$13+U28*ForcedChoiceCorrections!$B$14+V28*ForcedChoiceCorrections!$B$15) | Y28: =IF(AND(ISNUMBER(SEARCH("pass",L28)),ISNUMBER(X28)),COUNTIFS(L$2:L$90,"*pass*",X$2:X$90,">"&X28)+1,"") | Z28: Main St activity centre, train/bus interchange & Croydon Park; benchmark near Maroondah ED. 27 Oct 2026 research pass: drive times/ED and/or AVM price added; L re-evaluated. | SCORES 27 Oct 2026: M (near family) and T (price) are formulas from J and G; O from K. N, P, Q, R, S, U, V are ESTIMATES (Claude, general knowledge, not site-checked); S also rests on train Yes/No marked 'verify'. | AA28: 27. Croydon | Outer East Melbourne | Active Shortlist | P: Medium (Leafy parks) | Y: Low (Inland) | Lens: Practical outer-east control with rail & services | Price: [Blank] | Basis: Not verified in report | Note: Main St activity centre, train/bus interchange & Croydon Park; benchmark near Maroondah ED. | AB28: Yes | AC28: Croydon station, Lilydale line (per sheet note) | AD28: Maroondah Hospital ED | AE28: 1500000 | AF28: Maximum purchase price, excluding transaction and moving costs | AG28: AVM estimate | AH28: 27 Oct 2026 | AI28: Pass | AJ28: AVM house value ($898,896) is under $1.5M cap. Not a sale median.
A29: Warragul | B29: West Gippsland | C29: Active Shortlist | D29: High (Rolling hills/gardens) | E29: Low (Inland) | F29: Regional town with V/Line rail & local hospital ED | G29: 620000 | H29: 3-bed house median $620k; 4-bed $732.5k (Domain) | I29: 657200 | J29: 58 | K29: 2 | L29: Active — provisional pass | M29: =IF(J29="","",ROUND(MAX(0,10*(1-J29/Filters!$B$4)),1)) | N29: 5 | O29: =IF(K29="","",ROUND(MAX(0,10*(1-K29/Filters!$B$5)),1)) | P29: 3 | Q29: 8 | R29: 6 | S29: 6 | T29: =IF(G29="","",ROUND(MAX(0,MIN(10,10*(Filters!$B$2-G29)/(Filters!$B$2-500000))),1)) | U29: 0 | V29: 4 | W29: =IF(M29="",0,COUNT(M29:V29)) | X29: =IF(W29<10,"",M29*ForcedChoiceCorrections!$B$6+N29*ForcedChoiceCorrections!$B$7+O29*ForcedChoiceCorrections!$B$8+P29*ForcedChoiceCorrections!$B$9+Q29*ForcedChoiceCorrections!$B$10+R29*ForcedChoiceCorrections!$B$11+S29*ForcedChoiceCorrections!$B$12+T29*ForcedChoiceCorrections!$B$13+U29*ForcedChoiceCorrections!$B$14+V29*ForcedChoiceCorrections!$B$15) | Y29: =IF(AND(ISNUMBER(SEARCH("pass",L29)),ISNUMBER(X29)),COUNTIFS(L$2:L$90,"*pass*",X$2:X$90,">"&X29)+1,"") | Z29: Town-centre V/Line station & West Gippsland Hospital ED (verify wait times & GW drive). | SCORES 27 Oct 2026: M (near family) and T (price) are formulas from J and G; O from K. N, P, Q, R, S, U, V are ESTIMATES (Claude, general knowledge, not site-checked); S also rests on train Yes/No marked 'verify'. | AA29: 28. Warragul | West Gippsland | Active Shortlist | P: High (Rolling hills/gardens) | Y: Low (Inland) | Lens: Regional town with V/Line rail & local hospital ED | Price: 620000 | Basis: 3-bed house median $620k; 4-bed $732.5k (Domain) | Note: Town-centre V/Line station & West Gippsland Hospital ED (verify wait times & GW drive). | AB29: Yes | AC29: Warragul station, V/Line Gippsland (per sheet note) | AD29: West Gippsland Hospital ED (local) | AE29: 1500000 | AF29: Maximum purchase price, excluding transaction and moving costs | AG29: Suburb median | AH29: 26 Oct 2026 | AI29: Pass | AJ29: Published house price ($620,000) is under $1.5M cap.
A30: Mount Eliza | B30: Mornington Peninsula | C30: Active Shortlist | D30: High (Woodland & gullies) | E30: High (Canadian Bay/coast) | F30: Rare overlap of bushland reserves, village & bay | G30: 1610862 | H30: AVM estimate (30 Sep 2026), NOT a verified sale median; unit $778,590; 313 sales in last 12m (OnTheHouse/Cotality, read 27 Oct 2026) | I30: =G30*(1+Settings!$B$6) | J30: 34 | K30: 10 | L30: Active — needs data | O30: =IF(K30="","",ROUND(MAX(0,10*(1-K30/Filters!$B$5)),1)) | W30: =IF(M30="",0,COUNT(M30:V30)) | X30: =IF(W30<10,"",M30*ForcedChoiceCorrections!$B$6+N30*ForcedChoiceCorrections!$B$7+O30*ForcedChoiceCorrections!$B$8+P30*ForcedChoiceCorrections!$B$9+Q30*ForcedChoiceCorrections!$B$10+R30*ForcedChoiceCorrections!$B$11+S30*ForcedChoiceCorrections!$B$12+T30*ForcedChoiceCorrections!$B$13+U30*ForcedChoiceCorrections!$B$14+V30*ForcedChoiceCorrections!$B$15) | Y30: =IF(AND(ISNUMBER(SEARCH("pass",L30)),ISNUMBER(X30)),COUNTIFS(L$2:L$90,"*pass*",X$2:X$90,">"&X30)+1,"") | Z30: Tests BOTH parents' bushland preference and your coastal-nature preference; verify bus 781 & Frankston ED drive. 27 Oct 2026 research pass: drive times/ED and/or AVM price added; L re-evaluated. | AA30: 29. Mount Eliza | Mornington Peninsula | Active Shortlist | P: High (Woodland & gullies) | Y: High (Canadian Bay/coast) | Lens: Rare overlap of bushland reserves, village & bay | Price: [Blank] | Basis: Not verified in report | Note: Tests BOTH parents' bushland preference and your coastal-nature preference; verify bus 781 & Frankston ED drive. | AB30: No | AC30: No rail; bus 781 to Frankston (per sheet note) | AD30: Peninsula University Hospital ED | AE30: 1500000 | AF30: Maximum purchase price, excluding transaction and moving costs | AG30: AVM estimate | AH30: 27 Oct 2026 | AI30: Needs data | AJ30: AVM house value ($1,610,862) is over the $1.5M cap; needs a documented search for 3+ bed homes under the cap.
A31: Mornington | B31: Mornington Peninsula | C31: Active Shortlist | D31: Medium (Parks & gardens) | E31: High (Bay beaches/harbor) | F31: Established coastal town centre & Main Street | G31: 1096505 | H31: AVM estimate (30 Sep 2026), NOT a verified sale median; unit $790,244; 629 sales in last 12m (OnTheHouse/Cotality, read 27 Oct 2026) | I31: =G31*(1+Settings!$B$6) | J31: 40 | K31: 15 | L31: Active — provisional pass | M31: =IF(J31="","",ROUND(MAX(0,10*(1-J31/Filters!$B$4)),1)) | N31: 7 | O31: =IF(K31="","",ROUND(MAX(0,10*(1-K31/Filters!$B$5)),1)) | P31: 3 | Q31: 9 | R31: 7 | S31: 3 | T31: =IF(G31="","",ROUND(MAX(0,MIN(10,10*(Filters!$B$2-G31)/(Filters!$B$2-500000))),1)) | U31: 9 | V31: 3 | W31: =IF(M31="",0,COUNT(M31:V31)) | X31: =IF(W31<10,"",M31*ForcedChoiceCorrections!$B$6+N31*ForcedChoiceCorrections!$B$7+O31*ForcedChoiceCorrections!$B$8+P31*ForcedChoiceCorrections!$B$9+Q31*ForcedChoiceCorrections!$B$10+R31*ForcedChoiceCorrections!$B$11+S31*ForcedChoiceCorrections!$B$12+T31*ForcedChoiceCorrections!$B$13+U31*ForcedChoiceCorrections!$B$14+V31*ForcedChoiceCorrections!$B$15) | Y31: =IF(AND(ISNUMBER(SEARCH("pass",L31)),ISNUMBER(X31)),COUNTIFS(L$2:L$90,"*pass*",X$2:X$90,">"&X31)+1,"") | Z31: Substantial town services on bay; no passenger train (bus to Frankston); verify Frankston/Rosebud ED drive. 27 Oct 2026 research pass: drive times/ED and/or AVM price added; L re-evaluated. | SCORES 27 Oct 2026: M (near family) and T (price) are formulas from J and G; O from K. N, P, Q, R, S, U, V are ESTIMATES (Claude, general knowledge, not site-checked); S also rests on train Yes/No marked 'verify'. | AA31: 30. Mornington | Mornington Peninsula | Active Shortlist | P: Medium (Parks & gardens) | Y: High (Bay beaches/harbor) | Lens: Established coastal town centre & Main Street | Price: [Blank] | Basis: Not verified in report | Note: Substantial town services on bay; no passenger train (bus to Frankston); verify Frankston/Rosebud ED drive. | AB31: No | AC31: No passenger train; bus to Frankston (per sheet note) | AD31: Peninsula University Hospital ED | AE31: 1500000 | AF31: Maximum purchase price, excluding transaction and moving costs | AG31: AVM estimate | AH31: 27 Oct 2026 | AI31: Pass | AJ31: AVM house value ($1,096,505) is under $1.5M cap. Not a sale median.
A32: Clifton Springs | B32: Bellarine Peninsula | C32: Active Shortlist | D32: Medium (Dell & coastal reserve) | E32: High (Bay views & foreshore) | F32: High-value Bellarine coastal alternative | G32: 715000 | H32: House sale median $715,000 (196 sales, Property.com.au) | I32: 757900 | J32: 95 | K32: 23 | L32: Fails: GW drive | O32: =IF(K32="","",ROUND(MAX(0,10*(1-K32/Filters!$B$5)),1)) | W32: =IF(M32="",0,COUNT(M32:V32)) | X32: =IF(W32<10,"",M32*ForcedChoiceCorrections!$B$6+N32*ForcedChoiceCorrections!$B$7+O32*ForcedChoiceCorrections!$B$8+P32*ForcedChoiceCorrections!$B$9+Q32*ForcedChoiceCorrections!$B$10+R32*ForcedChoiceCorrections!$B$11+S32*ForcedChoiceCorrections!$B$12+T32*ForcedChoiceCorrections!$B$13+U32*ForcedChoiceCorrections!$B$14+V32*ForcedChoiceCorrections!$B$15) | Y32: =IF(AND(ISNUMBER(SEARCH("pass",L32)),ISNUMBER(X32)),COUNTIFS(L$2:L$90,"*pass*",X$2:X$90,">"&X32)+1,"") | Z32: Port Phillip bay frontage & Dell picnic area; verify Univ Hospital Geelong ED drive & public transport. | AA32: 31. Clifton Springs | Bellarine Peninsula | Active Shortlist | P: Medium (Dell & coastal reserve) | Y: High (Bay views & foreshore) | Lens: High-value Bellarine coastal alternative | Price: 715000 | Basis: House sale median $715,000 (196 sales, Property.com.au) | Note: Port Phillip bay frontage & Dell picnic area; verify Univ Hospital Geelong ED drive & public transport. | AB32: No | AC32: No rail; Geelong via bus (recall; verify) | AD32: University Hospital Geelong ED | AE32: 1500000 | AF32: Maximum purchase price, excluding transaction and moving costs | AG32: Suburb median | AH32: 26 Oct 2026 | AI32: Pass | AJ32: Published house price ($715,000) is under $1.5M cap.
A33: Warburton | B33: Yarra Valley | C33: Watchlist | D33: Very High (Mountain & river) | E33: Low (River, non-coastal) | F33: Maximum forest/mountain scenery test | G33: 717500 | H33: 3-bed house median $717.5k (34 sales); 4-bed $702.5k | I33: 760550 | J33: 65 | K33: 53 | L33: Provisional pass | M33: =IF(J33="","",ROUND(MAX(0,10*(1-J33/Filters!$B$4)),1)) | N33: 10 | O33: =IF(K33="","",ROUND(MAX(0,10*(1-K33/Filters!$B$5)),1)) | P33: 1 | Q33: 4 | R33: 8 | S33: 1 | T33: =IF(G33="","",ROUND(MAX(0,MIN(10,10*(Filters!$B$2-G33)/(Filters!$B$2-500000))),1)) | U33: 0 | V33: 1 | W33: =IF(M33="",0,COUNT(M33:V33)) | X33: =IF(W33<10,"",M33*ForcedChoiceCorrections!$B$6+N33*ForcedChoiceCorrections!$B$7+O33*ForcedChoiceCorrections!$B$8+P33*ForcedChoiceCorrections!$B$9+Q33*ForcedChoiceCorrections!$B$10+R33*ForcedChoiceCorrections!$B$11+S33*ForcedChoiceCorrections!$B$12+T33*ForcedChoiceCorrections!$B$13+U33*ForcedChoiceCorrections!$B$14+V33*ForcedChoiceCorrections!$B$15) | Y33: =IF(AND(ISNUMBER(SEARCH("pass",L33)),ISNUMBER(X33)),COUNTIFS(L$2:L$90,"*pass*",X$2:X$90,">"&X33)+1,"") | Z33: ABS 2021: 24.3% aged 65+, 8.1% non-Eng HH. Tough practicality test on winter comfort, fire risk & distant ED. 27 Oct 2026 research pass: drive times/ED and/or AVM price added; L re-evaluated. | SCORES 27 Oct 2026: M (near family) and T (price) are formulas from J and G; O from K. N, P, Q, R, S, U, V are ESTIMATES (Claude, general knowledge, not site-checked); S also rests on train Yes/No marked 'verify'. | AA33: 32. Warburton | Yarra Valley | Watchlist | P: Very High (Mountain & river) | Y: Low (River, non-coastal) | Lens: Maximum forest/mountain scenery test | Price: 717500 | Basis: 3-bed house median $717.5k (34 sales); 4-bed $702.5k | Note: ABS 2021: 24.3% aged 65+, 8.1% non-Eng HH. Tough practicality test on winter comfort, fire risk & distant ED. | AB33: No | AC33: No passenger rail (recall; verify) | AD33: Maroondah Hospital ED (drive times added 27 Oct 2026, Google Maps leave-now, not peak; Angliss may be closer, 24-hr status unverified) | AE33: 1500000 | AF33: Maximum purchase price, excluding transaction and moving costs | AG33: Suburb median | AH33: 26 Oct 2026 | AI33: Pass | AJ33: Published house price ($717,500) is under $1.5M cap.
A34: Trentham | B34: Macedon Ranges | C34: Watchlist | D34: High (Wombat Forest village) | E34: Low (Inland) | F34: Intimate forest village with older age profile | G34: 978750 | H34: 3-bed house median $978,750 (30 sales, Domain) | I34: 1037475 | J34: 97 | K34: 59 | L34: Fails: GW drive | O34: =IF(K34="","",ROUND(MAX(0,10*(1-K34/Filters!$B$5)),1)) | W34: =IF(M34="",0,COUNT(M34:V34)) | X34: =IF(W34<10,"",M34*ForcedChoiceCorrections!$B$6+N34*ForcedChoiceCorrections!$B$7+O34*ForcedChoiceCorrections!$B$8+P34*ForcedChoiceCorrections!$B$9+Q34*ForcedChoiceCorrections!$B$10+R34*ForcedChoiceCorrections!$B$11+S34*ForcedChoiceCorrections!$B$12+T34*ForcedChoiceCorrections!$B$13+U34*ForcedChoiceCorrections!$B$14+V34*ForcedChoiceCorrections!$B$15) | Y34: =IF(AND(ISNUMBER(SEARCH("pass",L34)),ISNUMBER(X34)),COUNTIFS(L$2:L$90,"*pass*",X$2:X$90,">"&X34)+1,"") | Z34: ABS 2021: 33.6% aged 65+, 4.7% non-Eng HH. CAUTION: Local health campus is community/aged care ONLY, not an ED. 27 Oct 2026 research pass: drive times/ED and/or AVM price added; L re-evaluated. | AA34: 33. Trentham | Macedon Ranges | Watchlist | P: High (Wombat Forest village) | Y: Low (Inland) | Lens: Intimate forest village with older age profile | Price: 978750 | Basis: 3-bed house median $978,750 (30 sales, Domain) | Note: ABS 2021: 33.6% aged 65+, 4.7% non-Eng HH. CAUTION: Local health campus is community/aged care ONLY, not an ED. | AB34: No | AC34: No station (line closed); nearest Woodend or Kyneton V/Line (recall; verify) | AD34: Grampians Health Ballarat (Ballarat Base) ED (24-hr: recall (major regional ED); Bendigo 68 min) (drive times: Google Maps leave-now, 27 Oct 2026 ~13:15–13:45 AEDT (midday, not peak), suburb name) | AE34: 1500000 | AF34: Maximum purchase price, excluding transaction and moving costs | AG34: Suburb median | AH34: 26 Oct 2026 | AI34: Pass | AJ34: Published house price ($978,750) is under $1.5M cap.
A35: Olinda | B35: Dandenong Ridge | C35: Watchlist | D35: Very High (Botanic gardens/ridge) | E35: Low (Inland) | F35: Dandenongs ridge village — high scenic appeal | G35: 1020069 | H35: AVM estimate (30 Sep 2026), NOT a verified sale median; unit $1,214,582; 37 sales in last 12m (OnTheHouse/Cotality, read 27 Oct 2026) — few sales, weak | I35: =G35*(1+Settings!$B$6) | J35: 33 | K35: 15 | L35: Provisional pass | M35: =IF(J35="","",ROUND(MAX(0,10*(1-J35/Filters!$B$4)),1)) | N35: 10 | O35: =IF(K35="","",ROUND(MAX(0,10*(1-K35/Filters!$B$5)),1)) | P35: 2 | Q35: 3 | R35: 9 | S35: 2 | T35: =IF(G35="","",ROUND(MAX(0,MIN(10,10*(Filters!$B$2-G35)/(Filters!$B$2-500000))),1)) | U35: 0 | V35: 3 | W35: =IF(M35="",0,COUNT(M35:V35)) | X35: =IF(W35<10,"",M35*ForcedChoiceCorrections!$B$6+N35*ForcedChoiceCorrections!$B$7+O35*ForcedChoiceCorrections!$B$8+P35*ForcedChoiceCorrections!$B$9+Q35*ForcedChoiceCorrections!$B$10+R35*ForcedChoiceCorrections!$B$11+S35*ForcedChoiceCorrections!$B$12+T35*ForcedChoiceCorrections!$B$13+U35*ForcedChoiceCorrections!$B$14+V35*ForcedChoiceCorrections!$B$15) | Y35: =IF(AND(ISNUMBER(SEARCH("pass",L35)),ISNUMBER(X35)),COUNTIFS(L$2:L$90,"*pass*",X$2:X$90,">"&X35)+1,"") | Z35: Parks Vic documents severe-weather/fire closures; bus 694 to Belgrave; verify winter damp, slopes & insurance. 27 Oct 2026 research pass: drive times/ED and/or AVM price added; L re-evaluated. | SCORES 27 Oct 2026: M (near family) and T (price) are formulas from J and G; O from K. N, P, Q, R, S, U, V are ESTIMATES (Claude, general knowledge, not site-checked); S also rests on train Yes/No marked 'verify'. Low sales count. | AA35: 34. Olinda | Dandenong Ridge | Watchlist | P: Very High (Botanic gardens/ridge) | Y: Low (Inland) | Lens: Dandenongs ridge village — high scenic appeal | Price: [Blank] | Basis: Not verified in report | Note: Parks Vic documents severe-weather/fire closures; bus 694 to Belgrave; verify winter damp, slopes & insurance. | AB35: No | AC35: No station; nearest Upwey/Belgrave (recall; verify) | AD35: Angliss Hospital ED (24-hr: verified, Eastern Health site) (drive times: Google Maps leave-now, 27 Oct 2026 ~13:15–13:45 AEDT (midday, not peak), suburb name) | AE35: 1500000 | AF35: Maximum purchase price, excluding transaction and moving costs | AG35: AVM estimate | AH35: 27 Oct 2026 | AI35: Pass | AJ35: AVM house value ($1,020,069) is under $1.5M cap. Not a sale median.
A36: Sassafras | B36: Dandenong Ridge | C36: Watchlist | D36: Very High (Forest ridge village) | E36: Low (Inland) | F36: Dandenongs ridge village comparator | G36: 1006318 | H36: AVM estimate (30 Sep 2026), NOT a verified sale median; unit $1,279,170; 17 sales in last 12m (OnTheHouse/Cotality, read 27 Oct 2026) — few sales, weak | I36: =G36*(1+Settings!$B$6) | J36: 29 | K36: 11 | L36: Provisional pass | M36: =IF(J36="","",ROUND(MAX(0,10*(1-J36/Filters!$B$4)),1)) | N36: 10 | O36: =IF(K36="","",ROUND(MAX(0,10*(1-K36/Filters!$B$5)),1)) | P36: 2 | Q36: 3 | R36: 9 | S36: 2 | T36: =IF(G36="","",ROUND(MAX(0,MIN(10,10*(Filters!$B$2-G36)/(Filters!$B$2-500000))),1)) | U36: 0 | V36: 3 | W36: =IF(M36="",0,COUNT(M36:V36)) | X36: =IF(W36<10,"",M36*ForcedChoiceCorrections!$B$6+N36*ForcedChoiceCorrections!$B$7+O36*ForcedChoiceCorrections!$B$8+P36*ForcedChoiceCorrections!$B$9+Q36*ForcedChoiceCorrections!$B$10+R36*ForcedChoiceCorrections!$B$11+S36*ForcedChoiceCorrections!$B$12+T36*ForcedChoiceCorrections!$B$13+U36*ForcedChoiceCorrections!$B$14+V36*ForcedChoiceCorrections!$B$15) | Y36: =IF(AND(ISNUMBER(SEARCH("pass",L36)),ISNUMBER(X36)),COUNTIFS(L$2:L$90,"*pass*",X$2:X$90,">"&X36)+1,"") | Z36: High tourism traffic on weekends; check everyday grocery/medical convenience & bushfire overlay. 27 Oct 2026 research pass: drive times/ED and/or AVM price added; L re-evaluated. | SCORES 27 Oct 2026: M (near family) and T (price) are formulas from J and G; O from K. N, P, Q, R, S, U, V are ESTIMATES (Claude, general knowledge, not site-checked); S also rests on train Yes/No marked 'verify'. Low sales count. | AA36: 35. Sassafras | Dandenong Ridge | Watchlist | P: Very High (Forest ridge village) | Y: Low (Inland) | Lens: Dandenongs ridge village comparator | Price: [Blank] | Basis: Not verified in report | Note: High tourism traffic on weekends; check everyday grocery/medical convenience & bushfire overlay. | AB36: No | AC36: No station; nearest Upwey/Belgrave (recall; verify) | AD36: Angliss Hospital ED (24-hr: verified, Eastern Health site) (drive times: Google Maps leave-now, 27 Oct 2026 ~13:15–13:45 AEDT (midday, not peak), suburb name) | AE36: 1500000 | AF36: Maximum purchase price, excluding transaction and moving costs | AG36: AVM estimate | AH36: 27 Oct 2026 | AI36: Pass | AJ36: AVM house value ($1,006,318) is under $1.5M cap. Not a sale median.
A37: Mount Dandenong | B37: Dandenong Ridge | C37: Watchlist | D37: Very High (Canopy & views) | E37: Low (Inland) | F37: Ridge canopy living test | G37: 982029 | H37: AVM estimate (30 Sep 2026), NOT a verified sale median; unit $1,079,082; 30 sales in last 12m (OnTheHouse/Cotality, read 27 Oct 2026) — few sales, weak | I37: =G37*(1+Settings!$B$6) | J37: 30 | K37: 19 | L37: Provisional pass | M37: =IF(J37="","",ROUND(MAX(0,10*(1-J37/Filters!$B$4)),1)) | N37: 10 | O37: =IF(K37="","",ROUND(MAX(0,10*(1-K37/Filters!$B$5)),1)) | P37: 2 | Q37: 2 | R37: 7 | S37: 1 | T37: =IF(G37="","",ROUND(MAX(0,MIN(10,10*(Filters!$B$2-G37)/(Filters!$B$2-500000))),1)) | U37: 0 | V37: 3 | W37: =IF(M37="",0,COUNT(M37:V37)) | X37: =IF(W37<10,"",M37*ForcedChoiceCorrections!$B$6+N37*ForcedChoiceCorrections!$B$7+O37*ForcedChoiceCorrections!$B$8+P37*ForcedChoiceCorrections!$B$9+Q37*ForcedChoiceCorrections!$B$10+R37*ForcedChoiceCorrections!$B$11+S37*ForcedChoiceCorrections!$B$12+T37*ForcedChoiceCorrections!$B$13+U37*ForcedChoiceCorrections!$B$14+V37*ForcedChoiceCorrections!$B$15) | Y37: =IF(AND(ISNUMBER(SEARCH("pass",L37)),ISNUMBER(X37)),COUNTIFS(L$2:L$90,"*pass*",X$2:X$90,">"&X37)+1,"") | Z37: Requires property-specific slope, tree-fall, insurance & emergency egress verification. 27 Oct 2026 research pass: drive times/ED and/or AVM price added; L re-evaluated. | SCORES 27 Oct 2026: M (near family) and T (price) are formulas from J and G; O from K. N, P, Q, R, S, U, V are ESTIMATES (Claude, general knowledge, not site-checked); S also rests on train Yes/No marked 'verify'. Low sales count. | AA37: 36. Mount Dandenong | Dandenong Ridge | Watchlist | P: Very High (Canopy & views) | Y: Low (Inland) | Lens: Ridge canopy living test | Price: [Blank] | Basis: Not verified in report | Note: Requires property-specific slope, tree-fall, insurance & emergency egress verification. | AB37: No | AC37: No station (recall; verify) | AD37: Angliss Hospital ED (24-hr: verified, Eastern Health site; Maroondah 24 min) (drive times: Google Maps leave-now, 27 Oct 2026 ~13:15–13:45 AEDT (midday, not peak), suburb name) | AE37: 1500000 | AF37: Maximum purchase price, excluding transaction and moving costs | AG37: AVM estimate | AH37: 27 Oct 2026 | AI37: Pass | AJ37: AVM house value ($982,029) is under $1.5M cap. Not a sale median.
A38: Emerald | B38: Dandenong Ranges | C38: Watchlist | D38: High (Emerald Lake & hills) | E38: Low (Inland) | F38: Larger hills town south-east of ridge | G38: 980699 | H38: AVM estimate (30 Sep 2026), NOT a verified sale median; unit $641,682; 84 sales in last 12m (OnTheHouse/Cotality, read 27 Oct 2026) | I38: =G38*(1+Settings!$B$6) | J38: 35 | K38: 22 | L38: Provisional pass | M38: =IF(J38="","",ROUND(MAX(0,10*(1-J38/Filters!$B$4)),1)) | N38: 9 | O38: =IF(K38="","",ROUND(MAX(0,10*(1-K38/Filters!$B$5)),1)) | P38: 2 | Q38: 6 | R38: 8 | S38: 2 | T38: =IF(G38="","",ROUND(MAX(0,MIN(10,10*(Filters!$B$2-G38)/(Filters!$B$2-500000))),1)) | U38: 0 | V38: 3 | W38: =IF(M38="",0,COUNT(M38:V38)) | X38: =IF(W38<10,"",M38*ForcedChoiceCorrections!$B$6+N38*ForcedChoiceCorrections!$B$7+O38*ForcedChoiceCorrections!$B$8+P38*ForcedChoiceCorrections!$B$9+Q38*ForcedChoiceCorrections!$B$10+R38*ForcedChoiceCorrections!$B$11+S38*ForcedChoiceCorrections!$B$12+T38*ForcedChoiceCorrections!$B$13+U38*ForcedChoiceCorrections!$B$14+V38*ForcedChoiceCorrections!$B$15) | Y38: =IF(AND(ISNUMBER(SEARCH("pass",L38)),ISNUMBER(X38)),COUNTIFS(L$2:L$90,"*pass*",X$2:X$90,">"&X38)+1,"") | Z38: Emerald Lake precinct; separate from ridge villages—verify routine services & ED drive. 27 Oct 2026 research pass: drive times/ED and/or AVM price added; L re-evaluated. | SCORES 27 Oct 2026: M (near family) and T (price) are formulas from J and G; O from K. N, P, Q, R, S, U, V are ESTIMATES (Claude, general knowledge, not site-checked); S also rests on train Yes/No marked 'verify'. | AA38: 37. Emerald | Dandenong Ranges | Watchlist | P: High (Emerald Lake & hills) | Y: Low (Inland) | Lens: Larger hills town south-east of ridge | Price: [Blank] | Basis: Not verified in report | Note: Emerald Lake precinct; separate from ridge villages—verify routine services & ED drive. | AB38: No | AC38: Puffing Billy tourist railway only (recall; verify) | AD38: Angliss Hospital ED (24-hr: verified, Eastern Health site; Casey 23 min) (drive times: Google Maps leave-now, 27 Oct 2026 ~13:15–13:45 AEDT (midday, not peak), suburb name) | AE38: 1500000 | AF38: Maximum purchase price, excluding transaction and moving costs | AG38: AVM estimate | AH38: 27 Oct 2026 | AI38: Pass | AJ38: AVM house value ($980,699) is under $1.5M cap. Not a sale median.
A39: Ferntree Gully | B39: East / Foothills | C39: Watchlist | D39: Medium-High (Foothills) | E39: Low (Inland) | F39: Larger housing/service catchment next to Upper FTG | G39: 872133 | H39: AVM estimate (30 Sep 2026), NOT a verified sale median; unit $678,759; 438 sales in last 12m (OnTheHouse/Cotality, read 27 Oct 2026) | I39: =G39*(1+Settings!$B$6) | J39: 14 | K39: 8 | L39: Provisional pass | M39: =IF(J39="","",ROUND(MAX(0,10*(1-J39/Filters!$B$4)),1)) | N39: 6 | O39: =IF(K39="","",ROUND(MAX(0,10*(1-K39/Filters!$B$5)),1)) | P39: 5 | Q39: 8 | R39: 4 | S39: 8 | T39: =IF(G39="","",ROUND(MAX(0,MIN(10,10*(Filters!$B$2-G39)/(Filters!$B$2-500000))),1)) | U39: 0 | V39: 6 | W39: =IF(M39="",0,COUNT(M39:V39)) | X39: =IF(W39<10,"",M39*ForcedChoiceCorrections!$B$6+N39*ForcedChoiceCorrections!$B$7+O39*ForcedChoiceCorrections!$B$8+P39*ForcedChoiceCorrections!$B$9+Q39*ForcedChoiceCorrections!$B$10+R39*ForcedChoiceCorrections!$B$11+S39*ForcedChoiceCorrections!$B$12+T39*ForcedChoiceCorrections!$B$13+U39*ForcedChoiceCorrections!$B$14+V39*ForcedChoiceCorrections!$B$15) | Y39: =IF(AND(ISNUMBER(SEARCH("pass",L39)),ISNUMBER(X39)),COUNTIFS(L$2:L$90,"*pass*",X$2:X$90,">"&X39)+1,"") | Z39: Belgrave line; compare flatter pockets and housing stock against Upper Ferntree Gully. 27 Oct 2026 research pass: drive times/ED and/or AVM price added; L re-evaluated. OnTheHouse shows the same house AVM ($872,133) for Ferntree Gully and Upper Ferntree Gully (same postcode) — treat as postcode-level, weak. | SCORES 27 Oct 2026: M (near family) and T (price) are formulas from J and G; O from K. N, P, Q, R, S, U, V are ESTIMATES (Claude, general knowledge, not site-checked); S also rests on train Yes/No marked 'verify'. Price = postcode-level AVM shared with Upper FTG. | AA39: 38. Ferntree Gully | East / Foothills | Watchlist | P: Medium-High (Foothills) | Y: Low (Inland) | Lens: Larger housing/service catchment next to Upper FTG | Price: [Blank] | Basis: Not verified in report | Note: Belgrave line; compare flatter pockets and housing stock against Upper Ferntree Gully. | AB39: Yes | AC39: Ferntree Gully station, Belgrave line (recall; verify) | AD39: Angliss Hospital ED (24-hr: verified, Eastern Health site) (drive times: Google Maps leave-now, 27 Oct 2026 ~13:15–13:45 AEDT (midday, not peak), suburb name) | AE39: 1500000 | AF39: Maximum purchase price, excluding transaction and moving costs | AG39: AVM estimate | AH39: 27 Oct 2026 | AI39: Pass | AJ39: AVM house value ($872,133) is under $1.5M cap. Not a sale median.
A40: Berwick | B40: South-East Melbourne | C40: Watchlist | D40: Medium (Wilson Botanic Park) | E40: Low (Inland) | F40: Healthcare-led south-east comparator | G40: 935845 | H40: AVM estimate (30 Sep 2026), NOT a verified sale median; unit $669,669; 987 sales in last 12m (OnTheHouse/Cotality, read 27 Oct 2026) | I40: =G40*(1+Settings!$B$6) | J40: 25 | K40: 6 | L40: Provisional pass | M40: =IF(J40="","",ROUND(MAX(0,10*(1-J40/Filters!$B$4)),1)) | N40: 5 | O40: =IF(K40="","",ROUND(MAX(0,10*(1-K40/Filters!$B$5)),1)) | P40: 7 | Q40: 9 | R40: 6 | S40: 8 | T40: =IF(G40="","",ROUND(MAX(0,MIN(10,10*(Filters!$B$2-G40)/(Filters!$B$2-500000))),1)) | U40: 1 | V40: 6 | W40: =IF(M40="",0,COUNT(M40:V40)) | X40: =IF(W40<10,"",M40*ForcedChoiceCorrections!$B$6+N40*ForcedChoiceCorrections!$B$7+O40*ForcedChoiceCorrections!$B$8+P40*ForcedChoiceCorrections!$B$9+Q40*ForcedChoiceCorrections!$B$10+R40*ForcedChoiceCorrections!$B$11+S40*ForcedChoiceCorrections!$B$12+T40*ForcedChoiceCorrections!$B$13+U40*ForcedChoiceCorrections!$B$14+V40*ForcedChoiceCorrections!$B$15) | Y40: =IF(AND(ISNUMBER(SEARCH("pass",L40)),ISNUMBER(X40)),COUNTIFS(L$2:L$90,"*pass*",X$2:X$90,">"&X40)+1,"") | Z40: Monash Health Casey Hospital 24-hr ED on site; verify whether residential pockets feel green enough. 27 Oct 2026 research pass: drive times/ED and/or AVM price added; L re-evaluated. | SCORES 27 Oct 2026: M (near family) and T (price) are formulas from J and G; O from K. N, P, Q, R, S, U, V are ESTIMATES (Claude, general knowledge, not site-checked); S also rests on train Yes/No marked 'verify'. | AA40: 39. Berwick | South-East Melbourne | Watchlist | P: Medium (Wilson Botanic Park) | Y: Low (Inland) | Lens: Healthcare-led south-east comparator | Price: [Blank] | Basis: Not verified in report | Note: Monash Health Casey Hospital 24-hr ED on site; verify whether residential pockets feel green enough. | AB40: Yes | AC40: Berwick station, Pakenham line (recall; verify) | AD40: Casey Hospital ED (24-hr: recall (major metro ED)) (drive times: Google Maps leave-now, 27 Oct 2026 ~13:15–13:45 AEDT (midday, not peak), suburb name) | AE40: 1500000 | AF40: Maximum purchase price, excluding transaction and moving costs | AG40: AVM estimate | AH40: 27 Oct 2026 | AI40: Pass | AJ40: AVM house value ($935,845) is under $1.5M cap. Not a sale median.
A41: Frankston South | B41: Mornington Peninsula | C41: Active Shortlist | D41: High (Sweetwater Creek reserve) | E41: High (Near beach/bay) | F41: Greener, bushier counterpart to Frankston | G41: 1195044 | H41: AVM estimate (30 Sep 2026), NOT a verified sale median; unit $781,232; 305 sales in last 12m (OnTheHouse/Cotality, read 27 Oct 2026) | I41: =G41*(1+Settings!$B$6) | J41: 31 | K41: 4 | L41: Active — provisional pass | M41: =IF(J41="","",ROUND(MAX(0,10*(1-J41/Filters!$B$4)),1)) | N41: 7 | O41: =IF(K41="","",ROUND(MAX(0,10*(1-K41/Filters!$B$5)),1)) | P41: 3 | Q41: 6 | R41: 6 | S41: 4 | T41: =IF(G41="","",ROUND(MAX(0,MIN(10,10*(Filters!$B$2-G41)/(Filters!$B$2-500000))),1)) | U41: 7 | V41: 5 | W41: =IF(M41="",0,COUNT(M41:V41)) | X41: =IF(W41<10,"",M41*ForcedChoiceCorrections!$B$6+N41*ForcedChoiceCorrections!$B$7+O41*ForcedChoiceCorrections!$B$8+P41*ForcedChoiceCorrections!$B$9+Q41*ForcedChoiceCorrections!$B$10+R41*ForcedChoiceCorrections!$B$11+S41*ForcedChoiceCorrections!$B$12+T41*ForcedChoiceCorrections!$B$13+U41*ForcedChoiceCorrections!$B$14+V41*ForcedChoiceCorrections!$B$15) | Y41: =IF(AND(ISNUMBER(SEARCH("pass",L41)),ISNUMBER(X41)),COUNTIFS(L$2:L$90,"*pass*",X$2:X$90,">"&X41)+1,"") | Z41: Sweetwater Creek nature reserve; weaker station walk than central Frankston. Promoted to Active 26 Oct 2026 as a bush-plus-bay overlap candidate. 27 Oct 2026 research pass: drive times/ED and/or AVM price added; L re-evaluated. | SCORES 27 Oct 2026: M (near family) and T (price) are formulas from J and G; O from K. N, P, Q, R, S, U, V are ESTIMATES (Claude, general knowledge, not site-checked); S also rests on train Yes/No marked 'verify'. | AA41: 40. Frankston South | Mornington Peninsula | Active Shortlist | P: High (Sweetwater Creek reserve) | Y: High (Near beach/bay) | Lens: Greener, bushier counterpart to Frankston | Price: [Blank] | Basis: Not verified in report | Note: Sweetwater Creek nature reserve; weaker station walk than central Frankston. Promoted to Active 26 Oct 2026 as a bush-plus-bay overlap candidate. | AB41: No | AC41: No station in suburb; Frankston station nearby (recall; verify) | AD41: Peninsula University Hospital ED (drive times added 27 Oct 2026, Google Maps leave-now by suburb name, not postcode, not peak) | AE41: 1500000 | AF41: Maximum purchase price, excluding transaction and moving costs | AG41: AVM estimate | AH41: 27 Oct 2026 | AI41: Pass | AJ41: AVM house value ($1,195,044) is under $1.5M cap. Not a sale median.
A42: Hurstbridge | B42: North-East Fringe | C42: Watchlist | D42: High (Bushland village) | E42: Low (Inland) | F42: Smaller bushland village beyond Diamond Creek | G42: 980767 | H42: AVM estimate (30 Sep 2026), NOT a verified sale median; unit $630,315; 44 sales in last 12m (OnTheHouse/Cotality, read 27 Oct 2026) | I42: =G42*(1+Settings!$B$6) | J42: 41 | K42: 29 | L42: Provisional pass | M42: =IF(J42="","",ROUND(MAX(0,10*(1-J42/Filters!$B$4)),1)) | N42: 8 | O42: =IF(K42="","",ROUND(MAX(0,10*(1-K42/Filters!$B$5)),1)) | P42: 1 | Q42: 5 | R42: 8 | S42: 6 | T42: =IF(G42="","",ROUND(MAX(0,MIN(10,10*(Filters!$B$2-G42)/(Filters!$B$2-500000))),1)) | U42: 0 | V42: 5 | W42: =IF(M42="",0,COUNT(M42:V42)) | X42: =IF(W42<10,"",M42*ForcedChoiceCorrections!$B$6+N42*ForcedChoiceCorrections!$B$7+O42*ForcedChoiceCorrections!$B$8+P42*ForcedChoiceCorrections!$B$9+Q42*ForcedChoiceCorrections!$B$10+R42*ForcedChoiceCorrections!$B$11+S42*ForcedChoiceCorrections!$B$12+T42*ForcedChoiceCorrections!$B$13+U42*ForcedChoiceCorrections!$B$14+V42*ForcedChoiceCorrections!$B$15) | Y42: =IF(AND(ISNUMBER(SEARCH("pass",L42)),ISNUMBER(X42)),COUNTIFS(L$2:L$90,"*pass*",X$2:X$90,">"&X42)+1,"") | Z42: Hurstbridge rail terminus; test whether extra distance over Diamond Creek/Eltham adds value. 27 Oct 2026 research pass: drive times/ED and/or AVM price added; L re-evaluated. | SCORES 27 Oct 2026: M (near family) and T (price) are formulas from J and G; O from K. N, P, Q, R, S, U, V are ESTIMATES (Claude, general knowledge, not site-checked); S also rests on train Yes/No marked 'verify'. | AA42: 41. Hurstbridge | North-East Fringe | Watchlist | P: High (Bushland village) | Y: Low (Inland) | Lens: Smaller bushland village beyond Diamond Creek | Price: [Blank] | Basis: Not verified in report | Note: Hurstbridge rail terminus; test whether extra distance over Diamond Creek/Eltham adds value. | AB42: Yes | AC42: Hurstbridge station, Hurstbridge line terminus (recall; verify) | AD42: Northern Hospital Epping ED (24-hr: recall (major metro ED); Austin 32 min) (drive times: Google Maps leave-now, 27 Oct 2026 ~13:15–13:45 AEDT (midday, not peak), suburb name) | AE42: 1500000 | AF42: Maximum purchase price, excluding transaction and moving costs | AG42: AVM estimate | AH42: 27 Oct 2026 | AI42: Pass | AJ42: AVM house value ($980,767) is under $1.5M cap. Not a sale median.
A43: Ballarat | B43: Central Highlands | C43: Watchlist | D43: Medium-High (Lake Wendouree/gardens) | E43: Low (Inland lake) | F43: Major regional city control with Base Hospital ED | G43: 722940 | H43: AVM estimate (30 Sep 2026), NOT a verified sale median; unit $509,096; 269 sales in last 12m (OnTheHouse/Cotality, read 27 Oct 2026) | I43: =G43*(1+Settings!$B$6) | J43: 111 | K43: 3 | L43: Fails: GW drive | O43: =IF(K43="","",ROUND(MAX(0,10*(1-K43/Filters!$B$5)),1)) | W43: =IF(M43="",0,COUNT(M43:V43)) | X43: =IF(W43<10,"",M43*ForcedChoiceCorrections!$B$6+N43*ForcedChoiceCorrections!$B$7+O43*ForcedChoiceCorrections!$B$8+P43*ForcedChoiceCorrections!$B$9+Q43*ForcedChoiceCorrections!$B$10+R43*ForcedChoiceCorrections!$B$11+S43*ForcedChoiceCorrections!$B$12+T43*ForcedChoiceCorrections!$B$13+U43*ForcedChoiceCorrections!$B$14+V43*ForcedChoiceCorrections!$B$15) | Y43: =IF(AND(ISNUMBER(SEARCH("pass",L43)),ISNUMBER(X43)),COUNTIFS(L$2:L$90,"*pass*",X$2:X$90,">"&X43)+1,"") | Z43: Grampians Health Ballarat Base Hospital ED; test only if longer family journey to GW is acceptable. 27 Oct 2026 research pass: drive times/ED and/or AVM price added; L re-evaluated. Ballarat treated as Ballarat Central for price and drive. | AA43: 42. Ballarat | Central Highlands | Watchlist | P: Medium-High (Lake Wendouree/gardens) | Y: Low (Inland lake) | Lens: Major regional city control with Base Hospital ED | Price: [Blank] | Basis: Not verified in report | Note: Grampians Health Ballarat Base Hospital ED; test only if longer family journey to GW is acceptable. | AB43: Yes | AC43: Ballarat station, V/Line Ballarat line (recall; verify) | AD43: Grampians Health Ballarat (Ballarat Base) ED (24-hr: recall (major regional ED). Origin: Ballarat Central) (drive times: Google Maps leave-now, 27 Oct 2026 ~13:15–13:45 AEDT (midday, not peak), suburb name) | AE43: 1500000 | AF43: Maximum purchase price, excluding transaction and moving costs | AG43: AVM estimate | AH43: 27 Oct 2026 | AI43: Pass | AJ43: AVM house value ($722,940) is under $1.5M cap. Not a sale median.
A44: Bendigo | B44: Central Victoria | C44: Watchlist | D44: Medium-High (Rosalind Park/bush) | E44: Low (Inland) | F44: Major regional city control with 24-hr ED | G44: 658696 | H44: AVM estimate (30 Sep 2026), NOT a verified sale median; unit $466,415; 197 sales in last 12m (OnTheHouse/Cotality, read 27 Oct 2026) | I44: =G44*(1+Settings!$B$6) | J44: 140 | K44: 7 | L44: Fails: GW drive | O44: =IF(K44="","",ROUND(MAX(0,10*(1-K44/Filters!$B$5)),1)) | W44: =IF(M44="",0,COUNT(M44:V44)) | X44: =IF(W44<10,"",M44*ForcedChoiceCorrections!$B$6+N44*ForcedChoiceCorrections!$B$7+O44*ForcedChoiceCorrections!$B$8+P44*ForcedChoiceCorrections!$B$9+Q44*ForcedChoiceCorrections!$B$10+R44*ForcedChoiceCorrections!$B$11+S44*ForcedChoiceCorrections!$B$12+T44*ForcedChoiceCorrections!$B$13+U44*ForcedChoiceCorrections!$B$14+V44*ForcedChoiceCorrections!$B$15) | Y44: =IF(AND(ISNUMBER(SEARCH("pass",L44)),ISNUMBER(X44)),COUNTIFS(L$2:L$90,"*pass*",X$2:X$90,">"&X44)+1,"") | Z44: Bendigo Hospital documented 24-hr/365-day ED; test only if regional travel distance is acceptable. 27 Oct 2026 research pass: drive times/ED and/or AVM price added; L re-evaluated. | AA44: 43. Bendigo | Central Victoria | Watchlist | P: Medium-High (Rosalind Park/bush) | Y: Low (Inland) | Lens: Major regional city control with 24-hr ED | Price: [Blank] | Basis: Not verified in report | Note: Bendigo Hospital documented 24-hr/365-day ED; test only if regional travel distance is acceptable. | AB44: Yes | AC44: Bendigo station, V/Line Bendigo line (recall; verify) | AD44: Bendigo Hospital ED (24-hr: recall (major regional ED)) (drive times: Google Maps leave-now, 27 Oct 2026 ~13:15–13:45 AEDT (midday, not peak), suburb name) | AE44: 1500000 | AF44: Maximum purchase price, excluding transaction and moving costs | AG44: AVM estimate | AH44: 27 Oct 2026 | AI44: Pass | AJ44: AVM house value ($658,696) is under $1.5M cap. Not a sale median.
A45: Dromana | B45: Mornington Peninsula | C45: Watchlist | D45: Medium (Arthurs Seat backdrop) | E45: High (Bay beach) | F45: Further-south Peninsula coastal comparator | G45: 906318 | H45: AVM estimate (30 Sep 2026), NOT a verified sale median; unit $705,984 (OnTheHouse/Cotality) | I45: =G45*(1+Settings!$B$6) | J45: 47 | K45: 11 | L45: Provisional pass | M45: =IF(J45="","",ROUND(MAX(0,10*(1-J45/Filters!$B$4)),1)) | N45: 7 | O45: =IF(K45="","",ROUND(MAX(0,10*(1-K45/Filters!$B$5)),1)) | P45: 2 | Q45: 6 | R45: 6 | S45: 2 | T45: =IF(G45="","",ROUND(MAX(0,MIN(10,10*(Filters!$B$2-G45)/(Filters!$B$2-500000))),1)) | U45: 9 | V45: 2 | W45: =IF(M45="",0,COUNT(M45:V45)) | X45: =IF(W45<10,"",M45*ForcedChoiceCorrections!$B$6+N45*ForcedChoiceCorrections!$B$7+O45*ForcedChoiceCorrections!$B$8+P45*ForcedChoiceCorrections!$B$9+Q45*ForcedChoiceCorrections!$B$10+R45*ForcedChoiceCorrections!$B$11+S45*ForcedChoiceCorrections!$B$12+T45*ForcedChoiceCorrections!$B$13+U45*ForcedChoiceCorrections!$B$14+V45*ForcedChoiceCorrections!$B$15) | Y45: =IF(AND(ISNUMBER(SEARCH("pass",L45)),ISNUMBER(X45)),COUNTIFS(L$2:L$90,"*pass*",X$2:X$90,">"&X45)+1,"") | Z45: Compare Rosebud vs Frankston ED access and year-round vs holiday-town feel. 27 Oct 2026: drive times, ED and AVM price added. ED: Rosebud ED is 24/7 but treats less serious cases; serious cases transfer to Frankston (Peninsula Health). | SCORES 27 Oct 2026: M (near family) and T (price) are formulas from J and G; O from K. N, P, Q, R, S, U, V are ESTIMATES (Claude, general knowledge, not site-checked); S also rests on train Yes/No marked 'verify'. | AA45: 44. Dromana | Mornington Peninsula | Watchlist | P: Medium (Arthurs Seat backdrop) | Y: High (Bay beach) | Lens: Further-south Peninsula coastal comparator | Price: [Blank] | Basis: Not verified in report | Note: Compare Rosebud vs Frankston ED access and year-round vs holiday-town feel. | AB45: No | AC45: No passenger rail on the Peninsula south of Frankston (recall; verify) | AD45: Rosebud Hospital ED (drive times: Google Maps leave-now 27 Oct 2026, suburb name not postcode, not peak) | AE45: 1500000 | AF45: Maximum purchase price, excluding transaction and moving costs | AG45: AVM estimate | AH45: 27 Oct 2026 | AI45: Pass | AJ45: AVM house value ($906,318) is under $1.5M cap. Not a sale median.
A46: Castlemaine | B46: Central Victoria | C46: Watchlist | D46: High (Box-Ironbark bush/arts) | E46: Low (Inland) | F46: Historic country town on Bendigo V/Line | G46: 747758 | H46: AVM estimate (30 Sep 2026), NOT a verified sale median; unit $531,635; 188 sales in last 12m (OnTheHouse/Cotality, read 27 Oct 2026) | I46: =G46*(1+Settings!$B$6) | J46: 114 | K46: 36 | L46: Fails: GW drive | O46: =IF(K46="","",ROUND(MAX(0,10*(1-K46/Filters!$B$5)),1)) | W46: =IF(M46="",0,COUNT(M46:V46)) | X46: =IF(W46<10,"",M46*ForcedChoiceCorrections!$B$6+N46*ForcedChoiceCorrections!$B$7+O46*ForcedChoiceCorrections!$B$8+P46*ForcedChoiceCorrections!$B$9+Q46*ForcedChoiceCorrections!$B$10+R46*ForcedChoiceCorrections!$B$11+S46*ForcedChoiceCorrections!$B$12+T46*ForcedChoiceCorrections!$B$13+U46*ForcedChoiceCorrections!$B$14+V46*ForcedChoiceCorrections!$B$15) | Y46: =IF(AND(ISNUMBER(SEARCH("pass",L46)),ISNUMBER(X46)),COUNTIFS(L$2:L$90,"*pass*",X$2:X$90,">"&X46)+1,"") | Z46: Do not assume local health service equals a major 24-hr ED; Bendigo ED is reference point. 27 Oct 2026 research pass: drive times/ED and/or AVM price added; L re-evaluated. | AA46: 45. Castlemaine | Central Victoria | Watchlist | P: High (Box-Ironbark bush/arts) | Y: Low (Inland) | Lens: Historic country town on Bendigo V/Line | Price: [Blank] | Basis: Not verified in report | Note: Do not assume local health service equals a major 24-hr ED; Bendigo ED is reference point. | AB46: Yes | AC46: Castlemaine station, V/Line Bendigo line (recall; verify) | AD46: Bendigo Hospital ED (24-hr: recall (major regional ED); local Castlemaine Health not treated as ED. Origin: Castlemaine Town Hall) (drive times: Google Maps leave-now, 27 Oct 2026 ~13:15–13:45 AEDT (midday, not peak), suburb name) | AE46: 1500000 | AF46: Maximum purchase price, excluding transaction and moving costs | AG46: AVM estimate | AH46: 27 Oct 2026 | AI46: Pass | AJ46: AVM house value ($747,758) is under $1.5M cap. Not a sale median.
A47: Wonthaggi | B47: Bass Coast | C47: Watchlist | D47: Medium (Coastal hinterland) | E47: High (Near Bass Coast) | F47: Coastal Gippsland service-centre comparator | G47: 587666 | H47: AVM estimate (30 Sep 2026), NOT a verified sale median; unit $427,703; 206 sales in last 12m (OnTheHouse/Cotality, read 27 Oct 2026) | I47: =G47*(1+Settings!$B$6) | J47: 88 | K47: 3 | L47: Provisional pass | M47: =IF(J47="","",ROUND(MAX(0,10*(1-J47/Filters!$B$4)),1)) | N47: 6 | O47: =IF(K47="","",ROUND(MAX(0,10*(1-K47/Filters!$B$5)),1)) | P47: 1 | Q47: 7 | R47: 5 | S47: 1 | T47: =IF(G47="","",ROUND(MAX(0,MIN(10,10*(Filters!$B$2-G47)/(Filters!$B$2-500000))),1)) | U47: 6 | V47: 1 | W47: =IF(M47="",0,COUNT(M47:V47)) | X47: =IF(W47<10,"",M47*ForcedChoiceCorrections!$B$6+N47*ForcedChoiceCorrections!$B$7+O47*ForcedChoiceCorrections!$B$8+P47*ForcedChoiceCorrections!$B$9+Q47*ForcedChoiceCorrections!$B$10+R47*ForcedChoiceCorrections!$B$11+S47*ForcedChoiceCorrections!$B$12+T47*ForcedChoiceCorrections!$B$13+U47*ForcedChoiceCorrections!$B$14+V47*ForcedChoiceCorrections!$B$15) | Y47: =IF(AND(ISNUMBER(SEARCH("pass",L47)),ISNUMBER(X47)),COUNTIFS(L$2:L$90,"*pass*",X$2:X$90,">"&X47)+1,"") | Z47: Bass Coast Health Wonthaggi Hospital; verify ED capability & GW travel time before promoting. 27 Oct 2026 research pass: drive times/ED and/or AVM price added; L re-evaluated. | SCORES 27 Oct 2026: M (near family) and T (price) are formulas from J and G; O from K. N, P, Q, R, S, U, V are ESTIMATES (Claude, general knowledge, not site-checked); S also rests on train Yes/No marked 'verify'. GW drive 88 min, 2 min under cap. | AA47: 46. Wonthaggi | Bass Coast | Watchlist | P: Medium (Coastal hinterland) | Y: High (Near Bass Coast) | Lens: Coastal Gippsland service-centre comparator | Price: [Blank] | Basis: Not verified in report | Note: Bass Coast Health Wonthaggi Hospital; verify ED capability & GW travel time before promoting. | AB47: No | AC47: No passenger rail (recall; verify) | AD47: Wonthaggi Hospital ED (24-hr: verified, healthdirect) (drive times: Google Maps leave-now, 27 Oct 2026 ~13:15–13:45 AEDT (midday, not peak), suburb name) | AE47: 1500000 | AF47: Maximum purchase price, excluding transaction and moving costs | AG47: AVM estimate | AH47: 27 Oct 2026 | AI47: Pass | AJ47: AVM house value ($587,666) is under $1.5M cap. Not a sale median.
A48: Inverloch | B48: Bass Coast | C48: Watchlist | D48: Medium (Screw Creek/foreshore) | E48: High (Inlet & surf beach) | F48: Coastal Gippsland lifestyle counterpart to Wonthaggi | G48: 823858 | H48: AVM estimate (30 Sep 2026), NOT a verified sale median; unit $523,497; 199 sales in last 12m (OnTheHouse/Cotality, read 27 Oct 2026) | I48: =G48*(1+Settings!$B$6) | J48: 96 | K48: 15 | L48: Fails: GW drive | O48: =IF(K48="","",ROUND(MAX(0,10*(1-K48/Filters!$B$5)),1)) | W48: =IF(M48="",0,COUNT(M48:V48)) | X48: =IF(W48<10,"",M48*ForcedChoiceCorrections!$B$6+N48*ForcedChoiceCorrections!$B$7+O48*ForcedChoiceCorrections!$B$8+P48*ForcedChoiceCorrections!$B$9+Q48*ForcedChoiceCorrections!$B$10+R48*ForcedChoiceCorrections!$B$11+S48*ForcedChoiceCorrections!$B$12+T48*ForcedChoiceCorrections!$B$13+U48*ForcedChoiceCorrections!$B$14+V48*ForcedChoiceCorrections!$B$15) | Y48: =IF(AND(ISNUMBER(SEARCH("pass",L48)),ISNUMBER(X48)),COUNTIFS(L$2:L$90,"*pass*",X$2:X$90,">"&X48)+1,"") | Z48: Shared pathway & inlet walks; no passenger rail; verify Wonthaggi/Latrobe ED drive. 27 Oct 2026 research pass: drive times/ED and/or AVM price added; L re-evaluated. | AA48: 47. Inverloch | Bass Coast | Watchlist | P: Medium (Screw Creek/foreshore) | Y: High (Inlet & surf beach) | Lens: Coastal Gippsland lifestyle counterpart to Wonthaggi | Price: [Blank] | Basis: Not verified in report | Note: Shared pathway & inlet walks; no passenger rail; verify Wonthaggi/Latrobe ED drive. | AB48: No | AC48: No passenger rail (recall; verify) | AD48: Wonthaggi Hospital ED (24-hr: verified, healthdirect) (drive times: Google Maps leave-now, 27 Oct 2026 ~13:15–13:45 AEDT (midday, not peak), suburb name) | AE48: 1500000 | AF48: Maximum purchase price, excluding transaction and moving costs | AG48: AVM estimate | AH48: 27 Oct 2026 | AI48: Pass | AJ48: AVM house value ($823,858) is under $1.5M cap. Not a sale median.
A49: [SYNTHETIC TEST — Ringwood Leafy Pocket] | B49: East Melbourne | C49: Synthetic Test | D49: Medium-High | E49: Low | F49: Synthetic test row verifying Pass & Rank math | G49: 1045000 | H49: Synthetic test row (clear before live use) | I49: 1107700 | J49: 18 | K49: 12 | L49: Excluded: test row | M49: 7 | N49: 8 | O49: 7 | P49: 2 | Q49: 9 | R49: 9 | S49: 8 | T49: 6 | U49: 8 | V49: 8 | W49: =IF(M49="",0,COUNT(M49:V49)) | X49: =IF(W49<10,"",M49*ForcedChoiceCorrections!$B$6+N49*ForcedChoiceCorrections!$B$7+O49*ForcedChoiceCorrections!$B$8+P49*ForcedChoiceCorrections!$B$9+Q49*ForcedChoiceCorrections!$B$10+R49*ForcedChoiceCorrections!$B$11+S49*ForcedChoiceCorrections!$B$12+T49*ForcedChoiceCorrections!$B$13+U49*ForcedChoiceCorrections!$B$14+V49*ForcedChoiceCorrections!$B$15) | Y49: =IF(AND(ISNUMBER(SEARCH("pass",L49)),ISNUMBER(X49)),COUNTIFS(L$2:L$90,"*pass*",X$2:X$90,">"&X49)+1,"") | Z49: [SYNTHETIC TEST] Demonstrates 'Pass' & Rank #1 when drive times & 0-10 scores are entered. | AA49: 48. [SYNTHETIC TEST — Ringwood Leafy Pocket] | East Melbourne | Synthetic Test | P: Medium-High | Y: Low | Lens: Synthetic test row verifying Pass & Rank math | Price: 1045000 | Basis: Synthetic test row (clear before live use) | Note: [SYNTHETIC TEST] Demonstrates 'Pass' & Rank #1 when drive times & 0-10 scores are entered. | AE49: 1500000 | AF49: Maximum purchase price, excluding transaction and moving costs | AG49: Benchmark synthetic price | AH49: 26 Oct 2026 | AI49: Pass | AJ49: Synthetic test calibration model.
A50: [SYNTHETIC TEST — Ocean Grove Woodland Pocket] | B50: Bellarine Peninsula | C50: Synthetic Test | D50: Medium-High | E50: High | F50: Synthetic test row verifying coastal vs GW filter | G50: 980000 | H50: Synthetic test row (clear before live use) | I50: 1038800 | J50: 24 | K50: 19 | L50: Excluded: test row | M50: 9 | N50: 5 | O50: 4 | P50: 10 | Q50: 7 | R50: 5 | S50: 7 | T50: 8 | U50: 9 | V50: 5 | W50: =IF(M50="",0,COUNT(M50:V50)) | X50: =IF(W50<10,"",M50*ForcedChoiceCorrections!$B$6+N50*ForcedChoiceCorrections!$B$7+O50*ForcedChoiceCorrections!$B$8+P50*ForcedChoiceCorrections!$B$9+Q50*ForcedChoiceCorrections!$B$10+R50*ForcedChoiceCorrections!$B$11+S50*ForcedChoiceCorrections!$B$12+T50*ForcedChoiceCorrections!$B$13+U50*ForcedChoiceCorrections!$B$14+V50*ForcedChoiceCorrections!$B$15) | Y50: =IF(AND(ISNUMBER(SEARCH("pass",L50)),ISNUMBER(X50)),COUNTIFS(L$2:L$90,"*pass*",X$2:X$90,">"&X50)+1,"") | Z50: [SYNTHETIC TEST] Demonstrates 'Pass' & Rank #2 under 25-min GW / 20-min ED test limits. | AA50: 49. [SYNTHETIC TEST — Ocean Grove Woodland Pocket] | Bellarine Peninsula | Synthetic Test | P: Medium-High | Y: High | Lens: Synthetic test row verifying coastal vs GW filter | Price: 980000 | Basis: Synthetic test row (clear before live use) | Note: [SYNTHETIC TEST] Demonstrates 'Pass' & Rank #2 under 25-min GW / 20-min ED test limits. | AE50: 1500000 | AF50: Maximum purchase price, excluding transaction and moving costs | AG50: Benchmark synthetic price | AH50: 26 Oct 2026 | AI50: Pass | AJ50: Synthetic test calibration model.
A51: Rosebud | B51: Mornington Peninsula | C51: Open-mind viewing | D51: Low-Medium (Coastal) | E51: High (Bay beach) | F51: Open-mind viewing: calibrate coastal feel against bush | G51: 753965 | H51: AVM estimate (30 Sep 2026), NOT a verified sale median; unit $667,803; 426 sales in last 12m (OnTheHouse/Cotality, read 27 Oct 2026) | I51: =G51*(1+Settings!$B$6) | J51: 49 | K51: 3 | L51: Provisional pass | M51: =IF(J51="","",ROUND(MAX(0,10*(1-J51/Filters!$B$4)),1)) | N51: 6 | O51: =IF(K51="","",ROUND(MAX(0,10*(1-K51/Filters!$B$5)),1)) | P51: 2 | Q51: 8 | R51: 4 | S51: 2 | T51: =IF(G51="","",ROUND(MAX(0,MIN(10,10*(Filters!$B$2-G51)/(Filters!$B$2-500000))),1)) | U51: 9 | V51: 2 | W51: =IF(M51="",0,COUNT(M51:V51)) | X51: =IF(W51<10,"",M51*ForcedChoiceCorrections!$B$6+N51*ForcedChoiceCorrections!$B$7+O51*ForcedChoiceCorrections!$B$8+P51*ForcedChoiceCorrections!$B$9+Q51*ForcedChoiceCorrections!$B$10+R51*ForcedChoiceCorrections!$B$11+S51*ForcedChoiceCorrections!$B$12+T51*ForcedChoiceCorrections!$B$13+U51*ForcedChoiceCorrections!$B$14+V51*ForcedChoiceCorrections!$B$15) | Y51: =IF(AND(ISNUMBER(SEARCH("pass",L51)),ISNUMBER(X51)),COUNTIFS(L$2:L$90,"*pass*",X$2:X$90,">"&X51)+1,"") | Z51: OPEN-MIND VIEWING PICK (nominated by NJD): view for calibration. Verify year-round services vs holiday-town feel, local ED status and drive to a 24-hr public ED, GW drive and price. 27 Oct 2026 research pass: drive times/ED and/or AVM price added; L re-evaluated. | SCORES 27 Oct 2026: M (near family) and T (price) are formulas from J and G; O from K. N, P, Q, R, S, U, V are ESTIMATES (Claude, general knowledge, not site-checked); S also rests on train Yes/No marked 'verify'. | AA51: 50. Rosebud | Mornington Peninsula | Open-mind viewing | P: Low-Medium (Coastal) | Y: High (Bay beach) | Lens: Open-mind viewing: calibrate coastal feel against bush | Price: [Blank] | Basis: Not verified | Note: OPEN-MIND VIEWING PICK (nominated by NJD): view for calibration. Verify year-round services vs holiday-town feel, local ED status and drive to a 24-hr public ED, GW drive and price. | AB51: No | AC51: No passenger rail on the Peninsula south of Frankston (from recall; verify) | AD51: Rosebud Hospital ED (24/7 but treats less serious cases (per earlier check); Peninsula University Hospital 27 min) (drive times: Google Maps leave-now, 27 Oct 2026 ~13:15–13:45 AEDT (midday, not peak), suburb name) | AE51: 1500000 | AF51: Maximum purchase price, excluding transaction and moving costs | AG51: AVM estimate | AH51: 27 Oct 2026 | AI51: Pass | AJ51: AVM house value ($753,965) is under $1.5M cap. Not a sale median.
A52: Rye | B52: Mornington Peninsula | C52: Open-mind viewing | D52: Low-Medium (Coastal) | E52: High (Bay/ocean beach) | F52: Open-mind viewing: calibrate coastal feel against bush | G52: 918392 | H52: AVM estimate (30 Sep 2026), NOT a verified sale median; unit $639,145; 300 sales in last 12m (OnTheHouse/Cotality, read 27 Oct 2026) | I52: =G52*(1+Settings!$B$6) | J52: 61 | K52: 9 | L52: Provisional pass | M52: =IF(J52="","",ROUND(MAX(0,10*(1-J52/Filters!$B$4)),1)) | N52: 7 | O52: =IF(K52="","",ROUND(MAX(0,10*(1-K52/Filters!$B$5)),1)) | P52: 1 | Q52: 6 | R52: 7 | S52: 2 | T52: =IF(G52="","",ROUND(MAX(0,MIN(10,10*(Filters!$B$2-G52)/(Filters!$B$2-500000))),1)) | U52: 10 | V52: 1 | W52: =IF(M52="",0,COUNT(M52:V52)) | X52: =IF(W52<10,"",M52*ForcedChoiceCorrections!$B$6+N52*ForcedChoiceCorrections!$B$7+O52*ForcedChoiceCorrections!$B$8+P52*ForcedChoiceCorrections!$B$9+Q52*ForcedChoiceCorrections!$B$10+R52*ForcedChoiceCorrections!$B$11+S52*ForcedChoiceCorrections!$B$12+T52*ForcedChoiceCorrections!$B$13+U52*ForcedChoiceCorrections!$B$14+V52*ForcedChoiceCorrections!$B$15) | Y52: =IF(AND(ISNUMBER(SEARCH("pass",L52)),ISNUMBER(X52)),COUNTIFS(L$2:L$90,"*pass*",X$2:X$90,">"&X52)+1,"") | Z52: OPEN-MIND VIEWING PICK (nominated by NJD): view for calibration. Verify year-round services vs holiday-town feel, ED access (nearest 24-hr public ED likely Frankston/Peninsula Univ Hospital), GW drive and price. 27 Oct 2026 research pass: drive times/ED and/or AVM price added; L re-evaluated. | SCORES 27 Oct 2026: M (near family) and T (price) are formulas from J and G; O from K. N, P, Q, R, S, U, V are ESTIMATES (Claude, general knowledge, not site-checked); S also rests on train Yes/No marked 'verify'. | AA52: 51. Rye | Mornington Peninsula | Open-mind viewing | P: Low-Medium (Coastal) | Y: High (Bay/ocean beach) | Lens: Open-mind viewing: calibrate coastal feel against bush | Price: [Blank] | Basis: Not verified | Note: OPEN-MIND VIEWING PICK (nominated by NJD): view for calibration. Verify year-round services vs holiday-town feel, ED access (nearest 24-hr public ED likely Frankston/Peninsula Univ Hospital), GW drive and price. | AB52: No | AC52: No passenger rail on the Peninsula south of Frankston (from recall; verify) | AD52: Rosebud Hospital ED (24/7 but treats less serious cases (per earlier check)) (drive times: Google Maps leave-now, 27 Oct 2026 ~13:15–13:45 AEDT (midday, not peak), suburb name) | AE52: 1500000 | AF52: Maximum purchase price, excluding transaction and moving costs | AG52: AVM estimate | AH52: 27 Oct 2026 | AI52: Pass | AJ52: AVM house value ($918,392) is under $1.5M cap. Not a sale median.
A53: Gisborne | B53: Macedon Ranges | C53: Watchlist | D53: Medium-High (Rural/gardens) | E53: Low (Inland) | F53: Regional town close to Melbourne, distinct from Woodend and Macedon | G53: 1043843 | H53: AVM estimate (30 Sep 2026), NOT a verified sale median; unit $589,444; 281 sales in last 12m (OnTheHouse/Cotality, read 27 Oct 2026) | I53: =G53*(1+Settings!$B$6) | J53: 67 | K53: 34 | L53: Provisional pass | M53: =IF(J53="","",ROUND(MAX(0,10*(1-J53/Filters!$B$4)),1)) | N53: 7 | O53: =IF(K53="","",ROUND(MAX(0,10*(1-K53/Filters!$B$5)),1)) | P53: 2 | Q53: 7 | R53: 7 | S53: 4 | T53: =IF(G53="","",ROUND(MAX(0,MIN(10,10*(Filters!$B$2-G53)/(Filters!$B$2-500000))),1)) | U53: 0 | V53: 5 | W53: =IF(M53="",0,COUNT(M53:V53)) | X53: =IF(W53<10,"",M53*ForcedChoiceCorrections!$B$6+N53*ForcedChoiceCorrections!$B$7+O53*ForcedChoiceCorrections!$B$8+P53*ForcedChoiceCorrections!$B$9+Q53*ForcedChoiceCorrections!$B$10+R53*ForcedChoiceCorrections!$B$11+S53*ForcedChoiceCorrections!$B$12+T53*ForcedChoiceCorrections!$B$13+U53*ForcedChoiceCorrections!$B$14+V53*ForcedChoiceCorrections!$B$15) | Y53: =IF(AND(ISNUMBER(SEARCH("pass",L53)),ISNUMBER(X53)),COUNTIFS(L$2:L$90,"*pass*",X$2:X$90,">"&X53)+1,"") | Z53: Regional add (within about 1.5 hrs of Melbourne, from recall; verify). Verify train access (nearest V/Line may be Riddells Creek), GW drive, price and nearest major public ED. 27 Oct 2026 research pass: drive times/ED and/or AVM price added; L re-evaluated. | SCORES 27 Oct 2026: M (near family) and T (price) are formulas from J and G; O from K. N, P, Q, R, S, U, V are ESTIMATES (Claude, general knowledge, not site-checked); S also rests on train Yes/No marked 'verify'. | AA53: 52. Gisborne | Macedon Ranges | Watchlist | P: Medium-High (Rural/gardens) | Y: Low (Inland) | Lens: Regional town close to Melbourne, distinct from Woodend and Macedon | Price: [Blank] | Basis: Not verified | Note: Regional add (within about 1.5 hrs of Melbourne, from recall; verify). Verify train access (nearest V/Line may be Riddells Creek), GW drive, price and nearest major public ED. | AB53: Yes | AC53: Gisborne station (in New Gisborne, ~3 km), V/Line Bendigo line (recall; verify) | AD53: Sunshine Hospital ED (24-hr: recall (major metro ED). Origin: Gisborne Post Office (suburb pin gave a 2h+ route)) (drive times: Google Maps leave-now, 27 Oct 2026 ~13:15–13:45 AEDT (midday, not peak), suburb name) | AE53: 1500000 | AF53: Maximum purchase price, excluding transaction and moving costs | AG53: AVM estimate | AH53: 27 Oct 2026 | AI53: Pass | AJ53: AVM house value ($1,043,843) is under $1.5M cap. Not a sale median.
A54: Riddells Creek | B54: Macedon Ranges | C54: Watchlist | D54: Medium-High (Village/countryside) | E54: Low (Inland) | F54: Small village with V/Line access (to verify) | G54: 994380 | H54: AVM estimate (30 Sep 2026), NOT a verified sale median; unit $647,157; 85 sales in last 12m (OnTheHouse/Cotality, read 27 Oct 2026) | I54: =G54*(1+Settings!$B$6) | J54: 71 | K54: 38 | L54: Provisional pass | M54: =IF(J54="","",ROUND(MAX(0,10*(1-J54/Filters!$B$4)),1)) | N54: 7 | O54: =IF(K54="","",ROUND(MAX(0,10*(1-K54/Filters!$B$5)),1)) | P54: 2 | Q54: 4 | R54: 7 | S54: 5 | T54: =IF(G54="","",ROUND(MAX(0,MIN(10,10*(Filters!$B$2-G54)/(Filters!$B$2-500000))),1)) | U54: 0 | V54: 5 | W54: =IF(M54="",0,COUNT(M54:V54)) | X54: =IF(W54<10,"",M54*ForcedChoiceCorrections!$B$6+N54*ForcedChoiceCorrections!$B$7+O54*ForcedChoiceCorrections!$B$8+P54*ForcedChoiceCorrections!$B$9+Q54*ForcedChoiceCorrections!$B$10+R54*ForcedChoiceCorrections!$B$11+S54*ForcedChoiceCorrections!$B$12+T54*ForcedChoiceCorrections!$B$13+U54*ForcedChoiceCorrections!$B$14+V54*ForcedChoiceCorrections!$B$15) | Y54: =IF(AND(ISNUMBER(SEARCH("pass",L54)),ISNUMBER(X54)),COUNTIFS(L$2:L$90,"*pass*",X$2:X$90,">"&X54)+1,"") | Z54: Regional add (within about 1.5 hrs of Melbourne, from recall; verify). Verify V/Line station and service frequency, GW drive, price and nearest major public ED. 27 Oct 2026 research pass: drive times/ED and/or AVM price added; L re-evaluated. | SCORES 27 Oct 2026: M (near family) and T (price) are formulas from J and G; O from K. N, P, Q, R, S, U, V are ESTIMATES (Claude, general knowledge, not site-checked); S also rests on train Yes/No marked 'verify'. | AA54: 53. Riddells Creek | Macedon Ranges | Watchlist | P: Medium-High (Village/countryside) | Y: Low (Inland) | Lens: Small village with V/Line access (to verify) | Price: [Blank] | Basis: Not verified | Note: Regional add (within about 1.5 hrs of Melbourne, from recall; verify). Verify V/Line station and service frequency, GW drive, price and nearest major public ED. | AB54: Yes | AC54: Riddells Creek station, V/Line Bendigo line (recall; verify) | AD54: Sunshine Hospital ED (24-hr: recall (major metro ED); Northern 45 min) (drive times: Google Maps leave-now, 27 Oct 2026 ~13:15–13:45 AEDT (midday, not peak), suburb name) | AE54: 1500000 | AF54: Maximum purchase price, excluding transaction and moving costs | AG54: AVM estimate | AH54: 27 Oct 2026 | AI54: Pass | AJ54: AVM house value ($994,380) is under $1.5M cap. Not a sale median.
A55: Yarra Glen | B55: Yarra Valley | C55: Watchlist | D55: High (Valley/vineyards) | E55: Low (Inland) | F55: Yarra Valley village, quieter than Healesville | G55: 936458 | H55: AVM estimate (30 Sep 2026), NOT a verified sale median; unit $668,777; 48 sales in last 12m (OnTheHouse/Cotality, read 27 Oct 2026) | I55: =G55*(1+Settings!$B$6) | J55: 44 | K55: 30 | L55: Provisional pass | M55: =IF(J55="","",ROUND(MAX(0,10*(1-J55/Filters!$B$4)),1)) | N55: 8 | O55: =IF(K55="","",ROUND(MAX(0,10*(1-K55/Filters!$B$5)),1)) | P55: 1 | Q55: 5 | R55: 7 | S55: 1 | T55: =IF(G55="","",ROUND(MAX(0,MIN(10,10*(Filters!$B$2-G55)/(Filters!$B$2-500000))),1)) | U55: 0 | V55: 2 | W55: =IF(M55="",0,COUNT(M55:V55)) | X55: =IF(W55<10,"",M55*ForcedChoiceCorrections!$B$6+N55*ForcedChoiceCorrections!$B$7+O55*ForcedChoiceCorrections!$B$8+P55*ForcedChoiceCorrections!$B$9+Q55*ForcedChoiceCorrections!$B$10+R55*ForcedChoiceCorrections!$B$11+S55*ForcedChoiceCorrections!$B$12+T55*ForcedChoiceCorrections!$B$13+U55*ForcedChoiceCorrections!$B$14+V55*ForcedChoiceCorrections!$B$15) | Y55: =IF(AND(ISNUMBER(SEARCH("pass",L55)),ISNUMBER(X55)),COUNTIFS(L$2:L$90,"*pass*",X$2:X$90,">"&X55)+1,"") | Z55: Regional add (within about 1.5 hrs of Melbourne, from recall; verify). Likely no train; verify GW drive, price and ED journey (Maroondah/Angliss). Compare with Healesville. 27 Oct 2026 research pass: drive times/ED and/or AVM price added; L re-evaluated. | SCORES 27 Oct 2026: M (near family) and T (price) are formulas from J and G; O from K. N, P, Q, R, S, U, V are ESTIMATES (Claude, general knowledge, not site-checked); S also rests on train Yes/No marked 'verify'. | AA55: 54. Yarra Glen | Yarra Valley | Watchlist | P: High (Valley/vineyards) | Y: Low (Inland) | Lens: Yarra Valley village, quieter than Healesville | Price: [Blank] | Basis: Not verified | Note: Regional add (within about 1.5 hrs of Melbourne, from recall; verify). Likely no train; verify GW drive, price and ED journey (Maroondah/Angliss). Compare with Healesville. | AB55: No | AC55: No passenger rail (recall; verify) | AD55: Maroondah Hospital ED (24-hr: recall (major metro ED)) (drive times: Google Maps leave-now, 27 Oct 2026 ~13:15–13:45 AEDT (midday, not peak), suburb name) | AE55: 1500000 | AF55: Maximum purchase price, excluding transaction and moving costs | AG55: AVM estimate | AH55: 27 Oct 2026 | AI55: Pass | AJ55: AVM house value ($936,458) is under $1.5M cap. Not a sale median.
A56: Drouin | B56: West Gippsland | C56: Watchlist | D56: Medium-High (Hills/gardens) | E56: Low (Inland) | F56: Gippsland-corridor town alongside Warragul | G56: 701797 | H56: AVM estimate (30 Sep 2026), NOT a verified sale median; unit $456,821; 549 sales in last 12m (OnTheHouse/Cotality, read 27 Oct 2026) | I56: =G56*(1+Settings!$B$6) | J56: 57 | K56: 9 | L56: Provisional pass | M56: =IF(J56="","",ROUND(MAX(0,10*(1-J56/Filters!$B$4)),1)) | N56: 5 | O56: =IF(K56="","",ROUND(MAX(0,10*(1-K56/Filters!$B$5)),1)) | P56: 2 | Q56: 7 | R56: 6 | S56: 5 | T56: =IF(G56="","",ROUND(MAX(0,MIN(10,10*(Filters!$B$2-G56)/(Filters!$B$2-500000))),1)) | U56: 0 | V56: 4 | W56: =IF(M56="",0,COUNT(M56:V56)) | X56: =IF(W56<10,"",M56*ForcedChoiceCorrections!$B$6+N56*ForcedChoiceCorrections!$B$7+O56*ForcedChoiceCorrections!$B$8+P56*ForcedChoiceCorrections!$B$9+Q56*ForcedChoiceCorrections!$B$10+R56*ForcedChoiceCorrections!$B$11+S56*ForcedChoiceCorrections!$B$12+T56*ForcedChoiceCorrections!$B$13+U56*ForcedChoiceCorrections!$B$14+V56*ForcedChoiceCorrections!$B$15) | Y56: =IF(AND(ISNUMBER(SEARCH("pass",L56)),ISNUMBER(X56)),COUNTIFS(L$2:L$90,"*pass*",X$2:X$90,">"&X56)+1,"") | Z56: Regional add (within about 1.5 hrs of Melbourne, from recall; verify). Verify V/Line station, GW drive, price and ED access (West Gippsland Hospital at Warragul). Compare with Warragul. 27 Oct 2026 research pass: drive times/ED and/or AVM price added; L re-evaluated. | SCORES 27 Oct 2026: M (near family) and T (price) are formulas from J and G; O from K. N, P, Q, R, S, U, V are ESTIMATES (Claude, general knowledge, not site-checked); S also rests on train Yes/No marked 'verify'. | AA56: 55. Drouin | West Gippsland | Watchlist | P: Medium-High (Hills/gardens) | Y: Low (Inland) | Lens: Gippsland-corridor town alongside Warragul | Price: [Blank] | Basis: Not verified | Note: Regional add (within about 1.5 hrs of Melbourne, from recall; verify). Verify V/Line station, GW drive, price and ED access (West Gippsland Hospital at Warragul). Compare with Warragul. | AB56: Yes | AC56: Drouin station, V/Line Gippsland line (recall; verify) | AD56: West Gippsland Hospital ED (Warragul) (24-hr: verified, South Gippsland Shire directory) (drive times: Google Maps leave-now, 27 Oct 2026 ~13:15–13:45 AEDT (midday, not peak), suburb name) | AE56: 1500000 | AF56: Maximum purchase price, excluding transaction and moving costs | AG56: AVM estimate | AH56: 27 Oct 2026 | AI56: Pass | AJ56: AVM house value ($701,797) is under $1.5M cap. Not a sale median.
A57: West Footscray | B57: West | C57: Watchlist | D57: Not assessed | E57: Not assessed | F57: Not assessed | G57: 1046286 | H57: AVM estimate (30 Jun 2026), NOT a verified sale median; unit $520,983 (OnTheHouse/Cotality) | I57: =G57*(1+Settings!$B$6) | J57: 39 | K57: 6 | L57: Provisional pass | M57: =IF(J57="","",ROUND(MAX(0,10*(1-J57/Filters!$B$4)),1)) | N57: 2 | O57: =IF(K57="","",ROUND(MAX(0,10*(1-K57/Filters!$B$5)),1)) | P57: 8 | Q57: 8 | R57: 5 | S57: 8 | T57: =IF(G57="","",ROUND(MAX(0,MIN(10,10*(Filters!$B$2-G57)/(Filters!$B$2-500000))),1)) | U57: 2 | V57: 9 | W57: =IF(M57="",0,COUNT(M57:V57)) | X57: =IF(W57<10,"",M57*ForcedChoiceCorrections!$B$6+N57*ForcedChoiceCorrections!$B$7+O57*ForcedChoiceCorrections!$B$8+P57*ForcedChoiceCorrections!$B$9+Q57*ForcedChoiceCorrections!$B$10+R57*ForcedChoiceCorrections!$B$11+S57*ForcedChoiceCorrections!$B$12+T57*ForcedChoiceCorrections!$B$13+U57*ForcedChoiceCorrections!$B$14+V57*ForcedChoiceCorrections!$B$15) | Y57: =IF(AND(ISNUMBER(SEARCH("pass",L57)),ISNUMBER(X57)),COUNTIFS(L$2:L$90,"*pass*",X$2:X$90,">"&X57)+1,"") | Z57: Added 27 Oct 2026 from realestate.com.au collection "Parents." (Listings tab). Fit ratings (P/Y/lens) not yet assessed. ED: Western Health: ED "always open". | SCORES 27 Oct 2026: M (near family) and T (price) are formulas from J and G; O from K. N, P, Q, R, S, U, V are ESTIMATES (Claude, general knowledge, not site-checked); S also rests on train Yes/No marked 'verify'. | AB57: Yes | AC57: West Footscray station, Sunbury line (recall; verify) | AD57: Footscray Hospital ED (new hospital, opened Feb 2026) (drive times: Google Maps leave-now 27 Oct 2026, suburb name not postcode, not peak) | AE57: 1500000 | AF57: Maximum purchase price, excluding transaction and moving costs | AG57: AVM estimate | AH57: 27 Oct 2026 | AI57: Pass | AJ57: AVM house value ($1,046,286) is under $1.5M cap. Not a sale median.
A58: Rosanna | B58: North-East | C58: Watchlist | D58: Not assessed | E58: Not assessed | F58: Not assessed | G58: 1242201 | H58: AVM estimate (31 Aug 2026), NOT a verified sale median; unit $755,384 (OnTheHouse/Cotality) | I58: =G58*(1+Settings!$B$6) | J58: 34 | K58: 8 | L58: Provisional pass | M58: =IF(J58="","",ROUND(MAX(0,10*(1-J58/Filters!$B$4)),1)) | N58: 6 | O58: =IF(K58="","",ROUND(MAX(0,10*(1-K58/Filters!$B$5)),1)) | P58: 4 | Q58: 7 | R58: 6 | S58: 8 | T58: =IF(G58="","",ROUND(MAX(0,MIN(10,10*(Filters!$B$2-G58)/(Filters!$B$2-500000))),1)) | U58: 0 | V58: 8 | W58: =IF(M58="",0,COUNT(M58:V58)) | X58: =IF(W58<10,"",M58*ForcedChoiceCorrections!$B$6+N58*ForcedChoiceCorrections!$B$7+O58*ForcedChoiceCorrections!$B$8+P58*ForcedChoiceCorrections!$B$9+Q58*ForcedChoiceCorrections!$B$10+R58*ForcedChoiceCorrections!$B$11+S58*ForcedChoiceCorrections!$B$12+T58*ForcedChoiceCorrections!$B$13+U58*ForcedChoiceCorrections!$B$14+V58*ForcedChoiceCorrections!$B$15) | Y58: =IF(AND(ISNUMBER(SEARCH("pass",L58)),ISNUMBER(X58)),COUNTIFS(L$2:L$90,"*pass*",X$2:X$90,">"&X58)+1,"") | Z58: Added 27 Oct 2026 from realestate.com.au collection "Parents." (Listings tab). Fit ratings (P/Y/lens) not yet assessed. | SCORES 27 Oct 2026: M (near family) and T (price) are formulas from J and G; O from K. N, P, Q, R, S, U, V are ESTIMATES (Claude, general knowledge, not site-checked); S also rests on train Yes/No marked 'verify'. | AB58: Yes | AC58: Rosanna station, Hurstbridge line (recall; verify) | AD58: Austin Hospital ED (drive times: Google Maps leave-now 27 Oct 2026, suburb name not postcode, not peak) | AE58: 1500000 | AF58: Maximum purchase price, excluding transaction and moving costs | AG58: AVM estimate | AH58: 27 Oct 2026 | AI58: Pass | AJ58: AVM house value ($1,242,201) is under $1.5M cap. Not a sale median.
A59: Seaford | B59: South / Coastal | C59: Watchlist | D59: Not assessed | E59: Not assessed | F59: Not assessed | G59: 861235 | H59: AVM estimate (30 Sep 2026), NOT a verified sale median; unit $657,269 (OnTheHouse/Cotality) | I59: =G59*(1+Settings!$B$6) | J59: 24 | K59: 8 | L59: Provisional pass | M59: =IF(J59="","",ROUND(MAX(0,10*(1-J59/Filters!$B$4)),1)) | N59: 5 | O59: =IF(K59="","",ROUND(MAX(0,10*(1-K59/Filters!$B$5)),1)) | P59: 4 | Q59: 7 | R59: 4 | S59: 8 | T59: =IF(G59="","",ROUND(MAX(0,MIN(10,10*(Filters!$B$2-G59)/(Filters!$B$2-500000))),1)) | U59: 9 | V59: 6 | W59: =IF(M59="",0,COUNT(M59:V59)) | X59: =IF(W59<10,"",M59*ForcedChoiceCorrections!$B$6+N59*ForcedChoiceCorrections!$B$7+O59*ForcedChoiceCorrections!$B$8+P59*ForcedChoiceCorrections!$B$9+Q59*ForcedChoiceCorrections!$B$10+R59*ForcedChoiceCorrections!$B$11+S59*ForcedChoiceCorrections!$B$12+T59*ForcedChoiceCorrections!$B$13+U59*ForcedChoiceCorrections!$B$14+V59*ForcedChoiceCorrections!$B$15) | Y59: =IF(AND(ISNUMBER(SEARCH("pass",L59)),ISNUMBER(X59)),COUNTIFS(L$2:L$90,"*pass*",X$2:X$90,">"&X59)+1,"") | Z59: Added 27 Oct 2026 from realestate.com.au collection "Parents." (Listings tab). Fit ratings (P/Y/lens) not yet assessed. | SCORES 27 Oct 2026: M (near family) and T (price) are formulas from J and G; O from K. N, P, Q, R, S, U, V are ESTIMATES (Claude, general knowledge, not site-checked); S also rests on train Yes/No marked 'verify'. | AB59: Yes | AC59: Seaford station, Frankston line (recall; verify) | AD59: Peninsula University Hospital ED (drive times: Google Maps leave-now 27 Oct 2026, suburb name not postcode, not peak) | AE59: 1500000 | AF59: Maximum purchase price, excluding transaction and moving costs | AG59: AVM estimate | AH59: 27 Oct 2026 | AI59: Pass | AJ59: AVM house value ($861,235) is under $1.5M cap. Not a sale median.
A60: Chelsea | B60: South / Coastal | C60: Watchlist | D60: Not assessed | E60: Not assessed | F60: Not assessed | G60: 1161160 | H60: AVM estimate (31 Jul 2026), NOT a verified sale median; unit $734,277 (OnTheHouse/Cotality) | I60: =G60*(1+Settings!$B$6) | J60: 30 | K60: 19 | L60: Provisional pass | M60: =IF(J60="","",ROUND(MAX(0,10*(1-J60/Filters!$B$4)),1)) | N60: 4 | O60: =IF(K60="","",ROUND(MAX(0,10*(1-K60/Filters!$B$5)),1)) | P60: 4 | Q60: 7 | R60: 5 | S60: 8 | T60: =IF(G60="","",ROUND(MAX(0,MIN(10,10*(Filters!$B$2-G60)/(Filters!$B$2-500000))),1)) | U60: 9 | V60: 7 | W60: =IF(M60="",0,COUNT(M60:V60)) | X60: =IF(W60<10,"",M60*ForcedChoiceCorrections!$B$6+N60*ForcedChoiceCorrections!$B$7+O60*ForcedChoiceCorrections!$B$8+P60*ForcedChoiceCorrections!$B$9+Q60*ForcedChoiceCorrections!$B$10+R60*ForcedChoiceCorrections!$B$11+S60*ForcedChoiceCorrections!$B$12+T60*ForcedChoiceCorrections!$B$13+U60*ForcedChoiceCorrections!$B$14+V60*ForcedChoiceCorrections!$B$15) | Y60: =IF(AND(ISNUMBER(SEARCH("pass",L60)),ISNUMBER(X60)),COUNTIFS(L$2:L$90,"*pass*",X$2:X$90,">"&X60)+1,"") | Z60: Added 27 Oct 2026 from realestate.com.au collection "Parents." (Listings tab). Fit ratings (P/Y/lens) not yet assessed. ED: Dandenong and Monash Medical Centre Clayton both 23 min. | SCORES 27 Oct 2026: M (near family) and T (price) are formulas from J and G; O from K. N, P, Q, R, S, U, V are ESTIMATES (Claude, general knowledge, not site-checked); S also rests on train Yes/No marked 'verify'. | AB60: Yes | AC60: Chelsea station, Frankston line (recall; verify) | AD60: Peninsula University Hospital ED (drive times: Google Maps leave-now 27 Oct 2026, suburb name not postcode, not peak) | AE60: 1500000 | AF60: Maximum purchase price, excluding transaction and moving costs | AG60: AVM estimate | AH60: 27 Oct 2026 | AI60: Pass | AJ60: AVM house value ($1,161,160) is under $1.5M cap. Not a sale median.
A61: Curlewis | B61: Bellarine Peninsula | C61: Watchlist | D61: Not assessed | E61: Not assessed | F61: Not assessed | G61: 744355 | H61: AVM estimate (30 Sep 2026), NOT a verified sale median; unit $695,359 (OnTheHouse/Cotality) | I61: =G61*(1+Settings!$B$6) | J61: 104 | K61: 20 | L61: Fails: GW drive | O61: =IF(K61="","",ROUND(MAX(0,10*(1-K61/Filters!$B$5)),1)) | W61: =IF(M61="",0,COUNT(M61:V61)) | X61: =IF(W61<10,"",M61*ForcedChoiceCorrections!$B$6+N61*ForcedChoiceCorrections!$B$7+O61*ForcedChoiceCorrections!$B$8+P61*ForcedChoiceCorrections!$B$9+Q61*ForcedChoiceCorrections!$B$10+R61*ForcedChoiceCorrections!$B$11+S61*ForcedChoiceCorrections!$B$12+T61*ForcedChoiceCorrections!$B$13+U61*ForcedChoiceCorrections!$B$14+V61*ForcedChoiceCorrections!$B$15) | Y61: =IF(AND(ISNUMBER(SEARCH("pass",L61)),ISNUMBER(X61)),COUNTIFS(L$2:L$90,"*pass*",X$2:X$90,">"&X61)+1,"") | Z61: Added 27 Oct 2026 from realestate.com.au collection "Parents." (Listings tab). Fit ratings (P/Y/lens) not yet assessed. ED: GW time looked up mid-afternoon; Clifton Springs (26 Oct) was 95. | AB61: No | AC61: No rail; Geelong via bus (recall; verify) | AD61: University Hospital Geelong ED (drive times: Google Maps leave-now 27 Oct 2026, suburb name not postcode, not peak) | AE61: 1500000 | AF61: Maximum purchase price, excluding transaction and moving costs | AG61: AVM estimate | AH61: 27 Oct 2026 | AI61: Pass | AJ61: AVM house value ($744,355) is under $1.5M cap. Not a sale median.
A62: McCrae | B62: Mornington Peninsula | C62: Watchlist | D62: Not assessed | E62: Not assessed | F62: Not assessed | G62: 958743 | H62: AVM estimate (31 Aug 2026), NOT a verified sale median; unit $751,204 (OnTheHouse/Cotality) | I62: =G62*(1+Settings!$B$6) | J62: 49 | K62: 6 | L62: Provisional pass | M62: =IF(J62="","",ROUND(MAX(0,10*(1-J62/Filters!$B$4)),1)) | N62: 8 | O62: =IF(K62="","",ROUND(MAX(0,10*(1-K62/Filters!$B$5)),1)) | P62: 1 | Q62: 4 | R62: 6 | S62: 2 | T62: =IF(G62="","",ROUND(MAX(0,MIN(10,10*(Filters!$B$2-G62)/(Filters!$B$2-500000))),1)) | U62: 9 | V62: 2 | W62: =IF(M62="",0,COUNT(M62:V62)) | X62: =IF(W62<10,"",M62*ForcedChoiceCorrections!$B$6+N62*ForcedChoiceCorrections!$B$7+O62*ForcedChoiceCorrections!$B$8+P62*ForcedChoiceCorrections!$B$9+Q62*ForcedChoiceCorrections!$B$10+R62*ForcedChoiceCorrections!$B$11+S62*ForcedChoiceCorrections!$B$12+T62*ForcedChoiceCorrections!$B$13+U62*ForcedChoiceCorrections!$B$14+V62*ForcedChoiceCorrections!$B$15) | Y62: =IF(AND(ISNUMBER(SEARCH("pass",L62)),ISNUMBER(X62)),COUNTIFS(L$2:L$90,"*pass*",X$2:X$90,">"&X62)+1,"") | Z62: Added 27 Oct 2026 from realestate.com.au collection "Parents." (Listings tab). Fit ratings (P/Y/lens) not yet assessed. ED: Rosebud ED is 24/7 but treats less serious cases; serious cases transfer to Frankston (Peninsula Health). | SCORES 27 Oct 2026: M (near family) and T (price) are formulas from J and G; O from K. N, P, Q, R, S, U, V are ESTIMATES (Claude, general knowledge, not site-checked); S also rests on train Yes/No marked 'verify'. | AB62: No | AC62: No passenger rail on the Peninsula south of Frankston (recall; verify) | AD62: Rosebud Hospital ED (drive times: Google Maps leave-now 27 Oct 2026, suburb name not postcode, not peak) | AE62: 1500000 | AF62: Maximum purchase price, excluding transaction and moving costs | AG62: AVM estimate | AH62: 27 Oct 2026 | AI62: Pass | AJ62: AVM house value ($958,743) is under $1.5M cap. Not a sale median.
A63: Mount Martha | B63: Mornington Peninsula | C63: Watchlist | D63: Not assessed | E63: Not assessed | F63: Not assessed | G63: 1344095 | H63: AVM estimate (31 Aug 2026), NOT a verified sale median; unit $777,939 (OnTheHouse/Cotality) | I63: =G63*(1+Settings!$B$6) | J63: 47 | K63: 19 | L63: Provisional pass | M63: =IF(J63="","",ROUND(MAX(0,10*(1-J63/Filters!$B$4)),1)) | N63: 8 | O63: =IF(K63="","",ROUND(MAX(0,10*(1-K63/Filters!$B$5)),1)) | P63: 2 | Q63: 5 | R63: 7 | S63: 2 | T63: =IF(G63="","",ROUND(MAX(0,MIN(10,10*(Filters!$B$2-G63)/(Filters!$B$2-500000))),1)) | U63: 9 | V63: 2 | W63: =IF(M63="",0,COUNT(M63:V63)) | X63: =IF(W63<10,"",M63*ForcedChoiceCorrections!$B$6+N63*ForcedChoiceCorrections!$B$7+O63*ForcedChoiceCorrections!$B$8+P63*ForcedChoiceCorrections!$B$9+Q63*ForcedChoiceCorrections!$B$10+R63*ForcedChoiceCorrections!$B$11+S63*ForcedChoiceCorrections!$B$12+T63*ForcedChoiceCorrections!$B$13+U63*ForcedChoiceCorrections!$B$14+V63*ForcedChoiceCorrections!$B$15) | Y63: =IF(AND(ISNUMBER(SEARCH("pass",L63)),ISNUMBER(X63)),COUNTIFS(L$2:L$90,"*pass*",X$2:X$90,">"&X63)+1,"") | Z63: Added 27 Oct 2026 from realestate.com.au collection "Parents." (Listings tab). Fit ratings (P/Y/lens) not yet assessed. ED: Peninsula University Hospital 22 min. Rosebud ED is 24/7 but treats less serious cases; serious cases transfer to Frankston (Peninsula Health). | SCORES 27 Oct 2026: M (near family) and T (price) are formulas from J and G; O from K. N, P, Q, R, S, U, V are ESTIMATES (Claude, general knowledge, not site-checked); S also rests on train Yes/No marked 'verify'. | AB63: No | AC63: No passenger rail on the Peninsula south of Frankston (recall; verify) | AD63: Rosebud Hospital ED (drive times: Google Maps leave-now 27 Oct 2026, suburb name not postcode, not peak) | AE63: 1500000 | AF63: Maximum purchase price, excluding transaction and moving costs | AG63: AVM estimate | AH63: 27 Oct 2026 | AI63: Pass | AJ63: AVM house value ($1,344,095) is under $1.5M cap. Not a sale median.
A64: Mordialloc | B64: South / Coastal | C64: Watchlist | D64: Not assessed | E64: Not assessed | F64: Not assessed | G64: 1401241 | H64: AVM estimate (31 Aug 2026), NOT a verified sale median; unit $756,915 (OnTheHouse/Cotality) | I64: =G64*(1+Settings!$B$6) | J64: 28 | K64: 14 | L64: Provisional pass | M64: =IF(J64="","",ROUND(MAX(0,10*(1-J64/Filters!$B$4)),1)) | N64: 5 | O64: =IF(K64="","",ROUND(MAX(0,10*(1-K64/Filters!$B$5)),1)) | P64: 5 | Q64: 8 | R64: 7 | S64: 8 | T64: =IF(G64="","",ROUND(MAX(0,MIN(10,10*(Filters!$B$2-G64)/(Filters!$B$2-500000))),1)) | U64: 9 | V64: 7 | W64: =IF(M64="",0,COUNT(M64:V64)) | X64: =IF(W64<10,"",M64*ForcedChoiceCorrections!$B$6+N64*ForcedChoiceCorrections!$B$7+O64*ForcedChoiceCorrections!$B$8+P64*ForcedChoiceCorrections!$B$9+Q64*ForcedChoiceCorrections!$B$10+R64*ForcedChoiceCorrections!$B$11+S64*ForcedChoiceCorrections!$B$12+T64*ForcedChoiceCorrections!$B$13+U64*ForcedChoiceCorrections!$B$14+V64*ForcedChoiceCorrections!$B$15) | Y64: =IF(AND(ISNUMBER(SEARCH("pass",L64)),ISNUMBER(X64)),COUNTIFS(L$2:L$90,"*pass*",X$2:X$90,">"&X64)+1,"") | Z64: Added 27 Oct 2026 from realestate.com.au collection "Parents." (Listings tab). Fit ratings (P/Y/lens) not yet assessed. ED: Alfred Health: Sandringham ED 24 hrs, 7 days. Monash Medical Centre Clayton 18 min. | SCORES 27 Oct 2026: M (near family) and T (price) are formulas from J and G; O from K. N, P, Q, R, S, U, V are ESTIMATES (Claude, general knowledge, not site-checked); S also rests on train Yes/No marked 'verify'. | AB64: Yes | AC64: Mordialloc station, Frankston line (recall; verify) | AD64: Sandringham Hospital ED (drive times: Google Maps leave-now 27 Oct 2026, suburb name not postcode, not peak) | AE64: 1500000 | AF64: Maximum purchase price, excluding transaction and moving costs | AG64: AVM estimate | AH64: 27 Oct 2026 | AI64: Pass | AJ64: AVM house value ($1,401,241) is under $1.5M cap. Not a sale median.
A65: Newport | B65: West | C65: Watchlist | D65: Not assessed | E65: Not assessed | F65: Not assessed | G65: 1150951 | H65: AVM estimate (30 Sep 2026), NOT a verified sale median; unit $809,243 (OnTheHouse/Cotality) | I65: =G65*(1+Settings!$B$6) | J65: 35 | K65: 14 | L65: Provisional pass | M65: =IF(J65="","",ROUND(MAX(0,10*(1-J65/Filters!$B$4)),1)) | N65: 4 | O65: =IF(K65="","",ROUND(MAX(0,10*(1-K65/Filters!$B$5)),1)) | P65: 6 | Q65: 8 | R65: 6 | S65: 8 | T65: =IF(G65="","",ROUND(MAX(0,MIN(10,10*(Filters!$B$2-G65)/(Filters!$B$2-500000))),1)) | U65: 4 | V65: 9 | W65: =IF(M65="",0,COUNT(M65:V65)) | X65: =IF(W65<10,"",M65*ForcedChoiceCorrections!$B$6+N65*ForcedChoiceCorrections!$B$7+O65*ForcedChoiceCorrections!$B$8+P65*ForcedChoiceCorrections!$B$9+Q65*ForcedChoiceCorrections!$B$10+R65*ForcedChoiceCorrections!$B$11+S65*ForcedChoiceCorrections!$B$12+T65*ForcedChoiceCorrections!$B$13+U65*ForcedChoiceCorrections!$B$14+V65*ForcedChoiceCorrections!$B$15) | Y65: =IF(AND(ISNUMBER(SEARCH("pass",L65)),ISNUMBER(X65)),COUNTIFS(L$2:L$90,"*pass*",X$2:X$90,">"&X65)+1,"") | Z65: Added 27 Oct 2026 from realestate.com.au collection "Parents." (Listings tab). Fit ratings (P/Y/lens) not yet assessed. ED: Matches Williamstown row; Williamstown Hospital not checked. | SCORES 27 Oct 2026: M (near family) and T (price) are formulas from J and G; O from K. N, P, Q, R, S, U, V are ESTIMATES (Claude, general knowledge, not site-checked); S also rests on train Yes/No marked 'verify'. | AB65: Yes | AC65: Newport station, Werribee/Williamstown lines (recall; verify) | AD65: Footscray Hospital ED (drive times: Google Maps leave-now 27 Oct 2026, suburb name not postcode, not peak) | AE65: 1500000 | AF65: Maximum purchase price, excluding transaction and moving costs | AG65: AVM estimate | AH65: 27 Oct 2026 | AI65: Pass | AJ65: AVM house value ($1,150,951) is under $1.5M cap. Not a sale median.
A66: Arthurs Seat | B66: Mornington Peninsula | C66: Watchlist | D66: Not assessed | E66: Not assessed | F66: Not assessed | G66: 1430000 | H66: Sale median $1,430,000, latest 12 months, only 5 house sales (Microburbs; page says data updated Nov 2026, date unclear). WEAK evidence | I66: =G66*(1+Settings!$B$6) | J66: 52 | K66: 13 | L66: Provisional pass | M66: =IF(J66="","",ROUND(MAX(0,10*(1-J66/Filters!$B$4)),1)) | N66: 9 | O66: =IF(K66="","",ROUND(MAX(0,10*(1-K66/Filters!$B$5)),1)) | P66: 1 | Q66: 2 | R66: 6 | S66: 1 | T66: =IF(G66="","",ROUND(MAX(0,MIN(10,10*(Filters!$B$2-G66)/(Filters!$B$2-500000))),1)) | U66: 6 | V66: 2 | W66: =IF(M66="",0,COUNT(M66:V66)) | X66: =IF(W66<10,"",M66*ForcedChoiceCorrections!$B$6+N66*ForcedChoiceCorrections!$B$7+O66*ForcedChoiceCorrections!$B$8+P66*ForcedChoiceCorrections!$B$9+Q66*ForcedChoiceCorrections!$B$10+R66*ForcedChoiceCorrections!$B$11+S66*ForcedChoiceCorrections!$B$12+T66*ForcedChoiceCorrections!$B$13+U66*ForcedChoiceCorrections!$B$14+V66*ForcedChoiceCorrections!$B$15) | Y66: =IF(AND(ISNUMBER(SEARCH("pass",L66)),ISNUMBER(X66)),COUNTIFS(L$2:L$90,"*pass*",X$2:X$90,">"&X66)+1,"") | Z66: Added 27 Oct 2026 from realestate.com.au collection "Parents." (Listings tab). Fit ratings (P/Y/lens) not yet assessed. ED: Peninsula University Hospital 30 min. Rosebud ED is 24/7 but treats less serious cases; serious cases transfer to Frankston (Peninsula Health). | SCORES 27 Oct 2026: M (near family) and T (price) are formulas from J and G; O from K. N, P, Q, R, S, U, V are ESTIMATES (Claude, general knowledge, not site-checked); S also rests on train Yes/No marked 'verify'. Price from 5 sales only (weak). | AB66: No | AC66: No passenger rail on the Peninsula south of Frankston (recall; verify) | AD66: Rosebud Hospital ED (drive times: Google Maps leave-now 27 Oct 2026, suburb name not postcode, not peak) | AE66: 1500000 | AF66: Maximum purchase price, excluding transaction and moving costs | AG66: Suburb sale median (5 sales) | AH66: 27 Oct 2026 | AI66: Pass | AJ66: Sale median ($1,430,000) is under $1.5M cap, but based on only 5 sales. Treat as unreliable.
W67: =IF(M67="",0,COUNT(M67:V67)) | X67: =IF(W67<10,"",M67*ForcedChoiceCorrections!$B$6+N67*ForcedChoiceCorrections!$B$7+O67*ForcedChoiceCorrections!$B$8+P67*ForcedChoiceCorrections!$B$9+Q67*ForcedChoiceCorrections!$B$10+R67*ForcedChoiceCorrections!$B$11+S67*ForcedChoiceCorrections!$B$12+T67*ForcedChoiceCorrections!$B$13+U67*ForcedChoiceCorrections!$B$14+V67*ForcedChoiceCorrections!$B$15) | Y67: =IF(AND(ISNUMBER(SEARCH("pass",L67)),ISNUMBER(X67)),COUNTIFS(L$2:L$90,"*pass*",X$2:X$90,">"&X67)+1,"")
W68: =IF(M68="",0,COUNT(M68:V68)) | X68: =IF(W68<10,"",M68*ForcedChoiceCorrections!$B$6+N68*ForcedChoiceCorrections!$B$7+O68*ForcedChoiceCorrections!$B$8+P68*ForcedChoiceCorrections!$B$9+Q68*ForcedChoiceCorrections!$B$10+R68*ForcedChoiceCorrections!$B$11+S68*ForcedChoiceCorrections!$B$12+T68*ForcedChoiceCorrections!$B$13+U68*ForcedChoiceCorrections!$B$14+V68*ForcedChoiceCorrections!$B$15) | Y68: =IF(AND(ISNUMBER(SEARCH("pass",L68)),ISNUMBER(X68)),COUNTIFS(L$2:L$90,"*pass*",X$2:X$90,">"&X68)+1,"")
W69: =IF(M69="",0,COUNT(M69:V69)) | X69: =IF(W69<10,"",M69*ForcedChoiceCorrections!$B$6+N69*ForcedChoiceCorrections!$B$7+O69*ForcedChoiceCorrections!$B$8+P69*ForcedChoiceCorrections!$B$9+Q69*ForcedChoiceCorrections!$B$10+R69*ForcedChoiceCorrections!$B$11+S69*ForcedChoiceCorrections!$B$12+T69*ForcedChoiceCorrections!$B$13+U69*ForcedChoiceCorrections!$B$14+V69*ForcedChoiceCorrections!$B$15) | Y69: =IF(AND(ISNUMBER(SEARCH("pass",L69)),ISNUMBER(X69)),COUNTIFS(L$2:L$90,"*pass*",X$2:X$90,">"&X69)+1,"")
W70: =IF(M70="",0,COUNT(M70:V70)) | X70: =IF(W70<10,"",M70*ForcedChoiceCorrections!$B$6+N70*ForcedChoiceCorrections!$B$7+O70*ForcedChoiceCorrections!$B$8+P70*ForcedChoiceCorrections!$B$9+Q70*ForcedChoiceCorrections!$B$10+R70*ForcedChoiceCorrections!$B$11+S70*ForcedChoiceCorrections!$B$12+T70*ForcedChoiceCorrections!$B$13+U70*ForcedChoiceCorrections!$B$14+V70*ForcedChoiceCorrections!$B$15) | Y70: =IF(AND(ISNUMBER(SEARCH("pass",L70)),ISNUMBER(X70)),COUNTIFS(L$2:L$90,"*pass*",X$2:X$90,">"&X70)+1,"")
W71: =IF(M71="",0,COUNT(M71:V71)) | X71: =IF(W71<10,"",M71*ForcedChoiceCorrections!$B$6+N71*ForcedChoiceCorrections!$B$7+O71*ForcedChoiceCorrections!$B$8+P71*ForcedChoiceCorrections!$B$9+Q71*ForcedChoiceCorrections!$B$10+R71*ForcedChoiceCorrections!$B$11+S71*ForcedChoiceCorrections!$B$12+T71*ForcedChoiceCorrections!$B$13+U71*ForcedChoiceCorrections!$B$14+V71*ForcedChoiceCorrections!$B$15) | Y71: =IF(AND(ISNUMBER(SEARCH("pass",L71)),ISNUMBER(X71)),COUNTIFS(L$2:L$90,"*pass*",X$2:X$90,">"&X71)+1,"")
W72: =IF(M72="",0,COUNT(M72:V72)) | X72: =IF(W72<10,"",M72*ForcedChoiceCorrections!$B$6+N72*ForcedChoiceCorrections!$B$7+O72*ForcedChoiceCorrections!$B$8+P72*ForcedChoiceCorrections!$B$9+Q72*ForcedChoiceCorrections!$B$10+R72*ForcedChoiceCorrections!$B$11+S72*ForcedChoiceCorrections!$B$12+T72*ForcedChoiceCorrections!$B$13+U72*ForcedChoiceCorrections!$B$14+V72*ForcedChoiceCorrections!$B$15) | Y72: =IF(AND(ISNUMBER(SEARCH("pass",L72)),ISNUMBER(X72)),COUNTIFS(L$2:L$90,"*pass*",X$2:X$90,">"&X72)+1,"")
W73: =IF(M73="",0,COUNT(M73:V73)) | X73: =IF(W73<10,"",M73*ForcedChoiceCorrections!$B$6+N73*ForcedChoiceCorrections!$B$7+O73*ForcedChoiceCorrections!$B$8+P73*ForcedChoiceCorrections!$B$9+Q73*ForcedChoiceCorrections!$B$10+R73*ForcedChoiceCorrections!$B$11+S73*ForcedChoiceCorrections!$B$12+T73*ForcedChoiceCorrections!$B$13+U73*ForcedChoiceCorrections!$B$14+V73*ForcedChoiceCorrections!$B$15) | Y73: =IF(AND(ISNUMBER(SEARCH("pass",L73)),ISNUMBER(X73)),COUNTIFS(L$2:L$90,"*pass*",X$2:X$90,">"&X73)+1,"")
W74: =IF(M74="",0,COUNT(M74:V74)) | X74: =IF(W74<10,"",M74*ForcedChoiceCorrections!$B$6+N74*ForcedChoiceCorrections!$B$7+O74*ForcedChoiceCorrections!$B$8+P74*ForcedChoiceCorrections!$B$9+Q74*ForcedChoiceCorrections!$B$10+R74*ForcedChoiceCorrections!$B$11+S74*ForcedChoiceCorrections!$B$12+T74*ForcedChoiceCorrections!$B$13+U74*ForcedChoiceCorrections!$B$14+V74*ForcedChoiceCorrections!$B$15) | Y74: =IF(AND(ISNUMBER(SEARCH("pass",L74)),ISNUMBER(X74)),COUNTIFS(L$2:L$90,"*pass*",X$2:X$90,">"&X74)+1,"")
W75: =IF(M75="",0,COUNT(M75:V75)) | X75: =IF(W75<10,"",M75*ForcedChoiceCorrections!$B$6+N75*ForcedChoiceCorrections!$B$7+O75*ForcedChoiceCorrections!$B$8+P75*ForcedChoiceCorrections!$B$9+Q75*ForcedChoiceCorrections!$B$10+R75*ForcedChoiceCorrections!$B$11+S75*ForcedChoiceCorrections!$B$12+T75*ForcedChoiceCorrections!$B$13+U75*ForcedChoiceCorrections!$B$14+V75*ForcedChoiceCorrections!$B$15) | Y75: =IF(AND(ISNUMBER(SEARCH("pass",L75)),ISNUMBER(X75)),COUNTIFS(L$2:L$90,"*pass*",X$2:X$90,">"&X75)+1,"")
W76: =IF(M76="",0,COUNT(M76:V76)) | X76: =IF(W76<10,"",M76*ForcedChoiceCorrections!$B$6+N76*ForcedChoiceCorrections!$B$7+O76*ForcedChoiceCorrections!$B$8+P76*ForcedChoiceCorrections!$B$9+Q76*ForcedChoiceCorrections!$B$10+R76*ForcedChoiceCorrections!$B$11+S76*ForcedChoiceCorrections!$B$12+T76*ForcedChoiceCorrections!$B$13+U76*ForcedChoiceCorrections!$B$14+V76*ForcedChoiceCorrections!$B$15) | Y76: =IF(AND(ISNUMBER(SEARCH("pass",L76)),ISNUMBER(X76)),COUNTIFS(L$2:L$90,"*pass*",X$2:X$90,">"&X76)+1,"")
W77: =IF(M77="",0,COUNT(M77:V77)) | X77: =IF(W77<10,"",M77*ForcedChoiceCorrections!$B$6+N77*ForcedChoiceCorrections!$B$7+O77*ForcedChoiceCorrections!$B$8+P77*ForcedChoiceCorrections!$B$9+Q77*ForcedChoiceCorrections!$B$10+R77*ForcedChoiceCorrections!$B$11+S77*ForcedChoiceCorrections!$B$12+T77*ForcedChoiceCorrections!$B$13+U77*ForcedChoiceCorrections!$B$14+V77*ForcedChoiceCorrections!$B$15) | Y77: =IF(AND(ISNUMBER(SEARCH("pass",L77)),ISNUMBER(X77)),COUNTIFS(L$2:L$90,"*pass*",X$2:X$90,">"&X77)+1,"")
W78: =IF(M78="",0,COUNT(M78:V78)) | X78: =IF(W78<10,"",M78*ForcedChoiceCorrections!$B$6+N78*ForcedChoiceCorrections!$B$7+O78*ForcedChoiceCorrections!$B$8+P78*ForcedChoiceCorrections!$B$9+Q78*ForcedChoiceCorrections!$B$10+R78*ForcedChoiceCorrections!$B$11+S78*ForcedChoiceCorrections!$B$12+T78*ForcedChoiceCorrections!$B$13+U78*ForcedChoiceCorrections!$B$14+V78*ForcedChoiceCorrections!$B$15) | Y78: =IF(AND(ISNUMBER(SEARCH("pass",L78)),ISNUMBER(X78)),COUNTIFS(L$2:L$90,"*pass*",X$2:X$90,">"&X78)+1,"")
... W90: =IF(M90="",0,COUNT(M90:V90)) | X90: =IF(W90<10,"",M90*ForcedChoiceCorrections!$B$6+N90*ForcedChoiceCorrections!$B$7+O90*ForcedChoiceCorrections!$B$8+P90*ForcedChoiceCorrections!$B$9+Q90*ForcedChoiceCorrections!$B$10+R90*ForcedChoiceCorrections!$B$11+S90*ForcedChoiceCorrections!$B$12+T90*ForcedChoiceCorrections!$B$13+U90*ForcedChoiceCorrections!$B$14+V90*ForcedChoiceCorrections!$B$15) | Y90: =IF(AND(ISNUMBER(SEARCH("pass",L90)),ISNUMBER(X90)),COUNTIFS(L$2:L$90,"*pass*",X$2:X$90,">"&X90)+1,"")

Sheet Listings
A1: # | B1: Address | C1: Suburb | D1: Price guide (as listed) | E1: Guide low ($) | F1: Guide high ($) | G1: Budget check (vs Filters!B2) | H1: Beds | I1: Baths | J1: Cars | K1: Land (m²) | L1: Listing status | M1: Next inspection (as of 27 Oct) | N1: Agent | O1: Scorecard suburb (lookup key) | P1: Scorecard shortlist status | Q1: Drive to GW (min, suburb) | R1: Drive to ED (min, suburb) | S1: Train (suburb) | T1: Overall check | U1: Notes | V1: Listing URL (realestate.com.au) | W1: Source: realestate.com.au collection 'Parents.', read from browser 27 Oct 2026 (copied from the Google Sheet version of this tab). A–F, H–O, U are pasted values; G and P–T are formulas. Prices are agent guides (purchase price, before costs), compared with Filters!B2 purchase cap. Drive times and train are suburb-level from SuburbScorecard, not per address. Inspection times go stale after 31 Oct. Refresh = re-read the collection and overwrite pasted columns only.
A2: 1 | B2: 6 Beales Street | C2: Torquay | D2: $1,475,000-$1,575,000 | E2: 1475000 | F2: 1575000 | G2: =IF(E2="","Needs data",IF(F2<=Filters!$B$2,"Within cap",IF(E2<=Filters!$B$2,"Straddles cap","Over cap"))) | H2: 4 | I2: 2 | J2: 2 | K2: 411 | L2: Active | M2: Tue 27 Oct 5:00pm | N2: Chris Henson | O2: Torquay | P2: =IFERROR(INDEX(SuburbScorecard!$C:$C,MATCH($O2,SuburbScorecard!$A:$A,0)),"Not on scorecard") | Q2: =IFERROR(IF(INDEX(SuburbScorecard!$J:$J,MATCH($O2,SuburbScorecard!$A:$A,0))="","",INDEX(SuburbScorecard!$J:$J,MATCH($O2,SuburbScorecard!$A:$A,0))),"") | R2: =IFERROR(IF(INDEX(SuburbScorecard!$K:$K,MATCH($O2,SuburbScorecard!$A:$A,0))="","",INDEX(SuburbScorecard!$K:$K,MATCH($O2,SuburbScorecard!$A:$A,0))),"") | S2: =IFERROR(IF(INDEX(SuburbScorecard!$AB:$AB,MATCH($O2,SuburbScorecard!$A:$A,0))="","Needs data",INDEX(SuburbScorecard!$AB:$AB,MATCH($O2,SuburbScorecard!$A:$A,0))),"Needs data") | T2: =IF(L2="Under offer","Under offer",IF(G2="Over cap","Fails: budget",IF(NOT(AND(ISNUMBER(Q2),ISNUMBER(R2))),"Needs data",IF(Q2>Filters!$B$4,"Fails: GW drive",IF(R2>Filters!$B$5,"Fails: ED drive",IF(G2="Straddles cap","Pass if bought near low end","Pass")))))) | V2: https://www.realestate.com.au/property-house-vic-torquay-152666740
A3: 2 | B3: 1/1 Bruce Street | C3: West Footscray | D3: $1,200,000-$1,300,000 | E3: 1200000 | F3: 1300000 | G3: =IF(E3="","Needs data",IF(F3<=Filters!$B$2,"Within cap",IF(E3<=Filters!$B$2,"Straddles cap","Over cap"))) | H3: 3 | I3: 2 | J3: 2 | L3: Active | M3: Thu 29 Oct 5:15pm | N3: Huss Saad | O3: West Footscray | P3: =IFERROR(INDEX(SuburbScorecard!$C:$C,MATCH($O3,SuburbScorecard!$A:$A,0)),"Not on scorecard") | Q3: =IFERROR(IF(INDEX(SuburbScorecard!$J:$J,MATCH($O3,SuburbScorecard!$A:$A,0))="","",INDEX(SuburbScorecard!$J:$J,MATCH($O3,SuburbScorecard!$A:$A,0))),"") | R3: =IFERROR(IF(INDEX(SuburbScorecard!$K:$K,MATCH($O3,SuburbScorecard!$A:$A,0))="","",INDEX(SuburbScorecard!$K:$K,MATCH($O3,SuburbScorecard!$A:$A,0))),"") | S3: =IFERROR(IF(INDEX(SuburbScorecard!$AB:$AB,MATCH($O3,SuburbScorecard!$A:$A,0))="","Needs data",INDEX(SuburbScorecard!$AB:$AB,MATCH($O3,SuburbScorecard!$A:$A,0))),"Needs data") | T3: =IF(L3="Under offer","Under offer",IF(G3="Over cap","Fails: budget",IF(NOT(AND(ISNUMBER(Q3),ISNUMBER(R3))),"Needs data",IF(Q3>Filters!$B$4,"Fails: GW drive",IF(R3>Filters!$B$5,"Fails: ED drive",IF(G3="Straddles cap","Pass if bought near low end","Pass")))))) | V3: https://www.realestate.com.au/property-house-vic-west+footscray-152623144
A4: 3 | B4: 67 Donna Buang Road | C4: Warburton | D4: $900,000-$990,000 | E4: 900000 | F4: 990000 | G4: =IF(E4="","Needs data",IF(F4<=Filters!$B$2,"Within cap",IF(E4<=Filters!$B$2,"Straddles cap","Over cap"))) | H4: 5 | I4: 3 | J4: 4 | K4: 3235 | L4: Active | M4: None listed | N4: Suzie Brannelly | O4: Warburton | P4: =IFERROR(INDEX(SuburbScorecard!$C:$C,MATCH($O4,SuburbScorecard!$A:$A,0)),"Not on scorecard") | Q4: =IFERROR(IF(INDEX(SuburbScorecard!$J:$J,MATCH($O4,SuburbScorecard!$A:$A,0))="","",INDEX(SuburbScorecard!$J:$J,MATCH($O4,SuburbScorecard!$A:$A,0))),"") | R4: =IFERROR(IF(INDEX(SuburbScorecard!$K:$K,MATCH($O4,SuburbScorecard!$A:$A,0))="","",INDEX(SuburbScorecard!$K:$K,MATCH($O4,SuburbScorecard!$A:$A,0))),"") | S4: =IFERROR(IF(INDEX(SuburbScorecard!$AB:$AB,MATCH($O4,SuburbScorecard!$A:$A,0))="","Needs data",INDEX(SuburbScorecard!$AB:$AB,MATCH($O4,SuburbScorecard!$A:$A,0))),"Needs data") | T4: =IF(L4="Under offer","Under offer",IF(G4="Over cap","Fails: budget",IF(NOT(AND(ISNUMBER(Q4),ISNUMBER(R4))),"Needs data",IF(Q4>Filters!$B$4,"Fails: GW drive",IF(R4>Filters!$B$5,"Fails: ED drive",IF(G4="Straddles cap","Pass if bought near low end","Pass")))))) | U4: Drive times added 27 Oct (suburb centre). 3,235 m² block; check winter, fire and slope | V4: https://www.realestate.com.au/property-house-vic-warburton-150763740
A5: 4 | B5: 8 Williams Bay Grove | C5: Williamstown | D5: $1,700,000 | E5: 1700000 | F5: 1700000 | G5: =IF(E5="","Needs data",IF(F5<=Filters!$B$2,"Within cap",IF(E5<=Filters!$B$2,"Straddles cap","Over cap"))) | H5: 3 | I5: 2 | J5: 2 | L5: Active | M5: Sat 31 Oct 11:15am | N5: Katie Smith | O5: Williamstown | P5: =IFERROR(INDEX(SuburbScorecard!$C:$C,MATCH($O5,SuburbScorecard!$A:$A,0)),"Not on scorecard") | Q5: =IFERROR(IF(INDEX(SuburbScorecard!$J:$J,MATCH($O5,SuburbScorecard!$A:$A,0))="","",INDEX(SuburbScorecard!$J:$J,MATCH($O5,SuburbScorecard!$A:$A,0))),"") | R5: =IFERROR(IF(INDEX(SuburbScorecard!$K:$K,MATCH($O5,SuburbScorecard!$A:$A,0))="","",INDEX(SuburbScorecard!$K:$K,MATCH($O5,SuburbScorecard!$A:$A,0))),"") | S5: =IFERROR(IF(INDEX(SuburbScorecard!$AB:$AB,MATCH($O5,SuburbScorecard!$A:$A,0))="","Needs data",INDEX(SuburbScorecard!$AB:$AB,MATCH($O5,SuburbScorecard!$A:$A,0))),"Needs data") | T5: =IF(L5="Under offer","Under offer",IF(G5="Over cap","Fails: budget",IF(NOT(AND(ISNUMBER(Q5),ISNUMBER(R5))),"Needs data",IF(Q5>Filters!$B$4,"Fails: GW drive",IF(R5>Filters!$B$5,"Fails: ED drive",IF(G5="Straddles cap","Pass if bought near low end","Pass")))))) | V5: https://www.realestate.com.au/property-house-vic-williamstown-152686328
A6: 5 | B6: 25 Phillips Crescent | C6: Rosanna | D6: ESR $1,450,000-$1,550,000 | E6: 1450000 | F6: 1550000 | G6: =IF(E6="","Needs data",IF(F6<=Filters!$B$2,"Within cap",IF(E6<=Filters!$B$2,"Straddles cap","Over cap"))) | H6: 4 | I6: 3 | J6: 2 | K6: 655 | L6: Active | M6: Tue 27 Oct 5:00pm | N6: Ashlee Jade | O6: Rosanna | P6: =IFERROR(INDEX(SuburbScorecard!$C:$C,MATCH($O6,SuburbScorecard!$A:$A,0)),"Not on scorecard") | Q6: =IFERROR(IF(INDEX(SuburbScorecard!$J:$J,MATCH($O6,SuburbScorecard!$A:$A,0))="","",INDEX(SuburbScorecard!$J:$J,MATCH($O6,SuburbScorecard!$A:$A,0))),"") | R6: =IFERROR(IF(INDEX(SuburbScorecard!$K:$K,MATCH($O6,SuburbScorecard!$A:$A,0))="","",INDEX(SuburbScorecard!$K:$K,MATCH($O6,SuburbScorecard!$A:$A,0))),"") | S6: =IFERROR(IF(INDEX(SuburbScorecard!$AB:$AB,MATCH($O6,SuburbScorecard!$A:$A,0))="","Needs data",INDEX(SuburbScorecard!$AB:$AB,MATCH($O6,SuburbScorecard!$A:$A,0))),"Needs data") | T6: =IF(L6="Under offer","Under offer",IF(G6="Over cap","Fails: budget",IF(NOT(AND(ISNUMBER(Q6),ISNUMBER(R6))),"Needs data",IF(Q6>Filters!$B$4,"Fails: GW drive",IF(R6>Filters!$B$5,"Fails: ED drive",IF(G6="Straddles cap","Pass if bought near low end","Pass")))))) | V6: https://www.realestate.com.au/property-house-vic-rosanna-152574468
A7: 6 | B7: 29 Campbell Street | C7: Diamond Creek | D7: New price $1.25m | E7: 1250000 | F7: 1250000 | G7: =IF(E7="","Needs data",IF(F7<=Filters!$B$2,"Within cap",IF(E7<=Filters!$B$2,"Straddles cap","Over cap"))) | H7: 4 | I7: 2 | J7: 2 | K7: 884 | L7: Active | M7: Tue 27 Oct 6:00pm | N7: Sheryl Emerson | O7: Diamond Creek | P7: =IFERROR(INDEX(SuburbScorecard!$C:$C,MATCH($O7,SuburbScorecard!$A:$A,0)),"Not on scorecard") | Q7: =IFERROR(IF(INDEX(SuburbScorecard!$J:$J,MATCH($O7,SuburbScorecard!$A:$A,0))="","",INDEX(SuburbScorecard!$J:$J,MATCH($O7,SuburbScorecard!$A:$A,0))),"") | R7: =IFERROR(IF(INDEX(SuburbScorecard!$K:$K,MATCH($O7,SuburbScorecard!$A:$A,0))="","",INDEX(SuburbScorecard!$K:$K,MATCH($O7,SuburbScorecard!$A:$A,0))),"") | S7: =IFERROR(IF(INDEX(SuburbScorecard!$AB:$AB,MATCH($O7,SuburbScorecard!$A:$A,0))="","Needs data",INDEX(SuburbScorecard!$AB:$AB,MATCH($O7,SuburbScorecard!$A:$A,0))),"Needs data") | T7: =IF(L7="Under offer","Under offer",IF(G7="Over cap","Fails: budget",IF(NOT(AND(ISNUMBER(Q7),ISNUMBER(R7))),"Needs data",IF(Q7>Filters!$B$4,"Fails: GW drive",IF(R7>Filters!$B$5,"Fails: ED drive",IF(G7="Straddles cap","Pass if bought near low end","Pass")))))) | V7: https://www.realestate.com.au/property-house-vic-diamond+creek-152290624
A8: 7 | B8: 23 Park Street | C8: Mordialloc | D8: $1,750,000-$1,900,000 | E8: 1750000 | F8: 1900000 | G8: =IF(E8="","Needs data",IF(F8<=Filters!$B$2,"Within cap",IF(E8<=Filters!$B$2,"Straddles cap","Over cap"))) | H8: 4 | I8: 2 | J8: 2 | K8: 613 | L8: Active | M8: Tue 27 Oct 3:30pm | N8: Lou Colella | O8: Mordialloc | P8: =IFERROR(INDEX(SuburbScorecard!$C:$C,MATCH($O8,SuburbScorecard!$A:$A,0)),"Not on scorecard") | Q8: =IFERROR(IF(INDEX(SuburbScorecard!$J:$J,MATCH($O8,SuburbScorecard!$A:$A,0))="","",INDEX(SuburbScorecard!$J:$J,MATCH($O8,SuburbScorecard!$A:$A,0))),"") | R8: =IFERROR(IF(INDEX(SuburbScorecard!$K:$K,MATCH($O8,SuburbScorecard!$A:$A,0))="","",INDEX(SuburbScorecard!$K:$K,MATCH($O8,SuburbScorecard!$A:$A,0))),"") | S8: =IFERROR(IF(INDEX(SuburbScorecard!$AB:$AB,MATCH($O8,SuburbScorecard!$A:$A,0))="","Needs data",INDEX(SuburbScorecard!$AB:$AB,MATCH($O8,SuburbScorecard!$A:$A,0))),"Needs data") | T8: =IF(L8="Under offer","Under offer",IF(G8="Over cap","Fails: budget",IF(NOT(AND(ISNUMBER(Q8),ISNUMBER(R8))),"Needs data",IF(Q8>Filters!$B$4,"Fails: GW drive",IF(R8>Filters!$B$5,"Fails: ED drive",IF(G8="Straddles cap","Pass if bought near low end","Pass")))))) | V8: https://www.realestate.com.au/property-house-vic-mordialloc-152622844
A9: 8 | B9: 156A Nepean Highway | C9: Seaford | D9: $1,690,000-$1,850,000 | E9: 1690000 | F9: 1850000 | G9: =IF(E9="","Needs data",IF(F9<=Filters!$B$2,"Within cap",IF(E9<=Filters!$B$2,"Straddles cap","Over cap"))) | H9: 4 | I9: 2 | J9: 4 | K9: 319 | L9: Under offer | M9: None listed | N9: Dean Bozunovic | O9: Seaford | P9: =IFERROR(INDEX(SuburbScorecard!$C:$C,MATCH($O9,SuburbScorecard!$A:$A,0)),"Not on scorecard") | Q9: =IFERROR(IF(INDEX(SuburbScorecard!$J:$J,MATCH($O9,SuburbScorecard!$A:$A,0))="","",INDEX(SuburbScorecard!$J:$J,MATCH($O9,SuburbScorecard!$A:$A,0))),"") | R9: =IFERROR(IF(INDEX(SuburbScorecard!$K:$K,MATCH($O9,SuburbScorecard!$A:$A,0))="","",INDEX(SuburbScorecard!$K:$K,MATCH($O9,SuburbScorecard!$A:$A,0))),"") | S9: =IFERROR(IF(INDEX(SuburbScorecard!$AB:$AB,MATCH($O9,SuburbScorecard!$A:$A,0))="","Needs data",INDEX(SuburbScorecard!$AB:$AB,MATCH($O9,SuburbScorecard!$A:$A,0))),"Needs data") | T9: =IF(L9="Under offer","Under offer",IF(G9="Over cap","Fails: budget",IF(NOT(AND(ISNUMBER(Q9),ISNUMBER(R9))),"Needs data",IF(Q9>Filters!$B$4,"Fails: GW drive",IF(R9>Filters!$B$5,"Fails: ED drive",IF(G9="Straddles cap","Pass if bought near low end","Pass")))))) | V9: https://www.realestate.com.au/property-house-vic-seaford-152011424
A10: 9 | B10: 1/192 Nepean Highway | C10: Seaford | D10: $1,450,000-$1,595,000 | E10: 1450000 | F10: 1595000 | G10: =IF(E10="","Needs data",IF(F10<=Filters!$B$2,"Within cap",IF(E10<=Filters!$B$2,"Straddles cap","Over cap"))) | H10: 3 | I10: 2 | J10: 2 | K10: 1019 | L10: Active | M10: Sat 31 Oct 1:00pm | N10: Luke Magree | O10: Seaford | P10: =IFERROR(INDEX(SuburbScorecard!$C:$C,MATCH($O10,SuburbScorecard!$A:$A,0)),"Not on scorecard") | Q10: =IFERROR(IF(INDEX(SuburbScorecard!$J:$J,MATCH($O10,SuburbScorecard!$A:$A,0))="","",INDEX(SuburbScorecard!$J:$J,MATCH($O10,SuburbScorecard!$A:$A,0))),"") | R10: =IFERROR(IF(INDEX(SuburbScorecard!$K:$K,MATCH($O10,SuburbScorecard!$A:$A,0))="","",INDEX(SuburbScorecard!$K:$K,MATCH($O10,SuburbScorecard!$A:$A,0))),"") | S10: =IFERROR(IF(INDEX(SuburbScorecard!$AB:$AB,MATCH($O10,SuburbScorecard!$A:$A,0))="","Needs data",INDEX(SuburbScorecard!$AB:$AB,MATCH($O10,SuburbScorecard!$A:$A,0))),"Needs data") | T10: =IF(L10="Under offer","Under offer",IF(G10="Over cap","Fails: budget",IF(NOT(AND(ISNUMBER(Q10),ISNUMBER(R10))),"Needs data",IF(Q10>Filters!$B$4,"Fails: GW drive",IF(R10>Filters!$B$5,"Fails: ED drive",IF(G10="Straddles cap","Pass if bought near low end","Pass")))))) | V10: https://www.realestate.com.au/property-house-vic-seaford-151815440
