Workbook

Sheet StartHere
A1: Workflow Steps
A2: 1. Complete 'Me' first
A3: 2. Interview Mum & Dad separately
A4: 3. Enforce Max-2-Essential rule
A5: 4. Review DiscussionSummary
A6: 5. Verify suburb data
A8: Boundaries Table
A9: Type | B9: Description
A10: Manual | B10: Editable input cells in yellow
A11: Automatic | B11: Calculated outputs

Sheet Settings
A1: Parameter | B1: Value | C1: Notes
A2: Say in the decision: Mum | B2: 1
A3: Say in the decision: Dad | B3: 1
A4: Say in the decision: Me | B4: 1
A5: Max D (Essential) answers per person | B5: 2
A6: Purchase costs allowance (% of price) | B6: 0.06 | C6: (provisional estimate, not SRO calculation)
A7: Forced-choice override margin | B7: 0.02
A9: Priority Rating Scale | B9: Level | C9: Score
A10: A | B10: Level 1, Not needed | C10: 0
A11: B | B11: Level 2, Nice to have | C11: 1
A12: C | B12: Level 3, Important | C12: 2
A13: D | B13: Level 4, Essential | C13: 4
A15: Draft Baseline Weights | B15: Weight
A16: Q15.1 Nature | B16: 0.18
A17: Q15.2 Near family in GW | B17: 0
A18: Q15.3 Indian community | B18: 0.18
A19: Q15.4 Beach | B19: 0.1
A20: Q15.5 Hospital | B20: 0.15
A21: Q15.6 Train/bus | B21: 0.15
A22: Q15.7 Shops/doctor | B22: 0.09
A23: Q15.8 Village character | B23: 0.07
A24: Q15.9 Price | B24: 0.08
A25: Q15.10 Easy city trip | B25: 0

Sheet RawResponses
A1: Timestamp | B1: [Q0] Whose answers are these? | C1: [Q1] | D1: [Q2] | E1: [Q3] Total budget | F1: [Q4] Max drive to GW | G1: [Q4b] Max drive to GW (if D) | H1: [Q5] Max drive to ED | I1: [Q6] Stairs | J1: [Q7] Garden | K1: [Q7a] Living arrangement | L1: [Q7b] Home size | M1: [Q8] | N1: [Q9] | O1: [Q10] | P1: [Q11] | Q1: [Q12] | R1: [Q13] | S1: [Q13b] | T1: [Q13c] | U1: [Q14] | V1: [Q15.1] Nature | W1: [Q15.2] Near family in GW | X1: [Q15.3] Indian community | Y1: [Q15.4] Beach | Z1: [Q15.5] Hospital | AA1: [Q15.6] Train/bus | AB1: [Q15.7] Shops/doctor | AC1: [Q15.8] Village character | AD1: [Q15.9] Price | AE1: [Q15.10] Easy city trip | AF1: [Q15 Notes] | AG1: [Q16] | AH1: [Q17] | AI1: [Q18] | AJ1: [Q19] | AK1: [Q20] | AL1: [Q21]
A2: 0.375 | B2: Dad | E2: 1000000 | F2: C - 35m | H2: C - 30m | I2: B - Some stairs | J2: B - Small garden | O2: Nature | P2: Village character | Q2: Shops & doctor | V2: C | W2: C | X2: C | Y2: C | Z2: C | AA2: C | AB2: C | AC2: C | AD2: D | AE2: D
A3: 0.38541667 | B3: Me | F3: B - 25m | H3: B - 20m | I3: A - None | J3: C - Courtyard | O3: Nature | P3: Village character | Q3: Shops & doctor | V3: D | W3: D | X3: C | Y3: C | Z3: C | AA3: C | AB3: C | AC3: C | AD3: C | AE3: C
A4: 0.39583333 | B4: Mum | E4: 1250000 | F4: B - 25m | H4: B - 20m | I4: A - None at all (Single-level only) | J4: C - Courtyard | K4: D - Self-contained space | O4: Near family in GW | P4: Village character | Q4: Shops & doctor | V4: D | W4: D | X4: D | Y4: C | Z4: C | AA4: C | AB4: C | AC4: C | AD4: C | AE4: C
A5: 0.40625 | B5: Dad | E5: 1500000 | F5: D - 45 min or more | G5: 75 | H5: D - no limit | I5: C - Doesn't matter | J5: E - Depends on Garden | O5: Near family in GW | P5: Village character | Q5: Shops & doctor | V5: D | W5: D | X5: C | Y5: C | Z5: C | AA5: C | AB5: C | AC5: C | AD5: C | AE5: C

Sheet CleanedAnswers
A1: Person | B1: Latest Row | C1: Q15 Essential Count
A2: Mum | B2: =IFERROR(LOOKUP(2,1/(RawResponses!$B$2:$B$500="Mum"),ROW(RawResponses!$B$2:$B$500)),"") -> 4 | C2: {=IF(COUNTIF(INDEX(RawResponses!$A:$AL, B2, 22):INDEX(RawResponses!$A:$AL, B2, 31), "D")>Settings!$B$5, "Too many D's ("&COUNTIF(INDEX(RawResponses!$A:$AL, B2, 22):INDEX(RawResponses!$A:$AL, B2, 31), "D")&")", "OK ("&COUNTIF(INDEX(RawResponses!$A:$AL, B2, 22):INDEX(RawResponses!$A:$AL, B2, 31), "D")&")")} -> Too many D's (3)
A3: Dad | B3: =IFERROR(LOOKUP(2,1/(RawResponses!$B$2:$B$500="Dad"),ROW(RawResponses!$B$2:$B$500)),"") -> 5 | C3: {=IF(COUNTIF(INDEX(RawResponses!$A:$AL, B3, 22):INDEX(RawResponses!$A:$AL, B3, 31), "D")>Settings!$B$5, "Too many D's ("&COUNTIF(INDEX(RawResponses!$A:$AL, B3, 22):INDEX(RawResponses!$A:$AL, B3, 31), "D")&")", "OK ("&COUNTIF(INDEX(RawResponses!$A:$AL, B3, 22):INDEX(RawResponses!$A:$AL, B3, 31), "D")&")")} -> OK (2)
A4: Me | B4: =IFERROR(LOOKUP(2,1/(RawResponses!$B$2:$B$500="Me"),ROW(RawResponses!$B$2:$B$500)),"") -> 3 | C4: {=IF(COUNTIF(INDEX(RawResponses!$A:$AL, B4, 22):INDEX(RawResponses!$A:$AL, B4, 31), "D")>Settings!$B$5, "Too many D's ("&COUNTIF(INDEX(RawResponses!$A:$AL, B4, 22):INDEX(RawResponses!$A:$AL, B4, 31), "D")&")", "OK ("&COUNTIF(INDEX(RawResponses!$A:$AL, B4, 22):INDEX(RawResponses!$A:$AL, B4, 31), "D")&")")} -> OK (2)
A6: Question ID | B6: Mum Answer | C6: Dad Answer | D6: Me Answer | E6: Mum Code | F6: Dad Code | G6: Me Code
A7: [Q3] Total budget | B7: {=INDEX(RawResponses!$A:$AL, $B$2, MATCH($A7&"*", RawResponses!$A$1:$AL$1, 0))} -> 1250000 | C7: {=INDEX(RawResponses!$A:$AL, $B$3, MATCH($A7&"*", RawResponses!$A$1:$AL$1, 0))} -> 1500000 | D7: =INDEX(RawResponses!$A:$AL, $B$4, MATCH($A7&"*", RawResponses!$A$1:$AL$1, 0)) -> 0 | E7: =LEFT(B7, 1) -> 1 | F7: =LEFT(C7, 1) -> 1 | G7: =LEFT(D7, 1) -> 0
A8: [Q4] Max drive to GW | B8: {=INDEX(RawResponses!$A:$AL, $B$2, MATCH($A8&"*", RawResponses!$A$1:$AL$1, 0))} -> B - 25m | C8: {=INDEX(RawResponses!$A:$AL, $B$3, MATCH($A8&"*", RawResponses!$A$1:$AL$1, 0))} -> D - 45 min or more | D8: {=INDEX(RawResponses!$A:$AL, $B$4, MATCH($A8&"*", RawResponses!$A$1:$AL$1, 0))} -> B - 25m | E8: =LEFT(B8, 1) -> B | F8: =LEFT(C8, 1) -> D | G8: =LEFT(D8, 1) -> B
A9: [Q4b] Max drive to GW (if D) | B9: =INDEX(RawResponses!$A:$AL, $B$2, MATCH($A9&"*", RawResponses!$A$1:$AL$1, 0)) -> 0 | C9: {=INDEX(RawResponses!$A:$AL, $B$3, MATCH($A9&"*", RawResponses!$A$1:$AL$1, 0))} -> 75 | D9: =INDEX(RawResponses!$A:$AL, $B$4, MATCH($A9&"*", RawResponses!$A$1:$AL$1, 0)) -> 0 | E9: =IF(B9="","",B9) | F9: =IF(C9="","",C9) -> 75 | G9: =IF(D9="","",D9)
A10: [Q5] Max drive to ED | B10: {=INDEX(RawResponses!$A:$AL, $B$2, MATCH($A10&"*", RawResponses!$A$1:$AL$1, 0))} -> B - 20m | C10: {=INDEX(RawResponses!$A:$AL, $B$3, MATCH($A10&"*", RawResponses!$A$1:$AL$1, 0))} -> D - no limit | D10: {=INDEX(RawResponses!$A:$AL, $B$4, MATCH($A10&"*", RawResponses!$A$1:$AL$1, 0))} -> B - 20m | E10: =LEFT(B10, 1) -> B | F10: =LEFT(C10, 1) -> D | G10: =LEFT(D10, 1) -> B
A11: [Q6] Stairs | B11: {=INDEX(RawResponses!$A:$AL, $B$2, MATCH($A11&"*", RawResponses!$A$1:$AL$1, 0))} -> A - None at all (Single-level only) | C11: {=INDEX(RawResponses!$A:$AL, $B$3, MATCH($A11&"*", RawResponses!$A$1:$AL$1, 0))} -> C - Doesn't matter | D11: {=INDEX(RawResponses!$A:$AL, $B$4, MATCH($A11&"*", RawResponses!$A$1:$AL$1, 0))} -> A - None | E11: =LEFT(B11, 1) -> A | F11: =LEFT(C11, 1) -> C | G11: =LEFT(D11, 1) -> A
A12: [Q7] Garden | B12: {=INDEX(RawResponses!$A:$AL, $B$2, MATCH($A12&"*", RawResponses!$A$1:$AL$1, 0))} -> C - Courtyard | C12: {=INDEX(RawResponses!$A:$AL, $B$3, MATCH($A12&"*", RawResponses!$A$1:$AL$1, 0))} -> E - Depends on Garden | D12: {=INDEX(RawResponses!$A:$AL, $B$4, MATCH($A12&"*", RawResponses!$A$1:$AL$1, 0))} -> C - Courtyard | E12: =LEFT(B12, 1) -> C | F12: =LEFT(C12, 1) -> E | G12: =LEFT(D12, 1) -> C
A13: [Q7a] Living arrangement | B13: {=INDEX(RawResponses!$A:$AL, $B$2, MATCH($A13&"*", RawResponses!$A$1:$AL$1, 0))} -> D - Self-contained space | C13: =INDEX(RawResponses!$A:$AL, $B$3, MATCH($A13&"*", RawResponses!$A$1:$AL$1, 0)) -> 0 | D13: =INDEX(RawResponses!$A:$AL, $B$4, MATCH($A13&"*", RawResponses!$A$1:$AL$1, 0)) -> 0 | E13: =LEFT(B13, 1) -> D | F13: =LEFT(C13, 1) -> 0 | G13: =LEFT(D13, 1) -> 0
A14: [Q7b] Home size | B14: =INDEX(RawResponses!$A:$AL, $B$2, MATCH($A14&"*", RawResponses!$A$1:$AL$1, 0)) -> 0 | C14: =INDEX(RawResponses!$A:$AL, $B$3, MATCH($A14&"*", RawResponses!$A$1:$AL$1, 0)) -> 0 | D14: =INDEX(RawResponses!$A:$AL, $B$4, MATCH($A14&"*", RawResponses!$A$1:$AL$1, 0)) -> 0 | E14: =LEFT(B14, 1) -> 0 | F14: =LEFT(C14, 1) -> 0 | G14: =LEFT(D14, 1) -> 0
A15: [Q10] | B15: {=INDEX(RawResponses!$A:$AL, $B$2, MATCH($A15&"*", RawResponses!$A$1:$AL$1, 0))} -> Near family in GW | C15: {=INDEX(RawResponses!$A:$AL, $B$3, MATCH($A15&"*", RawResponses!$A$1:$AL$1, 0))} -> Near family in GW | D15: {=INDEX(RawResponses!$A:$AL, $B$4, MATCH($A15&"*", RawResponses!$A$1:$AL$1, 0))} -> Nature | E15: =LEFT(B15, 1) -> N | F15: =LEFT(C15, 1) -> N | G15: =LEFT(D15, 1) -> N
A16: [Q11] | B16: {=INDEX(RawResponses!$A:$AL, $B$2, MATCH($A16&"*", RawResponses!$A$1:$AL$1, 0))} -> Village character | C16: {=INDEX(RawResponses!$A:$AL, $B$3, MATCH($A16&"*", RawResponses!$A$1:$AL$1, 0))} -> Village character | D16: {=INDEX(RawResponses!$A:$AL, $B$4, MATCH($A16&"*", RawResponses!$A$1:$AL$1, 0))} -> Village character | E16: =LEFT(B16, 1) -> V | F16: =LEFT(C16, 1) -> V | G16: =LEFT(D16, 1) -> V
A17: [Q12] | B17: {=INDEX(RawResponses!$A:$AL, $B$2, MATCH($A17&"*", RawResponses!$A$1:$AL$1, 0))} -> Shops & doctor | C17: {=INDEX(RawResponses!$A:$AL, $B$3, MATCH($A17&"*", RawResponses!$A$1:$AL$1, 0))} -> Shops & doctor | D17: {=INDEX(RawResponses!$A:$AL, $B$4, MATCH($A17&"*", RawResponses!$A$1:$AL$1, 0))} -> Shops & doctor | E17: =LEFT(B17, 1) -> S | F17: =LEFT(C17, 1) -> S | G17: =LEFT(D17, 1) -> S
A18: [Q13] | B18: =INDEX(RawResponses!$A:$AL, $B$2, MATCH($A18&"*", RawResponses!$A$1:$AL$1, 0)) -> 0 | C18: =INDEX(RawResponses!$A:$AL, $B$3, MATCH($A18&"*", RawResponses!$A$1:$AL$1, 0)) -> 0 | D18: =INDEX(RawResponses!$A:$AL, $B$4, MATCH($A18&"*", RawResponses!$A$1:$AL$1, 0)) -> 0 | E18: =LEFT(B18, 1) -> 0 | F18: =LEFT(C18, 1) -> 0 | G18: =LEFT(D18, 1) -> 0
A19: [Q15.1] Nature | B19: {=INDEX(RawResponses!$A:$AL, $B$2, MATCH($A19&"*", RawResponses!$A$1:$AL$1, 0))} -> D | C19: {=INDEX(RawResponses!$A:$AL, $B$3, MATCH($A19&"*", RawResponses!$A$1:$AL$1, 0))} -> D | D19: {=INDEX(RawResponses!$A:$AL, $B$4, MATCH($A19&"*", RawResponses!$A$1:$AL$1, 0))} -> D | E19: =LEFT(B19, 1) -> D | F19: =LEFT(C19, 1) -> D | G19: =LEFT(D19, 1) -> D
A20: [Q15.2] Near family in GW | B20: {=INDEX(RawResponses!$A:$AL, $B$2, MATCH($A20&"*", RawResponses!$A$1:$AL$1, 0))} -> D | C20: {=INDEX(RawResponses!$A:$AL, $B$3, MATCH($A20&"*", RawResponses!$A$1:$AL$1, 0))} -> D | D20: {=INDEX(RawResponses!$A:$AL, $B$4, MATCH($A20&"*", RawResponses!$A$1:$AL$1, 0))} -> D | E20: =LEFT(B20, 1) -> D | F20: =LEFT(C20, 1) -> D | G20: =LEFT(D20, 1) -> D
A21: [Q15.3] Indian community | B21: {=INDEX(RawResponses!$A:$AL, $B$2, MATCH($A21&"*", RawResponses!$A$1:$AL$1, 0))} -> D | C21: {=INDEX(RawResponses!$A:$AL, $B$3, MATCH($A21&"*", RawResponses!$A$1:$AL$1, 0))} -> C | D21: {=INDEX(RawResponses!$A:$AL, $B$4, MATCH($A21&"*", RawResponses!$A$1:$AL$1, 0))} -> C | E21: =LEFT(B21, 1) -> D | F21: =LEFT(C21, 1) -> C | G21: =LEFT(D21, 1) -> C
A22: [Q15.4] Beach | B22: {=INDEX(RawResponses!$A:$AL, $B$2, MATCH($A22&"*", RawResponses!$A$1:$AL$1, 0))} -> C | C22: {=INDEX(RawResponses!$A:$AL, $B$3, MATCH($A22&"*", RawResponses!$A$1:$AL$1, 0))} -> C | D22: {=INDEX(RawResponses!$A:$AL, $B$4, MATCH($A22&"*", RawResponses!$A$1:$AL$1, 0))} -> C | E22: =LEFT(B22, 1) -> C | F22: =LEFT(C22, 1) -> C | G22: =LEFT(D22, 1) -> C
A23: [Q15.5] Hospital | B23: {=INDEX(RawResponses!$A:$AL, $B$2, MATCH($A23&"*", RawResponses!$A$1:$AL$1, 0))} -> C | C23: {=INDEX(RawResponses!$A:$AL, $B$3, MATCH($A23&"*", RawResponses!$A$1:$AL$1, 0))} -> C | D23: {=INDEX(RawResponses!$A:$AL, $B$4, MATCH($A23&"*", RawResponses!$A$1:$AL$1, 0))} -> C | E23: =LEFT(B23, 1) -> C | F23: =LEFT(C23, 1) -> C | G23: =LEFT(D23, 1) -> C
A24: [Q15.6] Train/bus | B24: {=INDEX(RawResponses!$A:$AL, $B$2, MATCH($A24&"*", RawResponses!$A$1:$AL$1, 0))} -> C | C24: {=INDEX(RawResponses!$A:$AL, $B$3, MATCH($A24&"*", RawResponses!$A$1:$AL$1, 0))} -> C | D24: {=INDEX(RawResponses!$A:$AL, $B$4, MATCH($A24&"*", RawResponses!$A$1:$AL$1, 0))} -> C | E24: =LEFT(B24, 1) -> C | F24: =LEFT(C24, 1) -> C | G24: =LEFT(D24, 1) -> C
A25: [Q15.7] Shops/doctor | B25: {=INDEX(RawResponses!$A:$AL, $B$2, MATCH($A25&"*", RawResponses!$A$1:$AL$1, 0))} -> C | C25: {=INDEX(RawResponses!$A:$AL, $B$3, MATCH($A25&"*", RawResponses!$A$1:$AL$1, 0))} -> C | D25: {=INDEX(RawResponses!$A:$AL, $B$4, MATCH($A25&"*", RawResponses!$A$1:$AL$1, 0))} -> C | E25: =LEFT(B25, 1) -> C | F25: =LEFT(C25, 1) -> C | G25: =LEFT(D25, 1) -> C
A26: [Q15.8] Village character | B26: {=INDEX(RawResponses!$A:$AL, $B$2, MATCH($A26&"*", RawResponses!$A$1:$AL$1, 0))} -> C | C26: {=INDEX(RawResponses!$A:$AL, $B$3, MATCH($A26&"*", RawResponses!$A$1:$AL$1, 0))} -> C | D26: {=INDEX(RawResponses!$A:$AL, $B$4, MATCH($A26&"*", RawResponses!$A$1:$AL$1, 0))} -> C | E26: =LEFT(B26, 1) -> C | F26: =LEFT(C26, 1) -> C | G26: =LEFT(D26, 1) -> C
A27: [Q15.9] Price | B27: {=INDEX(RawResponses!$A:$AL, $B$2, MATCH($A27&"*", RawResponses!$A$1:$AL$1, 0))} -> C | C27: {=INDEX(RawResponses!$A:$AL, $B$3, MATCH($A27&"*", RawResponses!$A$1:$AL$1, 0))} -> C | D27: {=INDEX(RawResponses!$A:$AL, $B$4, MATCH($A27&"*", RawResponses!$A$1:$AL$1, 0))} -> C | E27: =LEFT(B27, 1) -> C | F27: =LEFT(C27, 1) -> C | G27: =LEFT(D27, 1) -> C
A28: [Q15.10] Easy city trip | B28: {=INDEX(RawResponses!$A:$AL, $B$2, MATCH($A28&"*", RawResponses!$A$1:$AL$1, 0))} -> C | C28: {=INDEX(RawResponses!$A:$AL, $B$3, MATCH($A28&"*", RawResponses!$A$1:$AL$1, 0))} -> C | D28: {=INDEX(RawResponses!$A:$AL, $B$4, MATCH($A28&"*", RawResponses!$A$1:$AL$1, 0))} -> C | E28: =LEFT(B28, 1) -> C | F28: =LEFT(C28, 1) -> C | G28: =LEFT(D28, 1) -> C

Sheet Filters
A1: Filter | B1: Strictest Constraint | C1: Notes | D1: Survey-derived value (reference only)
A2: Q3 Total budget | B2: 1500000 | C2: Confirmed family decision 27 Oct 2026: budget cap set to $1,500,000 maximum purchase price (excluding transaction & moving costs). Replaces survey strictest of $1,250,000. | D2: 1250000
A3: Total acquisition ceiling (Price + 6% costs) | B3: =B2 * (1 + Settings!B6) -> 1590000 | C3: Total outlay cap ($1,590,000) including 6% stamp duty/conveyancing/moving allowance on $1,500,000 purchase price.
A4: Q4/Q4b Max drive to GW | B4: 90 | C4: Family decision 26 Oct 2026: hard max 90 min (60 min preferred); a train option is now preferred, not required (see row 9, changed by NJD, family to confirm). Replaces survey strictest of 25 min (Mum/Me); Dad said up to 75. | D4: =MIN(IF(CleanedAnswers!E8="D",IF(ISNUMBER(CleanedAnswers!B9),CleanedAnswers!B9,999),IFERROR(CHOOSE(MATCH(CleanedAnswers!E8,{"A","B","C"},0),15,25,35),999)),IF(CleanedAnswers!F8="D",IF(ISNUMBER(CleanedAnswers!C9),CleanedAnswers!C9,999),IFERROR(CHOOSE(MATCH(CleanedAnswers!F8,{"A","B","C"},0),15,25,35),999)),IF(CleanedAnswers!G8="D",IF(ISNUMBER(CleanedAnswers!D9),CleanedAnswers!D9,999),IFERROR(CHOOSE(MATCH(CleanedAnswers!G8,{"A","B","C"},0),15,25,35),999))) -> 25
A5: Q5 Max drive to ED | B5: 90 | C5: Family decision 26 Oct 2026: hard cap 90 min, and ED time is also scored (SuburbScorecard column O). Replaces survey strictest of 20 min (Mum/Me); Dad said no limit.
A6: Q6 Stairs | B6: Stairs allowed (single-level not required) | C6: CORRECTED 27 Oct 2026 by NJD: stairs are allowed, so this is no longer a hard filter. Previous value was the survey strictest answer (formula kept in D6). | D6: =IF(COUNTIF(CleanedAnswers!E11:G11, "A")>0, "A — None at all (Single-level only)", "Check") -> A — None at all (Single-level only)
A7: Q7a/Q7b Living arrangement | B7: Needs discussion (Living arrangement undecided): D — Self-contained space
A8: Q7 Garden | B8: Needs discussion (Depends — see notes)
A9: Train option | B9: Preferred, not required (scored via SuburbScorecard column S) | C9: CHANGED 26 Oct 2026 by NJD from 'Required (a train station in or at the edge of the suburb)', which had been recorded as a family decision earlier that day. Family to confirm. Reason: a hard rule removes bush and coastal areas that have not been viewed. Column AB on SuburbScorecard: Yes / No.
A10: Drive-time basis | B10: Google Maps drive time, 'leave now' typical traffic, looked up 26 Oct 2026 | C10: Not tested at peak hour. J = to Glen Waverley (suburb centre). K = to the nearest 24-hr public ED listed in SuburbScorecard column AD. Train Yes/No is from recall and sheet notes, not checked against timetables.

Sheet PriorityWeights
A1: Question | B1: Mum Code | C1: Dad Code | D1: Me Code | E1: Mum Score | F1: Dad Score | G1: Me Score | H1: Mum Norm | I1: Dad Norm | J1: Me Norm | K1: Combined Weight
A2: Nature | B2: =CleanedAnswers!E19 -> D | C2: =CleanedAnswers!F19 -> D | D2: =CleanedAnswers!G19 -> D | E2: =VLOOKUP(B2, Settings!$A$10:$C$13, 3, FALSE()) -> 4 | F2: =VLOOKUP(C2, Settings!$A$10:$C$13, 3, FALSE()) -> 4 | G2: =VLOOKUP(D2, Settings!$A$10:$C$13, 3, FALSE()) -> 4 | H2: =E2/SUM(E$2:E$11) -> 0.15384615 | I2: =F2/SUM(F$2:F$11) -> 0.16666667 | J2: =G2/SUM(G$2:G$11) -> 0.16666667 | K2: =(H2*Settings!$B$2 + I2*Settings!$B$3 + J2*Settings!$B$4)/(Settings!$B$2+Settings!$B$3+Settings!$B$4) -> 0.16239316
A3: Near family in GW | B3: =CleanedAnswers!E20 -> D | C3: =CleanedAnswers!F20 -> D | D3: =CleanedAnswers!G20 -> D | E3: =VLOOKUP(B3, Settings!$A$10:$C$13, 3, FALSE()) -> 4 | F3: =VLOOKUP(C3, Settings!$A$10:$C$13, 3, FALSE()) -> 4 | G3: =VLOOKUP(D3, Settings!$A$10:$C$13, 3, FALSE()) -> 4 | H3: =E3/SUM(E$2:E$11) -> 0.15384615 | I3: =F3/SUM(F$2:F$11) -> 0.16666667 | J3: =G3/SUM(G$2:G$11) -> 0.16666667 | K3: =(H3*Settings!$B$2 + I3*Settings!$B$3 + J3*Settings!$B$4)/(Settings!$B$2+Settings!$B$3+Settings!$B$4) -> 0.16239316
A4: Indian community | B4: =CleanedAnswers!E21 -> D | C4: =CleanedAnswers!F21 -> C | D4: =CleanedAnswers!G21 -> C | E4: =VLOOKUP(B4, Settings!$A$10:$C$13, 3, FALSE()) -> 4 | F4: =VLOOKUP(C4, Settings!$A$10:$C$13, 3, FALSE()) -> 2 | G4: =VLOOKUP(D4, Settings!$A$10:$C$13, 3, FALSE()) -> 2 | H4: =E4/SUM(E$2:E$11) -> 0.15384615 | I4: =F4/SUM(F$2:F$11) -> 0.083333333 | J4: =G4/SUM(G$2:G$11) -> 0.083333333 | K4: =(H4*Settings!$B$2 + I4*Settings!$B$3 + J4*Settings!$B$4)/(Settings!$B$2+Settings!$B$3+Settings!$B$4) -> 0.10683761
A5: Beach | B5: =CleanedAnswers!E22 -> C | C5: =CleanedAnswers!F22 -> C | D5: =CleanedAnswers!G22 -> C | E5: =VLOOKUP(B5, Settings!$A$10:$C$13, 3, FALSE()) -> 2 | F5: =VLOOKUP(C5, Settings!$A$10:$C$13, 3, FALSE()) -> 2 | G5: =VLOOKUP(D5, Settings!$A$10:$C$13, 3, FALSE()) -> 2 | H5: =E5/SUM(E$2:E$11) -> 0.076923077 | I5: =F5/SUM(F$2:F$11) -> 0.083333333 | J5: =G5/SUM(G$2:G$11) -> 0.083333333 | K5: =(H5*Settings!$B$2 + I5*Settings!$B$3 + J5*Settings!$B$4)/(Settings!$B$2+Settings!$B$3+Settings!$B$4) -> 0.081196581
A6: Hospital | B6: =CleanedAnswers!E23 -> C | C6: =CleanedAnswers!F23 -> C | D6: =CleanedAnswers!G23 -> C | E6: =VLOOKUP(B6, Settings!$A$10:$C$13, 3, FALSE()) -> 2 | F6: =VLOOKUP(C6, Settings!$A$10:$C$13, 3, FALSE()) -> 2 | G6: =VLOOKUP(D6, Settings!$A$10:$C$13, 3, FALSE()) -> 2 | H6: =E6/SUM(E$2:E$11) -> 0.076923077 | I6: =F6/SUM(F$2:F$11) -> 0.083333333 | J6: =G6/SUM(G$2:G$11) -> 0.083333333 | K6: =(H6*Settings!$B$2 + I6*Settings!$B$3 + J6*Settings!$B$4)/(Settings!$B$2+Settings!$B$3+Settings!$B$4) -> 0.081196581
A7: Train/bus | B7: =CleanedAnswers!E24 -> C | C7: =CleanedAnswers!F24 -> C | D7: =CleanedAnswers!G24 -> C | E7: =VLOOKUP(B7, Settings!$A$10:$C$13, 3, FALSE()) -> 2 | F7: =VLOOKUP(C7, Settings!$A$10:$C$13, 3, FALSE()) -> 2 | G7: =VLOOKUP(D7, Settings!$A$10:$C$13, 3, FALSE()) -> 2 | H7: =E7/SUM(E$2:E$11) -> 0.076923077 | I7: =F7/SUM(F$2:F$11) -> 0.083333333 | J7: =G7/SUM(G$2:G$11) -> 0.083333333 | K7: =(H7*Settings!$B$2 + I7*Settings!$B$3 + J7*Settings!$B$4)/(Settings!$B$2+Settings!$B$3+Settings!$B$4) -> 0.081196581
A8: Shops/doctor | B8: =CleanedAnswers!E25 -> C | C8: =CleanedAnswers!F25 -> C | D8: =CleanedAnswers!G25 -> C | E8: =VLOOKUP(B8, Settings!$A$10:$C$13, 3, FALSE()) -> 2 | F8: =VLOOKUP(C8, Settings!$A$10:$C$13, 3, FALSE()) -> 2 | G8: =VLOOKUP(D8, Settings!$A$10:$C$13, 3, FALSE()) -> 2 | H8: =E8/SUM(E$2:E$11) -> 0.076923077 | I8: =F8/SUM(F$2:F$11) -> 0.083333333 | J8: =G8/SUM(G$2:G$11) -> 0.083333333 | K8: =(H8*Settings!$B$2 + I8*Settings!$B$3 + J8*Settings!$B$4)/(Settings!$B$2+Settings!$B$3+Settings!$B$4) -> 0.081196581
A9: Village character | B9: =CleanedAnswers!E26 -> C | C9: =CleanedAnswers!F26 -> C | D9: =CleanedAnswers!G26 -> C | E9: =VLOOKUP(B9, Settings!$A$10:$C$13, 3, FALSE()) -> 2 | F9: =VLOOKUP(C9, Settings!$A$10:$C$13, 3, FALSE()) -> 2 | G9: =VLOOKUP(D9, Settings!$A$10:$C$13, 3, FALSE()) -> 2 | H9: =E9/SUM(E$2:E$11) -> 0.076923077 | I9: =F9/SUM(F$2:F$11) -> 0.083333333 | J9: =G9/SUM(G$2:G$11) -> 0.083333333 | K9: =(H9*Settings!$B$2 + I9*Settings!$B$3 + J9*Settings!$B$4)/(Settings!$B$2+Settings!$B$3+Settings!$B$4) -> 0.081196581
A10: Price | B10: =CleanedAnswers!E27 -> C | C10: =CleanedAnswers!F27 -> C | D10: =CleanedAnswers!G27 -> C | E10: =VLOOKUP(B10, Settings!$A$10:$C$13, 3, FALSE()) -> 2 | F10: =VLOOKUP(C10, Settings!$A$10:$C$13, 3, FALSE()) -> 2 | G10: =VLOOKUP(D10, Settings!$A$10:$C$13, 3, FALSE()) -> 2 | H10: =E10/SUM(E$2:E$11) -> 0.076923077 | I10: =F10/SUM(F$2:F$11) -> 0.083333333 | J10: =G10/SUM(G$2:G$11) -> 0.083333333 | K10: =(H10*Settings!$B$2 + I10*Settings!$B$3 + J10*Settings!$B$4)/(Settings!$B$2+Settings!$B$3+Settings!$B$4) -> 0.081196581
A11: Easy city trip | B11: =CleanedAnswers!E28 -> C | C11: =CleanedAnswers!F28 -> C | D11: =CleanedAnswers!G28 -> C | E11: =VLOOKUP(B11, Settings!$A$10:$C$13, 3, FALSE()) -> 2 | F11: =VLOOKUP(C11, Settings!$A$10:$C$13, 3, FALSE()) -> 2 | G11: =VLOOKUP(D11, Settings!$A$10:$C$13, 3, FALSE()) -> 2 | H11: =E11/SUM(E$2:E$11) -> 0.076923077 | I11: =F11/SUM(F$2:F$11) -> 0.083333333 | J11: =G11/SUM(G$2:G$11) -> 0.083333333 | K11: =(H11*Settings!$B$2 + I11*Settings!$B$3 + J11*Settings!$B$4)/(Settings!$B$2+Settings!$B$3+Settings!$B$4) -> 0.081196581

Sheet ForcedChoiceCorrections
A1: Matchup | B1: Result
A2: Q10 | B2: +7.2% from Nature to Near family in GW
A3: Q12 | B3: +2.6% from Village character to Shops & doctor
A5: Final Normalized Weights | B5: Weight
A6: Near family in GW | B6: 0.153
A7: Nature | B7: 0.133
A8: Hospital | B8: 0.133
A9: Indian community | B9: 0.117
A10: Shops & doctor | B10: 0.108
A11: Village character | B11: 0.088
A12: Train/bus | B12: 0.081
A13: Price | B13: 0.081
A14: Beach | B14: 0.061
A15: City trip | B15: 0.045

Sheet SuburbScorecard
A1: Location | B1: Region | C1: Shortlist Status | D1: Parents Inland/Bush Fit (P) | E1: My Coastal-Nature Fit (Y) | F1: Primary Investigation Lens | G1: Published House Price | H1: Price Basis | I1: Price + Est. 6% Costs | J1: Drive to GW (min) | K1: Drive to 24-Hr Public ED (min) | L1: Hard Filter Status | M1: Score: Near family in GW | N1: Score: Nature | O1: Score: Hospital | P1: Score: Indian community | Q1: Score: Shops & doctor | R1: Score: Village character | S1: Score: Train/bus | T1: Score: Price | U1: Score: Beach | V1: Score: City trip | W1: Scores Entered | X1: Weighted Score (0-10) | Y1: Rank (Passing Only) | Z1: Healthcare & ABS Verification Notes | AA1: Legacy import text (frozen 27 Oct 2026; not used by any formula — edit columns A–H and Z instead) | AB1: Train Option (Yes/No) | AC1: Train Station / Basis | AD1: ED Used for Drive Time (K) | AE1: Budget cap — purchase price | AF1: Budget basis | AG1: Price evidence type | AH1: Price evidence date | AI1: Budget result | AJ1: Budget note
A2: Blackburn | B2: East Melbourne | C2: Active Shortlist | D2: Medium (Leafy streets) | E2: Low (Inland) | F2: Leafy daily living vs housing cost | G2: 1600000 | H2: Sale median, rolling 12m (OnTheHouse); unit $820k | I2: {=IF(ISNUMBER(G2:G90), IF(G2:G90>0, G2:G90 * (1 + Settings!$B$6), ""), "")} -> 1696000 | J2: 11 | K2: 7 | L2: Active — needs data | O2: =IF(K2="","",ROUND(MAX(0,10*(1-K2/Filters!$B$5)),1)) -> 9.2 | W2: =IF(M2="",0,COUNT(M2:V2)) -> 0 | X2: =IF(W2<10,"",M2*ForcedChoiceCorrections!$B$6+N2*ForcedChoiceCorrections!$B$7+O2*ForcedChoiceCorrections!$B$8+P2*ForcedChoiceCorrections!$B$9+Q2*ForcedChoiceCorrections!$B$10+R2*ForcedChoiceCorrections!$B$11+S2*ForcedChoiceCorrections!$B$12+T2*ForcedChoiceCorrections!$B$13+U2*ForcedChoiceCorrections!$B$14+V2*ForcedChoiceCorrections!$B$15) | Y2: =IF(AND(ISNUMBER(SEARCH("pass",L2)),ISNUMBER(X2)),COUNTIFS(L$2:L$90,"*pass*",X$2:X$90,">"&X2)+1,"") | Z2: ABS 2021: 32.4% overseas-born, 31.6% non-Eng HH. Station/ED journeys unverified. | AA2: 1. Blackburn | East Melbourne | Active Shortlist | P: Medium (Leafy streets) | Y: Low (Inland) | Lens: Leafy daily living vs housing cost | Price: 1600000 | Basis: Sale median, rolling 12m (OnTheHouse); unit $820k | Note: ABS 2021: 32.4% overseas-born, 31.6% non-Eng HH. Station/ED journeys unverified. | AB2: Yes | AC2: Blackburn station, Lilydale line (recall; verify) | AD2: Box Hill Hospital ED | AE2: 1500000 | AF2: Maximum purchase price, excluding transaction and moving costs | AG2: Suburb median | AH2: 26 Oct 2026 | AI2: Needs data | AJ2: House median $1.60M (OnTheHouse) exceeds $1.5M cap, but unit/villa median is $820k. Awaiting documented search for suitable single-level homes/units under $1.5M.
A3: Ringwood | B3: East Melbourne | C3: Active Shortlist | D3: Medium-High (Foothills gateway) | E3: Low (Inland) | F3: Rail, services & access to greener surroundings | G3: 1045000 | H3: Sale median, rolling 12m (OnTheHouse); unit $650k | I3: 1107700 | J3: 12 | K3: 5 | L3: Active — provisional pass | O3: =IF(K3="","",ROUND(MAX(0,10*(1-K3/Filters!$B$5)),1)) -> 9.4 | W3: =IF(M3="",0,COUNT(M3:V3)) -> 0 | X3: =IF(W3<10,"",M3*ForcedChoiceCorrections!$B$6+N3*ForcedChoiceCorrections!$B$7+O3*ForcedChoiceCorrections!$B$8+P3*ForcedChoiceCorrections!$B$9+Q3*ForcedChoiceCorrections!$B$10+R3*ForcedChoiceCorrections!$B$11+S3*ForcedChoiceCorrections!$B$12+T3*ForcedChoiceCorrections!$B$13+U3*ForcedChoiceCorrections!$B$14+V3*ForcedChoiceCorrections!$B$15) | Y3: =IF(AND(ISNUMBER(SEARCH("pass",L3)),ISNUMBER(X3)),COUNTIFS(L$2:L$90,"*pass*",X$2:X$90,">"&X3)+1,"") | Z3: ABS 2021: 35.7% overseas-born, 33.3% non-Eng HH. Belgrave/Lilydale rail; Maroondah Hospital ED nearby (verify drive). | AA3: 2. Ringwood | East Melbourne | Active Shortlist | P: Medium-High (Foothills gateway) | Y: Low (Inland) | Lens: Rail, services & access to greener surroundings | Price: 1045000 | Basis: Sale median, rolling 12m (OnTheHouse); unit $650k | Note: ABS 2021: 35.7% overseas-born, 33.3% non-Eng HH. Belgrave/Lilydale rail; Maroondah Hospital ED nearby (verify drive). | AB3: Yes | AC3: Ringwood station, Lilydale/Belgrave lines (recall; verify) | AD3: Maroondah Hospital ED | AE3: 1500000 | AF3: Maximum purchase price, excluding transaction and moving costs | AG3: Suburb median | AH3: 26 Oct 2026 | AI3: Pass | AJ3: Published house price ($1,045,000) is under $1.5M cap.
A4: Heidelberg | B4: North-East Melbourne | C4: Active Shortlist | D4: Medium (Yarra parkland) | E4: Low (Inland) | F4: Healthcare-led established suburb option | G4: 1452000 | H4: Sale median, rolling 12m (35 sales); unit $700k | I4: 1539120 | J4: 25 | K4: 4 | L4: Active — provisional pass | O4: =IF(K4="","",ROUND(MAX(0,10*(1-K4/Filters!$B$5)),1)) -> 9.6 | W4: =IF(M4="",0,COUNT(M4:V4)) -> 0 | X4: =IF(W4<10,"",M4*ForcedChoiceCorrections!$B$6+N4*ForcedChoiceCorrections!$B$7+O4*ForcedChoiceCorrections!$B$8+P4*ForcedChoiceCorrections!$B$9+Q4*ForcedChoiceCorrections!$B$10+R4*ForcedChoiceCorrections!$B$11+S4*ForcedChoiceCorrections!$B$12+T4*ForcedChoiceCorrections!$B$13+U4*ForcedChoiceCorrections!$B$14+V4*ForcedChoiceCorrections!$B$15) | Y4: =IF(AND(ISNUMBER(SEARCH("pass",L4)),ISNUMBER(X4)),COUNTIFS(L$2:L$90,"*pass*",X$2:X$90,">"&X4)+1,"") | Z4: ABS 2021: 28.1% overseas-born, 28.4% non-Eng HH. Austin Hospital precinct; verify residential pocket & gradients. | AA4: 3. Heidelberg | North-East Melbourne | Active Shortlist | P: Medium (Yarra parkland) | Y: Low (Inland) | Lens: Healthcare-led established suburb option | Price: 1452000 | Basis: Sale median, rolling 12m (35 sales); unit $700k | Note: ABS 2021: 28.1% overseas-born, 28.4% non-Eng HH. Austin Hospital precinct; verify residential pocket & gradients. | AB4: Yes | AC4: Heidelberg station, Hurstbridge line (recall; verify) | AD4: Austin Hospital ED | AE4: 1500000 | AF4: Maximum purchase price, excluding transaction and moving costs | AG4: Suburb median | AH4: 26 Oct 2026 | AI4: Pass | AJ4: House median $1.452M (35 sales) is under $1.5M cap. Passes GW drive (25m) and ED drive (4m).
A5: Eltham | B5: North-East Melbourne | C5: Active Shortlist | D5: High (Bushland/trees) | E5: Low (Inland) | F5: Green/scenic lifestyle hypothesis | G5: 1273000 | H5: Sale median, rolling 12m (195 sales); unit $805k | I5: 1349380 | J5: 26 | K5: 16 | L5: Active — provisional pass | O5: =IF(K5="","",ROUND(MAX(0,10*(1-K5/Filters!$B$5)),1)) -> 8.2 | W5: =IF(M5="",0,COUNT(M5:V5)) -> 0 | X5: =IF(W5<10,"",M5*ForcedChoiceCorrections!$B$6+N5*ForcedChoiceCorrections!$B$7+O5*ForcedChoiceCorrections!$B$8+P5*ForcedChoiceCorrections!$B$9+Q5*ForcedChoiceCorrections!$B$10+R5*ForcedChoiceCorrections!$B$11+S5*ForcedChoiceCorrections!$B$12+T5*ForcedChoiceCorrections!$B$13+U5*ForcedChoiceCorrections!$B$14+V5*ForcedChoiceCorrections!$B$15) | Y5: =IF(AND(ISNUMBER(SEARCH("pass",L5)),ISNUMBER(X5)),COUNTIFS(L$2:L$90,"*pass*",X$2:X$90,">"&X5)+1,"") | Z5: ABS 2021: 18.5% overseas-born, 14.0% non-Eng HH. Hurstbridge line; verify ED & GW drive times. | AA5: 4. Eltham | North-East Melbourne | Active Shortlist | P: High (Bushland/trees) | Y: Low (Inland) | Lens: Green/scenic lifestyle hypothesis | Price: 1273000 | Basis: Sale median, rolling 12m (195 sales); unit $805k | Note: ABS 2021: 18.5% overseas-born, 14.0% non-Eng HH. Hurstbridge line; verify ED & GW drive times. | AB5: Yes | AC5: Eltham station, Hurstbridge line (recall; verify) | AD5: Austin Hospital ED | AE5: 1500000 | AF5: Maximum purchase price, excluding transaction and moving costs | AG5: Suburb median | AH5: 26 Oct 2026 | AI5: Pass | AJ5: House median $1.273M (195 sales) is under $1.5M cap. Passes GW drive (26m) and ED drive (16m).
A6: Upper Ferntree Gully | B6: East / Foothills | C6: Active Shortlist | D6: High (Foothills/forest) | E6: Low (Inland) | F6: Forest/foothills lifestyle with hospital & rail access | G6: 872133 | H6: AVM estimate (30 Sep 2026), NOT a verified sale median | I6: 924460.98 | J6: 16 | K6: 2 | L6: Active — provisional pass | O6: =IF(K6="","",ROUND(MAX(0,10*(1-K6/Filters!$B$5)),1)) -> 9.8 | W6: =IF(M6="",0,COUNT(M6:V6)) -> 0 | X6: =IF(W6<10,"",M6*ForcedChoiceCorrections!$B$6+N6*ForcedChoiceCorrections!$B$7+O6*ForcedChoiceCorrections!$B$8+P6*ForcedChoiceCorrections!$B$9+Q6*ForcedChoiceCorrections!$B$10+R6*ForcedChoiceCorrections!$B$11+S6*ForcedChoiceCorrections!$B$12+T6*ForcedChoiceCorrections!$B$13+U6*ForcedChoiceCorrections!$B$14+V6*ForcedChoiceCorrections!$B$15) | Y6: =IF(AND(ISNUMBER(SEARCH("pass",L6)),ISNUMBER(X6)),COUNTIFS(L$2:L$90,"*pass*",X$2:X$90,">"&X6)+1,"") | Z6: ABS 2021: 19.2% overseas-born, 12.2% non-Eng HH. Belgrave line; 10-min walk/bus 732 to Angliss Hospital (verify 24-hr ED status & drive). | AA6: 5. Upper Ferntree Gully | East / Foothills | Active Shortlist | P: High (Foothills/forest) | Y: Low (Inland) | Lens: Forest/foothills lifestyle with hospital & rail access | Price: 872133 | Basis: AVM estimate (30 Sep 2026), NOT a verified sale median | Note: ABS 2021: 19.2% overseas-born, 12.2% non-Eng HH. Belgrave line; 10-min walk/bus 732 to Angliss Hospital (verify 24-hr ED status & drive). | AB6: Yes | AC6: Upper Ferntree Gully station, Belgrave line (per sheet note) | AD6: Angliss Hospital ED (24-hr status still to verify) | AE6: 1500000 | AF6: Maximum purchase price, excluding transaction and moving costs | AG6: Suburb median | AH6: 26 Oct 2026 | AI6: Pass | AJ6: Published house price ($872,133) is under $1.5M cap.
A7: Glen Waverley | B7: East Melbourne | C7: Active Shortlist | D7: Low-Medium (Suburban) | E7: Low (Inland) | F7: Current stay baseline — multicultural convenience | G7: 1763500 | H7: Sale median, rolling 12m (454 sales); unit $930k | I7: 1869310 | J7: 0 | K7: 13 | L7: Active — needs data | O7: =IF(K7="","",ROUND(MAX(0,10*(1-K7/Filters!$B$5)),1)) -> 8.6 | W7: =IF(M7="",0,COUNT(M7:V7)) -> 0 | X7: =IF(W7<10,"",M7*ForcedChoiceCorrections!$B$6+N7*ForcedChoiceCorrections!$B$7+O7*ForcedChoiceCorrections!$B$8+P7*ForcedChoiceCorrections!$B$9+Q7*ForcedChoiceCorrections!$B$10+R7*ForcedChoiceCorrections!$B$11+S7*ForcedChoiceCorrections!$B$12+T7*ForcedChoiceCorrections!$B$13+U7*ForcedChoiceCorrections!$B$14+V7*ForcedChoiceCorrections!$B$15) | Y7: =IF(AND(ISNUMBER(SEARCH("pass",L7)),ISNUMBER(X7)),COUNTIFS(L$2:L$90,"*pass*",X$2:X$90,">"&X7)+1,"") | Z7: ABS 2021: 58.7% overseas-born, 63.0% non-Eng HH. Baseline benchmark for family proximity. | AA7: 6. Glen Waverley | East Melbourne | Active Shortlist | P: Low-Medium (Suburban) | Y: Low (Inland) | Lens: Current stay baseline — multicultural convenience | Price: 1763500 | Basis: Sale median, rolling 12m (454 sales); unit $930k | Note: ABS 2021: 58.7% overseas-born, 63.0% non-Eng HH. Baseline benchmark for family proximity. | AB7: Yes | AC7: Glen Waverley station, Glen Waverley line (recall; verify) | AD7: Monash Medical Centre Clayton ED | AE7: 1500000 | AF7: Maximum purchase price, excluding transaction and moving costs | AG7: Suburb median | AH7: 26 Oct 2026 | AI7: Needs data | AJ7: House median $1.76M (454 sales) exceeds $1.5M cap; unit median $930k. Awaiting documented search for suitable single-level homes/units under $1.5M.
A8: Warrandyte | B8: North-East / Yarra | C8: Active Shortlist | D8: High (River & state park) | E8: Low (River, non-coastal) | F8: River-and-bush living within metro boundary | H8: Not verified in report | J8: 20 | K8: 14 | L8: Needs data | O8: =IF(K8="","",ROUND(MAX(0,10*(1-K8/Filters!$B$5)),1)) -> 8.4 | W8: =IF(M8="",0,COUNT(M8:V8)) -> 0 | X8: =IF(W8<10,"",M8*ForcedChoiceCorrections!$B$6+N8*ForcedChoiceCorrections!$B$7+O8*ForcedChoiceCorrections!$B$8+P8*ForcedChoiceCorrections!$B$9+Q8*ForcedChoiceCorrections!$B$10+R8*ForcedChoiceCorrections!$B$11+S8*ForcedChoiceCorrections!$B$12+T8*ForcedChoiceCorrections!$B$13+U8*ForcedChoiceCorrections!$B$14+V8*ForcedChoiceCorrections!$B$15) | Y8: =IF(AND(ISNUMBER(SEARCH("pass",L8)),ISNUMBER(X8)),COUNTIFS(L$2:L$90,"*pass*",X$2:X$90,">"&X8)+1,"") | Z8: ABS 2021: 17.7% aged 65+, 17.0% non-Eng HH. Direct city bus 906; no local rail; check fire overlay & ED drive. | AA8: 7. Warrandyte | North-East / Yarra | Active Shortlist | P: High (River & state park) | Y: Low (River, non-coastal) | Lens: River-and-bush living within metro boundary | Price: [Blank] | Basis: Not verified in report | Note: ABS 2021: 17.7% aged 65+, 17.0% non-Eng HH. Direct city bus 906; no local rail; check fire overlay & ED drive. | AB8: No | AC8: No rail; bus 906 (per sheet note) | AD8: Maroondah Hospital ED | AE8: 1500000 | AF8: Maximum purchase price, excluding transaction and moving costs | AG8: [Awaiting search] | AH8: 26 Oct 2026 | AI8: Needs data | AJ8: No verified pricing entered.
A9: Diamond Creek | B9: North-East Fringe | C9: Active Shortlist | D9: High (Green wedge & trail) | E9: Low (Inland) | F9: Practical metro nature compromise with rail | G9: 885000 | H9: 3-bed house median $885k; 4-bed $1,240k (Domain) | I9: 938100 | J9: 33 | K9: 19 | L9: Active — provisional pass | O9: =IF(K9="","",ROUND(MAX(0,10*(1-K9/Filters!$B$5)),1)) -> 7.9 | W9: =IF(M9="",0,COUNT(M9:V9)) -> 0 | X9: =IF(W9<10,"",M9*ForcedChoiceCorrections!$B$6+N9*ForcedChoiceCorrections!$B$7+O9*ForcedChoiceCorrections!$B$8+P9*ForcedChoiceCorrections!$B$9+Q9*ForcedChoiceCorrections!$B$10+R9*ForcedChoiceCorrections!$B$11+S9*ForcedChoiceCorrections!$B$12+T9*ForcedChoiceCorrections!$B$13+U9*ForcedChoiceCorrections!$B$14+V9*ForcedChoiceCorrections!$B$15) | Y9: =IF(AND(ISNUMBER(SEARCH("pass",L9)),ISNUMBER(X9)),COUNTIFS(L$2:L$90,"*pass*",X$2:X$90,">"&X9)+1,"") | Z9: ABS 2021: 13.1% aged 65+, 12.2% non-Eng HH. Hurstbridge line station & trail; verify ED & GW drive. | AA9: 8. Diamond Creek | North-East Fringe | Active Shortlist | P: High (Green wedge & trail) | Y: Low (Inland) | Lens: Practical metro nature compromise with rail | Price: 885000 | Basis: 3-bed house median $885k; 4-bed $1,240k (Domain) | Note: ABS 2021: 13.1% aged 65+, 12.2% non-Eng HH. Hurstbridge line station & trail; verify ED & GW drive. | AB9: Yes | AC9: Diamond Creek station, Hurstbridge line (per sheet note) | AD9: Austin Hospital ED | AE9: 1500000 | AF9: Maximum purchase price, excluding transaction and moving costs | AG9: Suburb median | AH9: 26 Oct 2026 | AI9: Pass | AJ9: Published house price ($885,000) is under $1.5M cap.
A10: Mentone | B10: Bayside Melbourne | C10: Active Shortlist | D10: Low-Medium (Suburban gardens) | E10: High (Bay beach) | F10: Coastal daily living on metro rail line | G10: 1497099 | H10: Sale median (Aussie/CoreLogic); Woodards shows $1.30m | I10: 1586924.9 | J10: 25 | K10: 16 | L10: Active — provisional pass | O10: =IF(K10="","",ROUND(MAX(0,10*(1-K10/Filters!$B$5)),1)) -> 8.2 | W10: =IF(M10="",0,COUNT(M10:V10)) -> 0 | X10: =IF(W10<10,"",M10*ForcedChoiceCorrections!$B$6+N10*ForcedChoiceCorrections!$B$7+O10*ForcedChoiceCorrections!$B$8+P10*ForcedChoiceCorrections!$B$9+Q10*ForcedChoiceCorrections!$B$10+R10*ForcedChoiceCorrections!$B$11+S10*ForcedChoiceCorrections!$B$12+T10*ForcedChoiceCorrections!$B$13+U10*ForcedChoiceCorrections!$B$14+V10*ForcedChoiceCorrections!$B$15) | Y10: =IF(AND(ISNUMBER(SEARCH("pass",L10)),ISNUMBER(X10)),COUNTIFS(L$2:L$90,"*pass*",X$2:X$90,">"&X10)+1,"") | Z10: ABS 2021: 28.8% overseas-born, 22.4% non-Eng HH. Reconcile price sources & verify ED drive. | AA10: 9. Mentone | Bayside Melbourne | Active Shortlist | P: Low-Medium (Suburban gardens) | Y: High (Bay beach) | Lens: Coastal daily living on metro rail line | Price: 1497099 | Basis: Sale median (Aussie/CoreLogic); Woodards shows $1.30m | Note: ABS 2021: 28.8% overseas-born, 22.4% non-Eng HH. Reconcile price sources & verify ED drive. | AB10: Yes | AC10: Mentone station, Frankston line (recall; verify) | AD10: Monash Medical Centre Clayton ED | AE10: 1500000 | AF10: Maximum purchase price, excluding transaction and moving costs | AG10: Suburb median | AH10: 26 Oct 2026 | AI10: Pass | AJ10: House median $1.497M (CoreLogic) / $1.30M (Woodards) is under $1.5M cap. Passes GW drive (25m) and ED drive (16m).
A11: Frankston | B11: South / Coastal | C11: Active Shortlist | D11: Medium (Sweetwater/gullies) | E11: High (Bay beach) | F11: Coastal practicality & accessible property price | G11: 834296 | H11: Sale median, rolling 12m (Aussie/Cotality); unit $573k | I11: 884353.76 | J11: 25 | K11: 4 | L11: Active — provisional pass | O11: =IF(K11="","",ROUND(MAX(0,10*(1-K11/Filters!$B$5)),1)) -> 9.6 | W11: =IF(M11="",0,COUNT(M11:V11)) -> 0 | X11: =IF(W11<10,"",M11*ForcedChoiceCorrections!$B$6+N11*ForcedChoiceCorrections!$B$7+O11*ForcedChoiceCorrections!$B$8+P11*ForcedChoiceCorrections!$B$9+Q11*ForcedChoiceCorrections!$B$10+R11*ForcedChoiceCorrections!$B$11+S11*ForcedChoiceCorrections!$B$12+T11*ForcedChoiceCorrections!$B$13+U11*ForcedChoiceCorrections!$B$14+V11*ForcedChoiceCorrections!$B$15) | Y11: =IF(AND(ISNUMBER(SEARCH("pass",L11)),ISNUMBER(X11)),COUNTIFS(L$2:L$90,"*pass*",X$2:X$90,">"&X11)+1,"") | Z11: ABS 2021: 22.5% overseas-born, 15.2% non-Eng HH. Peninsula Univ Hospital ED; ~66m train to CBD. | AA11: 10. Frankston | South / Coastal | Active Shortlist | P: Medium (Sweetwater/gullies) | Y: High (Bay beach) | Lens: Coastal practicality & accessible property price | Price: 834296 | Basis: Sale median, rolling 12m (Aussie/Cotality); unit $573k | Note: ABS 2021: 22.5% overseas-born, 15.2% non-Eng HH. Peninsula Univ Hospital ED; ~66m train to CBD. | AB11: Yes | AC11: Frankston station, Frankston line (recall; verify) | AD11: Peninsula University Hospital ED | AE11: 1500000 | AF11: Maximum purchase price, excluding transaction and moving costs | AG11: Suburb median | AH11: 26 Oct 2026 | AI11: Pass | AJ11: Published house price ($834,296) is under $1.5M cap.
A12: Altona | B12: West Coastal | C12: Active Shortlist | D12: Low-Medium (Flat coastal) | E12: High (Bay beach/wetlands) | F12: Coastal village alternative at lower price point | G12: 1155073 | H12: AVM estimate (31 Aug 2026), NOT a verified sale median | I12: 1224377.4 | J12: 35 | K12: 15 | L12: Active — provisional pass | O12: =IF(K12="","",ROUND(MAX(0,10*(1-K12/Filters!$B$5)),1)) -> 8.3 | W12: =IF(M12="",0,COUNT(M12:V12)) -> 0 | X12: =IF(W12<10,"",M12*ForcedChoiceCorrections!$B$6+N12*ForcedChoiceCorrections!$B$7+O12*ForcedChoiceCorrections!$B$8+P12*ForcedChoiceCorrections!$B$9+Q12*ForcedChoiceCorrections!$B$10+R12*ForcedChoiceCorrections!$B$11+S12*ForcedChoiceCorrections!$B$12+T12*ForcedChoiceCorrections!$B$13+U12*ForcedChoiceCorrections!$B$14+V12*ForcedChoiceCorrections!$B$15) | Y12: =IF(AND(ISNUMBER(SEARCH("pass",L12)),ISNUMBER(X12)),COUNTIFS(L$2:L$90,"*pass*",X$2:X$90,">"&X12)+1,"") | Z12: ABS 2021: 28.3% overseas-born, 23.8% non-Eng HH. Cross-city drive to Glen Waverley needs testing. | AA12: 11. Altona | West Coastal | Active Shortlist | P: Low-Medium (Flat coastal) | Y: High (Bay beach/wetlands) | Lens: Coastal village alternative at lower price point | Price: 1155073 | Basis: AVM estimate (31 Aug 2026), NOT a verified sale median | Note: ABS 2021: 28.3% overseas-born, 23.8% non-Eng HH. Cross-city drive to Glen Waverley needs testing. | AB12: Yes | AC12: Altona station, Werribee line (recall; verify) | AD12: Footscray Hospital ED | AE12: 1500000 | AF12: Maximum purchase price, excluding transaction and moving costs | AG12: Suburb median | AH12: 26 Oct 2026 | AI12: Pass | AJ12: Published house price ($1,155,073) is under $1.5M cap.
A13: Williamstown | B13: West Coastal | C13: Active Shortlist | D13: Medium (Botanic gardens) | E13: High (Historic harbor/beach) | F13: Picturesque coastal character vs cost | G13: 1642163 | H13: AVM estimate (30 Sep 2026), NOT a verified sale median | I13: 1740692.8 | J13: 31 | K13: 13 | L13: Active — needs data | O13: =IF(K13="","",ROUND(MAX(0,10*(1-K13/Filters!$B$5)),1)) -> 8.6 | W13: =IF(M13="",0,COUNT(M13:V13)) -> 0 | X13: =IF(W13<10,"",M13*ForcedChoiceCorrections!$B$6+N13*ForcedChoiceCorrections!$B$7+O13*ForcedChoiceCorrections!$B$8+P13*ForcedChoiceCorrections!$B$9+Q13*ForcedChoiceCorrections!$B$10+R13*ForcedChoiceCorrections!$B$11+S13*ForcedChoiceCorrections!$B$12+T13*ForcedChoiceCorrections!$B$13+U13*ForcedChoiceCorrections!$B$14+V13*ForcedChoiceCorrections!$B$15) | Y13: =IF(AND(ISNUMBER(SEARCH("pass",L13)),ISNUMBER(X13)),COUNTIFS(L$2:L$90,"*pass*",X$2:X$90,">"&X13)+1,"") | Z13: ABS 2021: 22.6% overseas-born, 20.0% non-Eng HH. Cross-city travel to Glen Waverley & ED capacity need checking. | AA13: 12. Williamstown | West Coastal | Active Shortlist | P: Medium (Botanic gardens) | Y: High (Historic harbor/beach) | Lens: Picturesque coastal character vs cost | Price: 1642163 | Basis: AVM estimate (30 Sep 2026), NOT a verified sale median | Note: ABS 2021: 22.6% overseas-born, 20.0% non-Eng HH. Cross-city travel to Glen Waverley & ED capacity need checking. | AB13: Yes | AC13: Williamstown station, Williamstown line (recall; verify) | AD13: Footscray Hospital ED | AE13: 1500000 | AF13: Maximum purchase price, excluding transaction and moving costs | AG13: AVM estimate | AH13: 26 Oct 2026 | AI13: Needs data | AJ13: Figure is an automated valuation model ($1.64M), not a verified sale median or specific property. Awaiting documented listing search under $1.5M.
A14: Healesville | B14: Yarra Valley | C14: Active Shortlist | D14: High (Valley & mountains) | E14: Low (Inland) | F14: Larger Yarra Valley town comparator | H14: Not verified in report | J14: 43 | K14: 33 | L14: Needs data | O14: =IF(K14="","",ROUND(MAX(0,10*(1-K14/Filters!$B$5)),1)) -> 6.3 | W14: =IF(M14="",0,COUNT(M14:V14)) -> 0 | X14: =IF(W14<10,"",M14*ForcedChoiceCorrections!$B$6+N14*ForcedChoiceCorrections!$B$7+O14*ForcedChoiceCorrections!$B$8+P14*ForcedChoiceCorrections!$B$9+Q14*ForcedChoiceCorrections!$B$10+R14*ForcedChoiceCorrections!$B$11+S14*ForcedChoiceCorrections!$B$12+T14*ForcedChoiceCorrections!$B$13+U14*ForcedChoiceCorrections!$B$14+V14*ForcedChoiceCorrections!$B$15) | Y14: =IF(AND(ISNUMBER(SEARCH("pass",L14)),ISNUMBER(X14)),COUNTIFS(L$2:L$90,"*pass*",X$2:X$90,">"&X14)+1,"") | Z14: 2021 pop 7,589. CAUTION: Eastern Health directs urgent ED patients to Maroondah Hospital ED (not local). | AA14: 13. Healesville | Yarra Valley | Active Shortlist | P: High (Valley & mountains) | Y: Low (Inland) | Lens: Larger Yarra Valley town comparator | Price: [Blank] | Basis: Not verified in report | Note: 2021 pop 7,589. CAUTION: Eastern Health directs urgent ED patients to Maroondah Hospital ED (not local). | AB14: No | AC14: No rail (recall; verify) | AD14: Maroondah Hospital ED (sheet note: urgent ED cases go here) | AE14: 1500000 | AF14: Maximum purchase price, excluding transaction and moving costs | AG14: [Awaiting search] | AH14: 26 Oct 2026 | AI14: Needs data | AJ14: No verified pricing entered.
A15: Kyneton | B15: Macedon Ranges | C15: Active Shortlist | D15: High (Country town & gardens) | E15: Low (Inland river) | F15: Country-town practicality with V/Line rail | G15: 810000 | H15: 3-bed house median $810k; 4-bed $980k (Domain) | I15: 858600 | J15: 77 | K15: 47 | L15: Active — provisional pass | O15: =IF(K15="","",ROUND(MAX(0,10*(1-K15/Filters!$B$5)),1)) -> 4.8 | W15: =IF(M15="",0,COUNT(M15:V15)) -> 0 | X15: =IF(W15<10,"",M15*ForcedChoiceCorrections!$B$6+N15*ForcedChoiceCorrections!$B$7+O15*ForcedChoiceCorrections!$B$8+P15*ForcedChoiceCorrections!$B$9+Q15*ForcedChoiceCorrections!$B$10+R15*ForcedChoiceCorrections!$B$11+S15*ForcedChoiceCorrections!$B$12+T15*ForcedChoiceCorrections!$B$13+U15*ForcedChoiceCorrections!$B$14+V15*ForcedChoiceCorrections!$B$15) | Y15: =IF(AND(ISNUMBER(SEARCH("pass",L15)),ISNUMBER(X15)),COUNTIFS(L$2:L$90,"*pass*",X$2:X$90,">"&X15)+1,"") | Z15: ABS 2021: 25.0% aged 65+, 6.9% non-Eng HH. CAUTION: Local facility is 24-hr Urgent Care Centre, NOT a major public ED. | AA15: 14. Kyneton | Macedon Ranges | Active Shortlist | P: High (Country town & gardens) | Y: Low (Inland river) | Lens: Country-town practicality with V/Line rail | Price: 810000 | Basis: 3-bed house median $810k; 4-bed $980k (Domain) | Note: ABS 2021: 25.0% aged 65+, 6.9% non-Eng HH. CAUTION: Local facility is 24-hr Urgent Care Centre, NOT a major public ED. | AB15: Yes | AC15: Kyneton station, V/Line Bendigo (per sheet note) | AD15: Bendigo Hospital ED (local 24-hr urgent care is not an ED) | AE15: 1500000 | AF15: Maximum purchase price, excluding transaction and moving costs | AG15: Suburb median | AH15: 26 Oct 2026 | AI15: Pass | AJ15: Published house price ($810,000) is under $1.5M cap.
A16: Woodend | B16: Macedon Ranges | C16: Active Shortlist | D16: High (Macedon Ranges forest) | E16: Low (Inland) | F16: Walkable station country town in Macedon Ranges | G16: 890000 | H16: 3-bed house median $890k; 4-bed $1,150k (Domain) | I16: 943400 | J16: 68 | K16: 55 | L16: Active — provisional pass | O16: =IF(K16="","",ROUND(MAX(0,10*(1-K16/Filters!$B$5)),1)) -> 3.9 | W16: =IF(M16="",0,COUNT(M16:V16)) -> 0 | X16: =IF(W16<10,"",M16*ForcedChoiceCorrections!$B$6+N16*ForcedChoiceCorrections!$B$7+O16*ForcedChoiceCorrections!$B$8+P16*ForcedChoiceCorrections!$B$9+Q16*ForcedChoiceCorrections!$B$10+R16*ForcedChoiceCorrections!$B$11+S16*ForcedChoiceCorrections!$B$12+T16*ForcedChoiceCorrections!$B$13+U16*ForcedChoiceCorrections!$B$14+V16*ForcedChoiceCorrections!$B$15) | Y16: =IF(AND(ISNUMBER(SEARCH("pass",L16)),ISNUMBER(X16)),COUNTIFS(L$2:L$90,"*pass*",X$2:X$90,">"&X16)+1,"") | Z16: V/Line Bendigo line. Check winter comfort, major public ED drive time & family trip frequency. | AA16: 15. Woodend | Macedon Ranges | Active Shortlist | P: High (Macedon Ranges forest) | Y: Low (Inland) | Lens: Walkable station country town in Macedon Ranges | Price: 890000 | Basis: 3-bed house median $890k; 4-bed $1,150k (Domain) | Note: V/Line Bendigo line. Check winter comfort, major public ED drive time & family trip frequency. | AB16: Yes | AC16: Woodend station, V/Line Bendigo (per sheet note) | AD16: Bendigo Hospital ED (nearest ED not confirmed; Northern Hospital Epping not tested) | AE16: 1500000 | AF16: Maximum purchase price, excluding transaction and moving costs | AG16: Suburb median | AH16: 26 Oct 2026 | AI16: Pass | AJ16: Published house price ($890,000) is under $1.5M cap.
A17: Macedon | B17: Macedon Ranges | C17: Active Shortlist | D17: High (Forest & Honour Ave) | E17: Low (Inland) | F17: Landscape-led Macedon Ranges option | H17: Not verified in report | J17: 62 | K17: 60 | L17: Needs data | O17: =IF(K17="","",ROUND(MAX(0,10*(1-K17/Filters!$B$5)),1)) -> 3.3 | W17: =IF(M17="",0,COUNT(M17:V17)) -> 0 | X17: =IF(W17<10,"",M17*ForcedChoiceCorrections!$B$6+N17*ForcedChoiceCorrections!$B$7+O17*ForcedChoiceCorrections!$B$8+P17*ForcedChoiceCorrections!$B$9+Q17*ForcedChoiceCorrections!$B$10+R17*ForcedChoiceCorrections!$B$11+S17*ForcedChoiceCorrections!$B$12+T17*ForcedChoiceCorrections!$B$13+U17*ForcedChoiceCorrections!$B$14+V17*ForcedChoiceCorrections!$B$15) | Y17: =IF(AND(ISNUMBER(SEARCH("pass",L17)),ISNUMBER(X17)),COUNTIFS(L$2:L$90,"*pass*",X$2:X$90,">"&X17)+1,"") | Z17: Distinguish Macedon from Mount Macedon; check bushfire overlay, gradients & major ED journey. | AA17: 16. Macedon | Macedon Ranges | Active Shortlist | P: High (Forest & Honour Ave) | Y: Low (Inland) | Lens: Landscape-led Macedon Ranges option | Price: [Blank] | Basis: Not verified in report | Note: Distinguish Macedon from Mount Macedon; check bushfire overlay, gradients & major ED journey. | AB17: Yes | AC17: Macedon station, V/Line Bendigo (recall; verify) | AD17: Bendigo Hospital ED (nearest ED not confirmed; Northern Hospital Epping not tested) | AE17: 1500000 | AF17: Maximum purchase price, excluding transaction and moving costs | AG17: [Awaiting search] | AH17: 26 Oct 2026 | AI17: Needs data | AJ17: No verified pricing entered.
A18: Torquay | B18: Surf Coast | C18: Active Shortlist | D18: Medium (Coastal heath) | E18: High (Surf Coast walk/beach) | F18: Everyday surf-coast walking lifestyle | G18: 1180000 | H18: House sale median $1,180,000; unit $891,250 (REA) | I18: 1250800 | J18: 88 | K18: 23 | L18: Active — provisional pass | O18: =IF(K18="","",ROUND(MAX(0,10*(1-K18/Filters!$B$5)),1)) -> 7.4 | W18: =IF(M18="",0,COUNT(M18:V18)) -> 0 | X18: =IF(W18<10,"",M18*ForcedChoiceCorrections!$B$6+N18*ForcedChoiceCorrections!$B$7+O18*ForcedChoiceCorrections!$B$8+P18*ForcedChoiceCorrections!$B$9+Q18*ForcedChoiceCorrections!$B$10+R18*ForcedChoiceCorrections!$B$11+S18*ForcedChoiceCorrections!$B$12+T18*ForcedChoiceCorrections!$B$13+U18*ForcedChoiceCorrections!$B$14+V18*ForcedChoiceCorrections!$B$15) | Y18: =IF(AND(ISNUMBER(SEARCH("pass",L18)),ISNUMBER(X18)),COUNTIFS(L$2:L$90,"*pass*",X$2:X$90,">"&X18)+1,"") | Z18: ABS 2021: 16.4% aged 65+, 7.4% non-Eng HH. Bus 54 to Marshall Station; relies on Univ Hospital Geelong for major public ED. | AA18: 17. Torquay | Surf Coast | Active Shortlist | P: Medium (Coastal heath) | Y: High (Surf Coast walk/beach) | Lens: Everyday surf-coast walking lifestyle | Price: 1180000 | Basis: House sale median $1,180,000; unit $891,250 (REA) | Note: ABS 2021: 16.4% aged 65+, 7.4% non-Eng HH. Bus 54 to Marshall Station; relies on Univ Hospital Geelong for major public ED. | AB18: No | AC18: No rail; bus 54 to Marshall Station (per sheet note) | AD18: University Hospital Geelong ED | AE18: 1500000 | AF18: Maximum purchase price, excluding transaction and moving costs | AG18: Suburb median | AH18: 26 Oct 2026 | AI18: Pass | AJ18: House median $1.180M is under $1.5M cap. Passes GW drive (88m <= 90m cap) and ED drive (23m).
A19: Ocean Grove | B19: Bellarine Peninsula | C19: Active Shortlist | D19: Medium-High (Nature reserve) | E19: High (Beach + woodland) | F19: Coast-plus-bushland alternative to Torquay | G19: 980000 | H19: House sale median $980,000 (325 sales); unit $770k | I19: 1038800 | J19: 92 | K19: 21 | L19: Fails: GW drive | O19: =IF(K19="","",ROUND(MAX(0,10*(1-K19/Filters!$B$5)),1)) -> 7.7 | W19: =IF(M19="",0,COUNT(M19:V19)) -> 0 | X19: =IF(W19<10,"",M19*ForcedChoiceCorrections!$B$6+N19*ForcedChoiceCorrections!$B$7+O19*ForcedChoiceCorrections!$B$8+P19*ForcedChoiceCorrections!$B$9+Q19*ForcedChoiceCorrections!$B$10+R19*ForcedChoiceCorrections!$B$11+S19*ForcedChoiceCorrections!$B$12+T19*ForcedChoiceCorrections!$B$13+U19*ForcedChoiceCorrections!$B$14+V19*ForcedChoiceCorrections!$B$15) | Y19: =IF(AND(ISNUMBER(SEARCH("pass",L19)),ISNUMBER(X19)),COUNTIFS(L$2:L$90,"*pass*",X$2:X$90,">"&X19)+1,"") | Z19: ABS 2021: 22.2% aged 65+, 5.1% non-Eng HH. 143-ha Nature Reserve; bus 55/56 to Geelong; relies on Univ Hospital Geelong ED. | AA19: 18. Ocean Grove | Bellarine Peninsula | Active Shortlist | P: Medium-High (Nature reserve) | Y: High (Beach + woodland) | Lens: Coast-plus-bushland alternative to Torquay | Price: 980000 | Basis: House sale median $980,000 (325 sales); unit $770k | Note: ABS 2021: 22.2% aged 65+, 5.1% non-Eng HH. 143-ha Nature Reserve; bus 55/56 to Geelong; relies on Univ Hospital Geelong ED. | AB19: No | AC19: No rail; bus 55/56 to Geelong (per sheet note) | AD19: University Hospital Geelong ED | AE19: 1500000 | AF19: Maximum purchase price, excluding transaction and moving costs | AG19: Suburb median | AH19: 26 Oct 2026 | AI19: Pass | AJ19: Published house price ($980,000) is under $1.5M cap.
A20: Newtown (Geelong) | B20: Geelong | C20: Active Shortlist | D20: Medium-High (Barwon River) | E20: Medium (Near bay/coast) | F20: Regional-city services + river sanctuary | H20: Not verified in report | J20: 72 | K20: 7 | L20: Needs data | O20: =IF(K20="","",ROUND(MAX(0,10*(1-K20/Filters!$B$5)),1)) -> 9.2 | W20: =IF(M20="",0,COUNT(M20:V20)) -> 0 | X20: =IF(W20<10,"",M20*ForcedChoiceCorrections!$B$6+N20*ForcedChoiceCorrections!$B$7+O20*ForcedChoiceCorrections!$B$8+P20*ForcedChoiceCorrections!$B$9+Q20*ForcedChoiceCorrections!$B$10+R20*ForcedChoiceCorrections!$B$11+S20*ForcedChoiceCorrections!$B$12+T20*ForcedChoiceCorrections!$B$13+U20*ForcedChoiceCorrections!$B$14+V20*ForcedChoiceCorrections!$B$15) | Y20: =IF(AND(ISNUMBER(SEARCH("pass",L20)),ISNUMBER(X20)),COUNTIFS(L$2:L$90,"*pass*",X$2:X$90,">"&X20)+1,"") | Z20: ABS 2021: 17.6% aged 65+, 10.9% non-Eng HH. Balyang Sanctuary on Barwon River; major public ED at Univ Hospital Geelong. | AA20: 19. Newtown (Geelong) | Geelong | Active Shortlist | P: Medium-High (Barwon River) | Y: Medium (Near bay/coast) | Lens: Regional-city services + river sanctuary | Price: [Blank] | Basis: Not verified in report | Note: ABS 2021: 17.6% aged 65+, 10.9% non-Eng HH. Balyang Sanctuary on Barwon River; major public ED at Univ Hospital Geelong. | AB20: No | AC20: No station in suburb; Geelong stations nearby (recall; verify) | AD20: University Hospital Geelong ED. Origin approximated (Balyang area); GW time from Geelong centre | AE20: 1500000 | AF20: Maximum purchase price, excluding transaction and moving costs | AG20: [Awaiting search] | AH20: 26 Oct 2026 | AI20: Needs data | AJ20: No verified pricing entered.
A21: Highton (Geelong) | B21: Geelong | C21: Active Shortlist | D21: Medium-High (Hills/river) | E21: Medium (Near coast) | F21: Village-centre regional-city comparator | H21: Not verified in report | J21: 74 | K21: 9 | L21: Needs data | O21: =IF(K21="","",ROUND(MAX(0,10*(1-K21/Filters!$B$5)),1)) -> 9 | W21: =IF(M21="",0,COUNT(M21:V21)) -> 0 | X21: =IF(W21<10,"",M21*ForcedChoiceCorrections!$B$6+N21*ForcedChoiceCorrections!$B$7+O21*ForcedChoiceCorrections!$B$8+P21*ForcedChoiceCorrections!$B$9+Q21*ForcedChoiceCorrections!$B$10+R21*ForcedChoiceCorrections!$B$11+S21*ForcedChoiceCorrections!$B$12+T21*ForcedChoiceCorrections!$B$13+U21*ForcedChoiceCorrections!$B$14+V21*ForcedChoiceCorrections!$B$15) | Y21: =IF(AND(ISNUMBER(SEARCH("pass",L21)),ISNUMBER(X21)),COUNTIFS(L$2:L$90,"*pass*",X$2:X$90,">"&X21)+1,"") | Z21: Highton Village UDF; compare pocket gradients, station access & Univ Hospital Geelong ED journey. | AA21: 20. Highton (Geelong) | Geelong | Active Shortlist | P: Medium-High (Hills/river) | Y: Medium (Near coast) | Lens: Village-centre regional-city comparator | Price: [Blank] | Basis: Not verified in report | Note: Highton Village UDF; compare pocket gradients, station access & Univ Hospital Geelong ED journey. | AB21: No | AC21: No station; bus to Geelong (recall; verify) | AD21: University Hospital Geelong ED | AE21: 1500000 | AF21: Maximum purchase price, excluding transaction and moving costs | AG21: [Awaiting search] | AH21: 26 Oct 2026 | AI21: Needs data | AJ21: No verified pricing entered.
A22: Belgrave | B22: Dandenong Ranges | C22: Active Shortlist | D22: High (Forest & hills) | E22: Low (Inland) | F22: Stronger hills lifestyle on metro rail line | H22: Not verified in report | J22: 21 | K22: 7 | L22: Needs data | O22: =IF(K22="","",ROUND(MAX(0,10*(1-K22/Filters!$B$5)),1)) -> 9.2 | W22: =IF(M22="",0,COUNT(M22:V22)) -> 0 | X22: =IF(W22<10,"",M22*ForcedChoiceCorrections!$B$6+N22*ForcedChoiceCorrections!$B$7+O22*ForcedChoiceCorrections!$B$8+P22*ForcedChoiceCorrections!$B$9+Q22*ForcedChoiceCorrections!$B$10+R22*ForcedChoiceCorrections!$B$11+S22*ForcedChoiceCorrections!$B$12+T22*ForcedChoiceCorrections!$B$13+U22*ForcedChoiceCorrections!$B$14+V22*ForcedChoiceCorrections!$B$15) | Y22: =IF(AND(ISNUMBER(SEARCH("pass",L22)),ISNUMBER(X22)),COUNTIFS(L$2:L$90,"*pass*",X$2:X$90,">"&X22)+1,"") | Z22: Belgrave metro rail terminus; check steep gradients, bushfire/storm closures & Angliss/Maroondah ED drive. | AA22: 21. Belgrave | Dandenong Ranges | Active Shortlist | P: High (Forest & hills) | Y: Low (Inland) | Lens: Stronger hills lifestyle on metro rail line | Price: [Blank] | Basis: Not verified in report | Note: Belgrave metro rail terminus; check steep gradients, bushfire/storm closures & Angliss/Maroondah ED drive. | AB22: Yes | AC22: Belgrave station, Belgrave line terminus (per sheet note) | AD22: Angliss Hospital ED (24-hr status still to verify) | AE22: 1500000 | AF22: Maximum purchase price, excluding transaction and moving costs | AG22: [Awaiting search] | AH22: 26 Oct 2026 | AI22: Needs data | AJ22: No verified pricing entered.
A23: Upwey | B23: Dandenong Ranges | C23: Active Shortlist | D23: High (Foothills village) | E23: Low (Inland) | F23: Village character vs healthcare/transport practicality | G23: 929500 | H23: House sale median $929,500 (104 sales, Property.com.au) | I23: 985270 | J23: 17 | K23: 4 | L23: Active — provisional pass | O23: =IF(K23="","",ROUND(MAX(0,10*(1-K23/Filters!$B$5)),1)) -> 9.6 | W23: =IF(M23="",0,COUNT(M23:V23)) -> 0 | X23: =IF(W23<10,"",M23*ForcedChoiceCorrections!$B$6+N23*ForcedChoiceCorrections!$B$7+O23*ForcedChoiceCorrections!$B$8+P23*ForcedChoiceCorrections!$B$9+Q23*ForcedChoiceCorrections!$B$10+R23*ForcedChoiceCorrections!$B$11+S23*ForcedChoiceCorrections!$B$12+T23*ForcedChoiceCorrections!$B$13+U23*ForcedChoiceCorrections!$B$14+V23*ForcedChoiceCorrections!$B$15) | Y23: =IF(AND(ISNUMBER(SEARCH("pass",L23)),ISNUMBER(X23)),COUNTIFS(L$2:L$90,"*pass*",X$2:X$90,">"&X23)+1,"") | Z23: Belgrave rail line township; closer to foothills edge than Belgrave. | AA23: 22. Upwey | Dandenong Ranges | Active Shortlist | P: High (Foothills village) | Y: Low (Inland) | Lens: Village character vs healthcare/transport practicality | Price: 929500 | Basis: House sale median $929,500 (104 sales, Property.com.au) | Note: Belgrave rail line township; closer to foothills edge than Belgrave. | AB23: Yes | AC23: Upwey station, Belgrave line (per sheet note) | AD23: Angliss Hospital ED (24-hr status still to verify) | AE23: 1500000 | AF23: Maximum purchase price, excluding transaction and moving costs | AG23: Suburb median | AH23: 26 Oct 2026 | AI23: Pass | AJ23: Published house price ($929,500) is under $1.5M cap.
A24: Tecoma | B24: Dandenong Ranges | C24: Active Shortlist | D24: High (Foothills/forest) | E24: Low (Inland) | F24: Established rail township between Upwey & Belgrave | H24: Not verified in report | J24: 19 | K24: 5 | L24: Needs data | O24: =IF(K24="","",ROUND(MAX(0,10*(1-K24/Filters!$B$5)),1)) -> 9.4 | W24: =IF(M24="",0,COUNT(M24:V24)) -> 0 | X24: =IF(W24<10,"",M24*ForcedChoiceCorrections!$B$6+N24*ForcedChoiceCorrections!$B$7+O24*ForcedChoiceCorrections!$B$8+P24*ForcedChoiceCorrections!$B$9+Q24*ForcedChoiceCorrections!$B$10+R24*ForcedChoiceCorrections!$B$11+S24*ForcedChoiceCorrections!$B$12+T24*ForcedChoiceCorrections!$B$13+U24*ForcedChoiceCorrections!$B$14+V24*ForcedChoiceCorrections!$B$15) | Y24: =IF(AND(ISNUMBER(SEARCH("pass",L24)),ISNUMBER(X24)),COUNTIFS(L$2:L$90,"*pass*",X$2:X$90,">"&X24)+1,"") | Z24: Belgrave rail line; council groups Belgrave-Tecoma-Upwey as established townships. | AA24: 23. Tecoma | Dandenong Ranges | Active Shortlist | P: High (Foothills/forest) | Y: Low (Inland) | Lens: Established rail township between Upwey & Belgrave | Price: [Blank] | Basis: Not verified in report | Note: Belgrave rail line; council groups Belgrave-Tecoma-Upwey as established townships. | AB24: Yes | AC24: Tecoma station, Belgrave line (per sheet note) | AD24: Angliss Hospital ED (24-hr status still to verify) | AE24: 1500000 | AF24: Maximum purchase price, excluding transaction and moving costs | AG24: [Awaiting search] | AH24: 26 Oct 2026 | AI24: Needs data | AJ24: No verified pricing entered.
A25: The Basin | B25: Dandenong Foothills | C25: Active Shortlist | D25: High (National park edge) | E25: Low (Inland) | F25: Forest-edge living without a ridge village | H25: Not verified in report | J25: 17 | K25: 10 | L25: Needs data | O25: =IF(K25="","",ROUND(MAX(0,10*(1-K25/Filters!$B$5)),1)) -> 8.9 | W25: =IF(M25="",0,COUNT(M25:V25)) -> 0 | X25: =IF(W25<10,"",M25*ForcedChoiceCorrections!$B$6+N25*ForcedChoiceCorrections!$B$7+O25*ForcedChoiceCorrections!$B$8+P25*ForcedChoiceCorrections!$B$9+Q25*ForcedChoiceCorrections!$B$10+R25*ForcedChoiceCorrections!$B$11+S25*ForcedChoiceCorrections!$B$12+T25*ForcedChoiceCorrections!$B$13+U25*ForcedChoiceCorrections!$B$14+V25*ForcedChoiceCorrections!$B$15) | Y25: =IF(AND(ISNUMBER(SEARCH("pass",L25)),ISNUMBER(X25)),COUNTIFS(L$2:L$90,"*pass*",X$2:X$90,">"&X25)+1,"") | Z25: Adjoins Dandenong Ranges National Park; verify bus/station link & Angliss Hospital ED drive. | AA25: 24. The Basin | Dandenong Foothills | Active Shortlist | P: High (National park edge) | Y: Low (Inland) | Lens: Forest-edge living without a ridge village | Price: [Blank] | Basis: Not verified in report | Note: Adjoins Dandenong Ranges National Park; verify bus/station link & Angliss Hospital ED drive. | AB25: No | AC25: No station; bus link unverified (per sheet note) | AD25: Angliss Hospital ED (24-hr status still to verify) | AE25: 1500000 | AF25: Maximum purchase price, excluding transaction and moving costs | AG25: [Awaiting search] | AH25: 26 Oct 2026 | AI25: Needs data | AJ25: No verified pricing entered.
A26: Montrose | B26: Dandenong Foothills | C26: Active Shortlist | D26: High (Mountain backdrop) | E26: Low (Inland) | F26: Foothills township between suburbs & ridge | H26: Not verified in report | J26: 22 | K26: 12 | L26: Needs data | O26: =IF(K26="","",ROUND(MAX(0,10*(1-K26/Filters!$B$5)),1)) -> 8.7 | W26: =IF(M26="",0,COUNT(M26:V26)) -> 0 | X26: =IF(W26<10,"",M26*ForcedChoiceCorrections!$B$6+N26*ForcedChoiceCorrections!$B$7+O26*ForcedChoiceCorrections!$B$8+P26*ForcedChoiceCorrections!$B$9+Q26*ForcedChoiceCorrections!$B$10+R26*ForcedChoiceCorrections!$B$11+S26*ForcedChoiceCorrections!$B$12+T26*ForcedChoiceCorrections!$B$13+U26*ForcedChoiceCorrections!$B$14+V26*ForcedChoiceCorrections!$B$15) | Y26: =IF(AND(ISNUMBER(SEARCH("pass",L26)),ISNUMBER(X26)),COUNTIFS(L$2:L$90,"*pass*",X$2:X$90,">"&X26)+1,"") | Z26: Township shopping & community hub; verify non-rail transport, fire exposure & ED journey. | AA26: 25. Montrose | Dandenong Foothills | Active Shortlist | P: High (Mountain backdrop) | Y: Low (Inland) | Lens: Foothills township between suburbs & ridge | Price: [Blank] | Basis: Not verified in report | Note: Township shopping & community hub; verify non-rail transport, fire exposure & ED journey. | AB26: No | AC26: No station; Mooroolbark/Lilydale stations nearby (recall; verify) | AD26: Maroondah Hospital ED | AE26: 1500000 | AF26: Maximum purchase price, excluding transaction and moving costs | AG26: [Awaiting search] | AH26: 26 Oct 2026 | AI26: Needs data | AJ26: No verified pricing entered.
A27: Mount Evelyn | B27: Yarra Ranges | C27: Active Shortlist | D27: High (Aqueduct & rail trails) | E27: Low (Inland) | F27: Forest village closer than Warburton | H27: Not verified in report | J27: 27 | K27: 17 | L27: Needs data | O27: =IF(K27="","",ROUND(MAX(0,10*(1-K27/Filters!$B$5)),1)) -> 8.1 | W27: =IF(M27="",0,COUNT(M27:V27)) -> 0 | X27: =IF(W27<10,"",M27*ForcedChoiceCorrections!$B$6+N27*ForcedChoiceCorrections!$B$7+O27*ForcedChoiceCorrections!$B$8+P27*ForcedChoiceCorrections!$B$9+Q27*ForcedChoiceCorrections!$B$10+R27*ForcedChoiceCorrections!$B$11+S27*ForcedChoiceCorrections!$B$12+T27*ForcedChoiceCorrections!$B$13+U27*ForcedChoiceCorrections!$B$14+V27*ForcedChoiceCorrections!$B$15) | Y27: =IF(AND(ISNUMBER(SEARCH("pass",L27)),ISNUMBER(X27)),COUNTIFS(L$2:L$90,"*pass*",X$2:X$90,">"&X27)+1,"") | Z27: Warburton Rail Trail & Aqueduct Trail (no passenger rail); verify Maroondah ED journey. | AA27: 26. Mount Evelyn | Yarra Ranges | Active Shortlist | P: High (Aqueduct & rail trails) | Y: Low (Inland) | Lens: Forest village closer than Warburton | Price: [Blank] | Basis: Not verified in report | Note: Warburton Rail Trail & Aqueduct Trail (no passenger rail); verify Maroondah ED journey. | AB27: No | AC27: No passenger rail (per sheet note) | AD27: Maroondah Hospital ED | AE27: 1500000 | AF27: Maximum purchase price, excluding transaction and moving costs | AG27: [Awaiting search] | AH27: 26 Oct 2026 | AI27: Needs data | AJ27: No verified pricing entered.
A28: Croydon | B28: Outer East Melbourne | C28: Active Shortlist | D28: Medium (Leafy parks) | E28: Low (Inland) | F28: Practical outer-east control with rail & services | H28: Not verified in report | J28: 18 | K28: 6 | L28: Needs data | O28: =IF(K28="","",ROUND(MAX(0,10*(1-K28/Filters!$B$5)),1)) -> 9.3 | W28: =IF(M28="",0,COUNT(M28:V28)) -> 0 | X28: =IF(W28<10,"",M28*ForcedChoiceCorrections!$B$6+N28*ForcedChoiceCorrections!$B$7+O28*ForcedChoiceCorrections!$B$8+P28*ForcedChoiceCorrections!$B$9+Q28*ForcedChoiceCorrections!$B$10+R28*ForcedChoiceCorrections!$B$11+S28*ForcedChoiceCorrections!$B$12+T28*ForcedChoiceCorrections!$B$13+U28*ForcedChoiceCorrections!$B$14+V28*ForcedChoiceCorrections!$B$15) | Y28: =IF(AND(ISNUMBER(SEARCH("pass",L28)),ISNUMBER(X28)),COUNTIFS(L$2:L$90,"*pass*",X$2:X$90,">"&X28)+1,"") | Z28: Main St activity centre, train/bus interchange & Croydon Park; benchmark near Maroondah ED. | AA28: 27. Croydon | Outer East Melbourne | Active Shortlist | P: Medium (Leafy parks) | Y: Low (Inland) | Lens: Practical outer-east control with rail & services | Price: [Blank] | Basis: Not verified in report | Note: Main St activity centre, train/bus interchange & Croydon Park; benchmark near Maroondah ED. | AB28: Yes | AC28: Croydon station, Lilydale line (per sheet note) | AD28: Maroondah Hospital ED | AE28: 1500000 | AF28: Maximum purchase price, excluding transaction and moving costs | AG28: [Awaiting search] | AH28: 26 Oct 2026 | AI28: Needs data | AJ28: No verified pricing entered.
A29: Warragul | B29: West Gippsland | C29: Active Shortlist | D29: High (Rolling hills/gardens) | E29: Low (Inland) | F29: Regional town with V/Line rail & local hospital ED | G29: 620000 | H29: 3-bed house median $620k; 4-bed $732.5k (Domain) | I29: 657200 | J29: 58 | K29: 2 | L29: Active — provisional pass | O29: =IF(K29="","",ROUND(MAX(0,10*(1-K29/Filters!$B$5)),1)) -> 9.8 | W29: =IF(M29="",0,COUNT(M29:V29)) -> 0 | X29: =IF(W29<10,"",M29*ForcedChoiceCorrections!$B$6+N29*ForcedChoiceCorrections!$B$7+O29*ForcedChoiceCorrections!$B$8+P29*ForcedChoiceCorrections!$B$9+Q29*ForcedChoiceCorrections!$B$10+R29*ForcedChoiceCorrections!$B$11+S29*ForcedChoiceCorrections!$B$12+T29*ForcedChoiceCorrections!$B$13+U29*ForcedChoiceCorrections!$B$14+V29*ForcedChoiceCorrections!$B$15) | Y29: =IF(AND(ISNUMBER(SEARCH("pass",L29)),ISNUMBER(X29)),COUNTIFS(L$2:L$90,"*pass*",X$2:X$90,">"&X29)+1,"") | Z29: Town-centre V/Line station & West Gippsland Hospital ED (verify wait times & GW drive). | AA29: 28. Warragul | West Gippsland | Active Shortlist | P: High (Rolling hills/gardens) | Y: Low (Inland) | Lens: Regional town with V/Line rail & local hospital ED | Price: 620000 | Basis: 3-bed house median $620k; 4-bed $732.5k (Domain) | Note: Town-centre V/Line station & West Gippsland Hospital ED (verify wait times & GW drive). | AB29: Yes | AC29: Warragul station, V/Line Gippsland (per sheet note) | AD29: West Gippsland Hospital ED (local) | AE29: 1500000 | AF29: Maximum purchase price, excluding transaction and moving costs | AG29: Suburb median | AH29: 26 Oct 2026 | AI29: Pass | AJ29: Published house price ($620,000) is under $1.5M cap.
A30: Mount Eliza | B30: Mornington Peninsula | C30: Active Shortlist | D30: High (Woodland & gullies) | E30: High (Canadian Bay/coast) | F30: Rare overlap of bushland reserves, village & bay | H30: Not verified in report | J30: 34 | K30: 10 | L30: Needs data | O30: =IF(K30="","",ROUND(MAX(0,10*(1-K30/Filters!$B$5)),1)) -> 8.9 | W30: =IF(M30="",0,COUNT(M30:V30)) -> 0 | X30: =IF(W30<10,"",M30*ForcedChoiceCorrections!$B$6+N30*ForcedChoiceCorrections!$B$7+O30*ForcedChoiceCorrections!$B$8+P30*ForcedChoiceCorrections!$B$9+Q30*ForcedChoiceCorrections!$B$10+R30*ForcedChoiceCorrections!$B$11+S30*ForcedChoiceCorrections!$B$12+T30*ForcedChoiceCorrections!$B$13+U30*ForcedChoiceCorrections!$B$14+V30*ForcedChoiceCorrections!$B$15) | Y30: =IF(AND(ISNUMBER(SEARCH("pass",L30)),ISNUMBER(X30)),COUNTIFS(L$2:L$90,"*pass*",X$2:X$90,">"&X30)+1,"") | Z30: Tests BOTH parents' bushland preference and your coastal-nature preference; verify bus 781 & Frankston ED drive. | AA30: 29. Mount Eliza | Mornington Peninsula | Active Shortlist | P: High (Woodland & gullies) | Y: High (Canadian Bay/coast) | Lens: Rare overlap of bushland reserves, village & bay | Price: [Blank] | Basis: Not verified in report | Note: Tests BOTH parents' bushland preference and your coastal-nature preference; verify bus 781 & Frankston ED drive. | AB30: No | AC30: No rail; bus 781 to Frankston (per sheet note) | AD30: Peninsula University Hospital ED | AE30: 1500000 | AF30: Maximum purchase price, excluding transaction and moving costs | AG30: [Awaiting search] | AH30: 26 Oct 2026 | AI30: Needs data | AJ30: No verified pricing entered.
A31: Mornington | B31: Mornington Peninsula | C31: Active Shortlist | D31: Medium (Parks & gardens) | E31: High (Bay beaches/harbor) | F31: Established coastal town centre & Main Street | H31: Not verified in report | J31: 40 | K31: 15 | L31: Needs data | O31: =IF(K31="","",ROUND(MAX(0,10*(1-K31/Filters!$B$5)),1)) -> 8.3 | W31: =IF(M31="",0,COUNT(M31:V31)) -> 0 | X31: =IF(W31<10,"",M31*ForcedChoiceCorrections!$B$6+N31*ForcedChoiceCorrections!$B$7+O31*ForcedChoiceCorrections!$B$8+P31*ForcedChoiceCorrections!$B$9+Q31*ForcedChoiceCorrections!$B$10+R31*ForcedChoiceCorrections!$B$11+S31*ForcedChoiceCorrections!$B$12+T31*ForcedChoiceCorrections!$B$13+U31*ForcedChoiceCorrections!$B$14+V31*ForcedChoiceCorrections!$B$15) | Y31: =IF(AND(ISNUMBER(SEARCH("pass",L31)),ISNUMBER(X31)),COUNTIFS(L$2:L$90,"*pass*",X$2:X$90,">"&X31)+1,"") | Z31: Substantial town services on bay; no passenger train (bus to Frankston); verify Frankston/Rosebud ED drive. | AA31: 30. Mornington | Mornington Peninsula | Active Shortlist | P: Medium (Parks & gardens) | Y: High (Bay beaches/harbor) | Lens: Established coastal town centre & Main Street | Price: [Blank] | Basis: Not verified in report | Note: Substantial town services on bay; no passenger train (bus to Frankston); verify Frankston/Rosebud ED drive. | AB31: No | AC31: No passenger train; bus to Frankston (per sheet note) | AD31: Peninsula University Hospital ED | AE31: 1500000 | AF31: Maximum purchase price, excluding transaction and moving costs | AG31: [Awaiting search] | AH31: 26 Oct 2026 | AI31: Needs data | AJ31: No verified pricing entered.
A32: Clifton Springs | B32: Bellarine Peninsula | C32: Active Shortlist | D32: Medium (Dell & coastal reserve) | E32: High (Bay views & foreshore) | F32: High-value Bellarine coastal alternative | G32: 715000 | H32: House sale median $715,000 (196 sales, Property.com.au) | I32: 757900 | J32: 95 | K32: 23 | L32: Fails: GW drive | O32: =IF(K32="","",ROUND(MAX(0,10*(1-K32/Filters!$B$5)),1)) -> 7.4 | W32: =IF(M32="",0,COUNT(M32:V32)) -> 0 | X32: =IF(W32<10,"",M32*ForcedChoiceCorrections!$B$6+N32*ForcedChoiceCorrections!$B$7+O32*ForcedChoiceCorrections!$B$8+P32*ForcedChoiceCorrections!$B$9+Q32*ForcedChoiceCorrections!$B$10+R32*ForcedChoiceCorrections!$B$11+S32*ForcedChoiceCorrections!$B$12+T32*ForcedChoiceCorrections!$B$13+U32*ForcedChoiceCorrections!$B$14+V32*ForcedChoiceCorrections!$B$15) | Y32: =IF(AND(ISNUMBER(SEARCH("pass",L32)),ISNUMBER(X32)),COUNTIFS(L$2:L$90,"*pass*",X$2:X$90,">"&X32)+1,"") | Z32: Port Phillip bay frontage & Dell picnic area; verify Univ Hospital Geelong ED drive & public transport. | AA32: 31. Clifton Springs | Bellarine Peninsula | Active Shortlist | P: Medium (Dell & coastal reserve) | Y: High (Bay views & foreshore) | Lens: High-value Bellarine coastal alternative | Price: 715000 | Basis: House sale median $715,000 (196 sales, Property.com.au) | Note: Port Phillip bay frontage & Dell picnic area; verify Univ Hospital Geelong ED drive & public transport. | AB32: No | AC32: No rail; Geelong via bus (recall; verify) | AD32: University Hospital Geelong ED | AE32: 1500000 | AF32: Maximum purchase price, excluding transaction and moving costs | AG32: Suburb median | AH32: 26 Oct 2026 | AI32: Pass | AJ32: Published house price ($715,000) is under $1.5M cap.
A33: Warburton | B33: Yarra Valley | C33: Watchlist | D33: Very High (Mountain & river) | E33: Low (River, non-coastal) | F33: Maximum forest/mountain scenery test | G33: 717500 | H33: 3-bed house median $717.5k (34 sales); 4-bed $702.5k | I33: 760550 | J33: 65 | K33: 53 | L33: Needs data | W33: =IF(M33="",0,COUNT(M33:V33)) -> 0 | X33: =IF(W33<10,"",M33*ForcedChoiceCorrections!$B$6+N33*ForcedChoiceCorrections!$B$7+O33*ForcedChoiceCorrections!$B$8+P33*ForcedChoiceCorrections!$B$9+Q33*ForcedChoiceCorrections!$B$10+R33*ForcedChoiceCorrections!$B$11+S33*ForcedChoiceCorrections!$B$12+T33*ForcedChoiceCorrections!$B$13+U33*ForcedChoiceCorrections!$B$14+V33*ForcedChoiceCorrections!$B$15) | Y33: =IF(AND(ISNUMBER(SEARCH("pass",L33)),ISNUMBER(X33)),COUNTIFS(L$2:L$90,"*pass*",X$2:X$90,">"&X33)+1,"") | Z33: ABS 2021: 24.3% aged 65+, 8.1% non-Eng HH. Tough practicality test on winter comfort, fire risk & distant ED. | AA33: 32. Warburton | Yarra Valley | Watchlist | P: Very High (Mountain & river) | Y: Low (River, non-coastal) | Lens: Maximum forest/mountain scenery test | Price: 717500 | Basis: 3-bed house median $717.5k (34 sales); 4-bed $702.5k | Note: ABS 2021: 24.3% aged 65+, 8.1% non-Eng HH. Tough practicality test on winter comfort, fire risk & distant ED. | AB33: No | AC33: No passenger rail (recall; verify) | AD33: Maroondah Hospital ED (drive times added 27 Oct 2026, Google Maps leave-now, not peak; Angliss may be closer, 24-hr status unverified) | AE33: 1500000 | AF33: Maximum purchase price, excluding transaction and moving costs | AG33: Suburb median | AH33: 26 Oct 2026 | AI33: Pass | AJ33: Published house price ($717,500) is under $1.5M cap.
A34: Trentham | B34: Macedon Ranges | C34: Watchlist | D34: High (Wombat Forest village) | E34: Low (Inland) | F34: Intimate forest village with older age profile | G34: 978750 | H34: 3-bed house median $978,750 (30 sales, Domain) | I34: 1037475 | L34: Needs data | W34: =IF(M34="",0,COUNT(M34:V34)) -> 0 | X34: =IF(W34<10,"",M34*ForcedChoiceCorrections!$B$6+N34*ForcedChoiceCorrections!$B$7+O34*ForcedChoiceCorrections!$B$8+P34*ForcedChoiceCorrections!$B$9+Q34*ForcedChoiceCorrections!$B$10+R34*ForcedChoiceCorrections!$B$11+S34*ForcedChoiceCorrections!$B$12+T34*ForcedChoiceCorrections!$B$13+U34*ForcedChoiceCorrections!$B$14+V34*ForcedChoiceCorrections!$B$15) | Y34: =IF(AND(ISNUMBER(SEARCH("pass",L34)),ISNUMBER(X34)),COUNTIFS(L$2:L$90,"*pass*",X$2:X$90,">"&X34)+1,"") | Z34: ABS 2021: 33.6% aged 65+, 4.7% non-Eng HH. CAUTION: Local health campus is community/aged care ONLY, not an ED. | AA34: 33. Trentham | Macedon Ranges | Watchlist | P: High (Wombat Forest village) | Y: Low (Inland) | Lens: Intimate forest village with older age profile | Price: 978750 | Basis: 3-bed house median $978,750 (30 sales, Domain) | Note: ABS 2021: 33.6% aged 65+, 4.7% non-Eng HH. CAUTION: Local health campus is community/aged care ONLY, not an ED. | AE34: 1500000 | AF34: Maximum purchase price, excluding transaction and moving costs | AG34: Suburb median | AH34: 26 Oct 2026 | AI34: Pass | AJ34: Published house price ($978,750) is under $1.5M cap.
A35: Olinda | B35: Dandenong Ridge | C35: Watchlist | D35: Very High (Botanic gardens/ridge) | E35: Low (Inland) | F35: Dandenongs ridge village — high scenic appeal | H35: Not verified in report | L35: Needs data | W35: =IF(M35="",0,COUNT(M35:V35)) -> 0 | X35: =IF(W35<10,"",M35*ForcedChoiceCorrections!$B$6+N35*ForcedChoiceCorrections!$B$7+O35*ForcedChoiceCorrections!$B$8+P35*ForcedChoiceCorrections!$B$9+Q35*ForcedChoiceCorrections!$B$10+R35*ForcedChoiceCorrections!$B$11+S35*ForcedChoiceCorrections!$B$12+T35*ForcedChoiceCorrections!$B$13+U35*ForcedChoiceCorrections!$B$14+V35*ForcedChoiceCorrections!$B$15) | Y35: =IF(AND(ISNUMBER(SEARCH("pass",L35)),ISNUMBER(X35)),COUNTIFS(L$2:L$90,"*pass*",X$2:X$90,">"&X35)+1,"") | Z35: Parks Vic documents severe-weather/fire closures; bus 694 to Belgrave; verify winter damp, slopes & insurance. | AA35: 34. Olinda | Dandenong Ridge | Watchlist | P: Very High (Botanic gardens/ridge) | Y: Low (Inland) | Lens: Dandenongs ridge village — high scenic appeal | Price: [Blank] | Basis: Not verified in report | Note: Parks Vic documents severe-weather/fire closures; bus 694 to Belgrave; verify winter damp, slopes & insurance. | AE35: 1500000 | AF35: Maximum purchase price, excluding transaction and moving costs | AG35: [Awaiting search] | AH35: 26 Oct 2026 | AI35: Needs data | AJ35: No verified pricing entered.
A36: Sassafras | B36: Dandenong Ridge | C36: Watchlist | D36: Very High (Forest ridge village) | E36: Low (Inland) | F36: Dandenongs ridge village comparator | H36: Not verified in report | L36: Needs data | W36: =IF(M36="",0,COUNT(M36:V36)) -> 0 | X36: =IF(W36<10,"",M36*ForcedChoiceCorrections!$B$6+N36*ForcedChoiceCorrections!$B$7+O36*ForcedChoiceCorrections!$B$8+P36*ForcedChoiceCorrections!$B$9+Q36*ForcedChoiceCorrections!$B$10+R36*ForcedChoiceCorrections!$B$11+S36*ForcedChoiceCorrections!$B$12+T36*ForcedChoiceCorrections!$B$13+U36*ForcedChoiceCorrections!$B$14+V36*ForcedChoiceCorrections!$B$15) | Y36: =IF(AND(ISNUMBER(SEARCH("pass",L36)),ISNUMBER(X36)),COUNTIFS(L$2:L$90,"*pass*",X$2:X$90,">"&X36)+1,"") | Z36: High tourism traffic on weekends; check everyday grocery/medical convenience & bushfire overlay. | AA36: 35. Sassafras | Dandenong Ridge | Watchlist | P: Very High (Forest ridge village) | Y: Low (Inland) | Lens: Dandenongs ridge village comparator | Price: [Blank] | Basis: Not verified in report | Note: High tourism traffic on weekends; check everyday grocery/medical convenience & bushfire overlay. | AE36: 1500000 | AF36: Maximum purchase price, excluding transaction and moving costs | AG36: [Awaiting search] | AH36: 26 Oct 2026 | AI36: Needs data | AJ36: No verified pricing entered.
A37: Mount Dandenong | B37: Dandenong Ridge | C37: Watchlist | D37: Very High (Canopy & views) | E37: Low (Inland) | F37: Ridge canopy living test | H37: Not verified in report | L37: Needs data | W37: =IF(M37="",0,COUNT(M37:V37)) -> 0 | X37: =IF(W37<10,"",M37*ForcedChoiceCorrections!$B$6+N37*ForcedChoiceCorrections!$B$7+O37*ForcedChoiceCorrections!$B$8+P37*ForcedChoiceCorrections!$B$9+Q37*ForcedChoiceCorrections!$B$10+R37*ForcedChoiceCorrections!$B$11+S37*ForcedChoiceCorrections!$B$12+T37*ForcedChoiceCorrections!$B$13+U37*ForcedChoiceCorrections!$B$14+V37*ForcedChoiceCorrections!$B$15) | Y37: =IF(AND(ISNUMBER(SEARCH("pass",L37)),ISNUMBER(X37)),COUNTIFS(L$2:L$90,"*pass*",X$2:X$90,">"&X37)+1,"") | Z37: Requires property-specific slope, tree-fall, insurance & emergency egress verification. | AA37: 36. Mount Dandenong | Dandenong Ridge | Watchlist | P: Very High (Canopy & views) | Y: Low (Inland) | Lens: Ridge canopy living test | Price: [Blank] | Basis: Not verified in report | Note: Requires property-specific slope, tree-fall, insurance & emergency egress verification. | AE37: 1500000 | AF37: Maximum purchase price, excluding transaction and moving costs | AG37: [Awaiting search] | AH37: 26 Oct 2026 | AI37: Needs data | AJ37: No verified pricing entered.
A38: Emerald | B38: Dandenong Ranges | C38: Watchlist | D38: High (Emerald Lake & hills) | E38: Low (Inland) | F38: Larger hills town south-east of ridge | H38: Not verified in report | L38: Needs data | W38: =IF(M38="",0,COUNT(M38:V38)) -> 0 | X38: =IF(W38<10,"",M38*ForcedChoiceCorrections!$B$6+N38*ForcedChoiceCorrections!$B$7+O38*ForcedChoiceCorrections!$B$8+P38*ForcedChoiceCorrections!$B$9+Q38*ForcedChoiceCorrections!$B$10+R38*ForcedChoiceCorrections!$B$11+S38*ForcedChoiceCorrections!$B$12+T38*ForcedChoiceCorrections!$B$13+U38*ForcedChoiceCorrections!$B$14+V38*ForcedChoiceCorrections!$B$15) | Y38: =IF(AND(ISNUMBER(SEARCH("pass",L38)),ISNUMBER(X38)),COUNTIFS(L$2:L$90,"*pass*",X$2:X$90,">"&X38)+1,"") | Z38: Emerald Lake precinct; separate from ridge villages—verify routine services & ED drive. | AA38: 37. Emerald | Dandenong Ranges | Watchlist | P: High (Emerald Lake & hills) | Y: Low (Inland) | Lens: Larger hills town south-east of ridge | Price: [Blank] | Basis: Not verified in report | Note: Emerald Lake precinct; separate from ridge villages—verify routine services & ED drive. | AE38: 1500000 | AF38: Maximum purchase price, excluding transaction and moving costs | AG38: [Awaiting search] | AH38: 26 Oct 2026 | AI38: Needs data | AJ38: No verified pricing entered.
A39: Ferntree Gully | B39: East / Foothills | C39: Watchlist | D39: Medium-High (Foothills) | E39: Low (Inland) | F39: Larger housing/service catchment next to Upper FTG | H39: Not verified in report | L39: Needs data | W39: =IF(M39="",0,COUNT(M39:V39)) -> 0 | X39: =IF(W39<10,"",M39*ForcedChoiceCorrections!$B$6+N39*ForcedChoiceCorrections!$B$7+O39*ForcedChoiceCorrections!$B$8+P39*ForcedChoiceCorrections!$B$9+Q39*ForcedChoiceCorrections!$B$10+R39*ForcedChoiceCorrections!$B$11+S39*ForcedChoiceCorrections!$B$12+T39*ForcedChoiceCorrections!$B$13+U39*ForcedChoiceCorrections!$B$14+V39*ForcedChoiceCorrections!$B$15) | Y39: =IF(AND(ISNUMBER(SEARCH("pass",L39)),ISNUMBER(X39)),COUNTIFS(L$2:L$90,"*pass*",X$2:X$90,">"&X39)+1,"") | Z39: Belgrave line; compare flatter pockets and housing stock against Upper Ferntree Gully. | AA39: 38. Ferntree Gully | East / Foothills | Watchlist | P: Medium-High (Foothills) | Y: Low (Inland) | Lens: Larger housing/service catchment next to Upper FTG | Price: [Blank] | Basis: Not verified in report | Note: Belgrave line; compare flatter pockets and housing stock against Upper Ferntree Gully. | AE39: 1500000 | AF39: Maximum purchase price, excluding transaction and moving costs | AG39: [Awaiting search] | AH39: 26 Oct 2026 | AI39: Needs data | AJ39: No verified pricing entered.
A40: Berwick | B40: South-East Melbourne | C40: Watchlist | D40: Medium (Wilson Botanic Park) | E40: Low (Inland) | F40: Healthcare-led south-east comparator | H40: Not verified in report | L40: Needs data | W40: =IF(M40="",0,COUNT(M40:V40)) -> 0 | X40: =IF(W40<10,"",M40*ForcedChoiceCorrections!$B$6+N40*ForcedChoiceCorrections!$B$7+O40*ForcedChoiceCorrections!$B$8+P40*ForcedChoiceCorrections!$B$9+Q40*ForcedChoiceCorrections!$B$10+R40*ForcedChoiceCorrections!$B$11+S40*ForcedChoiceCorrections!$B$12+T40*ForcedChoiceCorrections!$B$13+U40*ForcedChoiceCorrections!$B$14+V40*ForcedChoiceCorrections!$B$15) | Y40: =IF(AND(ISNUMBER(SEARCH("pass",L40)),ISNUMBER(X40)),COUNTIFS(L$2:L$90,"*pass*",X$2:X$90,">"&X40)+1,"") | Z40: Monash Health Casey Hospital 24-hr ED on site; verify whether residential pockets feel green enough. | AA40: 39. Berwick | South-East Melbourne | Watchlist | P: Medium (Wilson Botanic Park) | Y: Low (Inland) | Lens: Healthcare-led south-east comparator | Price: [Blank] | Basis: Not verified in report | Note: Monash Health Casey Hospital 24-hr ED on site; verify whether residential pockets feel green enough. | AE40: 1500000 | AF40: Maximum purchase price, excluding transaction and moving costs | AG40: [Awaiting search] | AH40: 26 Oct 2026 | AI40: Needs data | AJ40: No verified pricing entered.
A41: Frankston South | B41: Mornington Peninsula | C41: Active Shortlist | D41: High (Sweetwater Creek reserve) | E41: High (Near beach/bay) | F41: Greener, bushier counterpart to Frankston | H41: Not verified in report | J41: 31 | K41: 4 | L41: Needs data | W41: =IF(M41="",0,COUNT(M41:V41)) -> 0 | X41: =IF(W41<10,"",M41*ForcedChoiceCorrections!$B$6+N41*ForcedChoiceCorrections!$B$7+O41*ForcedChoiceCorrections!$B$8+P41*ForcedChoiceCorrections!$B$9+Q41*ForcedChoiceCorrections!$B$10+R41*ForcedChoiceCorrections!$B$11+S41*ForcedChoiceCorrections!$B$12+T41*ForcedChoiceCorrections!$B$13+U41*ForcedChoiceCorrections!$B$14+V41*ForcedChoiceCorrections!$B$15) | Y41: =IF(AND(ISNUMBER(SEARCH("pass",L41)),ISNUMBER(X41)),COUNTIFS(L$2:L$90,"*pass*",X$2:X$90,">"&X41)+1,"") | Z41: Sweetwater Creek nature reserve; weaker station walk than central Frankston. Promoted to Active 26 Oct 2026 as a bush-plus-bay overlap candidate. | AA41: 40. Frankston South | Mornington Peninsula | Active Shortlist | P: High (Sweetwater Creek reserve) | Y: High (Near beach/bay) | Lens: Greener, bushier counterpart to Frankston | Price: [Blank] | Basis: Not verified in report | Note: Sweetwater Creek nature reserve; weaker station walk than central Frankston. Promoted to Active 26 Oct 2026 as a bush-plus-bay overlap candidate. | AB41: No | AC41: No station in suburb; Frankston station nearby (recall; verify) | AD41: Peninsula University Hospital ED (drive times added 27 Oct 2026, Google Maps leave-now by suburb name, not postcode, not peak) | AE41: 1500000 | AF41: Maximum purchase price, excluding transaction and moving costs | AG41: [Awaiting search] | AH41: 26 Oct 2026 | AI41: Needs data | AJ41: No verified pricing entered.
A42: Hurstbridge | B42: North-East Fringe | C42: Watchlist | D42: High (Bushland village) | E42: Low (Inland) | F42: Smaller bushland village beyond Diamond Creek | H42: Not verified in report | L42: Needs data | W42: =IF(M42="",0,COUNT(M42:V42)) -> 0 | X42: =IF(W42<10,"",M42*ForcedChoiceCorrections!$B$6+N42*ForcedChoiceCorrections!$B$7+O42*ForcedChoiceCorrections!$B$8+P42*ForcedChoiceCorrections!$B$9+Q42*ForcedChoiceCorrections!$B$10+R42*ForcedChoiceCorrections!$B$11+S42*ForcedChoiceCorrections!$B$12+T42*ForcedChoiceCorrections!$B$13+U42*ForcedChoiceCorrections!$B$14+V42*ForcedChoiceCorrections!$B$15) | Y42: =IF(AND(ISNUMBER(SEARCH("pass",L42)),ISNUMBER(X42)),COUNTIFS(L$2:L$90,"*pass*",X$2:X$90,">"&X42)+1,"") | Z42: Hurstbridge rail terminus; test whether extra distance over Diamond Creek/Eltham adds value. | AA42: 41. Hurstbridge | North-East Fringe | Watchlist | P: High (Bushland village) | Y: Low (Inland) | Lens: Smaller bushland village beyond Diamond Creek | Price: [Blank] | Basis: Not verified in report | Note: Hurstbridge rail terminus; test whether extra distance over Diamond Creek/Eltham adds value. | AE42: 1500000 | AF42: Maximum purchase price, excluding transaction and moving costs | AG42: [Awaiting search] | AH42: 26 Oct 2026 | AI42: Needs data | AJ42: No verified pricing entered.
A43: Ballarat | B43: Central Highlands | C43: Watchlist | D43: Medium-High (Lake Wendouree/gardens) | E43: Low (Inland lake) | F43: Major regional city control with Base Hospital ED | H43: Not verified in report | L43: Needs data | W43: =IF(M43="",0,COUNT(M43:V43)) -> 0 | X43: =IF(W43<10,"",M43*ForcedChoiceCorrections!$B$6+N43*ForcedChoiceCorrections!$B$7+O43*ForcedChoiceCorrections!$B$8+P43*ForcedChoiceCorrections!$B$9+Q43*ForcedChoiceCorrections!$B$10+R43*ForcedChoiceCorrections!$B$11+S43*ForcedChoiceCorrections!$B$12+T43*ForcedChoiceCorrections!$B$13+U43*ForcedChoiceCorrections!$B$14+V43*ForcedChoiceCorrections!$B$15) | Y43: =IF(AND(ISNUMBER(SEARCH("pass",L43)),ISNUMBER(X43)),COUNTIFS(L$2:L$90,"*pass*",X$2:X$90,">"&X43)+1,"") | Z43: Grampians Health Ballarat Base Hospital ED; test only if longer family journey to GW is acceptable. | AA43: 42. Ballarat | Central Highlands | Watchlist | P: Medium-High (Lake Wendouree/gardens) | Y: Low (Inland lake) | Lens: Major regional city control with Base Hospital ED | Price: [Blank] | Basis: Not verified in report | Note: Grampians Health Ballarat Base Hospital ED; test only if longer family journey to GW is acceptable. | AE43: 1500000 | AF43: Maximum purchase price, excluding transaction and moving costs | AG43: [Awaiting search] | AH43: 26 Oct 2026 | AI43: Needs data | AJ43: No verified pricing entered.
A44: Bendigo | B44: Central Victoria | C44: Watchlist | D44: Medium-High (Rosalind Park/bush) | E44: Low (Inland) | F44: Major regional city control with 24-hr ED | H44: Not verified in report | L44: Needs data | W44: =IF(M44="",0,COUNT(M44:V44)) -> 0 | X44: =IF(W44<10,"",M44*ForcedChoiceCorrections!$B$6+N44*ForcedChoiceCorrections!$B$7+O44*ForcedChoiceCorrections!$B$8+P44*ForcedChoiceCorrections!$B$9+Q44*ForcedChoiceCorrections!$B$10+R44*ForcedChoiceCorrections!$B$11+S44*ForcedChoiceCorrections!$B$12+T44*ForcedChoiceCorrections!$B$13+U44*ForcedChoiceCorrections!$B$14+V44*ForcedChoiceCorrections!$B$15) | Y44: =IF(AND(ISNUMBER(SEARCH("pass",L44)),ISNUMBER(X44)),COUNTIFS(L$2:L$90,"*pass*",X$2:X$90,">"&X44)+1,"") | Z44: Bendigo Hospital documented 24-hr/365-day ED; test only if regional travel distance is acceptable. | AA44: 43. Bendigo | Central Victoria | Watchlist | P: Medium-High (Rosalind Park/bush) | Y: Low (Inland) | Lens: Major regional city control with 24-hr ED | Price: [Blank] | Basis: Not verified in report | Note: Bendigo Hospital documented 24-hr/365-day ED; test only if regional travel distance is acceptable. | AE44: 1500000 | AF44: Maximum purchase price, excluding transaction and moving costs | AG44: [Awaiting search] | AH44: 26 Oct 2026 | AI44: Needs data | AJ44: No verified pricing entered.
A45: Dromana | B45: Mornington Peninsula | C45: Watchlist | D45: Medium (Arthurs Seat backdrop) | E45: High (Bay beach) | F45: Further-south Peninsula coastal comparator | H45: Not verified in report | L45: Needs data | W45: =IF(M45="",0,COUNT(M45:V45)) -> 0 | X45: =IF(W45<10,"",M45*ForcedChoiceCorrections!$B$6+N45*ForcedChoiceCorrections!$B$7+O45*ForcedChoiceCorrections!$B$8+P45*ForcedChoiceCorrections!$B$9+Q45*ForcedChoiceCorrections!$B$10+R45*ForcedChoiceCorrections!$B$11+S45*ForcedChoiceCorrections!$B$12+T45*ForcedChoiceCorrections!$B$13+U45*ForcedChoiceCorrections!$B$14+V45*ForcedChoiceCorrections!$B$15) | Y45: =IF(AND(ISNUMBER(SEARCH("pass",L45)),ISNUMBER(X45)),COUNTIFS(L$2:L$90,"*pass*",X$2:X$90,">"&X45)+1,"") | Z45: Compare Rosebud vs Frankston ED access and year-round vs holiday-town feel. | AA45: 44. Dromana | Mornington Peninsula | Watchlist | P: Medium (Arthurs Seat backdrop) | Y: High (Bay beach) | Lens: Further-south Peninsula coastal comparator | Price: [Blank] | Basis: Not verified in report | Note: Compare Rosebud vs Frankston ED access and year-round vs holiday-town feel. | AE45: 1500000 | AF45: Maximum purchase price, excluding transaction and moving costs | AG45: [Awaiting search] | AH45: 26 Oct 2026 | AI45: Needs data | AJ45: No verified pricing entered.
A46: Castlemaine | B46: Central Victoria | C46: Watchlist | D46: High (Box-Ironbark bush/arts) | E46: Low (Inland) | F46: Historic country town on Bendigo V/Line | H46: Not verified in report | L46: Needs data | W46: =IF(M46="",0,COUNT(M46:V46)) -> 0 | X46: =IF(W46<10,"",M46*ForcedChoiceCorrections!$B$6+N46*ForcedChoiceCorrections!$B$7+O46*ForcedChoiceCorrections!$B$8+P46*ForcedChoiceCorrections!$B$9+Q46*ForcedChoiceCorrections!$B$10+R46*ForcedChoiceCorrections!$B$11+S46*ForcedChoiceCorrections!$B$12+T46*ForcedChoiceCorrections!$B$13+U46*ForcedChoiceCorrections!$B$14+V46*ForcedChoiceCorrections!$B$15) | Y46: =IF(AND(ISNUMBER(SEARCH("pass",L46)),ISNUMBER(X46)),COUNTIFS(L$2:L$90,"*pass*",X$2:X$90,">"&X46)+1,"") | Z46: Do not assume local health service equals a major 24-hr ED; Bendigo ED is reference point. | AA46: 45. Castlemaine | Central Victoria | Watchlist | P: High (Box-Ironbark bush/arts) | Y: Low (Inland) | Lens: Historic country town on Bendigo V/Line | Price: [Blank] | Basis: Not verified in report | Note: Do not assume local health service equals a major 24-hr ED; Bendigo ED is reference point. | AE46: 1500000 | AF46: Maximum purchase price, excluding transaction and moving costs | AG46: [Awaiting search] | AH46: 26 Oct 2026 | AI46: Needs data | AJ46: No verified pricing entered.
A47: Wonthaggi | B47: Bass Coast | C47: Watchlist | D47: Medium (Coastal hinterland) | E47: High (Near Bass Coast) | F47: Coastal Gippsland service-centre comparator | H47: Not verified in report | L47: Needs data | W47: =IF(M47="",0,COUNT(M47:V47)) -> 0 | X47: =IF(W47<10,"",M47*ForcedChoiceCorrections!$B$6+N47*ForcedChoiceCorrections!$B$7+O47*ForcedChoiceCorrections!$B$8+P47*ForcedChoiceCorrections!$B$9+Q47*ForcedChoiceCorrections!$B$10+R47*ForcedChoiceCorrections!$B$11+S47*ForcedChoiceCorrections!$B$12+T47*ForcedChoiceCorrections!$B$13+U47*ForcedChoiceCorrections!$B$14+V47*ForcedChoiceCorrections!$B$15) | Y47: =IF(AND(ISNUMBER(SEARCH("pass",L47)),ISNUMBER(X47)),COUNTIFS(L$2:L$90,"*pass*",X$2:X$90,">"&X47)+1,"") | Z47: Bass Coast Health Wonthaggi Hospital; verify ED capability & GW travel time before promoting. | AA47: 46. Wonthaggi | Bass Coast | Watchlist | P: Medium (Coastal hinterland) | Y: High (Near Bass Coast) | Lens: Coastal Gippsland service-centre comparator | Price: [Blank] | Basis: Not verified in report | Note: Bass Coast Health Wonthaggi Hospital; verify ED capability & GW travel time before promoting. | AE47: 1500000 | AF47: Maximum purchase price, excluding transaction and moving costs | AG47: [Awaiting search] | AH47: 26 Oct 2026 | AI47: Needs data | AJ47: No verified pricing entered.
A48: Inverloch | B48: Bass Coast | C48: Watchlist | D48: Medium (Screw Creek/foreshore) | E48: High (Inlet & surf beach) | F48: Coastal Gippsland lifestyle counterpart to Wonthaggi | H48: Not verified in report | L48: Needs data | W48: =IF(M48="",0,COUNT(M48:V48)) -> 0 | X48: =IF(W48<10,"",M48*ForcedChoiceCorrections!$B$6+N48*ForcedChoiceCorrections!$B$7+O48*ForcedChoiceCorrections!$B$8+P48*ForcedChoiceCorrections!$B$9+Q48*ForcedChoiceCorrections!$B$10+R48*ForcedChoiceCorrections!$B$11+S48*ForcedChoiceCorrections!$B$12+T48*ForcedChoiceCorrections!$B$13+U48*ForcedChoiceCorrections!$B$14+V48*ForcedChoiceCorrections!$B$15) | Y48: =IF(AND(ISNUMBER(SEARCH("pass",L48)),ISNUMBER(X48)),COUNTIFS(L$2:L$90,"*pass*",X$2:X$90,">"&X48)+1,"") | Z48: Shared pathway & inlet walks; no passenger rail; verify Wonthaggi/Latrobe ED drive. | AA48: 47. Inverloch | Bass Coast | Watchlist | P: Medium (Screw Creek/foreshore) | Y: High (Inlet & surf beach) | Lens: Coastal Gippsland lifestyle counterpart to Wonthaggi | Price: [Blank] | Basis: Not verified in report | Note: Shared pathway & inlet walks; no passenger rail; verify Wonthaggi/Latrobe ED drive. | AE48: 1500000 | AF48: Maximum purchase price, excluding transaction and moving costs | AG48: [Awaiting search] | AH48: 26 Oct 2026 | AI48: Needs data | AJ48: No verified pricing entered.
A49: [SYNTHETIC TEST — Ringwood Leafy Pocket] | B49: East Melbourne | C49: Synthetic Test | D49: Medium-High | E49: Low | F49: Synthetic test row verifying Pass & Rank math | G49: 1045000 | H49: Synthetic test row (clear before live use) | I49: 1107700 | J49: 18 | K49: 12 | L49: Excluded: test row | M49: 7 | N49: 8 | O49: 7 | P49: 2 | Q49: 9 | R49: 9 | S49: 8 | T49: 6 | U49: 8 | V49: 8 | W49: =IF(M49="",0,COUNT(M49:V49)) -> 10 | X49: =IF(W49<10,"",M49*ForcedChoiceCorrections!$B$6+N49*ForcedChoiceCorrections!$B$7+O49*ForcedChoiceCorrections!$B$8+P49*ForcedChoiceCorrections!$B$9+Q49*ForcedChoiceCorrections!$B$10+R49*ForcedChoiceCorrections!$B$11+S49*ForcedChoiceCorrections!$B$12+T49*ForcedChoiceCorrections!$B$13+U49*ForcedChoiceCorrections!$B$14+V49*ForcedChoiceCorrections!$B$15) -> 7.046 | Y49: =IF(AND(ISNUMBER(SEARCH("pass",L49)),ISNUMBER(X49)),COUNTIFS(L$2:L$90,"*pass*",X$2:X$90,">"&X49)+1,"") | Z49: [SYNTHETIC TEST] Demonstrates 'Pass' & Rank #1 when drive times & 0-10 scores are entered. | AA49: 48. [SYNTHETIC TEST — Ringwood Leafy Pocket] | East Melbourne | Synthetic Test | P: Medium-High | Y: Low | Lens: Synthetic test row verifying Pass & Rank math | Price: 1045000 | Basis: Synthetic test row (clear before live use) | Note: [SYNTHETIC TEST] Demonstrates 'Pass' & Rank #1 when drive times & 0-10 scores are entered. | AE49: 1500000 | AF49: Maximum purchase price, excluding transaction and moving costs | AG49: Benchmark synthetic price | AH49: 26 Oct 2026 | AI49: Pass | AJ49: Synthetic test calibration model.
A50: [SYNTHETIC TEST — Ocean Grove Woodland Pocket] | B50: Bellarine Peninsula | C50: Synthetic Test | D50: Medium-High | E50: High | F50: Synthetic test row verifying coastal vs GW filter | G50: 980000 | H50: Synthetic test row (clear before live use) | I50: 1038800 | J50: 24 | K50: 19 | L50: Excluded: test row | M50: 9 | N50: 5 | O50: 4 | P50: 10 | Q50: 7 | R50: 5 | S50: 7 | T50: 8 | U50: 9 | V50: 5 | W50: =IF(M50="",0,COUNT(M50:V50)) -> 10 | X50: =IF(W50<10,"",M50*ForcedChoiceCorrections!$B$6+N50*ForcedChoiceCorrections!$B$7+O50*ForcedChoiceCorrections!$B$8+P50*ForcedChoiceCorrections!$B$9+Q50*ForcedChoiceCorrections!$B$10+R50*ForcedChoiceCorrections!$B$11+S50*ForcedChoiceCorrections!$B$12+T50*ForcedChoiceCorrections!$B$13+U50*ForcedChoiceCorrections!$B$14+V50*ForcedChoiceCorrections!$B$15) -> 6.929 | Y50: =IF(AND(ISNUMBER(SEARCH("pass",L50)),ISNUMBER(X50)),COUNTIFS(L$2:L$90,"*pass*",X$2:X$90,">"&X50)+1,"") | Z50: [SYNTHETIC TEST] Demonstrates 'Pass' & Rank #2 under 25-min GW / 20-min ED test limits. | AA50: 49. [SYNTHETIC TEST — Ocean Grove Woodland Pocket] | Bellarine Peninsula | Synthetic Test | P: Medium-High | Y: High | Lens: Synthetic test row verifying coastal vs GW filter | Price: 980000 | Basis: Synthetic test row (clear before live use) | Note: [SYNTHETIC TEST] Demonstrates 'Pass' & Rank #2 under 25-min GW / 20-min ED test limits. | AE50: 1500000 | AF50: Maximum purchase price, excluding transaction and moving costs | AG50: Benchmark synthetic price | AH50: 26 Oct 2026 | AI50: Pass | AJ50: Synthetic test calibration model.
A51: Rosebud | B51: Mornington Peninsula | C51: Open-mind viewing | D51: Low-Medium (Coastal) | E51: High (Bay beach) | F51: Open-mind viewing: calibrate coastal feel against bush | H51: Not verified | L51: Needs data | O51: =IF(K51="","",ROUND(MAX(0,10*(1-K51/Filters!$B$5)),1)) | W51: =IF(M51="",0,COUNT(M51:V51)) -> 0 | X51: =IF(W51<10,"",M51*ForcedChoiceCorrections!$B$6+N51*ForcedChoiceCorrections!$B$7+O51*ForcedChoiceCorrections!$B$8+P51*ForcedChoiceCorrections!$B$9+Q51*ForcedChoiceCorrections!$B$10+R51*ForcedChoiceCorrections!$B$11+S51*ForcedChoiceCorrections!$B$12+T51*ForcedChoiceCorrections!$B$13+U51*ForcedChoiceCorrections!$B$14+V51*ForcedChoiceCorrections!$B$15) | Y51: =IF(AND(ISNUMBER(SEARCH("pass",L51)),ISNUMBER(X51)),COUNTIFS(L$2:L$90,"*pass*",X$2:X$90,">"&X51)+1,"") | Z51: OPEN-MIND VIEWING PICK (nominated by NJD): view for calibration. Verify year-round services vs holiday-town feel, local ED status and drive to a 24-hr public ED, GW drive and price. | AA51: 50. Rosebud | Mornington Peninsula | Open-mind viewing | P: Low-Medium (Coastal) | Y: High (Bay beach) | Lens: Open-mind viewing: calibrate coastal feel against bush | Price: [Blank] | Basis: Not verified | Note: OPEN-MIND VIEWING PICK (nominated by NJD): view for calibration. Verify year-round services vs holiday-town feel, local ED status and drive to a 24-hr public ED, GW drive and price. | AB51: No | AC51: No passenger rail on the Peninsula south of Frankston (from recall; verify) | AD51: Needs data (verify Frankston/Peninsula Univ Hospital vs local) | AE51: 1500000 | AF51: Maximum purchase price, excluding transaction and moving costs | AG51: [Awaiting search] | AH51: 26 Oct 2026 | AI51: Needs data | AJ51: No verified pricing entered.
A52: Rye | B52: Mornington Peninsula | C52: Open-mind viewing | D52: Low-Medium (Coastal) | E52: High (Bay/ocean beach) | F52: Open-mind viewing: calibrate coastal feel against bush | H52: Not verified | L52: Needs data | O52: =IF(K52="","",ROUND(MAX(0,10*(1-K52/Filters!$B$5)),1)) | W52: =IF(M52="",0,COUNT(M52:V52)) -> 0 | X52: =IF(W52<10,"",M52*ForcedChoiceCorrections!$B$6+N52*ForcedChoiceCorrections!$B$7+O52*ForcedChoiceCorrections!$B$8+P52*ForcedChoiceCorrections!$B$9+Q52*ForcedChoiceCorrections!$B$10+R52*ForcedChoiceCorrections!$B$11+S52*ForcedChoiceCorrections!$B$12+T52*ForcedChoiceCorrections!$B$13+U52*ForcedChoiceCorrections!$B$14+V52*ForcedChoiceCorrections!$B$15) | Y52: =IF(AND(ISNUMBER(SEARCH("pass",L52)),ISNUMBER(X52)),COUNTIFS(L$2:L$90,"*pass*",X$2:X$90,">"&X52)+1,"") | Z52: OPEN-MIND VIEWING PICK (nominated by NJD): view for calibration. Verify year-round services vs holiday-town feel, ED access (nearest 24-hr public ED likely Frankston/Peninsula Univ Hospital), GW drive and price. | AA52: 51. Rye | Mornington Peninsula | Open-mind viewing | P: Low-Medium (Coastal) | Y: High (Bay/ocean beach) | Lens: Open-mind viewing: calibrate coastal feel against bush | Price: [Blank] | Basis: Not verified | Note: OPEN-MIND VIEWING PICK (nominated by NJD): view for calibration. Verify year-round services vs holiday-town feel, ED access (nearest 24-hr public ED likely Frankston/Peninsula Univ Hospital), GW drive and price. | AB52: No | AC52: No passenger rail on the Peninsula south of Frankston (from recall; verify) | AD52: Needs data (verify Frankston/Peninsula Univ Hospital vs local) | AE52: 1500000 | AF52: Maximum purchase price, excluding transaction and moving costs | AG52: [Awaiting search] | AH52: 26 Oct 2026 | AI52: Needs data | AJ52: No verified pricing entered.
A53: Gisborne | B53: Macedon Ranges | C53: Watchlist | D53: Medium-High (Rural/gardens) | E53: Low (Inland) | F53: Regional town close to Melbourne, distinct from Woodend and Macedon | H53: Not verified | L53: Needs data | O53: =IF(K53="","",ROUND(MAX(0,10*(1-K53/Filters!$B$5)),1)) | W53: =IF(M53="",0,COUNT(M53:V53)) -> 0 | X53: =IF(W53<10,"",M53*ForcedChoiceCorrections!$B$6+N53*ForcedChoiceCorrections!$B$7+O53*ForcedChoiceCorrections!$B$8+P53*ForcedChoiceCorrections!$B$9+Q53*ForcedChoiceCorrections!$B$10+R53*ForcedChoiceCorrections!$B$11+S53*ForcedChoiceCorrections!$B$12+T53*ForcedChoiceCorrections!$B$13+U53*ForcedChoiceCorrections!$B$14+V53*ForcedChoiceCorrections!$B$15) | Y53: =IF(AND(ISNUMBER(SEARCH("pass",L53)),ISNUMBER(X53)),COUNTIFS(L$2:L$90,"*pass*",X$2:X$90,">"&X53)+1,"") | Z53: Regional add (within about 1.5 hrs of Melbourne, from recall; verify). Verify train access (nearest V/Line may be Riddells Creek), GW drive, price and nearest major public ED. | AA53: 52. Gisborne | Macedon Ranges | Watchlist | P: Medium-High (Rural/gardens) | Y: Low (Inland) | Lens: Regional town close to Melbourne, distinct from Woodend and Macedon | Price: [Blank] | Basis: Not verified | Note: Regional add (within about 1.5 hrs of Melbourne, from recall; verify). Verify train access (nearest V/Line may be Riddells Creek), GW drive, price and nearest major public ED. | AC53: Needs data | AD53: Needs data | AE53: 1500000 | AF53: Maximum purchase price, excluding transaction and moving costs | AG53: [Awaiting search] | AH53: 26 Oct 2026 | AI53: Needs data | AJ53: No verified pricing entered.
A54: Riddells Creek | B54: Macedon Ranges | C54: Watchlist | D54: Medium-High (Village/countryside) | E54: Low (Inland) | F54: Small village with V/Line access (to verify) | H54: Not verified | L54: Needs data | O54: =IF(K54="","",ROUND(MAX(0,10*(1-K54/Filters!$B$5)),1)) | W54: =IF(M54="",0,COUNT(M54:V54)) -> 0 | X54: =IF(W54<10,"",M54*ForcedChoiceCorrections!$B$6+N54*ForcedChoiceCorrections!$B$7+O54*ForcedChoiceCorrections!$B$8+P54*ForcedChoiceCorrections!$B$9+Q54*ForcedChoiceCorrections!$B$10+R54*ForcedChoiceCorrections!$B$11+S54*ForcedChoiceCorrections!$B$12+T54*ForcedChoiceCorrections!$B$13+U54*ForcedChoiceCorrections!$B$14+V54*ForcedChoiceCorrections!$B$15) | Y54: =IF(AND(ISNUMBER(SEARCH("pass",L54)),ISNUMBER(X54)),COUNTIFS(L$2:L$90,"*pass*",X$2:X$90,">"&X54)+1,"") | Z54: Regional add (within about 1.5 hrs of Melbourne, from recall; verify). Verify V/Line station and service frequency, GW drive, price and nearest major public ED. | AA54: 53. Riddells Creek | Macedon Ranges | Watchlist | P: Medium-High (Village/countryside) | Y: Low (Inland) | Lens: Small village with V/Line access (to verify) | Price: [Blank] | Basis: Not verified | Note: Regional add (within about 1.5 hrs of Melbourne, from recall; verify). Verify V/Line station and service frequency, GW drive, price and nearest major public ED. | AC54: Needs data | AD54: Needs data | AE54: 1500000 | AF54: Maximum purchase price, excluding transaction and moving costs | AG54: [Awaiting search] | AH54: 26 Oct 2026 | AI54: Needs data | AJ54: No verified pricing entered.
A55: Yarra Glen | B55: Yarra Valley | C55: Watchlist | D55: High (Valley/vineyards) | E55: Low (Inland) | F55: Yarra Valley village, quieter than Healesville | H55: Not verified | L55: Needs data | O55: =IF(K55="","",ROUND(MAX(0,10*(1-K55/Filters!$B$5)),1)) | W55: =IF(M55="",0,COUNT(M55:V55)) -> 0 | X55: =IF(W55<10,"",M55*ForcedChoiceCorrections!$B$6+N55*ForcedChoiceCorrections!$B$7+O55*ForcedChoiceCorrections!$B$8+P55*ForcedChoiceCorrections!$B$9+Q55*ForcedChoiceCorrections!$B$10+R55*ForcedChoiceCorrections!$B$11+S55*ForcedChoiceCorrections!$B$12+T55*ForcedChoiceCorrections!$B$13+U55*ForcedChoiceCorrections!$B$14+V55*ForcedChoiceCorrections!$B$15) | Y55: =IF(AND(ISNUMBER(SEARCH("pass",L55)),ISNUMBER(X55)),COUNTIFS(L$2:L$90,"*pass*",X$2:X$90,">"&X55)+1,"") | Z55: Regional add (within about 1.5 hrs of Melbourne, from recall; verify). Likely no train; verify GW drive, price and ED journey (Maroondah/Angliss). Compare with Healesville. | AA55: 54. Yarra Glen | Yarra Valley | Watchlist | P: High (Valley/vineyards) | Y: Low (Inland) | Lens: Yarra Valley village, quieter than Healesville | Price: [Blank] | Basis: Not verified | Note: Regional add (within about 1.5 hrs of Melbourne, from recall; verify). Likely no train; verify GW drive, price and ED journey (Maroondah/Angliss). Compare with Healesville. | AC55: Needs data | AD55: Needs data | AE55: 1500000 | AF55: Maximum purchase price, excluding transaction and moving costs | AG55: [Awaiting search] | AH55: 26 Oct 2026 | AI55: Needs data | AJ55: No verified pricing entered.
A56: Drouin | B56: West Gippsland | C56: Watchlist | D56: Medium-High (Hills/gardens) | E56: Low (Inland) | F56: Gippsland-corridor town alongside Warragul | H56: Not verified | L56: Needs data | O56: =IF(K56="","",ROUND(MAX(0,10*(1-K56/Filters!$B$5)),1)) | W56: =IF(M56="",0,COUNT(M56:V56)) -> 0 | X56: =IF(W56<10,"",M56*ForcedChoiceCorrections!$B$6+N56*ForcedChoiceCorrections!$B$7+O56*ForcedChoiceCorrections!$B$8+P56*ForcedChoiceCorrections!$B$9+Q56*ForcedChoiceCorrections!$B$10+R56*ForcedChoiceCorrections!$B$11+S56*ForcedChoiceCorrections!$B$12+T56*ForcedChoiceCorrections!$B$13+U56*ForcedChoiceCorrections!$B$14+V56*ForcedChoiceCorrections!$B$15) | Y56: =IF(AND(ISNUMBER(SEARCH("pass",L56)),ISNUMBER(X56)),COUNTIFS(L$2:L$90,"*pass*",X$2:X$90,">"&X56)+1,"") | Z56: Regional add (within about 1.5 hrs of Melbourne, from recall; verify). Verify V/Line station, GW drive, price and ED access (West Gippsland Hospital at Warragul). Compare with Warragul. | AA56: 55. Drouin | West Gippsland | Watchlist | P: Medium-High (Hills/gardens) | Y: Low (Inland) | Lens: Gippsland-corridor town alongside Warragul | Price: [Blank] | Basis: Not verified | Note: Regional add (within about 1.5 hrs of Melbourne, from recall; verify). Verify V/Line station, GW drive, price and ED access (West Gippsland Hospital at Warragul). Compare with Warragul. | AC56: Needs data | AD56: Needs data | AE56: 1500000 | AF56: Maximum purchase price, excluding transaction and moving costs | AG56: [Awaiting search] | AH56: 26 Oct 2026 | AI56: Needs data | AJ56: No verified pricing entered.
W57: =IF(M57="",0,COUNT(M57:V57)) -> 0 | X57: =IF(W57<10,"",M57*ForcedChoiceCorrections!$B$6+N57*ForcedChoiceCorrections!$B$7+O57*ForcedChoiceCorrections!$B$8+P57*ForcedChoiceCorrections!$B$9+Q57*ForcedChoiceCorrections!$B$10+R57*ForcedChoiceCorrections!$B$11+S57*ForcedChoiceCorrections!$B$12+T57*ForcedChoiceCorrections!$B$13+U57*ForcedChoiceCorrections!$B$14+V57*ForcedChoiceCorrections!$B$15) | Y57: =IF(AND(ISNUMBER(SEARCH("pass",L57)),ISNUMBER(X57)),COUNTIFS(L$2:L$90,"*pass*",X$2:X$90,">"&X57)+1,"")
W58: =IF(M58="",0,COUNT(M58:V58)) -> 0 | X58: =IF(W58<10,"",M58*ForcedChoiceCorrections!$B$6+N58*ForcedChoiceCorrections!$B$7+O58*ForcedChoiceCorrections!$B$8+P58*ForcedChoiceCorrections!$B$9+Q58*ForcedChoiceCorrections!$B$10+R58*ForcedChoiceCorrections!$B$11+S58*ForcedChoiceCorrections!$B$12+T58*ForcedChoiceCorrections!$B$13+U58*ForcedChoiceCorrections!$B$14+V58*ForcedChoiceCorrections!$B$15) | Y58: =IF(AND(ISNUMBER(SEARCH("pass",L58)),ISNUMBER(X58)),COUNTIFS(L$2:L$90,"*pass*",X$2:X$90,">"&X58)+1,"")
W59: =IF(M59="",0,COUNT(M59:V59)) -> 0 | X59: =IF(W59<10,"",M59*ForcedChoiceCorrections!$B$6+N59*ForcedChoiceCorrections!$B$7+O59*ForcedChoiceCorrections!$B$8+P59*ForcedChoiceCorrections!$B$9+Q59*ForcedChoiceCorrections!$B$10+R59*ForcedChoiceCorrections!$B$11+S59*ForcedChoiceCorrections!$B$12+T59*ForcedChoiceCorrections!$B$13+U59*ForcedChoiceCorrections!$B$14+V59*ForcedChoiceCorrections!$B$15) | Y59: =IF(AND(ISNUMBER(SEARCH("pass",L59)),ISNUMBER(X59)),COUNTIFS(L$2:L$90,"*pass*",X$2:X$90,">"&X59)+1,"")
W60: =IF(M60="",0,COUNT(M60:V60)) -> 0 | X60: =IF(W60<10,"",M60*ForcedChoiceCorrections!$B$6+N60*ForcedChoiceCorrections!$B$7+O60*ForcedChoiceCorrections!$B$8+P60*ForcedChoiceCorrections!$B$9+Q60*ForcedChoiceCorrections!$B$10+R60*ForcedChoiceCorrections!$B$11+S60*ForcedChoiceCorrections!$B$12+T60*ForcedChoiceCorrections!$B$13+U60*ForcedChoiceCorrections!$B$14+V60*ForcedChoiceCorrections!$B$15) | Y60: =IF(AND(ISNUMBER(SEARCH("pass",L60)),ISNUMBER(X60)),COUNTIFS(L$2:L$90,"*pass*",X$2:X$90,">"&X60)+1,"")
W61: =IF(M61="",0,COUNT(M61:V61)) -> 0 | X61: =IF(W61<10,"",M61*ForcedChoiceCorrections!$B$6+N61*ForcedChoiceCorrections!$B$7+O61*ForcedChoiceCorrections!$B$8+P61*ForcedChoiceCorrections!$B$9+Q61*ForcedChoiceCorrections!$B$10+R61*ForcedChoiceCorrections!$B$11+S61*ForcedChoiceCorrections!$B$12+T61*ForcedChoiceCorrections!$B$13+U61*ForcedChoiceCorrections!$B$14+V61*ForcedChoiceCorrections!$B$15) | Y61: =IF(AND(ISNUMBER(SEARCH("pass",L61)),ISNUMBER(X61)),COUNTIFS(L$2:L$90,"*pass*",X$2:X$90,">"&X61)+1,"")
W62: =IF(M62="",0,COUNT(M62:V62)) -> 0 | X62: =IF(W62<10,"",M62*ForcedChoiceCorrections!$B$6+N62*ForcedChoiceCorrections!$B$7+O62*ForcedChoiceCorrections!$B$8+P62*ForcedChoiceCorrections!$B$9+Q62*ForcedChoiceCorrections!$B$10+R62*ForcedChoiceCorrections!$B$11+S62*ForcedChoiceCorrections!$B$12+T62*ForcedChoiceCorrections!$B$13+U62*ForcedChoiceCorrections!$B$14+V62*ForcedChoiceCorrections!$B$15) | Y62: =IF(AND(ISNUMBER(SEARCH("pass",L62)),ISNUMBER(X62)),COUNTIFS(L$2:L$90,"*pass*",X$2:X$90,">"&X62)+1,"")
W63: =IF(M63="",0,COUNT(M63:V63)) -> 0 | X63: =IF(W63<10,"",M63*ForcedChoiceCorrections!$B$6+N63*ForcedChoiceCorrections!$B$7+O63*ForcedChoiceCorrections!$B$8+P63*ForcedChoiceCorrections!$B$9+Q63*ForcedChoiceCorrections!$B$10+R63*ForcedChoiceCorrections!$B$11+S63*ForcedChoiceCorrections!$B$12+T63*ForcedChoiceCorrections!$B$13+U63*ForcedChoiceCorrections!$B$14+V63*ForcedChoiceCorrections!$B$15) | Y63: =IF(AND(ISNUMBER(SEARCH("pass",L63)),ISNUMBER(X63)),COUNTIFS(L$2:L$90,"*pass*",X$2:X$90,">"&X63)+1,"")
W64: =IF(M64="",0,COUNT(M64:V64)) -> 0 | X64: =IF(W64<10,"",M64*ForcedChoiceCorrections!$B$6+N64*ForcedChoiceCorrections!$B$7+O64*ForcedChoiceCorrections!$B$8+P64*ForcedChoiceCorrections!$B$9+Q64*ForcedChoiceCorrections!$B$10+R64*ForcedChoiceCorrections!$B$11+S64*ForcedChoiceCorrections!$B$12+T64*ForcedChoiceCorrections!$B$13+U64*ForcedChoiceCorrections!$B$14+V64*ForcedChoiceCorrections!$B$15) | Y64: =IF(AND(ISNUMBER(SEARCH("pass",L64)),ISNUMBER(X64)),COUNTIFS(L$2:L$90,"*pass*",X$2:X$90,">"&X64)+1,"")
W65: =IF(M65="",0,COUNT(M65:V65)) -> 0 | X65: =IF(W65<10,"",M65*ForcedChoiceCorrections!$B$6+N65*ForcedChoiceCorrections!$B$7+O65*ForcedChoiceCorrections!$B$8+P65*ForcedChoiceCorrections!$B$9+Q65*ForcedChoiceCorrections!$B$10+R65*ForcedChoiceCorrections!$B$11+S65*ForcedChoiceCorrections!$B$12+T65*ForcedChoiceCorrections!$B$13+U65*ForcedChoiceCorrections!$B$14+V65*ForcedChoiceCorrections!$B$15) | Y65: =IF(AND(ISNUMBER(SEARCH("pass",L65)),ISNUMBER(X65)),COUNTIFS(L$2:L$90,"*pass*",X$2:X$90,">"&X65)+1,"")
W66: =IF(M66="",0,COUNT(M66:V66)) -> 0 | X66: =IF(W66<10,"",M66*ForcedChoiceCorrections!$B$6+N66*ForcedChoiceCorrections!$B$7+O66*ForcedChoiceCorrections!$B$8+P66*ForcedChoiceCorrections!$B$9+Q66*ForcedChoiceCorrections!$B$10+R66*ForcedChoiceCorrections!$B$11+S66*ForcedChoiceCorrections!$B$12+T66*ForcedChoiceCorrections!$B$13+U66*ForcedChoiceCorrections!$B$14+V66*ForcedChoiceCorrections!$B$15) | Y66: =IF(AND(ISNUMBER(SEARCH("pass",L66)),ISNUMBER(X66)),COUNTIFS(L$2:L$90,"*pass*",X$2:X$90,">"&X66)+1,"")
W67: =IF(M67="",0,COUNT(M67:V67)) -> 0 | X67: =IF(W67<10,"",M67*ForcedChoiceCorrections!$B$6+N67*ForcedChoiceCorrections!$B$7+O67*ForcedChoiceCorrections!$B$8+P67*ForcedChoiceCorrections!$B$9+Q67*ForcedChoiceCorrections!$B$10+R67*ForcedChoiceCorrections!$B$11+S67*ForcedChoiceCorrections!$B$12+T67*ForcedChoiceCorrections!$B$13+U67*ForcedChoiceCorrections!$B$14+V67*ForcedChoiceCorrections!$B$15) | Y67: =IF(AND(ISNUMBER(SEARCH("pass",L67)),ISNUMBER(X67)),COUNTIFS(L$2:L$90,"*pass*",X$2:X$90,">"&X67)+1,"")
W68: =IF(M68="",0,COUNT(M68:V68)) -> 0 | X68: =IF(W68<10,"",M68*ForcedChoiceCorrections!$B$6+N68*ForcedChoiceCorrections!$B$7+O68*ForcedChoiceCorrections!$B$8+P68*ForcedChoiceCorrections!$B$9+Q68*ForcedChoiceCorrections!$B$10+R68*ForcedChoiceCorrections!$B$11+S68*ForcedChoiceCorrections!$B$12+T68*ForcedChoiceCorrections!$B$13+U68*ForcedChoiceCorrections!$B$14+V68*ForcedChoiceCorrections!$B$15) | Y68: =IF(AND(ISNUMBER(SEARCH("pass",L68)),ISNUMBER(X68)),COUNTIFS(L$2:L$90,"*pass*",X$2:X$90,">"&X68)+1,"")
... W90: =IF(M90="",0,COUNT(M90:V90)) -> 0 | X90: =IF(W90<10,"",M90*ForcedChoiceCorrections!$B$6+N90*ForcedChoiceCorrections!$B$7+O90*ForcedChoiceCorrections!$B$8+P90*ForcedChoiceCorrections!$B$9+Q90*ForcedChoiceCorrections!$B$10+R90*ForcedChoiceCorrections!$B$11+S90*ForcedChoiceCorrections!$B$12+T90*ForcedChoiceCorrections!$B$13+U90*ForcedChoiceCorrections!$B$14+V90*ForcedChoiceCorrections!$B$15) | Y90: =IF(AND(ISNUMBER(SEARCH("pass",L90)),ISNUMBER(X90)),COUNTIFS(L$2:L$90,"*pass*",X$2:X$90,">"&X90)+1,"")

Sheet Listings
A1: # | B1: Address | C1: Suburb | D1: Price guide (as listed) | E1: Guide low ($) | F1: Guide high ($) | G1: Budget check (vs Filters!B2) | H1: Beds | I1: Baths | J1: Cars | K1: Land (m²) | L1: Listing status | M1: Next inspection (as of 27 Oct) | N1: Agent | O1: Scorecard suburb (lookup key) | P1: Scorecard shortlist status | Q1: Drive to GW (min, suburb) | R1: Drive to ED (min, suburb) | S1: Train (suburb) | T1: Overall check | U1: Notes | W1: Source: realestate.com.au collection 'Parents.', read from browser 27 Oct 2026 (copied from the Google Sheet version of this tab). A–F, H–O, U are pasted values; G and P–T are formulas. Prices are agent guides (purchase price, before costs), compared with Filters!B2 purchase cap. Drive times and train are suburb-level from SuburbScorecard, not per address. Inspection times go stale after 31 Oct. Refresh = re-read the collection and overwrite pasted columns only.
A2: 1 | B2: 6 Beales Street | C2: Torquay | D2: $1,475,000-$1,575,000 | E2: 1475000 | F2: 1575000 | G2: =IF(E2="","Needs data",IF(F2<=Filters!$B$2,"Within cap",IF(E2<=Filters!$B$2,"Straddles cap","Over cap"))) -> Straddles cap | H2: 4 | I2: 2 | J2: 2 | K2: 411 | L2: Active | M2: Tue 27 Oct 5:00pm | N2: Chris Henson | O2: Torquay | P2: =IFERROR(INDEX(SuburbScorecard!$C:$C,MATCH($O2,SuburbScorecard!$A:$A,0)),"Not on scorecard") -> Active Shortlist | Q2: =IFERROR(IF(INDEX(SuburbScorecard!$J:$J,MATCH($O2,SuburbScorecard!$A:$A,0))="","",INDEX(SuburbScorecard!$J:$J,MATCH($O2,SuburbScorecard!$A:$A,0))),"") -> 88 | R2: =IFERROR(IF(INDEX(SuburbScorecard!$K:$K,MATCH($O2,SuburbScorecard!$A:$A,0))="","",INDEX(SuburbScorecard!$K:$K,MATCH($O2,SuburbScorecard!$A:$A,0))),"") -> 23 | S2: =IFERROR(IF(INDEX(SuburbScorecard!$AB:$AB,MATCH($O2,SuburbScorecard!$A:$A,0))="","Needs data",INDEX(SuburbScorecard!$AB:$AB,MATCH($O2,SuburbScorecard!$A:$A,0))),"Needs data") -> No | T2: =IF(L2="Under offer","Under offer",IF(G2="Over cap","Fails: budget",IF(NOT(AND(ISNUMBER(Q2),ISNUMBER(R2))),"Needs data",IF(Q2>Filters!$B$4,"Fails: GW drive",IF(R2>Filters!$B$5,"Fails: ED drive",IF(G2="Straddles cap","Pass if bought near low end","Pass")))))) -> Pass if bought near low end
A3: 2 | B3: 1/1 Bruce Street | C3: West Footscray | D3: $1,200,000-$1,300,000 | E3: 1200000 | F3: 1300000 | G3: =IF(E3="","Needs data",IF(F3<=Filters!$B$2,"Within cap",IF(E3<=Filters!$B$2,"Straddles cap","Over cap"))) -> Within cap | H3: 3 | I3: 2 | J3: 2 | L3: Active | M3: Thu 29 Oct 5:15pm | N3: Huss Saad | O3: West Footscray | P3: =IFERROR(INDEX(SuburbScorecard!$C:$C,MATCH($O3,SuburbScorecard!$A:$A,0)),"Not on scorecard") -> Not on scorecard | Q3: =IFERROR(IF(INDEX(SuburbScorecard!$J:$J,MATCH($O3,SuburbScorecard!$A:$A,0))="","",INDEX(SuburbScorecard!$J:$J,MATCH($O3,SuburbScorecard!$A:$A,0))),"") | R3: =IFERROR(IF(INDEX(SuburbScorecard!$K:$K,MATCH($O3,SuburbScorecard!$A:$A,0))="","",INDEX(SuburbScorecard!$K:$K,MATCH($O3,SuburbScorecard!$A:$A,0))),"") | S3: =IFERROR(IF(INDEX(SuburbScorecard!$AB:$AB,MATCH($O3,SuburbScorecard!$A:$A,0))="","Needs data",INDEX(SuburbScorecard!$AB:$AB,MATCH($O3,SuburbScorecard!$A:$A,0))),"Needs data") -> Needs data | T3: =IF(L3="Under offer","Under offer",IF(G3="Over cap","Fails: budget",IF(NOT(AND(ISNUMBER(Q3),ISNUMBER(R3))),"Needs data",IF(Q3>Filters!$B$4,"Fails: GW drive",IF(R3>Filters!$B$5,"Fails: ED drive",IF(G3="Straddles cap","Pass if bought near low end","Pass")))))) -> Needs data | U3: Suburb not on scorecard
A4: 3 | B4: 67 Donna Buang Road | C4: Warburton | D4: $900,000-$990,000 | E4: 900000 | F4: 990000 | G4: =IF(E4="","Needs data",IF(F4<=Filters!$B$2,"Within cap",IF(E4<=Filters!$B$2,"Straddles cap","Over cap"))) -> Within cap | H4: 5 | I4: 3 | J4: 4 | K4: 3235 | L4: Active | M4: None listed | N4: Suzie Brannelly | O4: Warburton | P4: =IFERROR(INDEX(SuburbScorecard!$C:$C,MATCH($O4,SuburbScorecard!$A:$A,0)),"Not on scorecard") -> Watchlist | Q4: =IFERROR(IF(INDEX(SuburbScorecard!$J:$J,MATCH($O4,SuburbScorecard!$A:$A,0))="","",INDEX(SuburbScorecard!$J:$J,MATCH($O4,SuburbScorecard!$A:$A,0))),"") -> 65 | R4: =IFERROR(IF(INDEX(SuburbScorecard!$K:$K,MATCH($O4,SuburbScorecard!$A:$A,0))="","",INDEX(SuburbScorecard!$K:$K,MATCH($O4,SuburbScorecard!$A:$A,0))),"") -> 53 | S4: =IFERROR(IF(INDEX(SuburbScorecard!$AB:$AB,MATCH($O4,SuburbScorecard!$A:$A,0))="","Needs data",INDEX(SuburbScorecard!$AB:$AB,MATCH($O4,SuburbScorecard!$A:$A,0))),"Needs data") -> No | T4: =IF(L4="Under offer","Under offer",IF(G4="Over cap","Fails: budget",IF(NOT(AND(ISNUMBER(Q4),ISNUMBER(R4))),"Needs data",IF(Q4>Filters!$B$4,"Fails: GW drive",IF(R4>Filters!$B$5,"Fails: ED drive",IF(G4="Straddles cap","Pass if bought near low end","Pass")))))) -> Pass | U4: Drive times added 27 Oct (suburb centre). 3,235 m² block; check winter, fire and slope
A5: 4 | B5: 8 Williams Bay Grove | C5: Williamstown | D5: $1,700,000 | E5: 1700000 | F5: 1700000 | G5: =IF(E5="","Needs data",IF(F5<=Filters!$B$2,"Within cap",IF(E5<=Filters!$B$2,"Straddles cap","Over cap"))) -> Over cap | H5: 3 | I5: 2 | J5: 2 | L5: Active | M5: Sat 31 Oct 11:15am | N5: Katie Smith | O5: Williamstown | P5: =IFERROR(INDEX(SuburbScorecard!$C:$C,MATCH($O5,SuburbScorecard!$A:$A,0)),"Not on scorecard") -> Active Shortlist | Q5: =IFERROR(IF(INDEX(SuburbScorecard!$J:$J,MATCH($O5,SuburbScorecard!$A:$A,0))="","",INDEX(SuburbScorecard!$J:$J,MATCH($O5,SuburbScorecard!$A:$A,0))),"") -> 31 | R5: =IFERROR(IF(INDEX(SuburbScorecard!$K:$K,MATCH($O5,SuburbScorecard!$A:$A,0))="","",INDEX(SuburbScorecard!$K:$K,MATCH($O5,SuburbScorecard!$A:$A,0))),"") -> 13 | S5: =IFERROR(IF(INDEX(SuburbScorecard!$AB:$AB,MATCH($O5,SuburbScorecard!$A:$A,0))="","Needs data",INDEX(SuburbScorecard!$AB:$AB,MATCH($O5,SuburbScorecard!$A:$A,0))),"Needs data") -> Yes | T5: =IF(L5="Under offer","Under offer",IF(G5="Over cap","Fails: budget",IF(NOT(AND(ISNUMBER(Q5),ISNUMBER(R5))),"Needs data",IF(Q5>Filters!$B$4,"Fails: GW drive",IF(R5>Filters!$B$5,"Fails: ED drive",IF(G5="Straddles cap","Pass if bought near low end","Pass")))))) -> Fails: budget
A6: 5 | B6: 25 Phillips Crescent | C6: Rosanna | D6: ESR $1,450,000-$1,550,000 | E6: 1450000 | F6: 1550000 | G6: =IF(E6="","Needs data",IF(F6<=Filters!$B$2,"Within cap",IF(E6<=Filters!$B$2,"Straddles cap","Over cap"))) -> Straddles cap | H6: 4 | I6: 3 | J6: 2 | K6: 655 | L6: Active | M6: Tue 27 Oct 5:00pm | N6: Ashlee Jade | O6: Rosanna | P6: =IFERROR(INDEX(SuburbScorecard!$C:$C,MATCH($O6,SuburbScorecard!$A:$A,0)),"Not on scorecard") -> Not on scorecard | Q6: =IFERROR(IF(INDEX(SuburbScorecard!$J:$J,MATCH($O6,SuburbScorecard!$A:$A,0))="","",INDEX(SuburbScorecard!$J:$J,MATCH($O6,SuburbScorecard!$A:$A,0))),"") | R6: =IFERROR(IF(INDEX(SuburbScorecard!$K:$K,MATCH($O6,SuburbScorecard!$A:$A,0))="","",INDEX(SuburbScorecard!$K:$K,MATCH($O6,SuburbScorecard!$A:$A,0))),"") | S6: =IFERROR(IF(INDEX(SuburbScorecard!$AB:$AB,MATCH($O6,SuburbScorecard!$A:$A,0))="","Needs data",INDEX(SuburbScorecard!$AB:$AB,MATCH($O6,SuburbScorecard!$A:$A,0))),"Needs data") -> Needs data | T6: =IF(L6="Under offer","Under offer",IF(G6="Over cap","Fails: budget",IF(NOT(AND(ISNUMBER(Q6),ISNUMBER(R6))),"Needs data",IF(Q6>Filters!$B$4,"Fails: GW drive",IF(R6>Filters!$B$5,"Fails: ED drive",IF(G6="Straddles cap","Pass if bought near low end","Pass")))))) -> Needs data | U6: Suburb not on scorecard
A7: 6 | B7: 29 Campbell Street | C7: Diamond Creek | D7: New price $1.25m | E7: 1250000 | F7: 1250000 | G7: =IF(E7="","Needs data",IF(F7<=Filters!$B$2,"Within cap",IF(E7<=Filters!$B$2,"Straddles cap","Over cap"))) -> Within cap | H7: 4 | I7: 2 | J7: 2 | K7: 884 | L7: Active | M7: Tue 27 Oct 6:00pm | N7: Sheryl Emerson | O7: Diamond Creek | P7: =IFERROR(INDEX(SuburbScorecard!$C:$C,MATCH($O7,SuburbScorecard!$A:$A,0)),"Not on scorecard") -> Active Shortlist | Q7: =IFERROR(IF(INDEX(SuburbScorecard!$J:$J,MATCH($O7,SuburbScorecard!$A:$A,0))="","",INDEX(SuburbScorecard!$J:$J,MATCH($O7,SuburbScorecard!$A:$A,0))),"") -> 33 | R7: =IFERROR(IF(INDEX(SuburbScorecard!$K:$K,MATCH($O7,SuburbScorecard!$A:$A,0))="","",INDEX(SuburbScorecard!$K:$K,MATCH($O7,SuburbScorecard!$A:$A,0))),"") -> 19 | S7: =IFERROR(IF(INDEX(SuburbScorecard!$AB:$AB,MATCH($O7,SuburbScorecard!$A:$A,0))="","Needs data",INDEX(SuburbScorecard!$AB:$AB,MATCH($O7,SuburbScorecard!$A:$A,0))),"Needs data") -> Yes | T7: =IF(L7="Under offer","Under offer",IF(G7="Over cap","Fails: budget",IF(NOT(AND(ISNUMBER(Q7),ISNUMBER(R7))),"Needs data",IF(Q7>Filters!$B$4,"Fails: GW drive",IF(R7>Filters!$B$5,"Fails: ED drive",IF(G7="Straddles cap","Pass if bought near low end","Pass")))))) -> Pass
A8: 7 | B8: 23 Park Street | C8: Mordialloc | D8: $1,750,000-$1,900,000 | E8: 1750000 | F8: 1900000 | G8: =IF(E8="","Needs data",IF(F8<=Filters!$B$2,"Within cap",IF(E8<=Filters!$B$2,"Straddles cap","Over cap"))) -> Over cap | H8: 4 | I8: 2 | J8: 2 | K8: 613 | L8: Active | M8: Tue 27 Oct 3:30pm | N8: Lou Colella | O8: Mordialloc | P8: =IFERROR(INDEX(SuburbScorecard!$C:$C,MATCH($O8,SuburbScorecard!$A:$A,0)),"Not on scorecard") -> Not on scorecard | Q8: =IFERROR(IF(INDEX(SuburbScorecard!$J:$J,MATCH($O8,SuburbScorecard!$A:$A,0))="","",INDEX(SuburbScorecard!$J:$J,MATCH($O8,SuburbScorecard!$A:$A,0))),"") | R8: =IFERROR(IF(INDEX(SuburbScorecard!$K:$K,MATCH($O8,SuburbScorecard!$A:$A,0))="","",INDEX(SuburbScorecard!$K:$K,MATCH($O8,SuburbScorecard!$A:$A,0))),"") | S8: =IFERROR(IF(INDEX(SuburbScorecard!$AB:$AB,MATCH($O8,SuburbScorecard!$A:$A,0))="","Needs data",INDEX(SuburbScorecard!$AB:$AB,MATCH($O8,SuburbScorecard!$A:$A,0))),"Needs data") -> Needs data | T8: =IF(L8="Under offer","Under offer",IF(G8="Over cap","Fails: budget",IF(NOT(AND(ISNUMBER(Q8),ISNUMBER(R8))),"Needs data",IF(Q8>Filters!$B$4,"Fails: GW drive",IF(R8>Filters!$B$5,"Fails: ED drive",IF(G8="Straddles cap","Pass if bought near low end","Pass")))))) -> Fails: budget | U8: Suburb not on scorecard
A9: 8 | B9: 156A Nepean Highway | C9: Seaford | D9: $1,690,000-$1,850,000 | E9: 1690000 | F9: 1850000 | G9: =IF(E9="","Needs data",IF(F9<=Filters!$B$2,"Within cap",IF(E9<=Filters!$B$2,"Straddles cap","Over cap"))) -> Over cap | H9: 4 | I9: 2 | J9: 4 | K9: 319 | L9: Under offer | M9: None listed | N9: Dean Bozunovic | O9: Seaford | P9: =IFERROR(INDEX(SuburbScorecard!$C:$C,MATCH($O9,SuburbScorecard!$A:$A,0)),"Not on scorecard") -> Not on scorecard | Q9: =IFERROR(IF(INDEX(SuburbScorecard!$J:$J,MATCH($O9,SuburbScorecard!$A:$A,0))="","",INDEX(SuburbScorecard!$J:$J,MATCH($O9,SuburbScorecard!$A:$A,0))),"") | R9: =IFERROR(IF(INDEX(SuburbScorecard!$K:$K,MATCH($O9,SuburbScorecard!$A:$A,0))="","",INDEX(SuburbScorecard!$K:$K,MATCH($O9,SuburbScorecard!$A:$A,0))),"") | S9: =IFERROR(IF(INDEX(SuburbScorecard!$AB:$AB,MATCH($O9,SuburbScorecard!$A:$A,0))="","Needs data",INDEX(SuburbScorecard!$AB:$AB,MATCH($O9,SuburbScorecard!$A:$A,0))),"Needs data") -> Needs data | T9: =IF(L9="Under offer","Under offer",IF(G9="Over cap","Fails: budget",IF(NOT(AND(ISNUMBER(Q9),ISNUMBER(R9))),"Needs data",IF(Q9>Filters!$B$4,"Fails: GW drive",IF(R9>Filters!$B$5,"Fails: ED drive",IF(G9="Straddles cap","Pass if bought near low end","Pass")))))) -> Under offer | U9: Suburb not on scorecard
A10: 9 | B10: 1/192 Nepean Highway | C10: Seaford | D10: $1,450,000-$1,595,000 | E10: 1450000 | F10: 1595000 | G10: =IF(E10="","Needs data",IF(F10<=Filters!$B$2,"Within cap",IF(E10<=Filters!$B$2,"Straddles cap","Over cap"))) -> Straddles cap | H10: 3 | I10: 2 | J10: 2 | K10: 1019 | L10: Active | M10: Sat 31 Oct 1:00pm | N10: Luke Magree | O10: Seaford | P10: =IFERROR(INDEX(SuburbScorecard!$C:$C,MATCH($O10,SuburbScorecard!$A:$A,0)),"Not on scorecard") -> Not on scorecard | Q10: =IFERROR(IF(INDEX(SuburbScorecard!$J:$J,MATCH($O10,SuburbScorecard!$A:$A,0))="","",INDEX(SuburbScorecard!$J:$J,MATCH($O10,SuburbScorecard!$A:$A,0))),"") | R10: =IFERROR(IF(INDEX(SuburbScorecard!$K:$K,MATCH($O10,SuburbScorecard!$A:$A,0))="","",INDEX(SuburbScorecard!$K:$K,MATCH($O10,SuburbScorecard!$A:$A,0))),"") | S10: =IFERROR(IF(INDEX(SuburbScorecard!$AB:$AB,MATCH($O10,SuburbScorecard!$A:$A,0))="","Needs data",INDEX(SuburbScorecard!$AB:$AB,MATCH($O10,SuburbScorecard!$A:$A,0))),"Needs data") -> Needs data | T10: =IF(L10="Under offer","Under offer",IF(G10="Over cap","Fails: budget",IF(NOT(AND(ISNUMBER(Q10),ISNUMBER(R10))),"Needs data",IF(Q10>Filters!$B$4,"Fails: GW drive",IF(R10>Filters!$B$5,"Fails: ED drive",IF(G10="Straddles cap","Pass if bought near low end","Pass")))))) -> Needs data | U10: Suburb not on scorecard
A11: 10 | B11: 51 Granya Grove | C11: Mount Eliza | D11: $1,799,000-$1,978,000 | E11: 1799000 | F11: 1978000 | G11: =IF(E11="","Needs data",IF(F11<=Filters!$B$2,"Within cap",IF(E11<=Filters!$B$2,"Straddles cap","Over cap"))) -> Over cap | H11: 5 | I11: 2 | J11: 2 | K11: 976 | L11: Active | M11: Sat 31 Oct 1:00pm | N11: Bailey White | O11: Mount Eliza | P11: =IFERROR(INDEX(SuburbScorecard!$C:$C,MATCH($O11,SuburbScorecard!$A:$A,0)),"Not on scorecard") -> Active Shortlist | Q11: =IFERROR(IF(INDEX(SuburbScorecard!$J:$J,MATCH($O11,SuburbScorecard!$A:$A,0))="","",INDEX(SuburbScorecard!$J:$J,MATCH($O11,SuburbScorecard!$A:$A,0))),"") -> 34 | R11: =IFERROR(IF(INDEX(SuburbScorecard!$K:$K,MATCH($O11,SuburbScorecard!$A:$A,0))="","",INDEX(SuburbScorecard!$K:$K,MATCH($O11,SuburbScorecard!$A:$A,0))),"") -> 10 | S11: =IFERROR(IF(INDEX(SuburbScorecard!$AB:$AB,MATCH($O11,SuburbScorecard!$A:$A,0))="","Needs data",INDEX(SuburbScorecard!$AB:$AB,MATCH($O11,SuburbScorecard!$A:$A,0))),"Needs data") -> No | T11: =IF(L11="Under offer","Under offer",IF(G11="Over cap","Fails: budget",IF(NOT(AND(ISNUMBER(Q11),ISNUMBER(R11))),"Needs data",IF(Q11>Filters!$B$4,"Fails: GW drive",IF(R11>Filters!$B$5,"Fails: ED drive",IF(G11="Straddles cap","Pass if bought near low end","Pass")))))) -> Fails: budget
A12: 11 | B12: 54 Granya Grove | C12: Mount Eliza | D12: $1,275,000-$1,375,000 | E12: 1275000 | F12: 1375000 | G12: =IF(E12="","Needs data",IF(F12<=Filters!$B$2,"Within cap",IF(E12<=Filters!$B$2,"Straddles cap","Over cap"))) -> Within cap | H12: 3 | I12: 2 | J12: 2 | K12: 985 | L12: Active | M12: Sat 31 Oct 12:30pm | N12: Candice Blanch | O12: Mount Eliza | P12: =IFERROR(INDEX(SuburbScorecard!$C:$C,MATCH($O12,SuburbScorecard!$A:$A,0)),"Not on scorecard") -> Active Shortlist | Q12: =IFERROR(IF(INDEX(SuburbScorecard!$J:$J,MATCH($O12,SuburbScorecard!$A:$A,0))="","",INDEX(SuburbScorecard!$J:$J,MATCH($O12,SuburbScorecard!$A:$A,0))),"") -> 34 | R12: =IFERROR(IF(INDEX(SuburbScorecard!$K:$K,MATCH($O12,SuburbScorecard!$A:$A,0))="","",INDEX(SuburbScorecard!$K:$K,MATCH($O12,SuburbScorecard!$A:$A,0))),"") -> 10 | S12: =IFERROR(IF(INDEX(SuburbScorecard!$AB:$AB,MATCH($O12,SuburbScorecard!$A:$A,0))="","Needs data",INDEX(SuburbScorecard!$AB:$AB,MATCH($O12,SuburbScorecard!$A:$A,0))),"Needs data") -> No | T12: =IF(L12="Under offer","Under offer",IF(G12="Over cap","Fails: budget",IF(NOT(AND(ISNUMBER(Q12),ISNUMBER(R12))),"Needs data",IF(Q12>Filters!$B$4,"Fails: GW drive",IF(R12>Filters!$B$5,"Fails: ED drive",IF(G12="Straddles cap","Pass if bought near low end","Pass")))))) -> Pass
A13: 12 | B13: 110 Koornalla Crescent | C13: Mount Eliza | D13: $1,300,000-$1,430,000 | E13: 1300000 | F13: 1430000 | G13: =IF(E13="","Needs data",IF(F13<=Filters!$B$2,"Within cap",IF(E13<=Filters!$B$2,"Straddles cap","Over cap"))) -> Within cap | H13: 4 | I13: 2 | J13: 2 | K13: 981 | L13: Active | M13: None listed | N13: Will Crowder | O13: Mount Eliza | P13: =IFERROR(INDEX(SuburbScorecard!$C:$C,MATCH($O13,SuburbScorecard!$A:$A,0)),"Not on scorecard") -> Active Shortlist | Q13: =IFERROR(IF(INDEX(SuburbScorecard!$J:$J,MATCH($O13,SuburbScorecard!$A:$A,0))="","",INDEX(SuburbScorecard!$J:$J,MATCH($O13,SuburbScorecard!$A:$A,0))),"") -> 34 | R13: =IFERROR(IF(INDEX(SuburbScorecard!$K:$K,MATCH($O13,SuburbScorecard!$A:$A,0))="","",INDEX(SuburbScorecard!$K:$K,MATCH($O13,SuburbScorecard!$A:$A,0))),"") -> 10 | S13: =IFERROR(IF(INDEX(SuburbScorecard!$AB:$AB,MATCH($O13,SuburbScorecard!$A:$A,0))="","Needs data",INDEX(SuburbScorecard!$AB:$AB,MATCH($O13,SuburbScorecard!$A:$A,0))),"Needs data") -> No | T13: =IF(L13="Under offer","Under offer",IF(G13="Over cap","Fails: budget",IF(NOT(AND(ISNUMBER(Q13),ISNUMBER(R13))),"Needs data",IF(Q13>Filters!$B$4,"Fails: GW drive",IF(R13>Filters!$B$5,"Fails: ED drive",IF(G13="Straddles cap","Pass if bought near low end","Pass")))))) -> Pass
A14: 13 | B14: 1374 Nepean Highway | C14: Mount Eliza | D14: $890,000-$970,000 | E14: 890000 | F14: 970000 | G14: =IF(E14="","Needs data",IF(F14<=Filters!$B$2,"Within cap",IF(E14<=Filters!$B$2,"Straddles cap","Over cap"))) -> Within cap | H14: 4 | I14: 2 | J14: 2 | K14: 790 | L14: Active | M14: Sat 31 Oct 2:00pm | N14: Danae Eden | O14: Mount Eliza | P14: =IFERROR(INDEX(SuburbScorecard!$C:$C,MATCH($O14,SuburbScorecard!$A:$A,0)),"Not on scorecard") -> Active Shortlist | Q14: =IFERROR(IF(INDEX(SuburbScorecard!$J:$J,MATCH($O14,SuburbScorecard!$A:$A,0))="","",INDEX(SuburbScorecard!$J:$J,MATCH($O14,SuburbScorecard!$A:$A,0))),"") -> 34 | R14: =IFERROR(IF(INDEX(SuburbScorecard!$K:$K,MATCH($O14,SuburbScorecard!$A:$A,0))="","",INDEX(SuburbScorecard!$K:$K,MATCH($O14,SuburbScorecard!$A:$A,0))),"") -> 10 | S14: =IFERROR(IF(INDEX(SuburbScorecard!$AB:$AB,MATCH($O14,SuburbScorecard!$A:$A,0))="","Needs data",INDEX(SuburbScorecard!$AB:$AB,MATCH($O14,SuburbScorecard!$A:$A,0))),"Needs data") -> No | T14: =IF(L14="Under offer","Under offer",IF(G14="Over cap","Fails: budget",IF(NOT(AND(ISNUMBER(Q14),ISNUMBER(R14))),"Needs data",IF(Q14>Filters!$B$4,"Fails: GW drive",IF(R14>Filters!$B$5,"Fails: ED drive",IF(G14="Straddles cap","Pass if bought near low end","Pass")))))) -> Pass
A15: 14 | B15: 45 Seahaze Street | C15: Arthurs Seat | D15: Private sale $1,650,000-$1,750,000 | E15: 1650000 | F15: 1750000 | G15: =IF(E15="","Needs data",IF(F15<=Filters!$B$2,"Within cap",IF(E15<=Filters!$B$2,"Straddles cap","Over cap"))) -> Over cap | H15: 4 | I15: 2 | J15: 4 | K15: 819 | L15: Active | M15: None listed | N15: Tom Barr Smith | O15: Arthurs Seat | P15: =IFERROR(INDEX(SuburbScorecard!$C:$C,MATCH($O15,SuburbScorecard!$A:$A,0)),"Not on scorecard") -> Not on scorecard | Q15: =IFERROR(IF(INDEX(SuburbScorecard!$J:$J,MATCH($O15,SuburbScorecard!$A:$A,0))="","",INDEX(SuburbScorecard!$J:$J,MATCH($O15,SuburbScorecard!$A:$A,0))),"") | R15: =IFERROR(IF(INDEX(SuburbScorecard!$K:$K,MATCH($O15,SuburbScorecard!$A:$A,0))="","",INDEX(SuburbScorecard!$K:$K,MATCH($O15,SuburbScorecard!$A:$A,0))),"") | S15: =IFERROR(IF(INDEX(SuburbScorecard!$AB:$AB,MATCH($O15,SuburbScorecard!$A:$A,0))="","Needs data",INDEX(SuburbScorecard!$AB:$AB,MATCH($O15,SuburbScorecard!$A:$A,0))),"Needs data") -> Needs data | T15: =IF(L15="Under offer","Under offer",IF(G15="Over cap","Fails: budget",IF(NOT(AND(ISNUMBER(Q15),ISNUMBER(R15))),"Needs data",IF(Q15>Filters!$B$4,"Fails: GW drive",IF(R15>Filters!$B$5,"Fails: ED drive",IF(G15="Straddles cap","Pass if bought near low end","Pass")))))) -> Fails: budget | U15: Suburb not on scorecard (nearest scorecard suburb: Dromana, not substituted)
A16: 15 | B16: 4 McArthur Street | C16: Dromana | D16: $1,349,000 | E16: 1349000 | F16: 1349000 | G16: =IF(E16="","Needs data",IF(F16<=Filters!$B$2,"Within cap",IF(E16<=Filters!$B$2,"Straddles cap","Over cap"))) -> Within cap | H16: 3 | I16: 2 | J16: 2 | K16: 675 | L16: Active | M16: None listed | N16: Scott Joyce | O16: Dromana | P16: =IFERROR(INDEX(SuburbScorecard!$C:$C,MATCH($O16,SuburbScorecard!$A:$A,0)),"Not on scorecard") -> Watchlist | Q16: =IFERROR(IF(INDEX(SuburbScorecard!$J:$J,MATCH($O16,SuburbScorecard!$A:$A,0))="","",INDEX(SuburbScorecard!$J:$J,MATCH($O16,SuburbScorecard!$A:$A,0))),"") | R16: =IFERROR(IF(INDEX(SuburbScorecard!$K:$K,MATCH($O16,SuburbScorecard!$A:$A,0))="","",INDEX(SuburbScorecard!$K:$K,MATCH($O16,SuburbScorecard!$A:$A,0))),"") | S16: =IFERROR(IF(INDEX(SuburbScorecard!$AB:$AB,MATCH($O16,SuburbScorecard!$A:$A,0))="","Needs data",INDEX(SuburbScorecard!$AB:$AB,MATCH($O16,SuburbScorecard!$A:$A,0))),"Needs data") -> Needs data | T16: =IF(L16="Under offer","Under offer",IF(G16="Over cap","Fails: budget",IF(NOT(AND(ISNUMBER(Q16),ISNUMBER(R16))),"Needs data",IF(Q16>Filters!$B$4,"Fails: GW drive",IF(R16>Filters!$B$5,"Fails: ED drive",IF(G16="Straddles cap","Pass if bought near low end","Pass")))))) -> Needs data | U16: Scorecard has no drive times for Dromana
A17: 16 | B17: 3-5 Bonavista Way | C17: Curlewis | D17: $1,350,000-$1,450,000 | E17: 1350000 | F17: 1450000 | G17: =IF(E17="","Needs data",IF(F17<=Filters!$B$2,"Within cap",IF(E17<=Filters!$B$2,"Straddles cap","Over cap"))) -> Within cap | H17: 5 | I17: 3 | J17: 5 | K17: 580 | L17: Active | M17: Sat 31 Oct 11:50am | N17: Harley Lewis | O17: Curlewis | P17: =IFERROR(INDEX(SuburbScorecard!$C:$C,MATCH($O17,SuburbScorecard!$A:$A,0)),"Not on scorecard") -> Not on scorecard | Q17: =IFERROR(IF(INDEX(SuburbScorecard!$J:$J,MATCH($O17,SuburbScorecard!$A:$A,0))="","",INDEX(SuburbScorecard!$J:$J,MATCH($O17,SuburbScorecard!$A:$A,0))),"") | R17: =IFERROR(IF(INDEX(SuburbScorecard!$K:$K,MATCH($O17,SuburbScorecard!$A:$A,0))="","",INDEX(SuburbScorecard!$K:$K,MATCH($O17,SuburbScorecard!$A:$A,0))),"") | S17: =IFERROR(IF(INDEX(SuburbScorecard!$AB:$AB,MATCH($O17,SuburbScorecard!$A:$A,0))="","Needs data",INDEX(SuburbScorecard!$AB:$AB,MATCH($O17,SuburbScorecard!$A:$A,0))),"Needs data") -> Needs data | T17: =IF(L17="Under offer","Under offer",IF(G17="Over cap","Fails: budget",IF(NOT(AND(ISNUMBER(Q17),ISNUMBER(R17))),"Needs data",IF(Q17>Filters!$B$4,"Fails: GW drive",IF(R17>Filters!$B$5,"Fails: ED drive",IF(G17="Straddles cap","Pass if bought near low end","Pass")))))) -> Needs data | U17: Suburb not on scorecard
A18: 17 | B18: 36 Arthurs Avenue | C18: McCrae | D18: New price $1,500,000-$1,650,000 | E18: 1500000 | F18: 1650000 | G18: =IF(E18="","Needs data",IF(F18<=Filters!$B$2,"Within cap",IF(E18<=Filters!$B$2,"Straddles cap","Over cap"))) -> Straddles cap | H18: 5 | I18: 3 | J18: 6 | K18: 913 | L18: Active | M18: Sat 31 Oct 2:00pm | N18: Sam Austen | O18: McCrae | P18: =IFERROR(INDEX(SuburbScorecard!$C:$C,MATCH($O18,SuburbScorecard!$A:$A,0)),"Not on scorecard") -> Not on scorecard | Q18: =IFERROR(IF(INDEX(SuburbScorecard!$J:$J,MATCH($O18,SuburbScorecard!$A:$A,0))="","",INDEX(SuburbScorecard!$J:$J,MATCH($O18,SuburbScorecard!$A:$A,0))),"") | R18: =IFERROR(IF(INDEX(SuburbScorecard!$K:$K,MATCH($O18,SuburbScorecard!$A:$A,0))="","",INDEX(SuburbScorecard!$K:$K,MATCH($O18,SuburbScorecard!$A:$A,0))),"") | S18: =IFERROR(IF(INDEX(SuburbScorecard!$AB:$AB,MATCH($O18,SuburbScorecard!$A:$A,0))="","Needs data",INDEX(SuburbScorecard!$AB:$AB,MATCH($O18,SuburbScorecard!$A:$A,0))),"Needs data") -> Needs data | T18: =IF(L18="Under offer","Under offer",IF(G18="Over cap","Fails: budget",IF(NOT(AND(ISNUMBER(Q18),ISNUMBER(R18))),"Needs data",IF(Q18>Filters!$B$4,"Fails: GW drive",IF(R18>Filters!$B$5,"Fails: ED drive",IF(G18="Straddles cap","Pass if bought near low end","Pass")))))) -> Needs data | U18: Suburb not on scorecard
A19: 18 | B19: 2B Fowler Street | C19: Chelsea | D19: $1,400,000-$1,540,000 | E19: 1400000 | F19: 1540000 | G19: =IF(E19="","Needs data",IF(F19<=Filters!$B$2,"Within cap",IF(E19<=Filters!$B$2,"Straddles cap","Over cap"))) -> Straddles cap | H19: 5 | I19: 3 | J19: 3 | K19: 688 | L19: Active | M19: Wed 28 Oct 3:50pm | N19: Daniel Wright | O19: Chelsea | P19: =IFERROR(INDEX(SuburbScorecard!$C:$C,MATCH($O19,SuburbScorecard!$A:$A,0)),"Not on scorecard") -> Not on scorecard | Q19: =IFERROR(IF(INDEX(SuburbScorecard!$J:$J,MATCH($O19,SuburbScorecard!$A:$A,0))="","",INDEX(SuburbScorecard!$J:$J,MATCH($O19,SuburbScorecard!$A:$A,0))),"") | R19: =IFERROR(IF(INDEX(SuburbScorecard!$K:$K,MATCH($O19,SuburbScorecard!$A:$A,0))="","",INDEX(SuburbScorecard!$K:$K,MATCH($O19,SuburbScorecard!$A:$A,0))),"") | S19: =IFERROR(IF(INDEX(SuburbScorecard!$AB:$AB,MATCH($O19,SuburbScorecard!$A:$A,0))="","Needs data",INDEX(SuburbScorecard!$AB:$AB,MATCH($O19,SuburbScorecard!$A:$A,0))),"Needs data") -> Needs data | T19: =IF(L19="Under offer","Under offer",IF(G19="Over cap","Fails: budget",IF(NOT(AND(ISNUMBER(Q19),ISNUMBER(R19))),"Needs data",IF(Q19>Filters!$B$4,"Fails: GW drive",IF(R19>Filters!$B$5,"Fails: ED drive",IF(G19="Straddles cap","Pass if bought near low end","Pass")))))) -> Needs data | U19: Suburb not on scorecard
A20: 19 | B20: 13 Harcombe Crescent | C20: Torquay | D20: $1,200,000-$1,300,000 | E20: 1200000 | F20: 1300000 | G20: =IF(E20="","Needs data",IF(F20<=Filters!$B$2,"Within cap",IF(E20<=Filters!$B$2,"Straddles cap","Over cap"))) -> Within cap | H20: 4 | I20: 2 | J20: 2 | K20: 392 | L20: Active | M20: None listed | N20: Chris Henson | O20: Torquay | P20: =IFERROR(INDEX(SuburbScorecard!$C:$C,MATCH($O20,SuburbScorecard!$A:$A,0)),"Not on scorecard") -> Active Shortlist | Q20: =IFERROR(IF(INDEX(SuburbScorecard!$J:$J,MATCH($O20,SuburbScorecard!$A:$A,0))="","",INDEX(SuburbScorecard!$J:$J,MATCH($O20,SuburbScorecard!$A:$A,0))),"") -> 88 | R20: =IFERROR(IF(INDEX(SuburbScorecard!$K:$K,MATCH($O20,SuburbScorecard!$A:$A,0))="","",INDEX(SuburbScorecard!$K:$K,MATCH($O20,SuburbScorecard!$A:$A,0))),"") -> 23 | S20: =IFERROR(IF(INDEX(SuburbScorecard!$AB:$AB,MATCH($O20,SuburbScorecard!$A:$A,0))="","Needs data",INDEX(SuburbScorecard!$AB:$AB,MATCH($O20,SuburbScorecard!$A:$A,0))),"Needs data") -> No | T20: =IF(L20="Under offer","Under offer",IF(G20="Over cap","Fails: budget",IF(NOT(AND(ISNUMBER(Q20),ISNUMBER(R20))),"Needs data",IF(Q20>Filters!$B$4,"Fails: GW drive",IF(R20>Filters!$B$5,"Fails: ED drive",IF(G20="Straddles cap","Pass if bought near low end","Pass")))))) -> Pass
A21: 20 | B21: 6 Dowman Street | C21: Newport | D21: $1,790,000 | E21: 1790000 | F21: 1790000 | G21: =IF(E21="","Needs data",IF(F21<=Filters!$B$2,"Within cap",IF(E21<=Filters!$B$2,"Straddles cap","Over cap"))) -> Over cap | H21: 4 | I21: 2 | J21: 4 | K21: 417 | L21: Active | M21: Tue 27 Oct 5:00pm | N21: Nathan Smith | O21: Newport | P21: =IFERROR(INDEX(SuburbScorecard!$C:$C,MATCH($O21,SuburbScorecard!$A:$A,0)),"Not on scorecard") -> Not on scorecard | Q21: =IFERROR(IF(INDEX(SuburbScorecard!$J:$J,MATCH($O21,SuburbScorecard!$A:$A,0))="","",INDEX(SuburbScorecard!$J:$J,MATCH($O21,SuburbScorecard!$A:$A,0))),"") | R21: =IFERROR(IF(INDEX(SuburbScorecard!$K:$K,MATCH($O21,SuburbScorecard!$A:$A,0))="","",INDEX(SuburbScorecard!$K:$K,MATCH($O21,SuburbScorecard!$A:$A,0))),"") | S21: =IFERROR(IF(INDEX(SuburbScorecard!$AB:$AB,MATCH($O21,SuburbScorecard!$A:$A,0))="","Needs data",INDEX(SuburbScorecard!$AB:$AB,MATCH($O21,SuburbScorecard!$A:$A,0))),"Needs data") -> Needs data | T21: =IF(L21="Under offer","Under offer",IF(G21="Over cap","Fails: budget",IF(NOT(AND(ISNUMBER(Q21),ISNUMBER(R21))),"Needs data",IF(Q21>Filters!$B$4,"Fails: GW drive",IF(R21>Filters!$B$5,"Fails: ED drive",IF(G21="Straddles cap","Pass if bought near low end","Pass")))))) -> Fails: budget | U21: Suburb not on scorecard
A22: 21 | B22: 28 Stradbroke Avenue | C22: Frankston South | D22: Reserve $940,000 | E22: 940000 | F22: 940000 | G22: =IF(E22="","Needs data",IF(F22<=Filters!$B$2,"Within cap",IF(E22<=Filters!$B$2,"Straddles cap","Over cap"))) -> Within cap | H22: 4 | I22: 2 | J22: 1 | K22: 551 | L22: Active | M22: Sat 31 Oct 9:30am | N22: Brooke Wegener | O22: Frankston South | P22: =IFERROR(INDEX(SuburbScorecard!$C:$C,MATCH($O22,SuburbScorecard!$A:$A,0)),"Not on scorecard") -> Active Shortlist | Q22: =IFERROR(IF(INDEX(SuburbScorecard!$J:$J,MATCH($O22,SuburbScorecard!$A:$A,0))="","",INDEX(SuburbScorecard!$J:$J,MATCH($O22,SuburbScorecard!$A:$A,0))),"") -> 31 | R22: =IFERROR(IF(INDEX(SuburbScorecard!$K:$K,MATCH($O22,SuburbScorecard!$A:$A,0))="","",INDEX(SuburbScorecard!$K:$K,MATCH($O22,SuburbScorecard!$A:$A,0))),"") -> 4 | S22: =IFERROR(IF(INDEX(SuburbScorecard!$AB:$AB,MATCH($O22,SuburbScorecard!$A:$A,0))="","Needs data",INDEX(SuburbScorecard!$AB:$AB,MATCH($O22,SuburbScorecard!$A:$A,0))),"Needs data") -> No | T22: =IF(L22="Under offer","Under offer",IF(G22="Over cap","Fails: budget",IF(NOT(AND(ISNUMBER(Q22),ISNUMBER(R22))),"Needs data",IF(Q22>Filters!$B$4,"Fails: GW drive",IF(R22>Filters!$B$5,"Fails: ED drive",IF(G22="Straddles cap","Pass if bought near low end","Pass")))))) -> Pass | U22: Reserve price (auction); final price likely higher
A23: 22 | B23: 7 Gordon Avenue | C23: Tecoma | D23: $1,300,000-$1,400,000 | E23: 1300000 | F23: 1400000 | G23: =IF(E23="","Needs data",IF(F23<=Filters!$B$2,"Within cap",IF(E23<=Filters!$B$2,"Straddles cap","Over cap"))) -> Within cap | H23: 4 | I23: 2 | J23: 2 | K23: 1120 | L23: Under offer | M23: None listed | N23: Bree Roberts | O23: Tecoma | P23: =IFERROR(INDEX(SuburbScorecard!$C:$C,MATCH($O23,SuburbScorecard!$A:$A,0)),"Not on scorecard") -> Active Shortlist | Q23: =IFERROR(IF(INDEX(SuburbScorecard!$J:$J,MATCH($O23,SuburbScorecard!$A:$A,0))="","",INDEX(SuburbScorecard!$J:$J,MATCH($O23,SuburbScorecard!$A:$A,0))),"") -> 19 | R23: =IFERROR(IF(INDEX(SuburbScorecard!$K:$K,MATCH($O23,SuburbScorecard!$A:$A,0))="","",INDEX(SuburbScorecard!$K:$K,MATCH($O23,SuburbScorecard!$A:$A,0))),"") -> 5 | S23: =IFERROR(IF(INDEX(SuburbScorecard!$AB:$AB,MATCH($O23,SuburbScorecard!$A:$A,0))="","Needs data",INDEX(SuburbScorecard!$AB:$AB,MATCH($O23,SuburbScorecard!$A:$A,0))),"Needs data") -> Yes | T23: =IF(L23="Under offer","Under offer",IF(G23="Over cap","Fails: budget",IF(NOT(AND(ISNUMBER(Q23),ISNUMBER(R23))),"Needs data",IF(Q23>Filters!$B$4,"Fails: GW drive",IF(R23>Filters!$B$5,"Fails: ED drive",IF(G23="Straddles cap","Pass if bought near low end","Pass")))))) -> Under offer
A24: 23 | B24: 24 Monbulk Road | C24: Belgrave | D24: Auction $850,000-$920,000 | E24: 850000 | F24: 920000 | G24: =IF(E24="","Needs data",IF(F24<=Filters!$B$2,"Within cap",IF(E24<=Filters!$B$2,"Straddles cap","Over cap"))) -> Within cap | H24: 4 | I24: 2 | J24: 4 | K24: 3492 | L24: Active | M24: Wed 28 Oct 4:00pm | N24: Cristine Jones | O24: Belgrave | P24: =IFERROR(INDEX(SuburbScorecard!$C:$C,MATCH($O24,SuburbScorecard!$A:$A,0)),"Not on scorecard") -> Active Shortlist | Q24: =IFERROR(IF(INDEX(SuburbScorecard!$J:$J,MATCH($O24,SuburbScorecard!$A:$A,0))="","",INDEX(SuburbScorecard!$J:$J,MATCH($O24,SuburbScorecard!$A:$A,0))),"") -> 21 | R24: =IFERROR(IF(INDEX(SuburbScorecard!$K:$K,MATCH($O24,SuburbScorecard!$A:$A,0))="","",INDEX(SuburbScorecard!$K:$K,MATCH($O24,SuburbScorecard!$A:$A,0))),"") -> 7 | S24: =IFERROR(IF(INDEX(SuburbScorecard!$AB:$AB,MATCH($O24,SuburbScorecard!$A:$A,0))="","Needs data",INDEX(SuburbScorecard!$AB:$AB,MATCH($O24,SuburbScorecard!$A:$A,0))),"Needs data") -> Yes | T24: =IF(L24="Under offer","Under offer",IF(G24="Over cap","Fails: budget",IF(NOT(AND(ISNUMBER(Q24),ISNUMBER(R24))),"Needs data",IF(Q24>Filters!$B$4,"Fails: GW drive",IF(R24>Filters!$B$5,"Fails: ED drive",IF(G24="Straddles cap","Pass if bought near low end","Pass")))))) -> Pass | U24: Auction guide
A25: 24 | B25: 16 Forest Road | C25: Belgrave | D25: Reserve $1,035,000 | E25: 1035000 | F25: 1035000 | G25: =IF(E25="","Needs data",IF(F25<=Filters!$B$2,"Within cap",IF(E25<=Filters!$B$2,"Straddles cap","Over cap"))) -> Within cap | H25: 4 | I25: 2 | K25: 2070 | L25: Active | M25: Thu 29 Oct 6:00pm | N25: Austen Kosasih | O25: Belgrave | P25: =IFERROR(INDEX(SuburbScorecard!$C:$C,MATCH($O25,SuburbScorecard!$A:$A,0)),"Not on scorecard") -> Active Shortlist | Q25: =IFERROR(IF(INDEX(SuburbScorecard!$J:$J,MATCH($O25,SuburbScorecard!$A:$A,0))="","",INDEX(SuburbScorecard!$J:$J,MATCH($O25,SuburbScorecard!$A:$A,0))),"") -> 21 | R25: =IFERROR(IF(INDEX(SuburbScorecard!$K:$K,MATCH($O25,SuburbScorecard!$A:$A,0))="","",INDEX(SuburbScorecard!$K:$K,MATCH($O25,SuburbScorecard!$A:$A,0))),"") -> 7 | S25: =IFERROR(IF(INDEX(SuburbScorecard!$AB:$AB,MATCH($O25,SuburbScorecard!$A:$A,0))="","Needs data",INDEX(SuburbScorecard!$AB:$AB,MATCH($O25,SuburbScorecard!$A:$A,0))),"Needs data") -> Yes | T25: =IF(L25="Under offer","Under offer",IF(G25="Over cap","Fails: budget",IF(NOT(AND(ISNUMBER(Q25),ISNUMBER(R25))),"Needs data",IF(Q25>Filters!$B$4,"Fails: GW drive",IF(R25>Filters!$B$5,"Fails: ED drive",IF(G25="Straddles cap","Pass if bought near low end","Pass")))))) -> Pass | U25: Car spaces not shown on card; check listing. Reserve price (auction)
A26: 25 | B26: 3 Forest Road | C26: Belgrave | D26: $1,150,000-$1,250,000 | E26: 1150000 | F26: 1250000 | G26: =IF(E26="","Needs data",IF(F26<=Filters!$B$2,"Within cap",IF(E26<=Filters!$B$2,"Straddles cap","Over cap"))) -> Within cap | H26: 4 | I26: 2 | J26: 2 | K26: 1432 | L26: Active | M26: None listed | N26: Sam Skolnick | O26: Belgrave | P26: =IFERROR(INDEX(SuburbScorecard!$C:$C,MATCH($O26,SuburbScorecard!$A:$A,0)),"Not on scorecard") -> Active Shortlist | Q26: =IFERROR(IF(INDEX(SuburbScorecard!$J:$J,MATCH($O26,SuburbScorecard!$A:$A,0))="","",INDEX(SuburbScorecard!$J:$J,MATCH($O26,SuburbScorecard!$A:$A,0))),"") -> 21 | R26: =IFERROR(IF(INDEX(SuburbScorecard!$K:$K,MATCH($O26,SuburbScorecard!$A:$A,0))="","",INDEX(SuburbScorecard!$K:$K,MATCH($O26,SuburbScorecard!$A:$A,0))),"") -> 7 | S26: =IFERROR(IF(INDEX(SuburbScorecard!$AB:$AB,MATCH($O26,SuburbScorecard!$A:$A,0))="","Needs data",INDEX(SuburbScorecard!$AB:$AB,MATCH($O26,SuburbScorecard!$A:$A,0))),"Needs data") -> Yes | T26: =IF(L26="Under offer","Under offer",IF(G26="Over cap","Fails: budget",IF(NOT(AND(ISNUMBER(Q26),ISNUMBER(R26))),"Needs data",IF(Q26>Filters!$B$4,"Fails: GW drive",IF(R26>Filters!$B$5,"Fails: ED drive",IF(G26="Straddles cap","Pass if bought near low end","Pass")))))) -> Pass
A27: 26 | B27: 11 Dalkeith Crescent | C27: Belgrave | D27: $870,000-$946,000 | E27: 870000 | F27: 946000 | G27: =IF(E27="","Needs data",IF(F27<=Filters!$B$2,"Within cap",IF(E27<=Filters!$B$2,"Straddles cap","Over cap"))) -> Within cap | H27: 5 | I27: 2 | J27: 2 | K27: 1066 | L27: Active | M27: Tue 27 Oct 5:00pm | N27: Mick Dolphin | O27: Belgrave | P27: =IFERROR(INDEX(SuburbScorecard!$C:$C,MATCH($O27,SuburbScorecard!$A:$A,0)),"Not on scorecard") -> Active Shortlist | Q27: =IFERROR(IF(INDEX(SuburbScorecard!$J:$J,MATCH($O27,SuburbScorecard!$A:$A,0))="","",INDEX(SuburbScorecard!$J:$J,MATCH($O27,SuburbScorecard!$A:$A,0))),"") -> 21 | R27: =IFERROR(IF(INDEX(SuburbScorecard!$K:$K,MATCH($O27,SuburbScorecard!$A:$A,0))="","",INDEX(SuburbScorecard!$K:$K,MATCH($O27,SuburbScorecard!$A:$A,0))),"") -> 7 | S27: =IFERROR(IF(INDEX(SuburbScorecard!$AB:$AB,MATCH($O27,SuburbScorecard!$A:$A,0))="","Needs data",INDEX(SuburbScorecard!$AB:$AB,MATCH($O27,SuburbScorecard!$A:$A,0))),"Needs data") -> Yes | T27: =IF(L27="Under offer","Under offer",IF(G27="Over cap","Fails: budget",IF(NOT(AND(ISNUMBER(Q27),ISNUMBER(R27))),"Needs data",IF(Q27>Filters!$B$4,"Fails: GW drive",IF(R27>Filters!$B$5,"Fails: ED drive",IF(G27="Straddles cap","Pass if bought near low end","Pass")))))) -> Pass
A28: 27 | B28: 23 Sherwood Crescent | C28: Mount Martha | D28: $1,390,000-$1,490,000 | E28: 1390000 | F28: 1490000 | G28: =IF(E28="","Needs data",IF(F28<=Filters!$B$2,"Within cap",IF(E28<=Filters!$B$2,"Straddles cap","Over cap"))) -> Within cap | H28: 5 | I28: 3 | J28: 2 | K28: 920 | L28: Active | M28: None listed | N28: Brendan Collopy | O28: Mount Martha | P28: =IFERROR(INDEX(SuburbScorecard!$C:$C,MATCH($O28,SuburbScorecard!$A:$A,0)),"Not on scorecard") -> Not on scorecard | Q28: =IFERROR(IF(INDEX(SuburbScorecard!$J:$J,MATCH($O28,SuburbScorecard!$A:$A,0))="","",INDEX(SuburbScorecard!$J:$J,MATCH($O28,SuburbScorecard!$A:$A,0))),"") | R28: =IFERROR(IF(INDEX(SuburbScorecard!$K:$K,MATCH($O28,SuburbScorecard!$A:$A,0))="","",INDEX(SuburbScorecard!$K:$K,MATCH($O28,SuburbScorecard!$A:$A,0))),"") | S28: =IFERROR(IF(INDEX(SuburbScorecard!$AB:$AB,MATCH($O28,SuburbScorecard!$A:$A,0))="","Needs data",INDEX(SuburbScorecard!$AB:$AB,MATCH($O28,SuburbScorecard!$A:$A,0))),"Needs data") -> Needs data | T28: =IF(L28="Under offer","Under offer",IF(G28="Over cap","Fails: budget",IF(NOT(AND(ISNUMBER(Q28),ISNUMBER(R28))),"Needs data",IF(Q28>Filters!$B$4,"Fails: GW drive",IF(R28>Filters!$B$5,"Fails: ED drive",IF(G28="Straddles cap","Pass if bought near low end","Pass")))))) -> Needs data | U28: Suburb not on scorecard
A29: 28 | B29: 85 Terrys Avenue | C29: Tecoma | D29: $1,250,000-$1,340,000 | E29: 1250000 | F29: 1340000 | G29: =IF(E29="","Needs data",IF(F29<=Filters!$B$2,"Within cap",IF(E29<=Filters!$B$2,"Straddles cap","Over cap"))) -> Within cap | H29: 5 | I29: 2 | J29: 4 | K29: 1354 | L29: Active | M29: Tue 27 Oct 5:15pm | N29: Brad Conder | O29: Tecoma | P29: =IFERROR(INDEX(SuburbScorecard!$C:$C,MATCH($O29,SuburbScorecard!$A:$A,0)),"Not on scorecard") -> Active Shortlist | Q29: =IFERROR(IF(INDEX(SuburbScorecard!$J:$J,MATCH($O29,SuburbScorecard!$A:$A,0))="","",INDEX(SuburbScorecard!$J:$J,MATCH($O29,SuburbScorecard!$A:$A,0))),"") -> 19 | R29: =IFERROR(IF(INDEX(SuburbScorecard!$K:$K,MATCH($O29,SuburbScorecard!$A:$A,0))="","",INDEX(SuburbScorecard!$K:$K,MATCH($O29,SuburbScorecard!$A:$A,0))),"") -> 5 | S29: =IFERROR(IF(INDEX(SuburbScorecard!$AB:$AB,MATCH($O29,SuburbScorecard!$A:$A,0))="","Needs data",INDEX(SuburbScorecard!$AB:$AB,MATCH($O29,SuburbScorecard!$A:$A,0))),"Needs data") -> Yes | T29: =IF(L29="Under offer","Under offer",IF(G29="Over cap","Fails: budget",IF(NOT(AND(ISNUMBER(Q29),ISNUMBER(R29))),"Needs data",IF(Q29>Filters!$B$4,"Fails: GW drive",IF(R29>Filters!$B$5,"Fails: ED drive",IF(G29="Straddles cap","Pass if bought near low end","Pass")))))) -> Pass
A30: 29 | B30: 84 Belgrave Gembrook Road | C30: Belgrave | D30: $945,000-$1,035,000 | E30: 945000 | F30: 1035000 | G30: =IF(E30="","Needs data",IF(F30<=Filters!$B$2,"Within cap",IF(E30<=Filters!$B$2,"Straddles cap","Over cap"))) -> Within cap | H30: 5 | I30: 2 | J30: 2 | K30: 4089 | L30: Active | M30: Thu 29 Oct 1:30pm | N30: Jarrod Peterson | O30: Belgrave | P30: =IFERROR(INDEX(SuburbScorecard!$C:$C,MATCH($O30,SuburbScorecard!$A:$A,0)),"Not on scorecard") -> Active Shortlist | Q30: =IFERROR(IF(INDEX(SuburbScorecard!$J:$J,MATCH($O30,SuburbScorecard!$A:$A,0))="","",INDEX(SuburbScorecard!$J:$J,MATCH($O30,SuburbScorecard!$A:$A,0))),"") -> 21 | R30: =IFERROR(IF(INDEX(SuburbScorecard!$K:$K,MATCH($O30,SuburbScorecard!$A:$A,0))="","",INDEX(SuburbScorecard!$K:$K,MATCH($O30,SuburbScorecard!$A:$A,0))),"") -> 7 | S30: =IFERROR(IF(INDEX(SuburbScorecard!$AB:$AB,MATCH($O30,SuburbScorecard!$A:$A,0))="","Needs data",INDEX(SuburbScorecard!$AB:$AB,MATCH($O30,SuburbScorecard!$A:$A,0))),"Needs data") -> Yes | T30: =IF(L30="Under offer","Under offer",IF(G30="Over cap","Fails: budget",IF(NOT(AND(ISNUMBER(Q30),ISNUMBER(R30))),"Needs data",IF(Q30>Filters!$B$4,"Fails: GW drive",IF(R30>Filters!$B$5,"Fails: ED drive",IF(G30="Straddles cap","Pass if bought near low end","Pass")))))) -> Pass
A31: 30 | B31: 3 Fiocchi Avenue | C31: Frankston | D31: $1,350,000-$1,450,000 | E31: 1350000 | F31: 1450000 | G31: =IF(E31="","Needs data",IF(F31<=Filters!$B$2,"Within cap",IF(E31<=Filters!$B$2,"Straddles cap","Over cap"))) -> Within cap | H31: 4 | I31: 3 | J31: 2 | K31: 781 | L31: Active | M31: None listed | N31: Not shown | O31: Frankston | P31: =IFERROR(INDEX(SuburbScorecard!$C:$C,MATCH($O31,SuburbScorecard!$A:$A,0)),"Not on scorecard") -> Active Shortlist | Q31: =IFERROR(IF(INDEX(SuburbScorecard!$J:$J,MATCH($O31,SuburbScorecard!$A:$A,0))="","",INDEX(SuburbScorecard!$J:$J,MATCH($O31,SuburbScorecard!$A:$A,0))),"") -> 25 | R31: =IFERROR(IF(INDEX(SuburbScorecard!$K:$K,MATCH($O31,SuburbScorecard!$A:$A,0))="","",INDEX(SuburbScorecard!$K:$K,MATCH($O31,SuburbScorecard!$A:$A,0))),"") -> 4 | S31: =IFERROR(IF(INDEX(SuburbScorecard!$AB:$AB,MATCH($O31,SuburbScorecard!$A:$A,0))="","Needs data",INDEX(SuburbScorecard!$AB:$AB,MATCH($O31,SuburbScorecard!$A:$A,0))),"Needs data") -> Yes | T31: =IF(L31="Under offer","Under offer",IF(G31="Over cap","Fails: budget",IF(NOT(AND(ISNUMBER(Q31),ISNUMBER(R31))),"Needs data",IF(Q31>Filters!$B$4,"Fails: GW drive",IF(R31>Filters!$B$5,"Fails: ED drive",IF(G31="Straddles cap","Pass if bought near low end","Pass")))))) -> Pass | U31: Agent name not shown on card
A32: 31 | B32: 2 Bader Court | C32: Frankston South | D32: $1,500,000-$1,650,000 | E32: 1500000 | F32: 1650000 | G32: =IF(E32="","Needs data",IF(F32<=Filters!$B$2,"Within cap",IF(E32<=Filters!$B$2,"Straddles cap","Over cap"))) -> Straddles cap | H32: 4 | I32: 2 | J32: 4 | K32: 430 | L32: Active | M32: Thu 29 Oct 5:30pm | N32: Geoff Oxford | O32: Frankston South | P32: =IFERROR(INDEX(SuburbScorecard!$C:$C,MATCH($O32,SuburbScorecard!$A:$A,0)),"Not on scorecard") -> Active Shortlist | Q32: =IFERROR(IF(INDEX(SuburbScorecard!$J:$J,MATCH($O32,SuburbScorecard!$A:$A,0))="","",INDEX(SuburbScorecard!$J:$J,MATCH($O32,SuburbScorecard!$A:$A,0))),"") -> 31 | R32: =IFERROR(IF(INDEX(SuburbScorecard!$K:$K,MATCH($O32,SuburbScorecard!$A:$A,0))="","",INDEX(SuburbScorecard!$K:$K,MATCH($O32,SuburbScorecard!$A:$A,0))),"") -> 4 | S32: =IFERROR(IF(INDEX(SuburbScorecard!$AB:$AB,MATCH($O32,SuburbScorecard!$A:$A,0))="","Needs data",INDEX(SuburbScorecard!$AB:$AB,MATCH($O32,SuburbScorecard!$A:$A,0))),"Needs data") -> No | T32: =IF(L32="Under offer","Under offer",IF(G32="Over cap","Fails: budget",IF(NOT(AND(ISNUMBER(Q32),ISNUMBER(R32))),"Needs data",IF(Q32>Filters!$B$4,"Fails: GW drive",IF(R32>Filters!$B$5,"Fails: ED drive",IF(G32="Straddles cap","Pass if bought near low end","Pass")))))) -> Pass if bought near low end
A33: 32 | B33: 35 Mountain Avenue | C33: Frankston South | D33: $1,150,000-$1,250,000 | E33: 1150000 | F33: 1250000 | G33: =IF(E33="","Needs data",IF(F33<=Filters!$B$2,"Within cap",IF(E33<=Filters!$B$2,"Straddles cap","Over cap"))) -> Within cap | H33: 3 | I33: 2 | J33: 6 | K33: 2502 | L33: Active | M33: Sat 31 Oct 11:00am | N33: Ashley Weston | O33: Frankston South | P33: =IFERROR(INDEX(SuburbScorecard!$C:$C,MATCH($O33,SuburbScorecard!$A:$A,0)),"Not on scorecard") -> Active Shortlist | Q33: =IFERROR(IF(INDEX(SuburbScorecard!$J:$J,MATCH($O33,SuburbScorecard!$A:$A,0))="","",INDEX(SuburbScorecard!$J:$J,MATCH($O33,SuburbScorecard!$A:$A,0))),"") -> 31 | R33: =IFERROR(IF(INDEX(SuburbScorecard!$K:$K,MATCH($O33,SuburbScorecard!$A:$A,0))="","",INDEX(SuburbScorecard!$K:$K,MATCH($O33,SuburbScorecard!$A:$A,0))),"") -> 4 | S33: =IFERROR(IF(INDEX(SuburbScorecard!$AB:$AB,MATCH($O33,SuburbScorecard!$A:$A,0))="","Needs data",INDEX(SuburbScorecard!$AB:$AB,MATCH($O33,SuburbScorecard!$A:$A,0))),"Needs data") -> No | T33: =IF(L33="Under offer","Under offer",IF(G33="Over cap","Fails: budget",IF(NOT(AND(ISNUMBER(Q33),ISNUMBER(R33))),"Needs data",IF(Q33>Filters!$B$4,"Fails: GW drive",IF(R33>Filters!$B$5,"Fails: ED drive",IF(G33="Straddles cap","Pass if bought near low end","Pass")))))) -> Pass

Sheet DiscussionSummary
A1: Executive Dashboard
A3: Respondent Status | D3: Priority Weights (Before vs After)
A4: Mum | B4: =CleanedAnswers!B2 -> 4 | D4: Priority | E4: Draft Baseline | F4: Final Weight
A5: Dad | B5: =CleanedAnswers!B3 -> 5 | D5: Near family in GW | E5: 0 | F5: 0.153
A6: Me | B6: =CleanedAnswers!B4 -> 3 | D6: Nature | E6: 0.18 | F6: 0.133
D7: Hospital | E7: 0.15 | F7: 0.133
A8: Active Hard Filters | D8: Indian community | E8: 0.18 | F8: 0.117
A9: Budget Cap | B9: 1500000 | D9: Shops & doctor | E9: 0.09 | F9: 0.108
A10: Max GW Drive | B10: =Filters!B4 -> 90 | D10: Village character | E10: 0.07 | F10: 0.088
A11: Max ED Drive | B11: =Filters!B5 -> 90 | D11: Train/bus | E11: 0.15 | F11: 0.081
A12: Stairs | B12: =Filters!B6 -> Stairs allowed (single-level not required) | D12: Price | E12: 0.08 | F12: 0.081
D13: Beach | E13: 0.1 | F13: 0.061
A14: Suburb Counts | D14: City trip | E14: 0 | F14: 0.045
A15: Passing / Provisional Pass | B15: =COUNTIF(SuburbScorecard!L:L, "*Pass*") -> 13
A16: Needs Data | B16: =COUNTIF(SuburbScorecard!L:L, "*Needs data*") -> 38 | D16: Trade-off Disagreements
A17: Fails: budget | B17: =COUNTIF(SuburbScorecard!L:L, "Fails: budget") -> 0 | D17: Q7a/Q7b Living arrangement | E17: Needs discussion (Living arrangement undecided): D — Self-contained space
A18: Fails: GW drive | B18: =COUNTIF(SuburbScorecard!L:L, "Fails: GW drive") -> 2 | D18: Q7 Garden | E18: Needs discussion (Depends — see notes)
A19: Fails: ED drive | B19: =COUNTIF(SuburbScorecard!L:L, "Fails: ED drive") -> 0
